Workbook
Name _D11: [1]表二!#REF!
Name _D12: [1]表二!#REF!
Name _SHR1: #REF!
Name a: #REF!
Name B3BGH: #REF!
Name B3BH: #REF!
Name b3data: #REF!
Name BSC安装材料金额: '[2]dyb3'!#REF!
Name BSC任选设备金额: '[2]dyb3'!#REF!
Name button_area_1: #REF!
Name calc: '[3]DYB4'!#REF!
Name CC: #REF!
Name CDB: #REF!
Name celltips_area: #REF!
Name cif合计cly: '[4]表四(主材引)'!#REF!
Name cif合计sby: '[4]表四(引)'!#REF!
Name count: #REF!
Name CS: #REF!
Name CSC技工总工日: [6]CSC生成表3!$I$178
Name CSC总计clg: [6]国内主材表CSC!$H$42
Name CS技工总工日: '[6]CS表3(1)'!$L$160
Name CS普工总工日: '[6]CS表3(1)'!$M$160
Name CS总计clg: [6]国内主材表CS!$J$62
Name dflt1: #REF!
Name dflt2: #REF!
Name dflt3: #REF!
Name dflt4: #REF!
Name dflt5: #REF!
Name dflt6: #REF!
Name dflt7: #REF!
Name display_area_1: #REF!
Name exchange: '[3]DYB4'!$D$3
Name floor: #REF!
Name fob合计cly: '[4]表四(主材引)'!#REF!
Name fob合计sby: '[7]表四(引)'!#REF!
Name HLR服务费金额: [8]费用!$I$10
Name hy: #REF!
Name JKSBB4_ZHU: '[3]DYB4'!#REF!
Name JKSBB4Btj: [9]Macro1!#REF!
Name LOC: #REF!
Name LTR: #REF!
Name MSC服务费金额: '[2]B4-3'!#REF!
Name mz: #REF!
Name new监理费: [10]费率!$AN$4:$AZ$17
Name NS: #REF!
Name p: #REF!
Name pe: #REF!
Name pn: #REF!
Name PROGRAM_B3: #REF!
Name PROGRAM_JKSB: #REF!
Name PROGRAM_LXGC: #REF!
Name PROGRAM_SBB4: #REF!
Name PROGRAM_YQYB: #REF!
Name PROGRAM_ZCB4: #REF!
Name pt: #REF!
Name ptw: #REF!
Name q: #REF!
Name rjq: #REF!
Name sjf: [12]DATA!$X$1:[12]DATA!$Z$20
Name SS: #REF!

Sheet 表1-甲供物资平衡表
A1: 表1：B25302110AA0014项目结算送审甲供物资平衡表（第一分册） | N1: JMHSWX25052615025R | O1: JMHSWX25052615022R | P1: JMHSWX25052615021R | Q1: JMHSWX25051308476R | R1: JMPJWX25051308301R | S1: JMHSWX25041800897R | T1: JMJHWX25041800899R | U1: JMJHWX24122521503R | V1: JMJHWX24122845347R | W1: JMHSWX25071541474R | X1: JMPJWX25081257109R | Y1: JMPJWX25090573549R | Z1: JMPJWX25090573548R | AA1: JMHSWX25090473480R | AB1: JMHSWX25090473477R | AC1: JMJHWX25092982719R | AD1: JMHSWX25102086683R
A2: 单项工程名称：江门700MHz频段共建共享五期工程无线主设备项目——子项4：常规项目 | D2: 框架合同编号：CMGD-202500909 投资项目编号：B25302110AA0014 | N2: APO302127250700258 | O2: APO302127250700258 | P2: APO302127250700258 | Q2: APO302127250700258 | R2: APO302127250700258 | S2: APO302127250700258 | T2: APO302127250700258 | U2: APO302127250700258 | V2: APO302127250700258 | W2: APO302127250700258 | X2: APO302127251000020 | Y2: APO302127251000020 | Z2: APO302127251000020 | AA2: APO302127251000020 | AB2: APO302127251000020 | AC2: APO302127251000020 | AD2: APO302127251100301
A3: 订单编号：APO302127250700258、APO302127251000020、APO302127251100301 | N3: 1 | O3: 2 | P3: 3 | Q3: 4 | R3: 5 | S3: 6 | T3: 7 | U3: 8 | V3: 9 | W3: 10 | X3: 11 | Y3: 12 | Z3: 13 | AA3: 14 | AB3: 15 | AC3: 16 | AD3: 17 | AE3: 18 | AF3: 19 | AG3: 20 | AH3: 21
A4: 序号 | B4: 物料名称 | C4: 单位 | D4: 领用数量 | E4: 合同间调入数量 | F4: 利旧数量 | G4: 实际使用数量 | H4: 退库数量 | I4: 合同间调出数量 | J4: 最后一次领用材料单价（不含税价） | K4: 调入合同编号（包括框架合同及单项合同/订单编号） | L4: 调出合同编号（包括框架合同及单项合同/订单编号） | N4: CBN-江门鹤山市连城C-RAN1（江门鹤山三连工业区二）U-Z5H | O4: CBN-江门鹤山路管所（江门鹤山裕兴雨具）U-Z5H | P4: CBN-江门鹤山市鹤城二（江门鹤山创美）U-Z5H | Q4: CBN-江门鹤山福迳（江门鹤山甘牛集团）U-Z5H | R4: CBN-江门蓬江区滨江新区1二（江门新昌公园）U-Z5H | S4: CBN-江门鹤山浩龙（江门鹤山鹤城联东（设备替换））U-Z5H | T4: CBN-江门礼乐新丰（江门江海东海路（设备替换））U-Z5H | U4: CBN-江门轻轨礼乐站（江门捷宏一品）U-Z5H | V4: CBN-江门汇聪电子（江门白水带山脚）U-Z5H | W4: CBN-江门鹤山大朗（江门鹤山址山昆中石北）U-Z5H | X4: CBN-江门荷塘（江门蓬江技师荷塘校区）U-Z5H | Y4: CBN-江门益晖印刷（江门永达顺（新））U-Z5H | Z4: CBN-江门三堡（江门蓬江元岭村西）U-Z5H | AA4: CBN-江门鹤山大富（江门鹤山大墩村）U-Z5H | AB4: CBN-江门鹤山平岭（江门鹤山共和平岭山顶村）U-Z5H | AC4: CBN-江门柏年（江门江海连海二路）U-Z5H | AD4: CBN-江门鹤山新民（江门鹤山共和新联油漆）U-Z5H
D5: (1) | E5: (2) | F5: (3) | G5: (4) | H5: (5) | I5: (6) | J5: (7) | K5: 若调入物料涉及多个合同编号，需分行填列 | L5: 若调出物料涉及多个合同编号，需分行填列 | N5: 数量 | O5: 数量 | P5: 数量 | Q5: 数量 | R5: 数量 | S5: 数量 | T5: 数量 | U5: 数量 | V5: 数量 | W5: 数量 | X5: 数量 | Y5: 数量 | Z5: 数量 | AA5: 数量 | AB5: 数量 | AC5: 数量 | AD5: 数量
A6: 1 | B6: 10G-1.4KM单模光模块 | C6: 个 | D6: 16 | E6: 0 | F6: 0 | G6: =D6+E6+F6 -> 16 | H6: 0 | I6: 0 | J6: 10.4 | W6: 5 | Y6: 4 | Z6: 4 | AA6: 1 | AB6: 1 | AC6: 1
A7: 2 | B7: 25G-10KM单模光模块 | C7: 个 | D7: 34 | E7: 0 | F7: 0 | G7: =D7+E7+F7 -> 34 | H7: 0 | I7: 0 | J7: 201.7 | N7: 2 | O7: 2 | P7: 2 | Q7: 2 | R7: 2 | S7: 2 | T7: 2 | U7: 2 | V7: 2 | W7: 2 | X7: 2 | Y7: 2 | Z7: 2 | AA7: 2 | AB7: 2 | AC7: 2 | AD7: 2
A8: 3 | B8: 25G-2KM单模光模块 | C8: 个 | D8: 56 | E8: 0 | F8: 0 | G8: =D8+E8+F8 -> 56 | H8: 0 | I8: 0 | J8: 48.99 | N8: 4 | O8: 4 | P8: 4 | Q8: 4 | R8: 4 | S8: 4 | T8: 4 | U8: 4 | V8: 4 | X8: 4 | AA8: 4 | AB8: 4 | AC8: 4 | AD8: 4
A9: 4 | B9: 4448天线\700/900/1800/FA\4+4+4+8通道\电调（短款）dBi\四频13/14/16.5/15/14.5 | C9: 面 | D9: 15 | E9: 3 | F9: 0 | G9: =D9+E9+F9 -> 18 | H9: 0 | I9: 0 | J9: 3957.36 | R9: 3 | U9: 3 | V9: 3 | Y9: 3 | AA9: 0 | AB9: 3
A10: 5 | B10: 绿色700-900M宽频四通道电调天线 | C10: 面 | D10: 18 | E10: 0 | F10: 0 | G10: =D10+E10+F10 -> 18 | H10: 0 | I10: 0 | J10: 1558.96 | N10: 3 | O10: 3 | Q10: 3 | T10: 3 | AC10: 3 | AD10: 3
A11: 6 | B11: BBU 直流电源线 | C11: 根 | D11: 4 | E11: 0 | F11: 0 | G11: =D11+E11+F11 -> 4 | H11: 0 | I11: 0 | J11: 0 | W11: 1 | AA11: 1 | AB11: 1 | AC11: 1
A12: 7 | B12: 单模1 LCUPC-FC/UPC G.652D 15M黄色|LC/PC-FC/PC-15M-φ2-SM/IOFC-FC/UPC-LC/PC G652D 1F φ2 PVC 15M//LC/F | C12: 根 | D12: 34 | E12: 0 | F12: 0 | G12: =D12+E12+F12 -> 34 | H12: 0 | I12: 0 | J12: 0 | N12: 2 | O12: 2 | P12: 2 | Q12: 2 | R12: 2 | S12: 2 | T12: 2 | U12: 2 | V12: 2 | W12: 2 | X12: 2 | Y12: 2 | Z12: 2 | AA12: 2 | AB12: 2 | AC12: 2 | AD12: 2
A13: 8 | B13: H07V-K&RV黄绿色1×16mm2电线(VDE/CE/CCC)|绝缘层颜色:/黄/绿色;绝缘层材质:/聚氯乙烯;额定电压:Nom(V);导体材质:/铜;标称截面积:Nom(mm^2);屏蔽层:/否;CPR认证:/E等级;导体规格:/1*16mm2; | H07V-K 16mm2(R | C13: 米 | D13: 177 | E13: 0 | F13: 0 | G13: =D13+E13+F13 -> 177 | H13: 0 | I13: 0 | J13: 0 | N13: 9 | O13: 9 | P13: 9 | Q13: 9 | R13: 9 | S13: 9 | T13: 9 | U13: 9 | V13: 9 | W13: 13 | X13: 9 | Y13: 9 | Z13: 9 | AA13: 13 | AB13: 13 | AC13: 13 | AD13: 17
A14: 9 | B14: R9214H S7200(W)整机(直流,不含光模块) | C14: 套 | D14: 21 | E14: 0 | F14: 3 | G14: =D14+E14+F14 -> 24 | H14: 0 | I14: 0 | J14: 0 | R14: 3 | U14: 3 | V14: 3 | W14: 3 | Y14: 3 | AA14: 3 | AB14: 3
A15: 10 | B15: R9264M M7290整机(直流,不含光模块) | C15: 套 | D15: 24 | E15: 3 | F15: 0 | G15: =D15+E15+F15 -> 27 | H15: 0 | I15: 0 | J15: 0 | N15: 3 | O15: 3 | P15: 3 | Q15: 3 | S15: 3 | T15: 3 | X15: 3 | AC15: 3 | AD15: 3
A16: 11 | B16: RF-01024084-012|射频电缆组件|3米|长度:3m;线材:RF1/2S-;B端连接器:4.3-10M;A端连接器:DM;硫化风险等级不涉及 | 626979000517 V1.0 | C16: 根 | D16: 132 | E16: 0 | F16: 0 | G16: =D16+E16+F16 -> 132 | H16: 0 | I16: 0 | J16: 0 | N16: 12 | O16: 12 | P16: 12 | R16: 12 | S16: 12 | T16: 12 | U16: 12 | V16: 12 | W16: 12 | X16: 12 | Z16: 12
A17: 12 | B17: RF-01024084-205|射频电缆组件|5米|长度:5m;线材:RF1/2S-;B端连接器:4.3-10M;A端连接器:DM;硫化风险等级不涉及 | 626979000517 V1.0 | C17: 根 | D17: 60 | E17: 0 | F17: 0 | G17: =D17+E17+F17 -> 60 | H17: 0 | I17: 0 | J17: 0 | Q17: 12 | AA17: 12 | AB17: 12 | AC17: 12 | AD17: 12
A18: 13 | B18: RF-01024084-012|射频电缆组件|10米|长度:10m;线材:RF1/2S-;B端连接器:4.3-10M;A端连接器:DM;硫化风险等级不涉及 | 626979000517 V1.0 | C18: 根 | D18: 12 | E18: 0 | F18: 0 | G18: =D18+E18+F18 -> 12 | H18: 0 | I18: 0 | J18: 0 | Y18: 12
A19: 14 | B19: UL 2586黑色D型(芯线：蓝/红)2X10mm2(2x8AWG)编织屏蔽电缆(UL/CE) | UL2586 2X10mm2(2x8AWG) | C19: 米 | D19: 415 | E19: 0 | F19: 0 | G19: =D19+E19+F19 -> 415 | H19: 0 | I19: 0 | J19: 0 | Q19: 45 | V19: 190 | AD19: 180
A20: 15 | B20: UL 2586黑色D型(芯线：蓝/红)2X6mm2(2x10AWG)编织屏蔽电缆(UL/CE) | UL 2586 2×6mm2(2x10AWG) | C20: 米 | D20: 1070 | E20: 0 | F20: 0 | G20: =D20+E20+F20 -> 1070 | H20: 0 | I20: 0 | J20: 0 | N20: 75 | O20: 60 | P20: 65 | R20: 70 | U20: 135 | V20: 15 | W20: 165 | X20: 45 | Y20: 105 | Z20: 80 | AA20: 45 | AB20: 150 | AC20: 60
A21: 16 | B21: V9200安装件 | C21: 套 | D21: 4 | E21: 0 | F21: 0 | G21: =D21+E21+F21 -> 4 | H21: 0 | I21: 0 | J21: 0 | W21: 1 | AA21: 1 | AB21: 1 | AC21: 1
A22: 17 | B22: V9200风扇模块VFC | C22: 块 | D22: 4 | E22: 0 | F22: 0 | G22: =D22+E22+F22 -> 4 | H22: 0 | I22: 0 | J22: 0 | W22: 1 | AA22: 1 | AB22: 1 | AC22: 1
A23: 18 | B23: V9200工程安装辅料 | C23: 套 | D23: 4 | E23: 0 | F23: 0 | G23: =D23+E23+F23 -> 4 | H23: 0 | I23: 0 | J23: 0 | W23: 1 | AA23: 1 | AB23: 1 | AC23: 1
A24: 19 | B24: V9200机箱 | C24: 套 | D24: 4 | E24: 0 | F24: 0 | G24: =D24+E24+F24 -> 4 | H24: 0 | I24: 0 | J24: 143.36 | W24: 1 | AA24: 1 | AB24: 1 | AC24: 1
A25: 20 | B25: V9200基带处理模块VBPe0d | C25: 块 | D25: 7 | E25: 0 | F25: 1 | G25: =D25+E25+F25 -> 8 | H25: 0 | I25: 0 | J25: 0 | R25: 1 | U25: 1 | W25: 1 | Y25: 1 | Z25: 1 | AA25: 1 | AB25: 1
A26: 21 | B26: V9200基带处理模块VBPe0e | C26: 块 | D26: 9 | E26: 0 | F26: 0 | G26: =D26+E26+F26 -> 9 | H26: 0 | I26: 0 | J26: 20135.98 | N26: 1 | O26: 1 | P26: 1 | Q26: 1 | S26: 1 | T26: 1 | X26: 1 | AC26: 1 | AD26: 1
A27: 22 | B27: V9200交换管理模块VSWd0A | C27: 块 | D27: 4 | E27: 0 | F27: 0 | G27: =D27+E27+F27 -> 4 | H27: 0 | I27: 0 | J27: 819.55 | W27: 1 | AA27: 1 | AB27: 1 | AC27: 1
A28: 23 | B28: GPS&BDS双模天线 | C28: 套 | D28: 1 | E28: 0 | F28: 0 | G28: =D28+E28+F28 -> 1 | H28: 0 | I28: 0 | J28: 819.55 | AC28: 1
A29: 24 | B29: GPS&BDS避雷器及辅料 | C29: 套 | D29: 1 | E29: 0 | F29: 0 | G29: =D29+E29+F29 -> 1 | H29: 0 | I29: 0 | J29: 819.55 | AC29: 1
A30: 25 | B30: 北斗三&GPS避雷器 | C30: 套 | D30: 4 | E30: 0 | F30: 0 | G30: =D30+E30+F30 -> 4 | H30: 0 | I30: 0 | J30: 0 | W30: 1 | AA30: 1 | AB30: 1 | AC30: 1
A31: 26 | B31: 北斗三&GPS天线及辅料 | C31: 套 | D31: 4 | E31: 0 | F31: 0 | G31: =D31+E31+F31 -> 4 | H31: 0 | I31: 0 | J31: 14.83 | W31: 1 | AA31: 1 | AB31: 1 | AC31: 1
A32: 27 | B32: 多频段智能天线\700～900/1800/FAD\4+4+8通道\独立电调\四频14/16.5/13.5/15.5dBi | C32: 面 | D32: 3 | E32: 0 | F32: 0 | G32: =D32+E32+F32 -> 3 | H32: 0 | I32: 0 | J32: 3454.6 | S32: 3
A33: 28 | B33: 室内单芯单模光纤跳线 | C33: 根 | D33: 8 | E33: 0 | F33: 0 | G33: =D33+E33+F33 -> 8 | H33: 0 | I33: 0 | J33: 69.91 | W33: 2 | AA33: 2 | AB33: 2 | AC33: 2
A34: 29 | B34: 直流电源模块VPD | C34: 块 | D34: 4 | E34: 0 | F34: 0 | G34: =D34+E34+F34 -> 4 | H34: 0 | I34: 0 | J34: 0 | W34: 1 | AA34: 1 | AB34: 1 | AC34: 1
A35: 30 | B35: 多频段智能天线\700～900/1800/FAD\4+4+8通道\独立电调\四频14/16.5/13.5/15.5dBi | C35: 面 | D35: 6 | E35: 0 | F35: 0 | G35: =D35+E35+F35 -> 6 | H35: 0 | I35: 0 | J35: 1891.76 | P35: 3 | X35: 3
A36: 31 | B36: 直流电源分配单元DCPD10B | C36: 套 | D36: 4 | E36: 0 | F36: 0 | G36: =D36+E36+F36 -> 4 | H36: 0 | I36: 0 | J36: 0 | W36: 1 | AA36: 1 | AB36: 1 | AC36: 1
A37: 32 | B37: DCPD10B安装辅料 | C37: 套 | D37: 4 | E37: 0 | F37: 0 | G37: =D37+E37+F37 -> 4 | H37: 0 | I37: 0 | J37: 0 | W37: 1 | AA37: 1 | AB37: 1 | AC37: 1
A38: 33 | B38: FDD宏基站\基站硬件\V9200增强型机箱单元\1800+900\中兴\直流 | C38: 套 | D38: 1 | E38: 0 | F38: 0 | G38: =D38+E38+F38 -> 1 | H38: 0 | I38: 0 | J38: 0 | AB38: 1
A39: 34 | B39: FIBER-95542-002光纤光缆组件|10米长度：10m;线材： LSZH 7mm两芯单模光缆；B端连接器： LC/PC;A端连接器： LC/PC;传输模式：单模；芯线数量： Nom2pcs; | C39: 根 | D39: 19 | E39: 0 | F39: 0 | G39: =D39+E39+F39 -> 19 | H39: 0 | I39: 0 | J39: 0 | N39: 2 | O39: 2 | P39: 1 | T39: 2 | U39: 2 | W39: 2 | Y39: 2 | AA39: 2 | AB39: 2 | AD39: 2
A40: 35 | B40: FIBER-95542-002光纤光缆组件|15米长度：15m;线材： LSZH 7mm两芯单模光缆；B端连接器： LC/PC;A端连接器： LC/PC;传输模式：单模；芯线数量： Nom2pcs; | C40: 根 | D40: 2 | E40: 0 | F40: 0 | G40: =D40+E40+F40 -> 2 | H40: 0 | I40: 0 | J40: 0 | S40: 2
A41: 36 | B41: FIBER-95542-002光纤光缆组件|20米长度：20m;线材： LSZH 7mm两芯单模光缆；B端连接器： LC/PC;A端连接器： LC/PC;传输模式：单模；芯线数量： Nom2pcs; | C41: 根 | D41: 12 | E41: 0 | F41: 0 | G41: =D41+E41+F41 -> 12 | H41: 0 | I41: 0 | J41: 0 | O41: 1 | Q41: 2 | R41: 2 | V41: 1 | X41: 3 | Z41: 2 | AA41: 1
A42: 37 | B42: FIBER-95542-002光纤光缆组件|30米长度：30m;线材： LSZH 7mm两芯单模光缆；B端连接器： LC/PC;A端连接器： LC/PC;传输模式：单模；芯线数量： Nom2pcs; | C42: 根 | D42: 2 | E42: 0 | F42: 0 | G42: =D42+E42+F42 -> 2 | H42: 0 | I42: 0 | J42: 0 | P42: 1 | R42: 1
A43: 38 | B43: FIBER-96972-001光纤光缆组件|25米长度：25m;线材： LSZH 7mm两芯单模光缆；B端连接器： FC/PC;A端连接器： LC/PC;传输模式：单模；芯线数量： Nom2pcs; | C43: 根 | D43: 5 | E43: 0 | F43: 0 | G43: =D43+E43+F43 -> 5 | H43: 0 | I43: 0 | J43: 0 | N43: 1 | O43: 1 | AC43: 3
A44: 39 | B44: FIBER-96972-001|光纤光缆组件|35米|长度:35m;线材:LSZH 7mm两芯单模光缆;B端连接器:FC/PC;A端连接器:LC/PC;传输模式:单模;芯线数量:Nom2pcs;接头型号:LC/PC,FC/PC; | 626792030817 V1.0 | C44: 根 | D44: 2 | E44: 0 | F44: 0 | G44: =D44+E44+F44 -> 2 | H44: 0 | I44: 0 | J44: 0 | S44: 1 | Y44: 1
A45: 40 | B45: FIBER-96972-001|光纤光缆组件|60米|长度:60m;线材:LSZH 7mm两芯单模光缆;B端连接器:FC/PC;A端连接器:LC/PC;传输模式:单模;芯线数量:Nom2pcs;接头型号:LC/PC,FC/PC; | 626792030817 V1.0 | C45: 根 | D45: 2 | E45: 0 | F45: 0 | G45: =D45+E45+F45 -> 2 | H45: 0 | I45: 0 | J45: 0 | T45: 1 | AD45: 1
A46: 41 | B46: FIBER-96972-001|光纤光缆组件|55米|长度:55m;线材:LSZH 7mm两芯单模光缆;B端连接器:FC/PC;A端连接器:LC/PC;传输模式:单模;芯线数量:Nom2pcs;接头型号:LC/PC,FC/PC; | 626792030817 V1.0 | C46: 根 | D46: 1 | E46: 0 | F46: 0 | G46: =D46+E46+F46 -> 1 | H46: 0 | I46: 0 | J46: 0 | W46: 1
A47: 42 | B47: FIBER-96972-001|光纤光缆组件|40米|长度:40m;线材:LSZH 7mm两芯单模光缆;B端连接器:FC/PC;A端连接器:LC/PC;传输模式:单模;芯线数量:Nom2pcs;接头型号:LC/PC,FC/PC; | 626792030817 V1.0 | C47: 根 | D47: 1 | E47: 0 | F47: 0 | G47: =D47+E47+F47 -> 1 | H47: 0 | I47: 0 | J47: 0 | Z47: 1
A48: 43 | B48: FIBER-96972-001|光纤光缆组件|50米|长度:50m;线材:LSZH 7mm两芯单模光缆;B端连接器:FC/PC;A端连接器:LC/PC;传输模式:单模;芯线数量:Nom2pcs;接头型号:LC/PC,FC/PC; | 626792030817 V1.0 | C48: 根 | D48: 2 | E48: 0 | F48: 0 | G48: =D48+E48+F48 -> 2 | H48: 0 | I48: 0 | J48: 0 | U48: 1 | AB48: 1
A49: 44 | B49: FIBER-96972-001|光纤光缆组件|90米|长度:90m;线材:LSZH 7mm两芯单模光缆;B端连接器:FC/PC;A端连接器:LC/PC;传输模式:单模;芯线数量:Nom2pcs;接头型号:LC/PC,FC/PC; | 626792030817 V1.0 | C49: 根 | D49: 1 | E49: 0 | F49: 0 | G49: =D49+E49+F49 -> 1 | H49: 0 | I49: 0 | J49: 0 | Q49: 1
A50: 45 | B50: FIBER-96972-001|光纤光缆组件|95米|长度:95m;线材:LSZH 7mm两芯单模光缆;B端连接器:FC/PC;A端连接器:LC/PC;传输模式:单模;芯线数量:Nom2pcs;接头型号:LC/PC,FC/PC; | 626792030817 V1.0 | C50: 根 | D50: 2 | E50: 0 | F50: 0 | G50: =D50+E50+F50 -> 2 | H50: 0 | I50: 0 | J50: 0 | V50: 2
A51: 46 | B51: FIBER-96972-001|光纤光缆组件|120米|长度:120m;线材:LSZH 7mm两芯单模光缆;B端连接器:FC/PC;A端连接器:LC/PC;传输模式:单模;芯线数量:Nom2pcs;接头型号:LC/PC,FC/PC; | 626792030817 V1.0 | C51: 根 | D51: 1 | E51: 0 | F51: 0 | G51: =D51+E51+F51 -> 1 | H51: 0 | I51: 0 | J51: 0 | P51: 1
A52: 47 | B52: 1/4" 50欧泡沫聚乙烯绝缘皱纹铜管外导体射频同轴电缆 | HCAAY-50-6//RF5014(1/4") | C52: 米 | D52: 100 | E52: 0 | F52: 0 | G52: =D52+E52+F52 -> 100 | H52: 0 | I52: 0 | J52: 0 | W52: 25 | AA52: 25 | AB52: 25 | AC52: 25
A53: 48 | B53: H07Z-K&UL3386红色16mm2(6AWG)电线(LSZH,VDE/CE/UL) | C53: 米 | D53: 78 | E53: 0 | F53: 0 | G53: =D53+E53+F53 -> 78 | H53: 0 | I53: 0 | J53: 0 | W53: 6 | AA53: 28 | AB53: 22 | AC53: 22
A54: 49 | B54: H07Z-K&UL3386蓝色16mm2(6AWG)电线(LSZH,VDE/CE/UL) | C54: 米 | D54: 78 | E54: 0 | F54: 0 | G54: =D54+E54+F54 -> 78 | H54: 0 | I54: 0 | J54: 0 | W54: 6 | AA54: 28 | AB54: 22 | AC54: 22
A55: 50 | B55: 700M基站\中兴\基站硬件\700M+900M\R9264M M7290(直流) | C55: 套 | D55: 27 | E55: 0 | F55: 0 | G55: =D55+E55+F55 -> 27 | H55: 0 | I55: 0 | J55: 0 | M55: 价值流
A56: 51 | B56: 700M基站\中兴\基站辅材\光跳线\光纤跳线(BBU侧) | C56: 套 | D56: 26 | E56: 0 | F56: 0 | G56: =D56+E56+F56 -> 26 | H56: 0 | I56: 0 | J56: 0 | M56: 价值流
A57: 52 | B57: 700M基站\中兴\基站硬件\普通光模块\25G-10KM单模光模块 | C57: 套 | D57: 50 | E57: 0 | F57: 0 | G57: =D57+E57+F57 -> 50 | H57: 0 | I57: 0 | J57: 0 | M57: 价值流
A58: 53 | B58: 700M基站\中兴\基站硬件\BBU主设备\V9200基带处理模块VBPe0e | C58: 套 | D58: 9 | E58: 0 | F58: 0 | G58: =D58+E58+F58 -> 9 | H58: 0 | I58: 0 | J58: 0 | M58: 价值流
A59: 54 | B59: 700M基站\中兴\基站辅材\单模光纤\2芯光纤 | C59: 套 | D59: 41 | E59: 0 | F59: 0 | G59: =D59+E59+F59 -> 41 | H59: 0 | I59: 0 | J59: 0 | M59: 价值流
A60: 55 | B60: 700M基站\中兴\基站硬件\BBU基本单元\V9200增强型机箱单元(直流) | C60: 套 | D60: 3 | E60: 0 | F60: 0 | G60: =D60+E60+F60 -> 3 | H60: 0 | I60: 0 | J60: 0 | M60: 价值流
A61: 56 | B61: 700M基站\中兴\基站硬件\BBU主设备\V9200交换管理模块VSWd0A | C61: 套 | D61: 3 | E61: 0 | F61: 0 | G61: =D61+E61+F61 -> 3 | H61: 0 | I61: 0 | J61: 0 | M61: 价值流
A62: 57 | B62: 700M基站\中兴\基站辅材\RRU直流电源线-6平方 | C62: 米 | D62: 1070 | E62: 0 | F62: 0 | G62: =D62+E62+F62 -> 1070 | H62: 0 | I62: 0 | J62: 0 | M62: 价值流
A63: 58 | B63: 700M基站\中兴\基站辅材\RRU直流电源线-10平方 | C63: 米 | D63: 235 | E63: 0 | F63: 0 | G63: =D63+E63+F63 -> 235 | H63: 0 | I63: 0 | J63: 0 | M63: 价值流
A64: 59 | B64: 700M基站\中兴\基站辅材\北斗三GPS天线 | C64: 套 | D64: 4 | E64: 0 | F64: 0 | G64: =D64+E64+F64 -> 4 | H64: 0 | I64: 0 | J64: 0 | M64: 价值流
A65: 60 | B65: 700M基站\中兴\基站硬件\传输口光模块\10G-1.4KM回传单模光模块 | C65: 套 | D65: 3 | E65: 0 | F65: 0 | G65: =D65+E65+F65 -> 3 | H65: 0 | I65: 0 | J65: 0 | M65: 价值流
A66: 61 | B66: 700M基站\中兴\基站硬件\直流分配单元\直流电源分配单元DCPD10B | C66: 套 | D66: 3 | E66: 0 | F66: 0 | G66: =D66+E66+F66 -> 3 | H66: 0 | I66: 0 | J66: 0 | M66: 价值流
... A71: 66 | B71: 25G-2KM单模光模块\中兴\基站硬件\通用\5G基站 | C71: 套 | D71: 32 | E71: 0 | F71: 0 | G71: =D71+E71+F71 -> 32 | H71: 0 | I71: 0 | J71: 0 | M71: 价值流
B72: 合计 | D72: =SUM(D6:D71) -> 4084 | E72: =SUM(E6:E71) -> 6 | F72: =SUM(F6:F71) -> 4 | G72: =SUM(G6:G71) -> 4094 | H72: =SUM(H6:H71) -> 0 | I72: =SUM(I6:I71) -> 0 | J72: =SUM(J6:J71) -> 33946.5 | M72: 价值流
A74: 备注： | B74: 一、剩余需扣减金额=（领用数量+项目间调入数量+利旧数量-实际使用数量-退库数量-项目间调出数量）*最后一次领用材料单价
B75: 二、资料要求。1、甲供物资出库清单（包含数量与单价）；2、甲供物资调入清单证明（其他项目、站点、合同调入等，其中调入清单需要注明调入合同编号及是否已进行结算，若已完成结算提供结算报告复印件，未完成结算审计的则注明未结算）；3、甲供物资利旧清单证明；4、甲供物资退库清单证明；5、甲供物资调出清单证明（调出其他项目、站点、合同等，其中调出清单需要注明调出合同编号及是否已进行结算，若已进行结算提供结算报告复印件，未进行结算则不需提供）
B77: 施工单位签字： 监理单位签字： | G77: 建设单位签字：
B78: 施工单位盖章： 监理单位签字： | G78: 建设单位盖章：

Sheet 表2-通信工程结算送审工程量、甲供材、费用明细表
B1: 表2：B25302110AA0014项目结算送审工程量明细表（第一分册）
B3: 一、结算送审工程量明细表 | F3: ='表1-甲供物资平衡表'!N3 -> 1 | G3: ='表1-甲供物资平衡表'!O3 -> 2 | H3: ='表1-甲供物资平衡表'!P3 -> 3 | I3: ='表1-甲供物资平衡表'!Q3 -> 4 | J3: ='表1-甲供物资平衡表'!R3 -> 5 | K3: ='表1-甲供物资平衡表'!S3 -> 6 | L3: ='表1-甲供物资平衡表'!T3 -> 7 | M3: ='表1-甲供物资平衡表'!U3 -> 8 | ... V3: ='表1-甲供物资平衡表'!AD3 -> 17
A4: 序号 | B4: 子项名称 | C4: 特征描述 | D4: 单位 | E4: 送审工程量 | F4: CBN-江门鹤山市连城C-RAN1（江门鹤山三连工业区二）U-Z5H | G4: CBN-江门鹤山路管所（江门鹤山裕兴雨具）U-Z5H | H4: CBN-江门鹤山市鹤城二（江门鹤山创美）U-Z5H | I4: CBN-江门鹤山福迳（江门鹤山甘牛集团）U-Z5H | J4: CBN-江门蓬江区滨江新区1二（江门新昌公园）U-Z5H | K4: CBN-江门鹤山浩龙（江门鹤山鹤城联东（设备替换））U-Z5H | L4: CBN-江门礼乐新丰（江门江海东海路（设备替换））U-Z5H | M4: CBN-江门轻轨礼乐站（江门捷宏一品）U-Z5H | N4: CBN-江门汇聪电子（江门白水带山脚）U-Z5H | O4: CBN-江门鹤山大朗（江门鹤山址山昆中石北）U-Z5H | P4: CBN-江门荷塘（江门蓬江技师荷塘校区）U-Z5H | Q4: CBN-江门益晖印刷（江门永达顺（新））U-Z5H | R4: CBN-江门三堡（江门蓬江元岭村西）U-Z5H | S4: CBN-江门鹤山大富（江门鹤山大墩村）U-Z5H | T4: CBN-江门鹤山平岭（江门鹤山共和平岭山顶村）U-Z5H | U4: CBN-江门柏年（江门江海连海二路）U-Z5H | V4: CBN-江门鹤山新民（江门鹤山共和新联油漆）U-Z5H
F5: 送审工程量 | G5: 送审工程量 | H5: 送审工程量 | I5: 送审工程量 | J5: 送审工程量 | K5: 送审工程量 | L5: 送审工程量 | M5: 送审工程量 | N5: 送审工程量 | O5: 送审工程量 | P5: 送审工程量 | Q5: 送审工程量 | R5: 送审工程量 | S5: 送审工程量 | T5: 送审工程量 | U5: 送审工程量 | V5: 送审工程量 | W5: 合计
A6: 1 | B6: 无线设备 | C6: 安装基带处理单元（机柜/箱嵌入式 BBU） | D6: 台 | E6: =SUM(F6:V6) -> 1 | S6: 1 | W6: =SUM(F6:V6) -> 1
A7: 2 | B7: 无线设备 | C7: 安装基带处理单元（壁挂式 BBU） | D7: 台 | E7: =SUM(F7:V7) -> 3 | O7: 1 | T7: 1 | U7: 1 | W7: =SUM(F7:V7) -> 3
A8: 3 | B8: 无线设备 | C8: 扩装设备板件 | D8: 块 | E8: =SUM(F8:V8) -> 13 | F8: 1 | G8: 1 | H8: 1 | I8: 1 | J8: 1 | K8: 1 | L8: 1 | M8: 1 | N8: 1 | P8: 1 | Q8: 1 | R8: 1 | V8: 1 | W8: =SUM(F8:V8) -> 13
A9: 4 | B9: 无线设备 | C9: 拆除设备板件 | D9: 块 | E9: =SUM(F9:V9) -> 1 | K9: 1 | W9: =SUM(F9:V9) -> 1
A10: 5 | B10: 无线设备 | C10: 放绑软光纤（设备机架间）（15m以下） | D10: 条 | E10: =SUM(F10:V10) -> 48 | F10: 2 | G10: 2 | H10: 2 | I10: 2 | J10: 2 | K10: 2 | L10: 2 | M10: 2 | N10: 2 | O10: 4 | P10: 2 | Q10: 2 | R10: 2 | S10: 6 | T10: 6 | U10: 6 | V10: 2 | W10: =SUM(F10:V10) -> 48
A11: 6 | B11: 无线设备 | C11: 安装定向天线（抱杆上） | D11: 副 | E11: =SUM(F11:V11) -> 3 | P11: 3 | W11: =SUM(F11:V11) -> 3
A12: 7 | B12: 无线设备 | C12: 安装定向天线（抱杆上宽体天线400mm 以上） | D12: 副 | E12: =SUM(F12:V12) -> 12 | H12: 3 | I12: 3 | N12: 3 | U12: 3 | W12: =SUM(F12:V12) -> 12
A13: 8 | B13: 无线设备 | C13: 安装定向天线（地面铁塔上、宽体天线400mm 以上）（安装高度40m以下） | D13: 副 | E13: =SUM(F13:V13) -> 9 | M13: 3 | T13: 3 | V13: 3 | W13: =SUM(F13:V13) -> 9
A14: 9 | B14: 无线设备 | C14: 拆除定向天线（地面铁塔上、宽体天线400mm 以上）（安装高度40m以下） | D14: 副 | E14: =SUM(F14:V14) -> 2 | M14: 2 | W14: =SUM(F14:V14) -> 2
A15: 10 | B15: 无线设备 | C15: 美化罩内安装定向天线-抱杆上 | D15: 副 | E15: =SUM(F15:V15) -> 9 | J15: 3 | K15: 3 | S15: 3 | W15: =SUM(F15:V15) -> 9
A16: 11 | B16: 无线设备 | C16: 美化罩内拆除定向天线-抱杆上 | D16: 副 | E16: =SUM(F16:V16) -> 9 | J16: 3 | K16: 3 | S16: 3 | W16: =SUM(F16:V16) -> 9
A17: 12 | B17: 无线设备 | C17: 无作业平台安装定向天线-地面铁塔上（安装高度40m以下） | D17: 副 | E17: =SUM(F17:V17) -> 6 | L17: 3 | Q17: 3 | W17: =SUM(F17:V17) -> 6
A18: 13 | B18: 无线设备 | C18: 无作业平台拆除定向天线-地面铁塔上（拆除高度40m以下） | D18: 副 | E18: =SUM(F18:V18) -> 3 | Q18: 3 | W18: =SUM(F18:V18) -> 3
A19: 14 | B19: 无线设备 | C19: 拆除定向天线（抱杆上、宽体天线400mm 以上） | D19: 副 | E19: =SUM(F19:V19) -> 3 | N19: 3 | W19: =SUM(F19:V19) -> 3
A20: 15 | B20: 无线设备 | C20: 安装射频拉远单元（抱杆上） | D20: 套 | E20: =SUM(F20:V20) -> 19 | H20: 3 | I20: 3 | N20: 3 | P20: 4 | R20: 3 | U20: 3 | W20: =SUM(F20:V20) -> 19
A21: 16 | B21: 无线设备 | C21: 拆除射频拉远单元（抱杆上） | D21: 套 | E21: =SUM(F21:V21) -> 1 | P21: 1 | W21: =SUM(F21:V21) -> 1
A22: 17 | B22: 无线设备 | C22: 美化罩内安装射频拉远单元-抱杆上 | D22: 套 | E22: =SUM(F22:V22) -> 6 | K22: 3 | S22: 3 | W22: =SUM(F22:V22) -> 6
A23: 18 | B23: 无线设备 | C23: 美化罩内拆除射频拉远单元-抱杆上 | D23: 套 | E23: =SUM(F23:V23) -> 6 | J23: 3 | K23: 3 | W23: =SUM(F23:V23) -> 6
A24: 19 | B24: 无线设备 | C24: 安装射频拉远单元（地面铁塔上）（安装高度40m以下） | D24: 套 | E24: =SUM(F24:V24) -> 9 | M24: 3 | T24: 3 | V24: 3 | W24: =SUM(F24:V24) -> 9
A25: 20 | B25: 无线设备 | C25: 无作业平台安装射频拉远单元-地面铁塔上（安装高度40m以下） | D25: 套 | E25: =SUM(F25:V25) -> 9 | L25: 3 | O25: 3 | Q25: 3 | W25: =SUM(F25:V25) -> 9
A26: 21 | B26: 无线设备 | C26: 无作业平台拆除射频拉远单元（地面铁塔上）（安装高度40m以下） | D26: 套 | E26: =SUM(F26:V26) -> 3 | L26: 3 | W26: =SUM(F26:V26) -> 3
A27: 22 | B27: 无线设备 | C27: 拆除定向天线-地面铁塔上（拆除高度40m以下） | D27: 套 | E27: =SUM(F27:V27) -> 3 | T27: 3 | W27: =SUM(F27:V27) -> 3
A28: 23 | B28: 无线设备 | C28: 安装射频拉远单元-楼顶铁塔上（安装高度20m以下） | D28: 套 | E28: =SUM(F28:V28) -> 6 | F28: 3 | G28: 3 | W28: =SUM(F28:V28) -> 6
A29: 24 | B29: 无线设备 | C29: 安装安装定向天线-楼顶铁塔上（安装高度20m以下）宽体天线400mm 以上 | D29: 套 | E29: =SUM(F29:V29) -> 6 | F29: 3 | G29: 3 | W29: =SUM(F29:V29) -> 6
A30: 25 | B30: 无线设备 | C30: 调测室外基站天、馈线系统（1/2英寸射频同轴电缆） | D30: 条 | E30: =SUM(F30:V30) -> 251 | F30: 12 | G30: 12 | H30: 12 | I30: 12 | K30: 12 | L30: 12 | M30: 20 | N30: 36 | O30: 13 | P30: 12 | Q30: 12 | R30: 12 | S30: 25 | T30: 25 | U30: 12 | V30: 12 | W30: =SUM(F30:V30) -> 251
A31: 26 | B31: 无线设备 | C31: 配合调测天、馈线系统 | D31: 扇区 | E31: =SUM(F31:V31) -> 51 | F31: 3 | G31: 3 | H31: 3 | I31: 3 | J31: 3 | K31: 3 | L31: 3 | M31: 3 | N31: 3 | O31: 3 | P31: 3 | Q31: 3 | R31: 3 | S31: 3 | T31: 3 | U31: 3 | V31: 3 | W31: =SUM(F31:V31) -> 51
A32: 27 | B32: 无线设备 | C32: 安装电源转换器/配电单元（室内） | D32: 台 | E32: =SUM(F32:V32) -> 3 | S32: 1 | T32: 1 | U32: 1 | W32: =SUM(F32:V32) -> 3
A33: 28 | B33: 无线设备 | C33: 安装室内墙挂综合箱（无源） | D33: 个 | E33: =SUM(F33:V33) -> 3 | O33: 1 | T33: 1 | U33: 1 | W33: =SUM(F33:V33) -> 3
A34: 29 | B34: 无线设备 | C34: 室外布放电力电缆（单芯相线截面积16平方毫米以下） | D34: 十米条 | E34: =SUM(F34:V34) -> 22.5 | F34: 0.9 | G34: 0.9 | H34: 0.9 | I34: 0.9 | J34: 0.9 | K34: 0.9 | L34: 0.9 | M34: 0.9 | O34: 0.9 | P34: 0.9 | Q34: 0.9 | R34: 0.9 | S34: 9 | T34: 0.9 | U34: 0.9 | V34: 0.9 | W34: =SUM(F34:V34) -> 22.5
A35: 30 | B35: 无线设备 | C35: 室外布放电力电缆（双芯相线截面积16平方毫米以下） | D35: 十米条 | E35: =SUM(F35:V35) -> 173 | F35: 7.5 | G35: 6 | H35: 6.5 | I35: 4.5 | J35: 7 | K35: 6.5 | L35: 18 | M35: 13.5 | N35: 20.5 | O35: 16.5 | P35: 4.5 | Q35: 10.5 | R35: 8 | S35: 4.5 | T35: 15 | U35: 6 | V35: 18 | W35: =SUM(F35:V35) -> 173
A36: 31 | B36: 无线设备 | C36: 室内布放电力电缆（单芯相线截面积16平方毫米以下） | D36: 十米条 | E36: =SUM(F36:V36) -> 17.3 | O36: 1.6 | S36: 6 | T36: 4.8 | U36: 4.9 | W36: =SUM(F36:V36) -> 17.3
A37: 32 | B37: 无线设备 | C37: 室内布放电力电缆（双芯相线截面积16平方毫米以下） | D37: 十米条 | E37: =SUM(F37:V37) -> 0.4 | O37: 0.1 | S37: 0.1 | T37: 0.1 | U37: 0.1 | W37: =SUM(F37:V37) -> 0.4
A38: 33 | B38: 无线设备 | C38: 拆除室外电力电缆（单芯相线截面积16平方毫米以下） | D38: 十米条 | E38: =SUM(F38:V38) -> 24.5 | K38: 6.5 | L38: 18 | W38: =SUM(F38:V38) -> 24.5
A39: 34 | B39: 无线设备 | C39: 布放射频同轴电缆1/2英寸以下（4m以下）-带端头已连接好 | D39: 条 | E39: =SUM(F39:V39) -> 272 | F39: 12 | G39: 12 | H39: 12 | I39: 12 | J39: 12 | K39: 12 | L39: 12 | M39: 20 | N39: 36 | O39: 12 | P39: 12 | Q39: 24 | R39: 12 | S39: 24 | T39: 24 | U39: 12 | V39: 12 | W39: =SUM(F39:V39) -> 272
A40: 35 | B40: 无线设备 | C40: 布放射频同轴电缆1/2英寸以下（4m以下） | D40: 条 | E40: =SUM(F40:V40) -> 4 | O40: 1 | S40: 1 | T40: 1 | U40: 1 | W40: =SUM(F40:V40) -> 4
A41: 36 | B41: 无线设备 | C41: 布放射频同轴电缆1/2英寸以下（4m以上每增加1m） | D41: 米条 | E41: =SUM(F41:V41) -> 84 | O41: 21 | S41: 21 | T41: 21 | U41: 21 | W41: =SUM(F41:V41) -> 84
A42: 37 | B42: 无线设备 | C42: 布放射频同轴电缆1/2英寸以下（4m以上每增加1m）-带端头 | D42: 米条 | E42: =SUM(F42:V42) -> 60 | I42: 12 | S42: 12 | T42: 12 | U42: 12 | V42: 12 | W42: =SUM(F42:V42) -> 60
A43: 38 | B43: 无线设备 | C43: 拆除射频同轴电缆1/2英寸以下（4m以下）-带端头 | D43: 条 | E43: =SUM(F43:V43) -> 92 | K43: 12 | L43: 12 | M43: 8 | N43: 24 | Q43: 12 | S43: 12 | T43: 12 | W43: =SUM(F43:V43) -> 92
A44: 39 | B44: 无线设备 | C44: 布放无线射频拉远单元用光缆 | D44: 米条 | E44: =SUM(F44:V44) -> 1510 | F44: 45 | G44: 40 | H44: 160 | I44: 130 | J44: 70 | K44: 65 | L44: 80 | M44: 70 | N44: 210 | O44: 75 | P44: 60 | Q44: 160 | R44: 80 | S44: 40 | T44: 70 | U44: 75 | V44: 80 | W44: =SUM(F44:V44) -> 1510
A45: 40 | B45: 无线设备 | C45: 拆除无线射频拉远单元用光缆 | D45: 米条 | E45: =SUM(F45:V45) -> 145 | K45: 65 | L45: 80 | W45: =SUM(F45:V45) -> 145
A46: 41 | B46: 无线设备 | C46: 第五代移动通信基站（配合基站割接、开通） | D46: 站 | E46: =SUM(F46:V46) -> 17 | F46: 1 | G46: 1 | H46: 1 | I46: 1 | J46: 1 | K46: 1 | L46: 1 | M46: 1 | N46: 1 | O46: 1 | P46: 1 | Q46: 1 | R46: 1 | S46: 1 | T46: 1 | U46: 1 | V46: 1 | W46: =SUM(F46:V46) -> 17
A47: 42 | B47: 无线设备 | C47: 第五代移动通信基站（配合联网调测） | D47: 站 | E47: =SUM(F47:V47) -> 17 | F47: 1 | G47: 1 | H47: 1 | I47: 1 | J47: 1 | K47: 1 | L47: 1 | M47: 1 | N47: 1 | O47: 1 | P47: 1 | Q47: 1 | R47: 1 | S47: 1 | T47: 1 | U47: 1 | V47: 1 | W47: =SUM(F47:V47) -> 17
A48: 43 | B48: 无线设备 | C48: 配合调测第五代移动通信基站系统（1km以上拉远站） | D48: 扇区 | E48: =SUM(F48:V48) -> 51 | F48: 3 | G48: 3 | H48: 3 | I48: 3 | J48: 3 | K48: 3 | L48: 3 | M48: 3 | N48: 3 | O48: 3 | P48: 3 | Q48: 3 | R48: 3 | S48: 3 | T48: 3 | U48: 3 | V48: 3 | W48: =SUM(F48:V48) -> 51
A49: 44 | B49: 无线设备 | C49: 室外布放控制信号线 | D49: 十米条 | E49: =SUM(F49:V49) -> 12.6 | F49: 0.9 | G49: 0.9 | H49: 0.9 | I49: 0.9 | J49: 0.9 | K49: 0.9 | L49: 0.9 | M49: 0.9 | N49: 0.9 | P49: 0.9 | Q49: 0.9 | R49: 0.9 | U49: 0.9 | V49: 0.9 | W49: =SUM(F49:V49) -> 12.6
A50: 45 | B50: 无线设备 | C50: 安装调测卫星全球定位系统(GPS)天线 | D50: 副 | E50: =SUM(F50:V50) -> 4 | O50: 1 | S50: 1 | T50: 1 | U50: 1 | W50: =SUM(F50:V50) -> 4
A51: 46 | B51: 无线设备 | C51: 安装(GPS)防雷器 | D51: 套 | E51: =SUM(F51:V51) -> 4 | O51: 1 | S51: 1 | T51: 1 | U51: 1 | W51: =SUM(F51:V51) -> 4
A52: 47 | C52: 扩装、更换基带单元侧光电转换模块 | D52: 个 | E52: =SUM(F52:V52) -> 102 | F52: 6 | G52: 6 | H52: 6 | I52: 6 | J52: 6 | K52: 6 | L52: 6 | M52: 6 | N52: 6 | O52: 6 | P52: 6 | Q52: 6 | R52: 6 | S52: 6 | T52: 6 | U52: 6 | V52: 6 | W52: =SUM(F52:V52) -> 102
A53: 48 | C53: 敷设硬质PVC管/槽 | D53: 十米 | E53: =SUM(F53:V53) -> 40 | P53: 40 | W53: =SUM(F53:V53) -> 40
A54: 49 | C54: 安装波纹软管 | D54: 十米 | E54: =SUM(F54:V54) -> 2.4 | M54: 0.6 | O54: 0.6 | P54: 0.6 | T54: 0.6 | W54: =SUM(F54:V54) -> 2.4
B56: 二、结算送审甲供物资使用量明细表
A57: 序号 | B57: 物资名称 | C57: 型号 | D57: 单位 | E57: 送审甲供物资量 | F57: CBN-江门鹤山市连城C-RAN1（江门鹤山三连工业区二）U-Z5H | G57: CBN-江门鹤山路管所（江门鹤山裕兴雨具）U-Z5H | H57: CBN-江门鹤山市鹤城二（江门鹤山创美）U-Z5H | I57: CBN-江门鹤山福迳（江门鹤山甘牛集团）U-Z5H | J57: CBN-江门蓬江区滨江新区1二（江门新昌公园）U-Z5H | K57: CBN-江门鹤山浩龙（江门鹤山鹤城联东（设备替换））U-Z5H | L57: CBN-江门礼乐新丰（江门江海东海路（设备替换））U-Z5H | M57: CBN-江门轻轨礼乐站（江门捷宏一品）U-Z5H | N57: CBN-江门汇聪电子（江门白水带山脚）U-Z5H | O57: CBN-江门鹤山大朗（江门鹤山址山昆中石北）U-Z5H | P57: CBN-江门荷塘（江门蓬江技师荷塘校区）U-Z5H | Q57: CBN-江门益晖印刷（江门永达顺（新））U-Z5H | R57: CBN-江门三堡（江门蓬江元岭村西）U-Z5H | S57: CBN-江门鹤山大富（江门鹤山大墩村）U-Z5H | T57: CBN-江门鹤山平岭（江门鹤山共和平岭山顶村）U-Z5H | U57: CBN-江门柏年（江门江海连海二路）U-Z5H | V57: CBN-江门鹤山新民（江门鹤山共和新联油漆）U-Z5H
F58: 送审工程量 | G58: 送审工程量 | H58: 送审工程量 | I58: 送审工程量 | J58: 送审工程量 | K58: 送审工程量 | L58: 送审工程量 | M58: 送审工程量 | N58: 送审工程量 | O58: 送审工程量 | P58: 送审工程量 | Q58: 送审工程量 | R58: 送审工程量 | S58: 送审工程量 | T58: 送审工程量 | U58: 送审工程量 | V58: 送审工程量
A59: 1 | B59: 10G-1.4KM单模光模块 | C59: 10G-1.4KM单模光模块 | D59: 个 | E59: 16 | O59: 5 | Q59: 4 | R59: 4 | S59: 1 | T59: 1 | U59: 1
A60: 2 | B60: 25G-10KM单模光模块 | C60: 25G-10KM单模光模块 | D60: 个 | E60: 34 | F60: 2 | G60: 2 | H60: 2 | I60: 2 | J60: 2 | K60: 2 | L60: 2 | M60: 2 | N60: 2 | O60: 2 | P60: 2 | Q60: 2 | R60: 2 | S60: 2 | T60: 2 | U60: 2 | V60: 2
A61: 3 | B61: 25G-2KM单模光模块 | C61: 25G-2KM单模光模块 | D61: 个 | E61: 56 | F61: 4 | G61: 4 | H61: 4 | I61: 4 | J61: 4 | K61: 4 | L61: 4 | M61: 4 | N61: 4 | P61: 4 | S61: 4 | T61: 4 | U61: 4 | V61: 4
A62: 4 | B62: 4448天线\700/900/1800/FA\4+4+4+8通道\电调（短款）dBi\四频13/14/16.5/15/14.5 | C62: 4448天线\700/900/1800/FA\4+4+4+8通道\电调（短款）dBi\四频13/14/16.5/15/14.5 | D62: 面 | E62: 15 | J62: 3 | M62: 3 | N62: 3 | Q62: 3 | S62: 0 | T62: 3
A63: 5 | B63: 绿色700-900M宽频四通道电调天线 | C63: 绿色700-900M宽频四通道电调天线 | D63: 面 | E63: 18 | F63: 3 | G63: 3 | I63: 3 | L63: 3 | U63: 3 | V63: 3
A64: 6 | B64: BBU 直流电源线 | C64: BBU 直流电源线 | D64: 根 | E64: 4 | O64: 1 | S64: 1 | T64: 1 | U64: 1
A65: 7 | B65: 单模1 LCUPC-FC/UPC G.652D 15M黄色|LC/PC-FC/PC-15M-φ2-SM/IOFC-FC/UPC-LC/PC G652D 1F φ2 PVC 15M//LC/F | C65: 单模1 LCUPC-FC/UPC G.652D 15M黄色|LC/PC-FC/PC-15M-φ2-SM/IOFC-FC/UPC-LC/PC G652D 1F φ2 PVC 15M//LC/F | D65: 根 | E65: 34 | F65: 2 | G65: 2 | H65: 2 | I65: 2 | J65: 2 | K65: 2 | L65: 2 | M65: 2 | N65: 2 | O65: 2 | P65: 2 | Q65: 2 | R65: 2 | S65: 2 | T65: 2 | U65: 2 | V65: 2
A66: 8 | B66: H07V-K&RV黄绿色1×16mm2电线(VDE/CE/CCC)|绝缘层颜色:/黄/绿色;绝缘层材质:/聚氯乙烯;额定电压:Nom(V);导体材质:/铜;标称截面积:Nom(mm^2);屏蔽层:/否;CPR认证:/E等级;导体规格:/1*16mm2; | H07V-K 16mm2(R | C66: H07V-K&RV黄绿色1×16mm2电线(VDE/CE/CCC)|绝缘层颜色:/黄/绿色;绝缘层材质:/聚氯乙烯;额定电压:Nom(V);导体材质:/铜;标称截面积:Nom(mm^2);屏蔽层:/否;CPR认证:/E等级;导体规格:/1*16mm2; | H07V-K 16mm2(R | D66: 米 | E66: 177 | F66: 9 | G66: 9 | H66: 9 | I66: 9 | J66: 9 | K66: 9 | L66: 9 | M66: 9 | N66: 9 | O66: 13 | P66: 9 | Q66: 9 | R66: 9 | S66: 13 | T66: 13 | U66: 13 | V66: 17
A67: 9 | B67: R9214H S7200(W)整机(直流,不含光模块) | C67: R9214H S7200(W)整机(直流,不含光模块) | D67: 套 | E67: 21 | J67: 3 | M67: 3 | N67: 3 | O67: 3 | Q67: 3 | S67: 3 | T67: 3
A68: 10 | B68: R9264M M7290整机(直流,不含光模块) | C68: R9264M M7290整机(直流,不含光模块) | D68: 套 | E68: 24 | F68: 3 | G68: 3 | H68: 3 | I68: 3 | K68: 3 | L68: 3 | P68: 3 | U68: 3 | V68: 3
A69: 11 | B69: RF-01024084-012|射频电缆组件|3米|长度:3m;线材:RF1/2S-;B端连接器:4.3-10M;A端连接器:DM;硫化风险等级不涉及 | 626979000517 V1.0 | C69: RF-01024084-012|射频电缆组件|3米|长度:3m;线材:RF1/2S-;B端连接器:4.3-10M;A端连接器:DM;硫化风险等级不涉及 | 626979000517 V1.0 | D69: 根 | E69: 132 | F69: 12 | G69: 12 | H69: 12 | J69: 12 | K69: 12 | L69: 12 | M69: 12 | N69: 12 | O69: 12 | P69: 12 | R69: 12
A70: 12 | B70: RF-01024084-205|射频电缆组件|5米|长度:5m;线材:RF1/2S-;B端连接器:4.3-10M;A端连接器:DM;硫化风险等级不涉及 | 626979000517 V1.0 | C70: RF-01024084-205|射频电缆组件|5米|长度:5m;线材:RF1/2S-;B端连接器:4.3-10M;A端连接器:DM;硫化风险等级不涉及 | 626979000517 V1.0 | D70: 根 | E70: 60 | I70: 12 | S70: 12 | T70: 12 | U70: 12 | V70: 12
A71: 13 | B71: RF-01024084-012|射频电缆组件|10米|长度:10m;线材:RF1/2S-;B端连接器:4.3-10M;A端连接器:DM;硫化风险等级不涉及 | 626979000517 V1.0 | C71: RF-01024084-012|射频电缆组件|10米|长度:10m;线材:RF1/2S-;B端连接器:4.3-10M;A端连接器:DM;硫化风险等级不涉及 | 626979000517 V1.0 | D71: 根 | E71: 12 | Q71: 12
A72: 14 | B72: UL 2586黑色D型(芯线：蓝/红)2X10mm2(2x8AWG)编织屏蔽电缆(UL/CE) | UL2586 2X10mm2(2x8AWG) | C72: UL 2586黑色D型(芯线：蓝/红)2X10mm2(2x8AWG)编织屏蔽电缆(UL/CE) | UL2586 2X10mm2(2x8AWG) | D72: 米 | E72: 415 | I72: 45 | N72: 190 | V72: 180
A73: 15 | B73: UL 2586黑色D型(芯线：蓝/红)2X6mm2(2x10AWG)编织屏蔽电缆(UL/CE) | UL 2586 2×6mm2(2x10AWG) | C73: UL 2586黑色D型(芯线：蓝/红)2X6mm2(2x10AWG)编织屏蔽电缆(UL/CE) | UL 2586 2×6mm2(2x10AWG) | D73: 米 | E73: 1070 | F73: 75 | G73: 60 | H73: 65 | J73: 70 | M73: 135 | N73: 15 | O73: 165 | P73: 45 | Q73: 105 | R73: 80 | S73: 45 | T73: 150 | U73: 60
A74: 16 | B74: V9200安装件 | C74: V9200安装件 | D74: 套 | E74: 4 | O74: 1 | S74: 1 | T74: 1 | U74: 1
A75: 17 | B75: V9200风扇模块VFC | C75: V9200风扇模块VFC | D75: 块 | E75: 4 | O75: 1 | S75: 1 | T75: 1 | U75: 1
A76: 18 | B76: V9200工程安装辅料 | C76: V9200工程安装辅料 | D76: 套 | E76: 4 | O76: 1 | S76: 1 | T76: 1 | U76: 1
A77: 19 | B77: V9200机箱 | C77: V9200机箱 | D77: 套 | E77: 4 | O77: 1 | S77: 1 | T77: 1 | U77: 1
A78: 20 | B78: V9200基带处理模块VBPe0d | C78: V9200基带处理模块VBPe0d | D78: 块 | E78: 7 | J78: 1 | M78: 1 | O78: 1 | Q78: 1 | R78: 1 | S78: 1 | T78: 1
A79: 21 | B79: V9200基带处理模块VBPe0e | C79: V9200基带处理模块VBPe0e | D79: 块 | E79: 9 | F79: 1 | G79: 1 | H79: 1 | I79: 1 | K79: 1 | L79: 1 | P79: 1 | U79: 1 | V79: 1
A80: 22 | B80: V9200交换管理模块VSWd0A | C80: V9200交换管理模块VSWd0A | D80: 块 | E80: 4 | O80: 1 | S80: 1 | T80: 1 | U80: 1
A81: 23 | B81: GPS&BDS双模天线 | C81: GPS&BDS双模天线 | D81: 套 | E81: 1 | U81: 1
A82: 24 | B82: GPS&BDS避雷器及辅料 | C82: GPS&BDS避雷器及辅料 | D82: 套 | E82: 1 | U82: 1
A83: 25 | B83: 北斗三&GPS避雷器 | C83: 北斗三&GPS避雷器 | D83: 套 | E83: 4 | O83: 1 | S83: 1 | T83: 1 | U83: 1
A84: 26 | B84: 北斗三&GPS天线及辅料 | C84: 北斗三&GPS天线及辅料 | D84: 套 | E84: 4 | O84: 1 | S84: 1 | T84: 1 | U84: 1
A85: 27 | B85: 多频段智能天线\700～900/1800/FAD\4+4+8通道\独立电调\四频14/16.5/13.5/15.5dBi | C85: 多频段智能天线\700～900/1800/FAD\4+4+8通道\独立电调\四频14/16.5/13.5/15.5dBi | D85: 面 | E85: 3 | K85: 3
A86: 28 | B86: 室内单芯单模光纤跳线 | C86: 室内单芯单模光纤跳线 | D86: 根 | E86: 8 | O86: 2 | S86: 2 | T86: 2 | U86: 2
A87: 29 | B87: 直流电源模块VPD | C87: 直流电源模块VPD | D87: 块 | E87: 4 | O87: 1 | S87: 1 | T87: 1 | U87: 1
A88: 30 | B88: 多频段智能天线\700～900/1800/FAD\4+4+8通道\独立电调\四频14/16.5/13.5/15.5dBi | C88: 多频段智能天线\700～900/1800/FAD\4+4+8通道\独立电调\四频14/16.5/13.5/15.5dBi | D88: 面 | E88: 6 | H88: 3 | P88: 3
A89: 31 | B89: 直流电源分配单元DCPD10B | C89: 直流电源分配单元DCPD10B | D89: 套 | E89: 4 | O89: 1 | S89: 1 | T89: 1 | U89: 1
A90: 32 | B90: DCPD10B安装辅料 | C90: DCPD10B安装辅料 | D90: 套 | E90: 4 | O90: 1 | S90: 1 | T90: 1 | U90: 1
A91: 33 | B91: FDD宏基站\基站硬件\V9200增强型机箱单元\1800+900\中兴\直流 | C91: FDD宏基站\基站硬件\V9200增强型机箱单元\1800+900\中兴\直流 | D91: 套 | E91: 1 | T91: 1
A92: 34 | B92: FIBER-95542-002光纤光缆组件|10米长度：10m;线材： LSZH 7mm两芯单模光缆；B端连接器： LC/PC;A端连接器： LC/PC;传输模式：单模；芯线数量： Nom2pcs; | C92: FIBER-95542-002光纤光缆组件|10米长度：10m;线材： LSZH 7mm两芯单模光缆；B端连接器： LC/PC;A端连接器： LC/PC;传输模式：单模；芯线数量： Nom2pcs; | D92: 根 | E92: 19 | F92: 2 | G92: 2 | H92: 1 | L92: 2 | M92: 2 | O92: 2 | Q92: 2 | S92: 2 | T92: 2 | V92: 2
A93: 35 | B93: FIBER-95542-002光纤光缆组件|15米长度：15m;线材： LSZH 7mm两芯单模光缆；B端连接器： LC/PC;A端连接器： LC/PC;传输模式：单模；芯线数量： Nom2pcs; | C93: FIBER-95542-002光纤光缆组件|15米长度：15m;线材： LSZH 7mm两芯单模光缆；B端连接器： LC/PC;A端连接器： LC/PC;传输模式：单模；芯线数量： Nom2pcs; | D93: 根 | E93: 2 | K93: 2
A94: 36 | B94: FIBER-95542-002光纤光缆组件|20米长度：20m;线材： LSZH 7mm两芯单模光缆；B端连接器： LC/PC;A端连接器： LC/PC;传输模式：单模；芯线数量： Nom2pcs; | C94: FIBER-95542-002光纤光缆组件|20米长度：20m;线材： LSZH 7mm两芯单模光缆；B端连接器： LC/PC;A端连接器： LC/PC;传输模式：单模；芯线数量： Nom2pcs; | D94: 根 | E94: 12 | G94: 1 | I94: 2 | J94: 2 | N94: 1 | P94: 3 | R94: 2 | S94: 1
A95: 37 | B95: FIBER-95542-002光纤光缆组件|30米长度：30m;线材： LSZH 7mm两芯单模光缆；B端连接器： LC/PC;A端连接器： LC/PC;传输模式：单模；芯线数量： Nom2pcs; | C95: FIBER-95542-002光纤光缆组件|30米长度：30m;线材： LSZH 7mm两芯单模光缆；B端连接器： LC/PC;A端连接器： LC/PC;传输模式：单模；芯线数量： Nom2pcs; | D95: 根 | E95: 2 | H95: 1 | J95: 1
A96: 38 | B96: FIBER-96972-001光纤光缆组件|25米长度：25m;线材： LSZH 7mm两芯单模光缆；B端连接器： FC/PC;A端连接器： LC/PC;传输模式：单模；芯线数量： Nom2pcs; | C96: FIBER-96972-001光纤光缆组件|25米长度：25m;线材： LSZH 7mm两芯单模光缆；B端连接器： FC/PC;A端连接器： LC/PC;传输模式：单模；芯线数量： Nom2pcs; | D96: 根 | E96: 5 | F96: 1 | G96: 1 | U96: 3
A97: 39 | B97: FIBER-96972-001|光纤光缆组件|35米|长度:35m;线材:LSZH 7mm两芯单模光缆;B端连接器:FC/PC;A端连接器:LC/PC;传输模式:单模;芯线数量:Nom2pcs;接头型号:LC/PC,FC/PC; | 626792030817 V1.0 | C97: FIBER-96972-001|光纤光缆组件|35米|长度:35m;线材:LSZH 7mm两芯单模光缆;B端连接器:FC/PC;A端连接器:LC/PC;传输模式:单模;芯线数量:Nom2pcs;接头型号:LC/PC,FC/PC; | 626792030817 V1.0 | D97: 根 | E97: 2 | K97: 1 | Q97: 1
A98: 40 | B98: FIBER-96972-001|光纤光缆组件|60米|长度:60m;线材:LSZH 7mm两芯单模光缆;B端连接器:FC/PC;A端连接器:LC/PC;传输模式:单模;芯线数量:Nom2pcs;接头型号:LC/PC,FC/PC; | 626792030817 V1.0 | C98: FIBER-96972-001|光纤光缆组件|60米|长度:60m;线材:LSZH 7mm两芯单模光缆;B端连接器:FC/PC;A端连接器:LC/PC;传输模式:单模;芯线数量:Nom2pcs;接头型号:LC/PC,FC/PC; | 626792030817 V1.0 | D98: 根 | E98: 2 | L98: 1 | V98: 1
A99: 41 | B99: FIBER-96972-001|光纤光缆组件|55米|长度:55m;线材:LSZH 7mm两芯单模光缆;B端连接器:FC/PC;A端连接器:LC/PC;传输模式:单模;芯线数量:Nom2pcs;接头型号:LC/PC,FC/PC; | 626792030817 V1.0 | C99: FIBER-96972-001|光纤光缆组件|55米|长度:55m;线材:LSZH 7mm两芯单模光缆;B端连接器:FC/PC;A端连接器:LC/PC;传输模式:单模;芯线数量:Nom2pcs;接头型号:LC/PC,FC/PC; | 626792030817 V1.0 | D99: 根 | E99: 1 | O99: 1
A100: 42 | B100: FIBER-96972-001|光纤光缆组件|40米|长度:40m;线材:LSZH 7mm两芯单模光缆;B端连接器:FC/PC;A端连接器:LC/PC;传输模式:单模;芯线数量:Nom2pcs;接头型号:LC/PC,FC/PC; | 626792030817 V1.0 | C100: FIBER-96972-001|光纤光缆组件|40米|长度:40m;线材:LSZH 7mm两芯单模光缆;B端连接器:FC/PC;A端连接器:LC/PC;传输模式:单模;芯线数量:Nom2pcs;接头型号:LC/PC,FC/PC; | 626792030817 V1.0 | D100: 根 | E100: 1 | R100: 1
A101: 43 | B101: FIBER-96972-001|光纤光缆组件|50米|长度:50m;线材:LSZH 7mm两芯单模光缆;B端连接器:FC/PC;A端连接器:LC/PC;传输模式:单模;芯线数量:Nom2pcs;接头型号:LC/PC,FC/PC; | 626792030817 V1.0 | C101: FIBER-96972-001|光纤光缆组件|50米|长度:50m;线材:LSZH 7mm两芯单模光缆;B端连接器:FC/PC;A端连接器:LC/PC;传输模式:单模;芯线数量:Nom2pcs;接头型号:LC/PC,FC/PC; | 626792030817 V1.0 | D101: 根 | E101: 2 | M101: 1 | T101: 1
A102: 44 | B102: FIBER-96972-001|光纤光缆组件|90米|长度:90m;线材:LSZH 7mm两芯单模光缆;B端连接器:FC/PC;A端连接器:LC/PC;传输模式:单模;芯线数量:Nom2pcs;接头型号:LC/PC,FC/PC; | 626792030817 V1.0 | C102: FIBER-96972-001|光纤光缆组件|90米|长度:90m;线材:LSZH 7mm两芯单模光缆;B端连接器:FC/PC;A端连接器:LC/PC;传输模式:单模;芯线数量:Nom2pcs;接头型号:LC/PC,FC/PC; | 626792030817 V1.0 | D102: 根 | E102: 1 | I102: 1
...

Sheet Sheet10
F1: 1 | G1: 2 | H1: 3 | I1: 4 | J1: 5 | K1: 6 | L1: 7 | M1: 8 | N1: 9 | O1: 10 | P1: 11 | Q1: 12 | R1: 13 | S1: 14 | T1: 15 | U1: 16 | V1: 17 | W1: 18 | X1: 19 | Y1: 20 | Z1: 21 | AA1: 22 | AB1: 23 | AC1: 24 | AD1: 25 | AE1: 26 | AF1: 27 | AG1: 28 | AH1: 29 | AI1: 30 | AJ1: 31 | AK1: 32 | AL1: 33 | AM1: 34 | AN1: 35 | AO1: 36
F2: 恩平市中山医院+互联网专线+语音专线+新增 | G2: 开平市公安局新昌派出所+互联网专线+搬迁 | H2: 开平市公安局新昌派出思始点+互联网专线+搬迁 | I2: 开平市公安局月山派出所+互联网专线+搬迁 | J2: 开平市中心医院（水口医院） | K2: 广东东方思维科技有限公司 | L2: 开平市美力服装有限公司 | M2: 恩平市供水有限公司+集团专线+搬迁 | N2: 恩平富辉纺织企业有限公司 | O2: 恩平市溢丰纺织有限公司 | P2: 开平水口镇联竹村委会+IPVPN专线+新增 | Q2: 开平市丰优农业开发有限公司 | R2: 恩平三力胶粘制品有限公司+互联网专线+新增 | S2: 恩平市公安消防大队集团专线搬迁 | T2: 开平市翡翠网吧 | U2: 开平市莱尚网咖网吧 | V2: 广发证券股份有限公司江门恩平证券营业部 | W2: 开平市公安局潭江派出所（巡警大对） | X2: 开平市水口镇东桥电镀有限公司 | Y2: 开平市公安局长沙派出所 | Z2: 开平+开平市应急管理局+新增 | AA2: 恩平+恩平市君堂镇人民政府+变更 | AB2: 开平市南大电力工程有限公司 | AC2: 恩平+广东通驿高速公路服务区有限公司大槐服务区+变更 | AD2: 开平+开平市环境卫生管理处+G325义祠路交叉公园内+新增 | AE2: 恩平+恩平市沙湖六乡市场+新增 | AF2: 恩平+恩平市科达声通电子器材厂（分厂）+新增 | AG2: 恩平+恩平市万国商业城开发有限公司+新增 | AH2: 恩平+江苏金江建设有限公司+新增 | AI2: 恩平+恩平市君堂镇中心小学（主校区）+新增 | AJ2: 开平市国营镇海林场（2条互联网专线+电路租用） | AK2: 开平+开平市公安局+南环簕冲红绿灯+新增 | AL2: 开平+广东开平文旅发展集团有限公司+Z端+新增 | AM2: 开平+开平百事通计算机+新增 | AN2: 开平+开平市百合镇消防专职队+新增 | AO2: 江门恩平市御茶餐饮店XWXJ
F3: 光缆 | G3: 城区光缆 | H3: 城区光缆 | I3: 乡镇光缆 | J3: 乡镇光缆 | K3: 乡镇光缆 | L3: 乡镇光缆 | M3: 乡镇光缆 | N3: 乡镇光缆 | O3: 乡镇光缆 | P3: 乡镇光缆 | Q3: 乡镇光缆 | R3: 乡镇光缆 | S3: 城区光缆 | T3: 城区光缆 | U3: 城区光缆 | V3: 城区光缆 | W3: 城区光缆 | X3: 乡镇光缆 | Y3: 乡镇光缆 | Z3: 城区光缆 | AA3: 乡镇光缆 | AB3: 城区光缆 | AC3: 乡镇光缆 | AD3: 城区光缆 | AE3: 乡镇光缆 | AF3: 城区光缆 | AG3: 城区光缆 | AH3: 城区光缆 | AI3: 乡镇光缆 | AJ3: 乡镇光缆 | AK3: 城区光缆 | AL3: 城区光缆 | AM3: 城区光缆 | AN3: 乡镇光缆 | AO3: 城区光缆
A4: 名称 | B4: 规格型号 | C4: 单位 | D4: 单价 | E4: 汇总数量 | F4: 数量 | G4: 数量 | H4: 数量 | I4: 数量 | J4: 数量 | K4: 数量 | L4: 数量 | M4: 数量 | N4: 数量 | O4: 数量 | P4: 数量 | Q4: 数量 | R4: 数量 | S4: 数量 | T4: 数量 | U4: 数量 | V4: 数量 | W4: 数量 | X4: 数量 | Y4: 数量 | Z4: 数量 | AA4: 数量 | AB4: 数量 | AC4: 数量 | AD4: 数量 | AE4: 数量 | AF4: 数量 | AG4: 数量 | AH4: 数量 | AI4: 数量 | AJ4: 数量 | AK4: 数量 | AL4: 数量 | AM4: 数量 | AN4: 数量 | AO4: 数量
A5: PE子管φ25/21mm | B5: φ25/21mm | C5: 米 | D5: 1.13 | E5: 0
A6: PE子管φ32/28mm | B6: φ32/28mm | C6: 米 | D6: 1.47 | E6: 0
A7: PE子管Φ28/24mm | B7: Φ28/24mm | C7: 米 | D7: 1.26 | E7: 0
A8: 5孔防盗塞古 | C8: 个 | D8: 8.5 | E8: 0
A9: 6孔防盗塞古 | C9: 个 | D9: 9 | E9: 0
A10: 子管堵塞内径Φ24mm | B10: 内径Φ24mm | C10: 个 | D10: 0.29 | E10: 0
A11: 子管堵塞内径Φ25mm | B11: 内径Φ25mm | C11: 个 | D11: 0.4 | E11: 0
A12: 12芯熔接配线一体化模块 | C12: 块 | D12: 8.74 | E12: 25 | F12: 0 | G12: 0 | H12: 1 | I12: 0 | J12: 0 | K12: 1 | L12: 1 | M12: 1 | N12: 0 | O12: 1 | P12: 0 | Q12: 0 | R12: 4 | S12: 0 | T12: 0 | U12: 2 | V12: 2 | W12: 0 | X12: 0 | Y12: 0 | Z12: 1 | AA12: 0 | AB12: 1 | AC12: 0 | AD12: 0 | AE12: 1 | AF12: 0 | AG12: 2 | AH12: 0 | AI12: 1 | AJ12: 0 | AK12: 2 | AL12: 0 | AM12: 2 | AN12: 0 | AO12: 2
A13: 综合机柜2200mm*600mm*600mm;配24DDF系统,48芯熔接单元,含2米FC双头尾纤 | B13: 2200mm*600mm*600mm;配24DDF系统,48芯熔接单元,含2米FC双头尾纤 | C13: 架 | D13: 2426.4 | E13: 0
A14: 小型综合机柜600mm*600mm*450mm;配24DDF系统，24芯熔接单元，含2米FC双头尾纤 | B14: 600mm*600mm*450mm;配24DDF系统，24芯熔接单元，含2米FC双头尾纤 | C14: 架 | D14: 420 | E14: 0
A15: D型（户外小型）楼道内普通配纤箱 | B15: 分纤箱 | C15: 台 | D15: 320 | E15: 0
A16: 多媒体机箱 (24芯) | B16: 分纤箱 | C16: 台 | D16: 730.77 | E16: 0
A17: 光纤分配箱48芯 | B17: 分纤箱 | C17: 台 | D17: 197.6 | E17: 0
A18: 光缆分纤箱光缆分纤箱/340×265×120/非金属/壁挂式/24芯/FC | B18: 光缆分纤箱/340×265×120/非金属/壁挂式/24芯/FC | C18: 台 | D18: 130.55 | E18: 0
A19: 光纤分配箱48芯（非金属）光缆分纤箱/420×320×125/非金属/壁挂式/48芯/SC | B19: 光缆分纤箱/420×320×125/非金属/壁挂式/48芯/SC | C19: 台 | D19: 197.6 | E19: 18 | F19: 0 | G19: 0 | H19: 0 | I19: 2 | J19: 1 | K19: 1 | L19: 1 | M19: 0 | N19: 0 | O19: 1 | P19: 0 | Q19: 1 | R19: 1 | S19: 0 | T19: 1 | U19: 0 | V19: 0 | W19: 1 | X19: 0 | Y19: 0 | Z19: 1 | AA19: 0 | AB19: 1 | AC19: 0 | AD19: 1 | AE19: 1 | AF19: 0 | AG19: 0 | AH19: 1 | AI19: 1 | AJ19: 1 | AK19: 0 | AL19: 1 | AM19: 0 | AN19: 0 | AO19: 0 | AP19: 0 | AQ19: 0 | AR19: 0
A20: 入户FTTH多媒体箱 | B20: 12芯分纤箱 | C20: 台 | D20: 173.50427 | E20: 0
A21: 光缆终端盒12芯，挂墙式 | B21: 12芯，挂墙式 | C21: 个 | D21: 160 | E21: 0
A22: 光缆终端盒24芯，挂墙式 | B22: 24芯，挂墙式 | C22: 个 | D22: 190 | E22: 1 | P22: 1
A23: 光缆终端盒48芯，挂墙式 | B23: 48芯，挂墙式 | C23: 个 | D23: 250 | E23: 6 | R23: 1 | S23: 2 | AC23: 1 | AM23: 1 | AN23: 1
A24: 光缆交接箱288芯满配 | B24: 288芯满配 | C24: 套 | D24: 5091.15 | E24: 0
A25: 光缆交接箱576芯满配(单面) | B25: 576芯满配(单面) | C25: 套 | D25: 7723.82 | E25: 1 | AO25: 1
A26: 光缆交接箱576芯满配(双面) | B26: 576芯满配(双面) | C26: 套 | D26: 7534.72 | E26: 0
A27: 光缆交接箱144芯(挂墙） | B27: 144芯(挂墙） | C27: 套 | D27: 2679.42 | E27: 1 | R27: 1
A28: 光缆接头盒48芯（1+4型） | B28: 48芯（1+4型） | C28: 套 | D28: 73.72 | E28: 0
A29: 光缆接头盒96芯（1+4型） | B29: 96芯（1+4型） | C29: 套 | D29: 88.67 | E29: 4 | S29: 1 | AC29: 2 | AN29: 1
A30: 光缆接头盒144芯（1+4型） | B30: 144芯（1+4型） | C30: 套 | D30: 112.2 | E30: 1 | AG30: 1
A31: 管道架空光缆GYTS-12B1 | B31: GYTS-12B1 | C31: 公里 | D31: 1095.16 | E31: 6.528 | G31: 0.081 | H31: 0.204 | I31: 0.159 | J31: 0.125 | K31: 0.152 | L31: 0.33 | M31: 0.617 | N31: 0.545 | O31: 0.119 | R31: 0.411 | T31: 0.038 | V31: 0.1 | W31: 0.089 | Y31: 0.126 | Z31: 0.159 | AA31: 0.205 | AB31: 0.173 | AD31: 0.232 | AE31: 0.14 | AF31: 0.278 | AG31: 0.237 | AH31: 0.313 | AI31: 0.167 | AK31: 0.307 | AL31: 0.053 | AM31: 0.676 | AN31: 0.055 | AO31: 0.437
A32: 管道架空光缆GYTS-24B1 | B32: GYTS-24B1 | C32: 公里 | D32: 1552.2 | E32: 3.242 | P32: 0.032 | Q32: 1.048 | S32: 0.155 | U32: 0.231 | AC32: 0.753 | AG32: 0.104 | AJ32: 0.708 | AM32: 0.211
A33: 管道架空光缆GYTS-48B1 | B33: GYTS-48B1 | C33: 公里 | D33: 2509.31 | E33: 0.44 | R33: 0.44
A34: 管道架空光缆GYTA-96B1 | B34: GYTA-96B1 | C34: 公里 | D34: 4678.8 | E34: 0
A35: 带状光缆GYTA-144B1 | B35: GYTA-144B1 | C35: 公里 | D35: 13801.609 | E35: 0
A36: 带状光缆GYTA-288B1 | B36: GYTA-288B1 | C36: 公里 | D36: 21051.137 | E36: 0
A37: 蝶形光缆 单芯 | B37: 单芯 | C37: 公里 | D37: 156.9 | E37: 0
A38: 蝶形光缆 2芯 | B38: 2芯 | C38: 公里 | D38: 279.64 | E38: 0
A39: 1:8FC/UPC盒式光分路器 | B39: 分光器 | C39: 台 | D39: 36.263 | E39: 0
A40: 1:8SC/UPC盒式光分路器 | B40: 分光器 | C40: 台 | D40: 36.208 | E40: 0
A41: 分光器托板式-成端型-FC/UPC-1:8 | B41: 分光器 | C41: 台 | D41: 36.01 | E41: 0
A42: 分光器托板式-成端型-FC/UPC-1:32 | B42: 分光器 | C42: 台 | D42: 84.74 | E42: 0
A43: 分光器托板式-尾纤型-FC/UPC-2:32 | B43: 分光器 | C43: 台 | D43: 307.22 | E43: 0
A44: 托板式光分路器（1:4） | B44: 分光器 | C44: 台 | D44: 87.18 | E44: 0
A45: 1:8SC/UPC插片式光分路器 | B45: 分光器 | C45: 台 | D45: 48.99 | E45: 0
... A57: 镀锌钢绞线7/2.6（热镀锌 | B57: 7/2.6（热镀锌） | C57: 公斤 | D57: 7.5 | E57: 0
A58: 镀锌钢绞线7/2.2（热镀锌） | B58: 7/2.2（热镀锌） | C58: 公斤 | D58: 7.3 | E58: 207.46 | F58: 0 | G58: 0 | H58: 0 | I58: 0 | J58: 0 | K58: 0 | L58: 4.6 | M58: 0 | N58: 8.05 | O58: 0 | P58: 0 | Q58: 0 | R58: 64.4 | S58: 0 | T58: 0 | U58: 0 | V58: 0 | W58: 0 | X58: 0 | Y58: 0 | Z58: 0 | AA58: 0 | AB58: 0 | AC58: 0 | AD58: 0 | AE58: 0 | AF58: 1.15 | AG58: 0 | AH58: 15.64 | AI58: 0 | AJ58: 45.54 | AK58: 0 | AL58: 0 | AM58: 55.43 | AN58: 12.65 | AO58: 0 | AP58: 0 | AQ58: 0 | AR58: 0
A59: 铜芯阻燃双层塑料电力线 | B59: RVVZ 16mm2 | C59: 米 | D59: 10 | E59: 0
A60: 电力电缆 | B60: RVVZ-1KV-3×2.5mm2 | C60: 米 | D60: 7.06 | E60: 0
A61: 网线 | B61: 五类线（包水晶头） | C61: 米 | D61: 1.5 | E61: 0
A62: 光纤走线槽 | B62: 光纤走线槽\铝合金\200x100mm\1米\承重部位2.0mm | C62: 公斤 | D62: 173.89 | E62: 0
A63: =SUM(F63:AO63) -> 274.67 | F63: =SUM(F5:F61) -> 0 | G63: =SUM(G5:G61) -> 0.081 | H63: =SUM(H5:H61) -> 1.204 | I63: =SUM(I5:I61) -> 2.159 | J63: =SUM(J5:J61) -> 1.125 | K63: =SUM(K5:K61) -> 2.152 | L63: =SUM(L5:L61) -> 6.93 | M63: =SUM(M5:M61) -> 1.617 | ... AO63: =SUM(AO5:AO61) -> 3.437

Sheet Sheet15
A1: 名称 | B1: PE子管φ25/21mm | C1: PE子管φ32/28mm | D1: PE子管Φ28/24mm | E1: 5孔防盗塞古 | F1: 6孔防盗塞古 | G1: 子管堵塞内径Φ24mm | H1: 子管堵塞内径Φ25mm | I1: 12芯熔接配线一体化模块 | J1: 综合机柜2200mm*600mm*600mm;配24DDF系统,48芯熔接单元,含2米FC双头尾纤 | K1: 小型综合机柜600mm*600mm*450mm;配24DDF系统，24芯熔接单元，含2米FC双头尾纤 | L1: D型（户外小型）楼道内普通配纤箱 | M1: 多媒体机箱 (24芯) | N1: 光纤分配箱48芯 | O1: 光缆分纤箱光缆分纤箱/340×265×120/非金属/壁挂式/24芯/FC | P1: 光纤分配箱48芯（非金属）光缆分纤箱/420×320×125/非金属/壁挂式/48芯/SC | Q1: 入户FTTH多媒体箱 | R1: 光缆终端盒12芯，挂墙式 | S1: 光缆终端盒24芯，挂墙式 | T1: 光缆终端盒48芯，挂墙式 | U1: 光缆交接箱288芯满配 | V1: 光缆交接箱576芯满配(单面) | W1: 光缆交接箱576芯满配(双面) | X1: 光缆交接箱144芯(挂墙） | Y1: 光缆接头盒48芯（1+4型） | Z1: 光缆接头盒96芯（1+4型） | AA1: 光缆接头盒144芯（1+4型） | AB1: 管道架空光缆GYTS-12B1 | AC1: 管道架空光缆GYTS-24B1 | AD1: 管道架空光缆GYTS-48B1 | AE1: 管道架空光缆GYTA-96B1 | AF1: 带状光缆GYTA-144B1 | AG1: 带状光缆GYTA-288B1 | AH1: 蝶形光缆 单芯 | AI1: 蝶形光缆 2芯 | AJ1: 1:8FC/UPC盒式光分路器 | AK1: 1:8SC/UPC盒式光分路器 | AL1: 分光器托板式-成端型-FC/UPC-1:8 | AM1: 分光器托板式-成端型-FC/UPC-1:32 | AN1: 分光器托板式-尾纤型-FC/UPC-2:32 | AO1: 托板式光分路器（1:4） | AP1: 1:8SC/UPC插片式光分路器 | AQ1: 1:64FC/UPC托盘式光分路器 | AR1: 单芯跳纤(3.0mm)(G.652D)FC/PC,2米/条 | AS1: 单芯跳纤\2米\FC\FC\G.652D\3mm\单模 | AT1: 单芯跳纤\2米\FC\LC\G.652D\3mm\单模 | AU1: 铠装跳纤单模单芯,FC/PC-FC/PC,20米 | AV1: 铠装跳纤单模单芯,FC/PC-SC/PC,20米 | AW1: 铠装跳纤单芯单模,FC-FC,20米 | AX1: 铠装跳纤单芯单模,FC-FC,30米 | AY1: 尾纤FC-FC-3米单模单芯 | AZ1: 尾纤铠装跳纤单模单芯,FC-SC,3米 | BA1: 尾纤铠装跳纤单芯单模,FC-FC,20米 | BB1: 镀锌钢绞线7/2.6（热镀锌 | BC1: 镀锌钢绞线7/2.2（热镀锌） | BD1: 铜芯阻燃双层塑料电力线 | BE1: 电力电缆 | BF1: 网线 | BG1: 光纤走线槽
A2: 恩平市中山医院+互联网专线+语音专线+新增 | I2: 0 | P2: 0 | BC2: 0
A3: 开平市公安局新昌派出所+互联网专线+搬迁 | I3: 0 | P3: 0 | AB3: 0.081 | BC3: 0
A4: 开平市公安局新昌派出思始点+互联网专线+搬迁 | I4: 1 | P4: 0 | AB4: 0.204 | BC4: 0
A5: 开平市公安局月山派出所+互联网专线+搬迁 | I5: 0 | P5: 2 | AB5: 0.159 | BC5: 0
A6: 开平市中心医院（水口医院） | I6: 0 | P6: 1 | AB6: 0.125 | BC6: 0
A7: 广东东方思维科技有限公司 | I7: 1 | P7: 1 | AB7: 0.152 | BC7: 0
A8: 开平市美力服装有限公司 | I8: 1 | P8: 1 | AB8: 0.33 | AC8: 0 | BC8: 4.6
A9: 恩平市供水有限公司+集团专线+搬迁 | I9: 1 | P9: 0 | AB9: 0.617 | BC9: 0
A10: 恩平富辉纺织企业有限公司 | I10: 0 | P10: 0 | AB10: 0.545 | BC10: 8.05
A11: 恩平市溢丰纺织有限公司 | I11: 1 | P11: 1 | AB11: 0.119 | BC11: 0
A12: 开平水口镇联竹村委会+IPVPN专线+新增 | I12: 0 | P12: 0 | S12: 1 | AC12: 0.032 | BC12: 0
A13: 开平市丰优农业开发有限公司 | I13: 0 | P13: 1 | AC13: 1.048 | BC13: 0
A14: 恩平三力胶粘制品有限公司+互联网专线+新增 | I14: 4 | P14: 1 | T14: 1 | X14: 1 | AB14: 0.411 | AD14: 0.44 | BC14: 64.4
A15: 恩平市公安消防大队集团专线搬迁 | I15: 0 | P15: 0 | T15: 2 | Z15: 1 | AC15: 0.155 | BC15: 0
A16: 开平市翡翠网吧 | I16: 0 | P16: 1 | AB16: 0.038 | BC16: 0
A17: 开平市莱尚网咖网吧 | I17: 2 | P17: 0 | AC17: 0.231 | BC17: 0
A18: 广发证券股份有限公司江门恩平证券营业部 | I18: 2 | P18: 0 | AB18: 0.1 | BC18: 0
A19: 开平市公安局潭江派出所（巡警大对） | I19: 0 | P19: 1 | AB19: 0.089 | BC19: 0
A20: 开平市水口镇东桥电镀有限公司 | I20: 0 | P20: 0 | BC20: 0
A21: 开平市公安局长沙派出所 | I21: 0 | P21: 0 | AB21: 0.126 | BC21: 0
A22: 开平+开平市应急管理局+新增 | I22: 1 | P22: 1 | AB22: 0.159 | BC22: 0
A23: 恩平+恩平市君堂镇人民政府+变更 | I23: 0 | P23: 0 | AB23: 0.205 | BC23: 0
A24: 开平市南大电力工程有限公司 | I24: 1 | P24: 1 | AB24: 0.173 | BC24: 0
A25: 恩平+广东通驿高速公路服务区有限公司大槐服务区+变更 | I25: 0 | P25: 0 | T25: 1 | Z25: 2 | AC25: 0.753 | BC25: 0
A26: 开平+开平市环境卫生管理处+G325义祠路交叉公园内+新增 | I26: 0 | P26: 1 | AB26: 0.232 | BC26: 0
A27: 恩平+恩平市沙湖六乡市场+新增 | I27: 1 | P27: 1 | AB27: 0.14 | BC27: 0
A28: 恩平+恩平市科达声通电子器材厂（分厂）+新增 | I28: 0 | P28: 0 | AB28: 0.278 | BC28: 1.15
A29: 恩平+恩平市万国商业城开发有限公司+新增 | I29: 2 | P29: 0 | AA29: 1 | AB29: 0.237 | AC29: 0.104 | BC29: 0
A30: 恩平+江苏金江建设有限公司+新增 | I30: 0 | P30: 1 | AB30: 0.313 | BC30: 15.64
A31: 恩平+恩平市君堂镇中心小学（主校区）+新增 | I31: 1 | P31: 1 | AB31: 0.167 | BC31: 0
A32: 开平市国营镇海林场（2条互联网专线+电路租用） | I32: 0 | P32: 1 | AC32: 0.708 | BC32: 45.54
A33: 开平+开平市公安局+南环簕冲红绿灯+新增 | I33: 2 | P33: 0 | AB33: 0.307 | BC33: 0
A34: 开平+广东开平文旅发展集团有限公司+Z端+新增 | I34: 0 | P34: 1 | AB34: 0.053 | BC34: 0
A35: 开平+开平百事通计算机+新增 | I35: 2 | P35: 0 | T35: 1 | AB35: 0.676 | AC35: 0.211 | BC35: 55.43
A36: 开平+开平市百合镇消防专职队+新增 | I36: 0 | P36: 0 | T36: 1 | Z36: 1 | AB36: 0.055 | BC36: 12.65
A37: 江门恩平市御茶餐饮店XWXJ | I37: 2 | P37: 0 | V37: 1 | AB37: 0.437 | BC37: 0
A38: =SUM(B38:BG38) -> 274.67 | B38: =SUM(B2:B37) -> 0 | C38: =SUM(C2:C37) -> 0 | D38: =SUM(D2:D37) -> 0 | E38: =SUM(E2:E37) -> 0 | F38: =SUM(F2:F37) -> 0 | G38: =SUM(G2:G37) -> 0 | H38: =SUM(H2:H37) -> 0 | I38: =SUM(I2:I37) -> 25 | ... BG38: =SUM(BG2:BG37) -> 0
A39: =A38-Sheet10!A63 -> 0 | P39: 0 | BC39: 0
A40: =A38+Sheet16!A47 -> 2733.4812 | P40: 0 | BC40: 0

Sheet Sheet11
F1: 1 | G1: 2 | H1: 3 | I1: 4 | J1: 5 | K1: 6 | L1: 7 | M1: 8 | N1: 9 | O1: 10 | P1: 11 | Q1: 12 | R1: 13 | S1: 14 | T1: 15 | U1: 16 | V1: 17 | W1: 18 | X1: 19 | Y1: 20 | Z1: 21 | AA1: 22 | AB1: 23 | AC1: 24 | AD1: 25 | AE1: 26 | AF1: 27 | AG1: 28 | AH1: 29 | AI1: 30 | AJ1: 31 | AK1: 32 | AL1: 33 | AM1: 34 | AN1: 35 | AO1: 36 | AP1: 37 | AQ1: 38 | AR1: 39 | AS1: 40 | AT1: 41 | AU1: 42 | AV1: 43 | AW1: 44 | AX1: 45
F2: 恩平市金丰电子器材厂+语音专线+变更 | G2: 恩平市中山医院+互联网专线+语音专线+新增 | H2: 国家税务总局恩平市税务局前进街办事点+互联网专线+新增+融合 | I2: 国家税务总局恩平市税务局恩城税务分局+互联网专线+新增+融合 | J2: 国家税务总局恩平市税务局圣堂税务分局+互联网专线+新增+融合 | K2: 国家税务总局恩平市税务局大槐税务分局+互联网专线+新增+融合 | L2: 开平市公安局赤坎派出所+互联网专线+搬迁 | M2: 开平市公安局新昌派出所+互联网专线+搬迁 | N2: 开平市公安局新昌派出思始点+互联网专线+搬迁 | O2: 开平市公安局月山派出所+互联网专线+搬迁 | P2: 江门开平市长沙福来旅店预覆盖工程（小微新建） | Q2: 江门开平市味香皇食品厂预覆盖工程（小微新建） | R2: 开平市中心医院（水口医院） | S2: 广东东方思维科技有限公司 | T2: 开平市美力服装有限公司 | U2: 恩平市供水有限公司+集团专线+搬迁 | V2: 恩平富辉纺织企业有限公司 | W2: 恩平市溢丰纺织有限公司 | X2: 开平市翡翠网吧 | Y2: 开平市莱尚网咖网吧 | Z2: 广发证券股份有限公司江门恩平证券营业部 | AA2: 开平市公安局潭江派出所（巡警大对） | AB2: 江门市合山水利工程管理处（互联网专线+电路租用） | AC2: 开平市广侨汽车销售服务有限公司（恩平店）（统一Centrex+互联网专线） | AD2: 开平市公安局长沙派出所 | AE2: 开平+粤顺牧业有限公司+新增 | AF2: 开平+开平市应急管理局+新增 | AG2: 恩平+恩平市君堂镇人民政府+变更 | AH2: 开平+开平市环境卫生管理处+G325义祠路交叉公园内+新增 | AI2: 恩平+恩平市沙湖六乡市场+新增 | AJ2: 恩平+恩平锦兴纺织印染企业有限公司+变更 | AK2: 恩平+恩平市科达声通电子器材厂（分厂）+新增 | AL2: 恩平+恩平市万国商业城开发有限公司+新增 | AM2: 恩平+江苏金江建设有限公司+新增 | AN2: 恩平+恩平市君堂镇中心小学（主校区）+新增 | AO2: 开平+开平市公安局+南环簕冲红绿灯+新增 | AP2: 恩平+恩平市水利局+青南角+二期+新增 | AQ2: 恩平+恩平市水利局+江北灌区+二期+新增 | AR2: 恩平+恩平市水利局+凤子山+二期+新增 | AS2: 跨市+中华人民共和国珠海出入境边防检查总站+开平边检站+新增 | AT2: 开平+广东开平文旅发展集团有限公司+Z端+新增 | AU2: 开平+开平市世界遗产管理中心+新增 | AV2: 开平+开平百事通计算机+新增 | AW2: 开平+开平市百合镇消防专职队+新增 | AX2: 江门恩平市御茶餐饮店XWXJ
F3: 城区 | G3: 设备 | H3: 城区 | I3: 城区 | J3: 乡镇 | K3: 乡镇 | L3: 乡镇 | M3: 城区 | N3: 城区 | O3: 乡镇 | P3: 城区 | Q3: 乡镇 | R3: 乡镇 | S3: 乡镇 | T3: 乡镇 | U3: 乡镇 | V3: 乡镇 | W3: 乡镇 | X3: 城区 | Y3: 城区 | Z3: 城区 | AA3: 城区 | AB3: 乡镇 | AC3: 城区 | AD3: 乡镇 | AE3: 乡镇 | AF3: 城区 | AG3: 乡镇 | AH3: 城区 | AI3: 乡镇 | AJ3: 乡镇 | AK3: 城区 | AL3: 城区 | AM3: 城区 | AN3: 乡镇 | AO3: 城区 | AP3: 乡镇 | AQ3: 乡镇 | AR3: 乡镇 | AS3: 城区 | AT3: 城区 | AU3: 城区 | AV3: 城区 | AW3: 乡镇 | AX3: 城区
A4: 名称 | B4: 规格型号 | C4: 单位 | D4: 单价 | E4: 汇总数量 | F4: 数量 | G4: 数量 | H4: 数量 | I4: 数量 | J4: 数量 | K4: 数量 | L4: 数量 | M4: 数量 | N4: 数量 | O4: 数量 | P4: 数量 | Q4: 数量 | R4: 数量 | S4: 数量 | T4: 数量 | U4: 数量 | V4: 数量 | W4: 数量 | X4: 数量 | Y4: 数量 | Z4: 数量 | AA4: 数量 | AB4: 数量 | AC4: 数量 | AD4: 数量 | AE4: 数量 | AF4: 数量 | AG4: 数量 | AH4: 数量 | AI4: 数量 | AJ4: 数量 | AK4: 数量 | AL4: 数量 | AM4: 数量 | AN4: 数量 | AO4: 数量 | AP4: 数量 | AQ4: 数量 | AR4: 数量 | AS4: 数量 | AT4: 数量 | AU4: 数量 | AV4: 数量 | AW4: 数量 | AX4: 数量
A5: PE子管φ25/21mm | B5: φ25/21mm | C5: 米 | D5: 1.13 | E5: 57 | F5: 0 | G5: 0 | H5: 0 | I5: 0 | J5: 0 | K5: 0 | L5: 0 | M5: 0 | N5: 0 | O5: 0 | P5: 0 | Q5: 0 | R5: 0 | S5: 0 | T5: 0 | U5: 0 | V5: 0 | W5: 0 | X5: 0 | Y5: 0 | Z5: 0 | AA5: 0 | AB5: 0 | AC5: 0 | AD5: 0 | AE5: 0 | AF5: 0 | AG5: 0 | AH5: 0 | AI5: 0 | AJ5: 0 | AK5: 0 | AL5: 0 | AM5: 0 | AN5: 0 | AO5: 0 | AP5: 0 | AQ5: 0 | AR5: 0 | AS5: 0 | AT5: 0 | AU5: 0 | AV5: 0 | AW5: 0 | AX5: 57
A6: PE子管φ32/28mm | B6: φ32/28mm | C6: 米 | D6: 1.47 | E6: 29 | F6: 0 | G6: 0 | H6: 0 | I6: 0 | J6: 0 | K6: 0 | L6: 0 | M6: 0 | N6: 0 | O6: 0 | P6: 0 | Q6: 0 | R6: 0 | S6: 0 | T6: 0 | U6: 0 | V6: 0 | W6: 0 | X6: 0 | Y6: 0 | Z6: 0 | AA6: 0 | AB6: 0 | AC6: 0 | AD6: 0 | AE6: 0 | AF6: 0 | AG6: 0 | AH6: 0 | AI6: 0 | AJ6: 0 | AK6: 0 | AL6: 0 | AM6: 0 | AN6: 0 | AO6: 0 | AP6: 0 | AQ6: 0 | AR6: 0 | AS6: 0 | AT6: 0 | AU6: 0 | AV6: 0 | AW6: 0 | AX6: 29
A7: PE子管Φ28/24mm | B7: Φ28/24mm | C7: 米 | D7: 1.26 | E7: 0
A8: 5孔防盗塞古 | C8: 个 | D8: 8.5 | E8: 0
A9: 6孔防盗塞古 | C9: 个 | D9: 9 | E9: 2 | AX9: 2
A10: 子管堵塞内径Φ24mm | B10: 内径Φ24mm | C10: 个 | D10: 0.29 | E10: 8 | AX10: 8
A11: 子管堵塞内径Φ25mm | B11: 内径Φ25mm | C11: 个 | D11: 0.4 | E11: 4 | AX11: 4
A12: 12芯熔接配线一体化模块 | C12: 块 | D12: 8.74 | E12: 5 | F12: 0 | G12: 0 | H12: 0 | I12: 0 | J12: 0 | K12: 0 | L12: 0 | M12: 0 | N12: 0 | O12: 0 | P12: 0 | Q12: 4 | R12: 0 | S12: 0 | T12: 0 | U12: 0 | V12: 0 | W12: 0 | X12: 0 | Y12: 0 | Z12: 0 | AA12: 0 | AB12: 0 | AC12: 0 | AD12: 0 | AE12: 0 | AF12: 0 | AG12: 0 | AH12: 0 | AI12: 0 | AJ12: 0 | AK12: 0 | AL12: 0 | AM12: 0 | AN12: 0 | AO12: 0 | AP12: 0 | AQ12: 0 | AR12: 0 | AS12: 0 | AT12: 0 | AU12: 0 | AV12: 0 | AW12: 0 | AX12: 1
A13: 综合机柜2200mm*600mm*600mm;配24DDF系统,48芯熔接单元,含2米FC双头尾纤 | B13: 2200mm*600mm*600mm;配24DDF系统,48芯熔接单元,含2米FC双头尾纤 | C13: 架 | D13: 2426.4 | E13: 0
A14: 小型综合机柜600mm*600mm*450mm;配24DDF系统，24芯熔接单元，含2米FC双头尾纤 | B14: 600mm*600mm*450mm;配24DDF系统，24芯熔接单元，含2米FC双头尾纤 | C14: 架 | D14: 420 | E14: 7 | N14: 1 | U14: 1 | V14: 1 | AC14: 1 | AK14: 1 | AL14: 1 | AM14: 1
A15: D型（户外小型）楼道内普通配纤箱 | B15: 分纤箱 | C15: 台 | D15: 320 | E15: 0
A16: 多媒体机箱 (24芯) | B16: 分纤箱 | C16: 台 | D16: 730.77 | E16: 1 | AN16: 1
A17: 光纤分配箱48芯 | B17: 分纤箱 | C17: 台 | D17: 197.6 | E17: 0
A18: 光缆分纤箱光缆分纤箱/340×265×120/非金属/壁挂式/24芯/FC | B18: 光缆分纤箱/340×265×120/非金属/壁挂式/24芯/FC | C18: 台 | D18: 130.55 | E18: 0
A19: 光纤分配箱48芯（非金属）光缆分纤箱/420×320×125/非金属/壁挂式/48芯/SC | B19: 光缆分纤箱/420×320×125/非金属/壁挂式/48芯/SC | C19: 台 | D19: 197.6 | E19: 9 | F19: 0 | G19: 0 | H19: 0 | I19: 0 | J19: 0 | K19: 0 | L19: 0 | M19: 0 | N19: 0 | O19: 0 | P19: 1 | Q19: 7 | R19: 0 | S19: 0 | T19: 0 | U19: 0 | V19: 0 | W19: 0 | X19: 0 | Y19: 0 | AA19: 0 | AB19: 0 | AC19: 0 | AD19: 0 | AE19: 0 | AF19: 0 | AG19: 0 | AH19: 0 | AI19: 0 | AJ19: 0 | AK19: 0 | AL19: 0 | AM19: 0 | AN19: 0 | AO19: 0 | AP19: 0 | AQ19: 0 | AR19: 0 | AS19: 0 | AT19: 0 | AU19: 0 | AV19: 0 | AW19: 0 | AX19: 1
A20: 入户FTTH多媒体箱 | B20: 12芯分纤箱 | C20: 台 | D20: 173.50427 | E20: 0
A21: 光缆终端盒12芯，挂墙式 | B21: 12芯，挂墙式 | C21: 个 | D21: 160 | E21: 0
A22: 光缆终端盒24芯，挂墙式 | B22: 24芯，挂墙式 | C22: 个 | D22: 190 | E22: 0
A23: 光缆终端盒48芯，挂墙式 | B23: 48芯，挂墙式 | C23: 个 | D23: 250 | E23: 0
A24: 光缆交接箱288芯满配 | B24: 288芯满配 | C24: 套 | D24: 5091.15 | E24: 0
A25: 光缆交接箱576芯满配(单面) | B25: 576芯满配(单面) | C25: 套 | D25: 7723.82 | E25: 0
A26: 光缆交接箱576芯满配(双面) | B26: 576芯满配(双面) | C26: 套 | D26: 7534.72 | E26: 0
A27: 光缆交接箱144芯(挂墙） | B27: 144芯(挂墙） | C27: 套 | D27: 2679.42 | E27: 0
A28: 光缆接头盒48芯（1+4型） | B28: 48芯（1+4型） | C28: 套 | D28: 73.72 | E28: 1 | Q28: 1
A29: 光缆接头盒96芯（1+4型） | B29: 96芯（1+4型） | C29: 套 | D29: 88.67 | E29: 0
A30: 光缆接头盒144芯（1+4型） | B30: 144芯（1+4型） | C30: 套 | D30: 112.2 | E30: 0
A31: 管道架空光缆GYTS-12B1 | B31: GYTS-12B1 | C31: 公里 | D31: 1095.16 | E31: 1.106 | P31: 0.05 | Q31: 0.426 | AX31: 0.63
A32: 管道架空光缆GYTS-24B1 | B32: GYTS-24B1 | C32: 公里 | D32: 1552.2 | E32: 0 | L32: 0
A33: 管道架空光缆GYTS-48B1 | B33: GYTS-48B1 | C33: 公里 | D33: 2509.31 | E33: 0.622 | L33: 0 | Q33: 0.622
A34: 管道架空光缆GYTA-96B1 | B34: GYTA-96B1 | C34: 公里 | D34: 4678.8 | E34: 0
A35: 带状光缆GYTA-144B1 | B35: GYTA-144B1 | C35: 公里 | D35: 13801.609 | E35: 0
A36: 带状光缆GYTA-288B1 | B36: GYTA-288B1 | C36: 公里 | D36: 21051.137 | E36: 0
A37: 蝶形光缆 单芯 | B37: 单芯 | C37: 公里 | D37: 156.9 | E37: 7.083 | Q37: 7.083
A38: 蝶形光缆 2芯 | B38: 2芯 | C38: 公里 | D38: 279.64 | E38: 0.747 | P38: 0.747
A39: 1:8FC/UPC盒式光分路器 | B39: 分光器 | C39: 台 | D39: 36.263 | E39: 3 | AX39: 3
A40: 1:8SC/UPC盒式光分路器 | B40: 分光器 | C40: 台 | D40: 36.208 | E40: 25 | P40: 3 | Q40: 22
A41: 分光器托板式-成端型-FC/UPC-1:8 | B41: 分光器 | C41: 台 | D41: 36.01 | E41: 5 | P41: 1 | Q41: 3 | AX41: 1
A42: 分光器托板式-成端型-FC/UPC-1:32 | B42: 分光器 | C42: 台 | D42: 84.74 | E42: 0
A43: 分光器托板式-尾纤型-FC/UPC-2:32 | B43: 分光器 | C43: 台 | D43: 307.22 | E43: 0
A44: 托板式光分路器（1:4） | B44: 分光器 | C44: 台 | D44: 87.18 | E44: 0
A45: 1:8SC/UPC插片式光分路器 | B45: 分光器 | C45: 台 | D45: 48.99 | E45: 0
A46: 1:64FC/UPC托盘式光分路器 | B46: 分光器 | C46: 台 | D46: 208.74 | E46: 0
A47: 单芯跳纤(3.0mm)(G.652D)FC/PC,2米/条 | B47: 尾纤 | C47: 条 | D47: 6.2 | E47: 200 | L47: 2 | M47: 3 | N47: 3 | O47: 2 | P47: 8 | Q47: 50 | R47: 2 | S47: 2 | T47: 3 | X47: 20 | Y47: 20 | AA47: 2 | AB47: 2 | AD47: 3 | AE47: 3 | AF47: 4 | AH47: 2 | AO47: 6 | AS47: 8 | AT47: 4 | AU47: 2 | AV47: 40 | AX47: 9
A48: 单芯跳纤\2米\FC\FC\G.652D\3mm\单模 | B48: 尾纤 | C48: 条 | D48: 5.88 | E48: 44 | H48: 2 | I48: 4 | J48: 4 | K48: 2 | U48: 4 | W48: 6 | Z48: 3 | AC48: 1 | AI48: 1 | AK48: 1 | AL48: 3 | AM48: 3 | AN48: 2 | AQ48: 4 | AR48: 4
A49: 单芯跳纤\2米\FC\LC\G.652D\3mm\单模 | B49: 尾纤 | C49: 条 | D49: 6.01 | E49: 80 | R49: 4 | S49: 4 | X49: 4 | Y49: 4 | AB49: 4 | AE49: 4 | AF49: 4 | AH49: 4 | AO49: 4 | AS49: 6 | AT49: 4 | AU49: 4 | AV49: 28 | AW49: 2
A50: 铠装跳纤单模单芯,FC/PC-FC/PC,20米 | B50: 尾纤 | C50: 条 | D50: 17.44 | E50: 0
A51: 铠装跳纤单模单芯,FC/PC-SC/PC,20米 | B51: 尾纤 | C51: 条 | D51: 22.79 | E51: 84 | P51: 1 | Q51: 3 | AB51: 2 | AF51: 2 | AH51: 2 | AO51: 16 | AT51: 2 | AV51: 54 | AW51: 2
A52: 铠装跳纤单芯单模,FC-FC,20米 | B52: 尾纤 | C52: 条 | D52: 17.44 | E52: 0
A53: 铠装跳纤单芯单模,FC-FC,30米 | B53: 尾纤 | C53: 条 | D53: 36.71 | E53: 0
A54: 尾纤FC-FC-3米单模单芯 | B54: FC-FC-3米单模单芯 | C54: 条 | D54: 5.93 | E54: 0
A55: 尾纤铠装跳纤单模单芯,FC-SC,3米 | B55: 铠装跳纤单模单芯,FC-SC,3米 | C55: 条 | D55: 5.88 | E55: 24 | H55: 2 | I55: 2 | J55: 2 | K55: 2 | W55: 4 | AC55: 1 | AI55: 1 | AK55: 1 | AL55: 1 | AM55: 1 | AN55: 1 | AP55: 2 | AQ55: 2 | AR55: 2
A56: 尾纤铠装跳纤单芯单模,FC-FC,20米 | B56: 铠装跳纤单芯单模,FC-FC,20米 | C56: 条 | D56: 17.44 | E56: 38 | H56: 4 | I56: 2 | J56: 2 | K56: 4 | U56: 2 | W56: 6 | X56: 4 | Y56: 4 | AP56: 2 | AQ56: 4 | AR56: 2 | AS56: 2
A57: 镀锌钢绞线7/2.6（热镀锌 | B57: 7/2.6（热镀锌） | C57: 公斤 | D57: 7.5 | E57: 17.25 | Q57: 7,6 | AX57: 17.25
A58: 镀锌钢绞线7/2.2（热镀锌） | B58: 7/2.2（热镀锌） | C58: 公斤 | D58: 7.3 | E58: 132.0032 | F58: 0 | G58: 0 | H58: 0 | I58: 0 | J58: 0 | K58: 0 | L58: 0 | M58: 0 | N58: 0 | O58: 0 | P58: 0 | Q58: 132.0032 | R58: 0 | S58: 0 | T58: 0 | U58: 0 | V58: 0 | W58: 0 | X58: 0 | Y58: 0 | Z58: 0 | AA58: 0 | AB58: 0 | AC58: 0 | AD58: 0 | AE58: 0 | AF58: 0 | AG58: 0 | AH58: 0 | AI58: 0 | AJ58: 0 | AK58: 0 | AL58: 0 | AM58: 0 | AN58: 0 | AO58: 0 | AP58: 0 | AQ58: 0 | AR58: 0 | AS58: 0 | AT58: 0 | AU58: 0 | AV58: 0 | AW58: 0 | AX58: 0
A59: 铜芯阻燃双层塑料电力线 | B59: RVVZ 16mm2 | C59: 米 | D59: 10 | E59: 0
A60: 电力电缆 | B60: RVVZ-1KV-3×2.5mm2 | C60: 米 | D60: 7.06 | E60: 0
A61: 网线 | B61: 五类线（包水晶头） | C61: 米 | D61: 1.5 | E61: 1674 | F61: 20 | H61: 20 | I61: 20 | J61: 30 | K61: 20 | L61: 10 | M61: 10 | N61: 10 | O61: 10 | R61: 5 | S61: 5 | T61: 22 | U61: 20 | V61: 20 | W61: 40 | X61: 10 | Y61: 10 | Z61: 30 | AA61: 10 | AB61: 10 | AC61: 20 | AD61: 10 | AE61: 6 | AF61: 10 | AG61: 20 | AH61: 10 | AI61: 20 | AJ61: 20 | AK61: 20 | AL61: 20 | AM61: 600 | AN61: 500 | AP61: 20 | AQ61: 20 | AR61: 20 | AS61: 8 | AT61: 10 | AU61: 6 | AW61: 2
A62: 光纤走线槽 | B62: 光纤走线槽\铝合金\200x100mm\1米\承重部位2.0mm | C62: 公斤 | D62: 173.89 | E62: 0
A63: =SUM(F63:AX63) -> 2458.8112 | F63: =SUM(F5:F62) -> 20 | G63: =SUM(G5:G62) -> 0 | H63: =SUM(H5:H62) -> 28 | I63: =SUM(I5:I62) -> 28 | J63: =SUM(J5:J62) -> 38 | K63: =SUM(K5:K62) -> 28 | L63: =SUM(L5:L62) -> 12 | M63: =SUM(M5:M62) -> 13 | ... AX63: =SUM(AX5:AX62) -> 132.88

Sheet Sheet16
A1: 名称 | B1: PE子管φ25/21mm | C1: PE子管φ32/28mm | D1: PE子管Φ28/24mm | E1: 5孔防盗塞古 | F1: 6孔防盗塞古 | G1: 子管堵塞内径Φ24mm | H1: 子管堵塞内径Φ25mm | I1: 12芯熔接配线一体化模块 | J1: 综合机柜2200mm*600mm*600mm;配24DDF系统,48芯熔接单元,含2米FC双头尾纤 | K1: 小型综合机柜600mm*600mm*450mm;配24DDF系统，24芯熔接单元，含2米FC双头尾纤 | L1: D型（户外小型）楼道内普通配纤箱 | M1: 多媒体机箱 (24芯) | N1: 光纤分配箱48芯 | O1: 光缆分纤箱光缆分纤箱/340×265×120/非金属/壁挂式/24芯/FC | P1: 光纤分配箱48芯（非金属）光缆分纤箱/420×320×125/非金属/壁挂式/48芯/SC | Q1: 入户FTTH多媒体箱 | R1: 光缆终端盒12芯，挂墙式 | S1: 光缆终端盒24芯，挂墙式 | T1: 光缆终端盒48芯，挂墙式 | U1: 光缆交接箱288芯满配 | V1: 光缆交接箱576芯满配(单面) | W1: 光缆交接箱576芯满配(双面) | X1: 光缆交接箱144芯(挂墙） | Y1: 光缆接头盒48芯（1+4型） | Z1: 光缆接头盒96芯（1+4型） | AA1: 光缆接头盒144芯（1+4型） | AB1: 管道架空光缆GYTS-12B1 | AC1: 管道架空光缆GYTS-24B1 | AD1: 管道架空光缆GYTS-48B1 | AE1: 管道架空光缆GYTA-96B1 | AF1: 带状光缆GYTA-144B1 | AG1: 带状光缆GYTA-288B1 | AH1: 蝶形光缆 单芯 | AI1: 蝶形光缆 2芯 | AJ1: 1:8FC/UPC盒式光分路器 | AK1: 1:8SC/UPC盒式光分路器 | AL1: 分光器托板式-成端型-FC/UPC-1:8 | AM1: 分光器托板式-成端型-FC/UPC-1:32 | AN1: 分光器托板式-尾纤型-FC/UPC-2:32 | AO1: 托板式光分路器（1:4） | AP1: 1:8SC/UPC插片式光分路器 | AQ1: 1:64FC/UPC托盘式光分路器 | AR1: 单芯跳纤(3.0mm)(G.652D)FC/PC,2米/条 | AS1: 单芯跳纤\2米\FC\FC\G.652D\3mm\单模 | AT1: 单芯跳纤\2米\FC\LC\G.652D\3mm\单模 | AU1: 铠装跳纤单模单芯,FC/PC-FC/PC,20米 | AV1: 铠装跳纤单模单芯,FC/PC-SC/PC,20米 | AW1: 铠装跳纤单芯单模,FC-FC,20米 | AX1: 铠装跳纤单芯单模,FC-FC,30米 | AY1: 尾纤FC-FC-3米单模单芯 | AZ1: 尾纤铠装跳纤单模单芯,FC-SC,3米 | BA1: 尾纤铠装跳纤单芯单模,FC-FC,20米 | BB1: 镀锌钢绞线7/2.6（热镀锌 | BC1: 镀锌钢绞线7/2.2（热镀锌） | BD1: 铜芯阻燃双层塑料电力线 | BE1: 电力电缆 | BF1: 网线 | BG1: 光纤走线槽
A2: 恩平市金丰电子器材厂+语音专线+变更 | B2: 0 | C2: 0 | I2: 0 | P2: 0 | BC2: 0 | BF2: 20
A3: 恩平市中山医院+互联网专线+语音专线+新增 | B3: 0 | C3: 0 | I3: 0 | P3: 0 | BC3: 0
A4: 国家税务总局恩平市税务局前进街办事点+互联网专线+新增+融合 | B4: 0 | C4: 0 | I4: 0 | P4: 0 | AS4: 2 | AZ4: 2 | BA4: 4 | BC4: 0 | BF4: 20
A5: 国家税务总局恩平市税务局恩城税务分局+互联网专线+新增+融合 | B5: 0 | C5: 0 | I5: 0 | P5: 0 | AS5: 4 | AZ5: 2 | BA5: 2 | BC5: 0 | BF5: 20
A6: 国家税务总局恩平市税务局圣堂税务分局+互联网专线+新增+融合 | B6: 0 | C6: 0 | I6: 0 | P6: 0 | AS6: 4 | AZ6: 2 | BA6: 2 | BC6: 0 | BF6: 30
A7: 国家税务总局恩平市税务局大槐税务分局+互联网专线+新增+融合 | B7: 0 | C7: 0 | I7: 0 | P7: 0 | AS7: 2 | AZ7: 2 | BA7: 4 | BC7: 0 | BF7: 20
A8: 开平市公安局赤坎派出所+互联网专线+搬迁 | B8: 0 | C8: 0 | I8: 0 | P8: 0 | AC8: 0 | AD8: 0 | AR8: 2 | BC8: 0 | BF8: 10
A9: 开平市公安局新昌派出所+互联网专线+搬迁 | B9: 0 | C9: 0 | I9: 0 | P9: 0 | AR9: 3 | BC9: 0 | BF9: 10
A10: 开平市公安局新昌派出思始点+互联网专线+搬迁 | B10: 0 | C10: 0 | I10: 0 | K10: 1 | P10: 0 | AR10: 3 | BC10: 0 | BF10: 10
A11: 开平市公安局月山派出所+互联网专线+搬迁 | B11: 0 | C11: 0 | I11: 0 | P11: 0 | AR11: 2 | BC11: 0 | BF11: 10
A12: 江门开平市长沙福来旅店预覆盖工程（小微新建） | B12: 0 | C12: 0 | I12: 0 | P12: 1 | AB12: 0.05 | AI12: 0.747 | AK12: 3 | AL12: 1 | AR12: 8 | AV12: 1 | BC12: 0
A13: 江门开平市味香皇食品厂预覆盖工程（小微新建） | B13: 0 | C13: 0 | I13: 4 | P13: 7 | Y13: 1 | AB13: 0.426 | AD13: 0.622 | AH13: 7.083 | AK13: 22 | AL13: 3 | AR13: 50 | AV13: 3 | BC13: 132.0032
A14: 开平市中心医院（水口医院） | B14: 0 | C14: 0 | I14: 0 | P14: 0 | AR14: 2 | AT14: 4 | BC14: 0 | BF14: 5
A15: 广东东方思维科技有限公司 | B15: 0 | C15: 0 | I15: 0 | P15: 0 | AR15: 2 | AT15: 4 | BC15: 0 | BF15: 5
A16: 开平市美力服装有限公司 | B16: 0 | C16: 0 | I16: 0 | P16: 0 | AR16: 3 | BC16: 0 | BF16: 22
A17: 恩平市供水有限公司+集团专线+搬迁 | B17: 0 | C17: 0 | I17: 0 | K17: 1 | P17: 0 | AS17: 4 | BA17: 2 | BC17: 0 | BF17: 20
A18: 恩平富辉纺织企业有限公司 | B18: 0 | C18: 0 | I18: 0 | K18: 1 | P18: 0 | BC18: 0 | BF18: 20
A19: 恩平市溢丰纺织有限公司 | B19: 0 | C19: 0 | I19: 0 | P19: 0 | AS19: 6 | AZ19: 4 | BA19: 6 | BC19: 0 | BF19: 40
A20: 开平市翡翠网吧 | B20: 0 | C20: 0 | I20: 0 | P20: 0 | AR20: 20 | AT20: 4 | BA20: 4 | BC20: 0 | BF20: 10
A21: 开平市莱尚网咖网吧 | B21: 0 | C21: 0 | I21: 0 | P21: 0 | AR21: 20 | AT21: 4 | BA21: 4 | BC21: 0 | BF21: 10
A22: 广发证券股份有限公司江门恩平证券营业部 | B22: 0 | C22: 0 | I22: 0 | AS22: 3 | BC22: 0 | BF22: 30
A23: 开平市公安局潭江派出所（巡警大对） | B23: 0 | C23: 0 | I23: 0 | P23: 0 | AR23: 2 | BC23: 0 | BF23: 10
A24: 江门市合山水利工程管理处（互联网专线+电路租用） | B24: 0 | C24: 0 | I24: 0 | P24: 0 | AR24: 2 | AT24: 4 | AV24: 2 | BC24: 0 | BF24: 10
A25: 开平市广侨汽车销售服务有限公司（恩平店）（统一Centrex+互联网专线） | B25: 0 | C25: 0 | I25: 0 | K25: 1 | P25: 0 | AS25: 1 | AZ25: 1 | BC25: 0 | BF25: 20
A26: 开平市公安局长沙派出所 | B26: 0 | C26: 0 | I26: 0 | P26: 0 | AR26: 3 | BC26: 0 | BF26: 10
A27: 开平+粤顺牧业有限公司+新增 | B27: 0 | C27: 0 | I27: 0 | P27: 0 | AR27: 3 | AT27: 4 | BC27: 0 | BF27: 6
A28: 开平+开平市应急管理局+新增 | B28: 0 | C28: 0 | I28: 0 | P28: 0 | AR28: 4 | AT28: 4 | AV28: 2 | BC28: 0 | BF28: 10
A29: 恩平+恩平市君堂镇人民政府+变更 | B29: 0 | C29: 0 | I29: 0 | P29: 0 | BC29: 0 | BF29: 20
A30: 开平+开平市环境卫生管理处+G325义祠路交叉公园内+新增 | B30: 0 | C30: 0 | I30: 0 | P30: 0 | AR30: 2 | AT30: 4 | AV30: 2 | BC30: 0 | BF30: 10
A31: 恩平+恩平市沙湖六乡市场+新增 | B31: 0 | C31: 0 | I31: 0 | P31: 0 | AS31: 1 | AZ31: 1 | BC31: 0 | BF31: 20
A32: 恩平+恩平锦兴纺织印染企业有限公司+变更 | B32: 0 | C32: 0 | I32: 0 | P32: 0 | BC32: 0 | BF32: 20
A33: 恩平+恩平市科达声通电子器材厂（分厂）+新增 | B33: 0 | C33: 0 | I33: 0 | K33: 1 | P33: 0 | AS33: 1 | AZ33: 1 | BC33: 0 | BF33: 20
A34: 恩平+恩平市万国商业城开发有限公司+新增 | B34: 0 | C34: 0 | I34: 0 | K34: 1 | P34: 0 | AS34: 3 | AZ34: 1 | BC34: 0 | BF34: 20
A35: 恩平+江苏金江建设有限公司+新增 | B35: 0 | C35: 0 | I35: 0 | K35: 1 | P35: 0 | AS35: 3 | AZ35: 1 | BC35: 0 | BF35: 600
A36: 恩平+恩平市君堂镇中心小学（主校区）+新增 | B36: 0 | C36: 0 | I36: 0 | M36: 1 | P36: 0 | AS36: 2 | AZ36: 1 | BC36: 0 | BF36: 500
A37: 开平+开平市公安局+南环簕冲红绿灯+新增 | B37: 0 | C37: 0 | I37: 0 | P37: 0 | AR37: 6 | AT37: 4 | AV37: 16 | BC37: 0
A38: 恩平+恩平市水利局+青南角+二期+新增 | B38: 0 | C38: 0 | I38: 0 | P38: 0 | AZ38: 2 | BA38: 2 | BC38: 0 | BF38: 20
A39: 恩平+恩平市水利局+江北灌区+二期+新增 | B39: 0 | C39: 0 | I39: 0 | P39: 0 | AS39: 4 | AZ39: 2 | BA39: 4 | BC39: 0 | BF39: 20
A40: 恩平+恩平市水利局+凤子山+二期+新增 | B40: 0 | C40: 0 | I40: 0 | P40: 0 | AS40: 4 | AZ40: 2 | BA40: 2 | BC40: 0 | BF40: 20
A41: 跨市+中华人民共和国珠海出入境边防检查总站+开平边检站+新增 | B41: 0 | C41: 0 | I41: 0 | P41: 0 | AR41: 8 | AT41: 6 | BA41: 2 | BC41: 0 | BF41: 8
A42: 开平+广东开平文旅发展集团有限公司+Z端+新增 | B42: 0 | C42: 0 | I42: 0 | P42: 0 | AR42: 4 | AT42: 4 | AV42: 2 | BC42: 0 | BF42: 10
A43: 开平+开平市世界遗产管理中心+新增 | B43: 0 | C43: 0 | I43: 0 | P43: 0 | AR43: 2 | AT43: 4 | BC43: 0 | BF43: 6
A44: 开平+开平百事通计算机+新增 | B44: 0 | C44: 0 | I44: 0 | P44: 0 | AR44: 40 | AT44: 28 | AV44: 54 | BC44: 0
A45: 开平+开平市百合镇消防专职队+新增 | B45: 0 | C45: 0 | I45: 0 | P45: 0 | AT45: 2 | AV45: 2 | BC45: 0 | BF45: 2
A46: 江门恩平市御茶餐饮店XWXJ | B46: 57 | C46: 29 | F46: 2 | G46: 8 | H46: 4 | I46: 1 | P46: 1 | AB46: 0.63 | AJ46: 3 | AL46: 1 | AR46: 9 | BB46: 17.25 | BC46: 0
A47: =SUM(B47:BF47) -> 2458.8112 | B47: =SUM(B2:B46) -> 57 | C47: =SUM(C2:C46) -> 29 | D47: =SUM(D2:D46) -> 0 | E47: =SUM(E2:E46) -> 0 | F47: =SUM(F2:F46) -> 2 | G47: =SUM(G2:G46) -> 8 | H47: =SUM(H2:H46) -> 4 | I47: =SUM(I2:I46) -> 5 | ... BF47: =SUM(BF2:BF46) -> 1674
A48: =A47-Sheet11!A63 -> 0

Sheet Sheet12
F1: 1 | G1: 2 | H1: 3 | I1: 4 | J1: 5 | K1: 6 | L1: 7 | M1: 8 | N1: 9 | O1: 10 | P1: 11 | Q1: 12 | R1: 13 | S1: 14 | T1: 15 | U1: 16 | V1: 17 | W1: 18 | X1: 19 | Y1: 20 | Z1: 21 | AA1: 22 | AB1: 23 | AC1: 24 | AD1: 25 | AE1: 26 | AF1: 27 | AG1: 28 | AH1: 29 | AI1: 30 | AJ1: 31 | AK1: 32 | AL1: 33 | AM1: 34 | AN1: 35 | AO1: 36 | AP1: 37 | AQ1: 38 | AR1: 39 | AS1: 40 | AT1: 41 | AU1: 42 | AV1: 43 | AW1: 44 | AX1: 45
F2: 恩平市金丰电子器材厂+语音专线+变更 | G2: 恩平市中山医院+互联网专线+语音专线+新增 | H2: 国家税务总局恩平市税务局前进街办事点+互联网专线+新增+融合 | I2: 国家税务总局恩平市税务局恩城税务分局+互联网专线+新增+融合 | J2: 国家税务总局恩平市税务局圣堂税务分局+互联网专线+新增+融合 | K2: 国家税务总局恩平市税务局大槐税务分局+互联网专线+新增+融合 | L2: 开平市公安局赤坎派出所+互联网专线+搬迁 | M2: 开平市公安局新昌派出所+互联网专线+搬迁 | N2: 开平市公安局新昌派出思始点+互联网专线+搬迁 | O2: 开平市公安局月山派出所+互联网专线+搬迁 | P2: 江门开平市长沙福来旅店预覆盖工程（小微新建） | Q2: 江门开平市味香皇食品厂预覆盖工程（小微新建） | R2: 开平市中心医院（水口医院） | S2: 广东东方思维科技有限公司 | T2: 开平市美力服装有限公司 | U2: 恩平市供水有限公司+集团专线+搬迁 | V2: 恩平富辉纺织企业有限公司 | W2: 恩平市溢丰纺织有限公司 | X2: 开平水口镇联竹村委会+IPVPN专线+新增 | Y2: 开平市丰优农业开发有限公司 | Z2: 恩平三力胶粘制品有限公司+互联网专线+新增 | AA2: 恩平市公安消防大队集团专线搬迁 | AB2: 开平市翡翠网吧 | AC2: 开平市莱尚网咖网吧 | AD2: 广发证券股份有限公司江门恩平证券营业部 | AE2: 开平市公安局潭江派出所（巡警大对） | AF2: 开平市水口镇东桥电镀有限公司 | AG2: 江门市合山水利工程管理处（互联网专线+电路租用） | AH2: 开平市广侨汽车销售服务有限公司（恩平店）（统一Centrex+互联网专线） | AI2: 开平市公安局长沙派出所 | AJ2: 开平+粤顺牧业有限公司+新增 | AK2: 开平+开平市应急管理局+新增 | AL2: 恩平+恩平市君堂镇人民政府+变更 | AM2: 开平市南大电力工程有限公司 | AN2: 恩平+广东通驿高速公路服务区有限公司大槐服务区+变更 | AO2: 开平+开平市环境卫生管理处+G325义祠路交叉公园内+新增 | AP2: 恩平+恩平市沙湖六乡市场+新增 | AQ2: 恩平+恩平锦兴纺织印染企业有限公司+变更 | AR2: 恩平+恩平市科达声通电子器材厂（分厂）+新增 | AS2: 恩平+恩平市万国商业城开发有限公司+新增 | AT2: 恩平+江苏金江建设有限公司+新增 | AU2: 恩平+恩平市君堂镇中心小学（主校区）+新增 | AV2: 开平市国营镇海林场（2条互联网专线+电路租用） | AW2: 开平+开平市公安局+南环簕冲红绿灯+新增 | AX2: 恩平+恩平市水利局+青南角+二期+新增 | AY2: 恩平+恩平市水利局+江北灌区+二期+新增 | AZ2: 恩平+恩平市水利局+凤子山+二期+新增 | BA2: 跨市+中华人民共和国珠海出入境边防检查总站+开平边检站+新增 | BB2: 开平+广东开平文旅发展集团有限公司+Z端+新增 | BC2: 开平+开平市世界遗产管理中心+新增 | BD2: 开平+开平百事通计算机+新增 | BE2: 开平+开平市百合镇消防专职队+新增 | BF2: 江门恩平市御茶餐饮店XWXJ
F3: 城区 | G3: 设备 | H3: 城区 | I3: 城区 | J3: 乡镇 | K3: 乡镇 | L3: 乡镇 | M3: 城区 | N3: 城区 | O3: 乡镇 | P3: 城区 | Q3: 乡镇 | R3: 乡镇 | S3: 乡镇 | T3: 乡镇 | U3: 乡镇 | V3: 乡镇 | W3: 乡镇 | X3: 城区 | Y3: 城区 | Z3: 城区 | AA3: 城区 | AB3: 乡镇 | AC3: 城区 | AD3: 乡镇 | AE3: 乡镇 | AF3: 城区 | AG3: 乡镇 | AH3: 城区 | AI3: 乡镇 | AJ3: 乡镇 | AK3: 城区 | AL3: 城区 | AM3: 城区 | AN3: 乡镇 | AO3: 城区 | AP3: 乡镇 | AQ3: 乡镇 | AR3: 乡镇 | AS3: 城区 | AT3: 城区 | AU3: 城区 | AV3: 城区 | AW3: 乡镇 | AX3: 城区
A4: 名称 | B4: 规格型号 | C4: 单位 | D4: 单价 | E4: 汇总数量 | F4: 数量 | G4: 数量 | H4: 数量 | I4: 数量 | J4: 数量 | K4: 数量 | L4: 数量 | M4: 数量 | N4: 数量 | O4: 数量 | P4: 数量 | Q4: 数量 | R4: 数量 | S4: 数量 | T4: 数量 | U4: 数量 | V4: 数量 | W4: 数量 | X4: 数量 | Y4: 数量 | Z4: 数量 | AA4: 数量 | AB4: 数量 | AC4: 数量 | AD4: 数量 | AE4: 数量 | AF4: 数量 | AG4: 数量 | AH4: 数量 | AI4: 数量 | AJ4: 数量 | AK4: 数量 | AL4: 数量 | AM4: 数量 | AN4: 数量 | AO4: 数量 | AP4: 数量 | AQ4: 数量 | AR4: 数量 | AS4: 数量 | AT4: 数量 | AU4: 数量 | AV4: 数量 | AW4: 数量 | AX4: 数量
A5: PE子管 | B5: φ25/21mm | C5: 米 | D5: 1.13 | E5: 57
A6: PE子管 | B6: φ32/28mm | C6: 米 | D6: 1.47 | E6: 29
A7: PE子管 | B7: Φ28/24mm | C7: 米 | D7: 1.26 | E7: 0
A8: 5孔防盗塞古 | C8: 个 | D8: 8.5 | E8: 0
A9: 6孔防盗塞古 | C9: 个 | D9: 9 | E9: 2
A10: 子管堵塞 | B10: 内径Φ24mm | C10: 个 | D10: 0.29 | E10: 8
A11: 子管堵塞 | B11: 内径Φ25mm | C11: 个 | D11: 0.4 | E11: 4
A12: 12芯熔接配线一体化模块 | C12: 块 | D12: 8.74 | E12: 5
A13: 综合机柜 | B13: 2200mm*600mm*600mm;配24DDF系统,48芯熔接单元,含2米FC双头尾纤 | C13: 架 | D13: 2426.4 | E13: 0
A14: 小型综合机柜 | B14: 600mm*600mm*450mm;配24DDF系统，24芯熔接单元，含2米FC双头尾纤 | C14: 架 | D14: 420 | E14: 7
A15: D型（户外小型）楼道内普通配纤箱 | B15: 分纤箱 | C15: 台 | D15: 320 | E15: 0
A16: 多媒体机箱 (24芯) | B16: 分纤箱 | C16: 台 | D16: 730.77 | E16: 1
A17: 光纤分配箱48芯 | B17: 分纤箱 | C17: 台 | D17: 197.6 | E17: 0
A18: 光缆分纤箱 | B18: 光缆分纤箱/340×265×120/非金属/壁挂式/24芯/FC | C18: 台 | D18: 130.55 | E18: 0
A19: 光纤分配箱48芯（非金属） | B19: 光缆分纤箱/420×320×125/非金属/壁挂式/48芯/SC | C19: 台 | D19: 197.6 | E19: 9
A20: 入户FTTH多媒体箱 | B20: 12芯分纤箱 | C20: 台 | D20: 173.50427 | E20: 0
A21: 光缆终端盒 | B21: 12芯，挂墙式 | C21: 个 | D21: 160 | E21: 0
A22: 光缆终端盒 | B22: 24芯，挂墙式 | C22: 个 | D22: 190 | E22: 0
A23: 光缆终端盒 | B23: 48芯，挂墙式 | C23: 个 | D23: 250 | E23: 0
A24: 光缆交接箱 | B24: 288芯满配 | C24: 套 | D24: 5091.15 | E24: 0
... A62: 光纤走线槽 | B62: 光纤走线槽\铝合金\200x100mm\1米\承重部位2.0mm | C62: 公斤 | D62: 173.89 | E62: 0

Sheet Sheet1
H1: 1 | I1: 2 | J1: 3 | K1: 4 | L1: 5 | M1: 6 | N1: 7 | O1: 8 | P1: 9 | Q1: 10 | R1: 11 | S1: 12 | T1: 13 | U1: 14 | V1: 15 | W1: 16 | X1: 17 | Y1: 18 | Z1: 19 | AA1: 20 | AB1: 21 | AC1: 22 | AD1: 23 | AE1: 24 | AF1: 25 | AG1: 26 | AH1: 27 | AI1: 28 | AJ1: 29 | AK1: 30 | AL1: 31 | AM1: 32 | AN1: 33 | AO1: 34 | AP1: 35 | AQ1: 36
H2: 恩平市中山医院+互联网专线+语音专线+新增 | I2: 开平市公安局新昌派出所+互联网专线+搬迁 | J2: 开平市公安局新昌派出思始点+互联网专线+搬迁 | K2: 开平市公安局月山派出所+互联网专线+搬迁 | L2: 开平市中心医院（水口医院） | M2: 广东东方思维科技有限公司 | N2: 开平市美力服装有限公司 | O2: 恩平市供水有限公司+集团专线+搬迁 | P2: 恩平富辉纺织企业有限公司 | Q2: 恩平市溢丰纺织有限公司 | R2: 开平水口镇联竹村委会+IPVPN专线+新增 | S2: 开平市丰优农业开发有限公司 | T2: 恩平三力胶粘制品有限公司+互联网专线+新增 | U2: 恩平市公安消防大队集团专线搬迁 | V2: 开平市翡翠网吧 | W2: 开平市莱尚网咖网吧 | X2: 广发证券股份有限公司江门恩平证券营业部 | Y2: 开平市公安局潭江派出所（巡警大对） | Z2: 开平市水口镇东桥电镀有限公司 | AA2: 开平市公安局长沙派出所 | AB2: 开平+开平市应急管理局+新增 | AC2: 恩平+恩平市君堂镇人民政府+变更 | AD2: 开平市南大电力工程有限公司 | AE2: 恩平+广东通驿高速公路服务区有限公司大槐服务区+变更 | AF2: 开平+开平市环境卫生管理处+G325义祠路交叉公园内+新增 | AG2: 恩平+恩平市沙湖六乡市场+新增 | AH2: 恩平+恩平市科达声通电子器材厂（分厂）+新增 | AI2: 恩平+恩平市万国商业城开发有限公司+新增 | AJ2: 恩平+江苏金江建设有限公司+新增 | AK2: 恩平+恩平市君堂镇中心小学（主校区）+新增 | AL2: 开平市国营镇海林场（2条互联网专线+电路租用） | AM2: 开平+开平市公安局+南环簕冲红绿灯+新增 | AN2: 开平+广东开平文旅发展集团有限公司+Z端+新增 | AO2: 开平+开平百事通计算机+新增 | AP2: 开平+开平市百合镇消防专职队+新增 | AQ2: 江门恩平市御茶餐饮店XWXJ
H3: 光缆 | I3: 城区光缆 | J3: 城区光缆 | K3: 乡镇光缆 | L3: 乡镇光缆 | M3: 乡镇光缆 | N3: 乡镇光缆 | O3: 乡镇光缆 | P3: 乡镇光缆 | Q3: 乡镇光缆 | R3: 乡镇光缆 | S3: 乡镇光缆 | T3: 乡镇光缆 | U3: 城区光缆 | V3: 城区光缆 | W3: 城区光缆 | X3: 城区光缆 | Y3: 城区光缆 | Z3: 乡镇光缆 | AA3: 乡镇光缆 | AB3: 城区光缆 | AC3: 乡镇光缆 | AD3: 城区光缆 | AE3: 乡镇光缆 | AF3: 城区光缆 | AG3: 乡镇光缆 | AH3: 城区光缆 | AI3: 城区光缆 | AJ3: 城区光缆 | AK3: 乡镇光缆 | AL3: 乡镇光缆 | AM3: 城区光缆 | AN3: 城区光缆 | AO3: 城区光缆 | AP3: 乡镇光缆 | AQ3: 城区光缆
A4: 序号 | B4: 定额编号 | C4: 项目名称 | D4: 单位 | E4: 技工 | F4: 普工 | G4: 工程量合计 | H4: 数量 | I4: 数量 | J4: 数量 | K4: 数量 | L4: 数量 | M4: 数量 | N4: 数量 | O4: 数量 | P4: 数量 | Q4: 数量 | R4: 数量 | S4: 数量 | T4: 数量 | U4: 数量 | V4: 数量 | W4: 数量 | X4: 数量 | Y4: 数量 | Z4: 数量 | AA4: 数量 | AB4: 数量 | AC4: 数量 | AD4: 数量 | AE4: 数量 | AF4: 数量 | AG4: 数量 | AH4: 数量 | AI4: 数量 | AJ4: 数量 | AK4: 数量 | AL4: 数量 | AM4: 数量 | AN4: 数量 | AO4: 数量 | AP4: 数量 | AQ4: 数量
A5: 1 | B5: TXL1-001 | C5: 直埋光（电）缆工程施工测量 | D5: 百米 | E5: 0.56 | F5: 0.14 | G5: 2.57 | M5: 0.6 | S5: 0.08 | T5: 0.33 | AE5: 0.27 | AF5: 0.8 | AG5: 0.01 | AH5: 0.05 | AI5: 0.12 | AK5: 0.31
A6: 2 | B6: TXL1-002 | C6: 架空光(电)缆工程施工测量 | D6: 百米 | E6: 0.46 | F6: 0.12 | G6: 66.21 | I6: 0.81 | J6: 1.69 | K6: 1.44 | L6: 0.8 | M6: 0.06 | N6: 2.7 | O6: 5.87 | P6: 4.9 | Q6: 0.89 | R6: 0.12 | S6: 9.84 | T6: 3.48 | U6: 1.05 | V6: 0.23 | W6: 1.98 | X6: 0.7 | Y6: 0.59 | AA6: 0.18 | AB6: 1.41 | AC6: 1.75 | AD6: 1.55 | AE6: 1.03 | AF6: 0.66 | AG6: 0.92 | AH6: 2.32 | AI6: 0.45 | AJ6: 1.79 | AK6: 0.96 | AL6: 6.78 | AN6: 0.23 | AO6: 8.48 | AP6: 0.55
A7: 3 | B7: TXL1-003 | C7: 管道光(电)缆工程施工测量 | D7: 百米 | E7: 0.35 | F7: 0.09 | G7: 21.31 | M7: 0.56 | T7: 4.06 | AA7: 0.9 | AE7: 5.78 | AF7: 0.53 | AG7: 0.01 | AH7: 0.01 | AI7: 2.24 | AJ7: 0.62 | AM7: 2.77 | AO7: 0.06 | AQ7: 3.77
A8: 4 | B8: TXL1-005 | C8: GPS定位 | D8: 点 | E8: 0.05 | F8: 0 | G8: 86 | I8: 2 | J8: 2 | K8: 2 | L8: 2 | M8: 2 | N8: 3 | O8: 2 | P8: 2 | Q8: 2 | R8: 2 | S8: 12 | T8: 6 | U8: 2 | V8: 2 | W8: 2 | X8: 2 | Y8: 2 | AA8: 2 | AB8: 2 | AC8: 2 | AD8: 2 | AE8: 3 | AF8: 2 | AG8: 2 | AH8: 2 | AI8: 2 | AJ8: 2 | AK8: 3 | AL8: 2 | AM8: 2 | AN8: 1 | AO8: 4 | AP8: 2 | AQ8: 2
A9: 5 | B9: TXL1-006 | C9: 单盘检验（单窗口） | D9: 芯盘 | E9: 0.02 | F9: 0 | G9: 0
A10: 6 | B10: TXL1-006-1 | C10: 单盘检验（双窗口） | D10: 芯盘 | E10: 0.024 | F10: 0 | G10: 708 | I10: 12 | J10: 12 | K10: 12 | L10: 12 | M10: 12 | N10: 24 | O10: 12 | P10: 12 | Q10: 12 | R10: 24 | S10: 24 | T10: 60 | U10: 48 | V10: 12 | W10: 24 | X10: 12 | Y10: 12 | AA10: 12 | AB10: 12 | AC10: 12 | AD10: 12 | AE10: 48 | AF10: 12 | AG10: 12 | AH10: 12 | AI10: 36 | AJ10: 24 | AK10: 24 | AL10: 24 | AM10: 12 | AN10: 12 | AO10: 48 | AP10: 12 | AQ10: 48
A11: 7 | B11: TXL1-008 | C11: 人工开挖路面混凝土（100mm以内） | D11: 百平方米 | E11: 3.33 | F11: 24.25 | G11: 0.735 | M11: 0.18 | S11: 0.024 | T11: 0.099 | AE11: 0.081 | AF11: 0.24 | AG11: 0.003 | AH11: 0.015 | AK11: 0.093
A12: 8 | B12: TXL1-009 | C12: 人工开挖路面混凝土（每增加10mm） | D12: 百平方米 | E12: 0.33 | F12: 1.75 | G12: 0
A13: 9 | B13: TXL1-010 | C13: 人工开挖路面沥青柏油（100mm以内） | D13: 百平方米 | E13: 1.88 | F13: 13 | G13: 0
A14: 10 | B14: TXL1-011 | C14: 人工开挖路面沥青柏油（每增加10mm） | D14: 百平方米 | E14: 0.19 | F14: 1.25 | G14: 0
A15: 11 | B15: TXL1-012 | C15: 人工开挖路面砂石（100mm以内） | D15: 百平方米 | E15: 1.04 | F15: 6.29 | G15: 0
A16: 12 | B16: TXL1-013 | C16: 人工开挖路面砂石（每增加10mm） | D16: 百平方米 | E16: 0.09 | F16: 0.59 | G16: 0
A17: 13 | B17: TXL1-014 | C17: 人工开挖路面混凝土砌块 | D17: 百平方米 | E17: 0.31 | F17: 2.88 | G17: 0
A18: 14 | B18: TXL1-015 | C18: 人工开挖路面水泥花砖 | D18: 百平方米 | E18: 0.31 | F18: 2.88 | G18: 0.036 | AI18: 0.036
A19: 15 | B19: TXL1-016 | C19: 人工开挖路面条石 | D19: 百平方米 | E19: 5 | F19: 25.88 | G19: 0
A20: 16 | B20: TXL2-001 | C20: 挖、松填光（电）缆沟及接头坑普通土 | D20: 百立方米 | E20: 0 | F20: 39.38 | G20: 1.323 | M20: 0.324 | S20: 0.0432 | T20: 0.1782 | AE20: 0.1458 | AF20: 0.432 | AG20: 0.0054 | AH20: 0.027 | AK20: 0.1674
A21: 17 | B21: TXL2-002 | C21: 挖、松填光（电）缆沟及接头坑硬土 | D21: 百立方米 | E21: 0 | F21: 51.5 | G21: 0.0648 | AI21: 0.0648
A22: 18 | B22: TXL2-003 | C22: 挖、松填光（电）缆沟及接头坑砂砾土 | D22: 百立方米 | E22: 0 | F22: 62.13 | G22: 0
A23: 19 | B23: TXL2-007 | C23: 挖、夯填光（电）缆沟及接头坑普通土 | D23: 百立方米 | E23: 0 | F23: 40.88 | G23: 0
A24: 20 | B24: TXL2-008 | C24: 挖、夯填光（电）缆沟及接头坑硬土 | D24: 百立方米 | E24: 0 | F24: 55 | G24: 0
A25: 21 | B25: TXL2-009 | C25: 挖、夯填光（电）缆沟及接头坑砂砾土 | D25: 百立方米 | E25: 0 | F25: 71.13 | G25: 0
A26: 22 | B26: TXL2-014 | C26: 手推车倒运土方 | D26: 百立方米 | E26: 0 | F26: 12 | G26: 0
A27: 23 | B27: TXL2-021 | C27: 丘陵、水田、城区敷设埋式光缆36芯以下 | D27: 千米条 | E27: 7.44 | F27: 30.58 | G27: 0.241 | M27: 0.06 | S27: 0.008 | T27: 0.033 | AE27: 0.042 | AF27: 0.08 | AG27: 0.001 | AH27: 0.005 | AI27: 0.012
A28: 24 | B28: TXL2-022 | C28: 丘陵、水田、城区敷设埋式光缆72芯以下 | D28: 千米条 | E28: 10.05 | F28: 33.69 | G28: 0
A29: 25 | B29: TXL2-023 | C29: 丘陵、水田、城区敷设埋式光缆96芯以下 | D29: 千米条 | E29: 12.76 | F29: 36.52 | G29: 0
A30: 26 | B30: TXL2-024 | C30: 丘陵、水田、城区敷设埋式光缆144芯以下 | D30: 千米条 | E30: 15.5 | F30: 38.44 | G30: 0
A31: 27 | B31: TXL2-025 | C31: 丘陵、水田、城区敷设埋式光缆288芯以下 | D31: 千米条 | E31: 17.88 | F31: 41.25 | G31: 0
A32: 28 | B32: TXL2-026 | C32: 丘陵、水田、城区敷设埋式光缆288芯以上 | D32: 千米条 | E32: 22.1 | F32: 45 | G32: 0
A33: 29 | B33: TXL2-027 | C33: 山区敷设埋式光缆36芯以下 | D33: 千米条 | E33: 9.05 | F33: 40.22 | G33: 0
A34: 30 | B34: TXL2-028 | C34: 山区敷设埋式光缆72芯以下 | D34: 千米条 | E34: 12.55 | F34: 43.54 | G34: 0
A35: 31 | B35: TXL2-029 | C35: 山区敷设埋式光缆96芯以下 | D35: 千米条 | E35: 15.86 | F35: 47.1 | G35: 0
A36: 32 | B36: TXL2-030 | C36: 山区敷设埋式光缆144芯以下 | D36: 千米条 | E36: 19.2 | F36: 50.14 | G36: 0
A37: 33 | B37: TXL2-031 | C37: 山区敷设埋式光缆288芯以下 | D37: 千米条 | E37: 22.53 | F37: 53.13 | G37: 0
A38: 34 | B38: TXL2-032 | C38: 山区敷设埋式光缆288芯以上 | D38: 千米条 | E38: 27.5 | F38: 57.46 | G38: 0
A39: 35 | B39: TXL2-033 | C39: 敷设埋式电缆200对以下 | D39: 千米条 | E39: 8.35 | F39: 22.84 | G39: 0
... A42: 38 | B42: TXL2-122 | C42: 埋设标石山区 | D42: 个 | E42: 0.09 | F42: 0.18 | G42: 0
A43: 39 | B43: TXL2-123 | C43: 安装宣传警示牌 | D43: 块 | E43: 0.1 | F43: 0.5 | G43: 2 | S43: 1 | AO43: 1
A44: 40 | B44: TXL2-127 | C44: 安装防雷设施敷设排流线（单条） | D44: 千米 | E44: 2.2 | F44: 8.25 | G44: 0
A45: 41 | B45: TXL3-001 | C45: 立9m以下水泥杆综合土 | D45: 根 | E45: 0.52 | F45: 0.56 | G45: 12 | S45: 9 | T45: 3
A46: 42 | B46: TXL3-004 | C46: 立11m以下水泥杆综合土 | D46: 根 | E46: 0.77 | F46: 0.85 | G46: 0
A47: 43 | B47: TXL3-007 | C47: 立13m以下水泥杆综合土 | D47: 根 | E47: 1.02 | F47: 1.23 | G47: 0
A48: 44 | B48: TXL3-010 | C48: 立13m以下水泥H杆综合土 | D48: 座 | E48: 1.92 | F48: 3.38 | G48: 0
A49: 45 | B49: TXL3-048 | C49: 装水泥撑杆综合土 | D49: 根 | E49: 0.62 | F49: 0.62 | G49: 0
A50: 46 | B50: TXL3-051 | C50: 水泥杆夹板法装7/2.2单股拉线综合土 | D50: 条 | E50: 0.78 | F50: 0.6 | G50: 0
A51: 47 | B51: TXL3-054 | C51: 水泥杆夹板法装7/2.6单股拉线综合土 | D51: 条 | E51: 0.84 | F51: 0.6 | G51: 8 | S51: 5 | T51: 3
A52: 48 | B52: TXL3-057 | C52: 水泥杆夹板法装7/3.0单股拉线综合土 | D52: 条 | E52: 0.98 | F52: 0.6 | G52: 0
A53: 49 | B53: TXL3-142 | C53: 安装拉线隔电子 | D53: 处 | E53: 0.24 | F53: 0.1 | G53: 0
A54: 50 | B54: TXL3-143 | C54: 安装拉线警示保护管 | D54: 处 | E54: 0.2 | F54: 0.2 | G54: 0
A55: 51 | B55: TXL3-144 | C55: 电杆接高装置(单槽钢) | D55: 处 | E55: 0.24 | F55: 0.24 | G55: 0
A56: 52 | B56: TXL3-145 | C56: 电杆接高装置(双槽钢) | D56: 处 | E56: 0.4 | F56: 0.4 | G56: 0
A57: 53 | B57: TXL3-146 | C57: 单杆地线拉线式 | D57: 条 | E57: 0.07 | F57: 0 | G57: 0
A58: 54 | B58: TXL3-147 | C58: 单杆地线直埋式 | D58: 条 | E58: 0.18 | F58: 0.18 | G58: 16 | K58: 1 | P58: 1 | S58: 7 | T58: 1 | AH58: 1 | AL58: 2 | AO58: 2 | AP58: 1
A59: 55 | B59: TXL3-149 | C59: 安装预留缆架 | D59: 架 | E59: 0.1 | F59: 0.1 | G59: 3 | S59: 2 | AL59: 1
A60: 56 | B60: TXL3-150 | C60: 安装吊线保护装置 | D60: m | E60: 0.05 | F60: 0.05 | G60: 0
A61: 57 | B61: TXL3-169 | C61: 水泥杆架设7/2.2吊线（丘陵） | D61: 千米条 | E61: 4.25 | F61: 4.54 | G61: 0
A62: 58 | B62: TXL3-170 | C62: 水泥杆架设7/2.2吊线（山区） | D62: 千米条 | E62: 4.67 | F62: 4.86 | G62: 0
A63: 59 | B63: TXL3-171 | C63: 水泥杆架设7/2.2吊线（城区） | D63: 千米条 | E63: 4.5 | F63: 4.9 | G63: 0
A64: 60 | B64: TXL3-180 | C64: 架设100米以内辅助吊线 | D64: 条档 | E64: 1 | F64: 1 | G64: 0
A65: 61 | B65: TXL3-192 | C65: 挂钩法架设架空光缆丘陵、城区、水田（36芯以下） | D65: 千米条 | E65: 8.68 | F65: 6.86 | G65: 1.658 | O65: 0.066 | S65: 1.01 | T65: 0.068 | AG65: 0.024 | AL65: 0.49
A66: 62 | B66: TXL3-193 | C66: 挂钩法架设架空光缆丘陵、城区、水田（72芯以下） | D66: 千米条 | E66: 9.93 | F66: 7.79 | G66: 0
A67: 63 | B67: TXL3-194 | C67: 挂钩法架设架空光缆丘陵、城区、水田（144芯以下） | D67: 千米条 | E67: 11.05 | F67: 8.75 | G67: 0
A68: 64 | B68: TXL3-195 | C68: 挂钩法架设架空光缆丘陵、城区、水田（288芯以下） | D68: 千米条 | E68: 11.68 | F68: 10.86 | G68: 0
A69: 65 | B69: TXL3-196 | C69: 挂钩法架设架空光缆丘陵、城区、水田（288芯以上） | D69: 千米条 | E69: 12.23 | F69: 11.39 | G69: 0
A70: 66 | B70: TXL3-197 | C70: 挂钩法架设架空光缆山区（36芯以下） | D70: 千米条 | E70: 10.24 | F70: 7.98 | G70: 0
A71: 67 | B71: TXL3-198 | C71: 挂钩法架设架空光缆山区（72芯以下） | D71: 千米条 | E71: 11.72 | F71: 9.13 | G71: 0
A72: 68 | B72: TXL3-199 | C72: 挂钩法架设架空光缆山区（144芯以下） | D72: 千米条 | E72: 12.94 | F72: 11.12 | G72: 0
A73: 69 | B73: TXL3-200 | C73: 挂钩法架设架空光缆山区（288芯以下） | D73: 千米条 | E73: 14.32 | F73: 13.2 | G73: 0
A74: 70 | B74: TXL3-201 | C74: 挂钩法架设架空光缆山区（288芯以上） | D74: 千米条 | E74: 15.25 | F74: 14.1 | G74: 0
A75: 71 | B75: TXL3-218 | C75: 吊线式架空电缆（100对以下） | D75: 千米条 | E75: 9.05 | F75: 10.63 | G75: 0
A76: 72 | B76: TXL4-001 | C76: 布放光(电)缆人孔抽水(积水) | D76: 个 | E76: 0.25 | F76: 0.5 | G76: 0
A77: 73 | B77: TXL4-002 | C77: 布放光(电)缆人孔抽水(流水) | D77: 个 | E77: 0.38 | F77: 1 | G77: 0
A78: 74 | B78: TXL4-003 | C78: 布放光(电)缆手孔抽水 | D78: 个 | E78: 0.13 | F78: 0.25 | G78: 17 | M78: 1 | T78: 2 | AA78: 1 | AE78: 1 | AF78: 1 | AG78: 1 | AH78: 1 | AI78: 2 | AM78: 1 | AO78: 1 | AQ78: 5
A79: 75 | B79: TXL4-004 | C79: 人工敷设塑料子管1孔子管 | D79: 千米 | E79: 4 | F79: 5.57 | G79: 0.264 | M79: 0.055 | S79: 0.008 | T79: 0.033 | AF79: 0.095 | AG79: 0.001 | AI79: 0.012 | AJ79: 0.029 | AK79: 0.031
A80: 76 | B80: TXL4-005 | C80: 人工敷设塑料子管2孔子管 | D80: 千米 | E80: 5.2 | F80: 8.13 | G80: 0
A81: 77 | B81: TXL4-005-1 | C81: 人工敷设塑料子管(6孔子管) | D81: 千米 | E81: 9.32 | F81: 18.14 | G81: 0.025 | AE81: 0.02 | AO81: 0.003 | AQ81: 0.002
A82: 78 | B82: TXL4-005-2 | C82: 人工敷设塑料子管(15孔子管) | D82: 千米 | E82: 27.5 | F82: 69.33 | G82: 0
A83: 79 | B83: TXL4-006 | C83: 人工敷设塑料子管3孔子管 | D83: 千米 | E83: 6.17 | F83: 10.54 | G83: 0
A84: 80 | B84: TXL4-007 | C84: 人工敷设塑料子管4孔子管 | D84: 千米 | E84: 7.13 | F84: 12.96 | G84: 0.089 | T84: 0.089
A85: 81 | B85: TXL4-008 | C85: 人工敷设塑料子管5孔子管 | D85: 千米 | E85: 8.1 | F85: 15.37 | G85: 0
A86: 82 | B86: TXL4-009 | C86: 空闲管孔中人工敷设一带纺织子管 | D86: 公里 | E86: 3.63 | F86: 5.15 | G86: 0
A87: 83 | B87: TXL4-010 | C87: 非空闲管孔中人工敷设一带纺织子管 | D87: 公里 | E87: 6.53 | F87: 9.27 | G87: 0
A88: 84 | B88: TXL4-011 | C88: 敷设管道光缆12芯以下 | D88: 千米条 | E88: 5.5 | F88: 10.94 | G88: 0.848 | M88: 0.071 | AA88: 0.105 | AF88: 0.068 | AG88: 0.027 | AH88: 0.016 | AI88: 0.104 | AJ88: 0.119 | AK88: 0.031 | AM88: 0.307
A89: 85 | B89: TXL4-012 | C89: 敷设管道光缆24芯以下 | D89: 千米条 | E89: 6.83 | F89: 13.08 | G89: 0.767 | AE89: 0.593 | AI89: 0.165 | AO89: 0.009
A90: 86 | B90: TXL4-013 | C90: 敷设管道光缆48芯以下 | D90: 千米条 | E90: 8.02 | F90: 15.35 | G90: 0.877 | T90: 0.44 | AQ90: 0.437
A91: 87 | B91: TXL4-014 | C91: 敷设管道光缆96芯以下 | D91: 千米条 | E91: 9.02 | F91: 17.62 | G91: 0
A92: 88 | B92: TXL4-015 | C92: 敷设管道光缆144芯以下 | D92: 千米条 | E92: 10.4 | F92: 19.87 | G92: 0
A93: 89 | B93: TXL4-016 | C93: 敷设管道光缆288芯以下 | D93: 千米条 | E93: 11.44 | F93: 21.86 | G93: 0
A94: 90 | B94: TXL4-019 | C94: 人工敷设管道电缆200对以下 | D94: 千米条 | E94: 11.76 | F94: 20.03 | G94: 0
A95: 91 | B95: TXL4-024 | C95: 机械敷设管道电缆200对以下 | D95: 千米条 | E95: 9.2 | F95: 15.67 | G95: 0
A96: 92 | B96: TXL4-033 | C96: 打人（手）孔墙洞砖砌人孔3孔管以下 | D96: 处 | E96: 0.36 | F96: 0.36 | G96: 0
A97: 93 | B97: TXL4-034 | C97: 打人（手）孔墙洞砖砌人孔3孔管以上 | D97: 处 | E97: 0.54 | F97: 0.54 | G97: 0
A98: 94 | B98: TXL4-035 | C98: 打人（手）孔墙洞混凝土人孔3孔管以下 | D98: 处 | E98: 0.6 | F98: 0.6 | G98: 0
A99: 95 | B99: TXL4-036 | C99: 打人（手）孔墙洞混凝土人孔3孔管以上 | D99: 处 | E99: 0.9 | F99: 0.9 | G99: 0
A100: 96 | B100: TXL4-037 | C100: 打穿楼墙洞砖墙 | D100: 个 | E100: 0.07 | F100: 0.06 | G100: 21 | I100: 1 | J100: 2 | L100: 1 | N100: 1 | P100: 1 | Q100: 2 | R100: 1 | T100: 1 | X100: 1 | AB100: 1 | AD100: 1 | AH100: 2 | AI100: 2 | AJ100: 1 | AK100: 2 | AO100: 1
A101: 97 | B101: TXL4-038 | C101: 打穿楼墙洞混凝土墙 | D101: 个 | E101: 0.14 | F101: 0.13 | G101: 0
A102: 98 | B102: TXL4-039 | C102: 打穿楼层洞预制板楼层 | D102: 个 | E102: 0.07 | F102: 0.06 | G102: 1 | Q102: 1
...

Sheet Sheet2
A1: 序号 | B1: 1 | C1: 2 | D1: 3 | E1: 4 | F1: 5 | G1: 6 | H1: 7 | I1: 8 | J1: 9 | K1: 10 | L1: 11 | M1: 12 | N1: 13 | O1: 14 | P1: 15 | Q1: 16 | R1: 17 | S1: 18 | T1: 19 | U1: 20 | V1: 21 | W1: 22 | X1: 23 | Y1: 24 | Z1: 25 | AA1: 26 | AB1: 27 | AC1: 28 | AD1: 29 | AE1: 30 | AF1: 31 | AG1: 32 | AH1: 33 | AI1: 34 | AJ1: 35 | AK1: 36 | AL1: 37 | AM1: 38 | AN1: 39 | AO1: 40 | AP1: 41 | AQ1: 42 | AR1: 43 | AS1: 44 | AT1: 45 | AU1: 46 | AV1: 47 | AW1: 48 | AX1: 49 | AY1: 50 | AZ1: 51 | BA1: 52 | BB1: 53 | BC1: 54 | BD1: 55 | BE1: 56 | BF1: 57 | BG1: 58 | BH1: 59 | BI1: 60 | BJ1: 61 | BK1: 62 | BL1: 63 | BM1: 64 | BN1: 65 | BO1: 66 | BP1: 67 | BQ1: 68 | BR1: 69 | BS1: 70 | BT1: 71 | BU1: 72 | BV1: 73 | BW1: 74 | BX1: 75 | BY1: 76 | BZ1: 77 | CA1: 78 | CB1: 79 | CC1: 80 | CD1: 81 | CE1: 82 | CF1: 83 | CG1: 84 | CH1: 85 | CI1: 86 | CJ1: 87 | CK1: 88 | CL1: 89 | CM1: 90 | CN1: 91 | CO1: 92 | CP1: 93 | CQ1: 94 | CR1: 95 | CS1: 96 | CT1: 97 | CU1: 98 | CV1: 99 | CW1: 100 | CX1: 101 | CY1: 102 | CZ1: 103 | DA1: 104 | DB1: 105 | DC1: 106 | DD1: 107 | DE1: 108 | DF1: 109 | DG1: 110 | DH1: 111 | DI1: 112 | DJ1: 113 | DK1: 114 | DL1: 115 | DM1: 116 | DN1: 117 | DO1: 118 | DP1: 119 | DQ1: 120 | DR1: 121 | DS1: 122 | DT1: 123 | DU1: 124 | DV1: 125 | DW1: 126 | DX1: 127 | DY1: 128 | DZ1: 129 | EA1: 130 | EB1: 131 | EC1: 132 | ED1: 133 | EE1: 134 | EF1: 135 | EG1: 136 | EH1: 137 | EI1: 138 | EJ1: 139 | EK1: 140 | EL1: 141 | EM1: 142 | EN1: 143 | EO1: 144 | EP1: 145 | EQ1: 146 | ER1: 147 | ES1: 148 | ET1: 149 | EU1: 150 | EV1: 151 | EW1: 152 | EX1: 153 | EY1: 154 | EZ1: 155 | FA1: 156 | FB1: 157 | FC1: 158 | FD1: 159 | FE1: 160 | FF1: 161 | FG1: 162 | FH1: 163 | FI1: 164 | FJ1: 165 | FK1: 166 | FL1: 167 | FM1: 168 | FN1: 169 | FO1: 170 | FP1: 171 | FQ1: 172 | FR1: 173 | FS1: 174 | FT1: 175 | FU1: 176 | FV1: 177 | FW1: 178 | FX1: 179 | FY1: 180 | FZ1: 181 | GA1: 182 | GB1: 183 | GC1: 184 | GD1: 185 | GE1: 186 | GF1: 187 | GG1: 188 | GH1: 189 | GI1: 190 | GJ1: 191 | GK1: 192 | GL1: 193 | GM1: 194 | GN1: 195 | GO1: 196 | GP1: 197 | GQ1: 198 | GR1: 199 | GS1: 200 | GT1: 201 | GU1: 202 | GV1: 203 | GW1: 204 | GX1: 205 | GY1: 206 | GZ1: 207 | HA1: 208 | HB1: 209 | HC1: 210 | HD1: 211 | HE1: 212 | HF1: 213 | HG1: 214 | HH1: 215 | HI1: 216 | HJ1: 217 | HK1: 218 | HL1: 219 | HM1: 220 | HN1: 221 | HO1: 222 | HP1: 223 | HQ1: 224 | HR1: 225 | HS1: 226 | HT1: 227 | HU1: 228 | HV1: 229 | HW1: 230 | HX1: 231 | HY1: 232 | HZ1: 233 | IA1: 234 | IB1: 235 | IC1: 236 | ID1: 237 | IE1: 238 | IF1: 239 | IG1: 240 | IH1: 241 | II1: 242 | IJ1: 243 | IK1: 244 | IL1: 245 | IM1: 246 | IN1: 247 | IO1: 248 | IP1: 249 | IQ1: 250 | IR1: 251 | IS1: 252 | IT1: 253 | IU1: 254 | IV1: 255 | IW1: 256 | IX1: 257 | IY1: 258 | IZ1: 259 | JA1: 260 | JB1: 261 | JC1: 262 | JD1: 263 | JE1: 264 | JF1: 265 | JG1: 266 | JH1: 267 | JI1: 268 | JJ1: 269 | JK1: 270 | JL1: 271 | JM1: 272 | JN1: 273 | JO1: 274 | JP1: 275 | JQ1: 276 | JR1: 277 | JS1: 278 | JT1: 279 | JU1: 280 | JV1: 281 | JW1: 282 | JX1: 283 | JY1: 284 | JZ1: 285 | KA1: 286 | KB1: 287 | KC1: 288 | KD1: 289 | KE1: 290 | KF1: 291 | KG1: 292 | KH1: 293 | KI1: 294 | KJ1: 295 | KK1: 296 | KL1: 297 | KM1: 298 | KN1: 299 | KO1: 300 | KP1: 301 | KQ1: 302 | KR1: 303 | KS1: 304 | KT1: 305 | KU1: 306 | KV1: 307 | KW1: 308 | KX1: 309 | KY1: 310 | KZ1: 311 | LA1: 312 | LB1: 313 | LC1: 314 | LD1: 315 | LE1: 316 | LF1: 317 | LG1: 318 | LH1: 319 | LI1: 320 | LJ1: 321 | LK1: 322 | LL1: 323 | LM1: 323 | LN1: 323 | LO1: 324 | LP1: 325 | LQ1: 326
A2: 定额编号 | B2: TXL1-001 | C2: TXL1-002 | D2: TXL1-003 | E2: TXL1-005 | F2: TXL1-006 | G2: TXL1-006-1 | H2: TXL1-008 | I2: TXL1-009 | J2: TXL1-010 | K2: TXL1-011 | L2: TXL1-012 | M2: TXL1-013 | N2: TXL1-014 | O2: TXL1-015 | P2: TXL1-016 | Q2: TXL2-001 | R2: TXL2-002 | S2: TXL2-003 | T2: TXL2-007 | U2: TXL2-008 | V2: TXL2-009 | W2: TXL2-014 | X2: TXL2-021 | Y2: TXL2-022 | Z2: TXL2-023 | AA2: TXL2-024 | AB2: TXL2-025 | AC2: TXL2-026 | AD2: TXL2-027 | AE2: TXL2-028 | AF2: TXL2-029 | AG2: TXL2-030 | AH2: TXL2-031 | AI2: TXL2-032 | AJ2: TXL2-033 | AK2: TXL2-109 | AL2: TXL2-121 | AM2: TXL2-122 | AN2: TXL2-123 | AO2: TXL2-127 | AP2: TXL3-001 | AQ2: TXL3-004 | AR2: TXL3-007 | AS2: TXL3-010 | AT2: TXL3-048 | AU2: TXL3-051 | AV2: TXL3-054 | AW2: TXL3-057 | AX2: TXL3-142 | AY2: TXL3-143 | AZ2: TXL3-144 | BA2: TXL3-145 | BB2: TXL3-146 | BC2: TXL3-147 | BD2: TXL3-149 | BE2: TXL3-150 | BF2: TXL3-169 | BG2: TXL3-170 | BH2: TXL3-171 | BI2: TXL3-180 | BJ2: TXL3-192 | BK2: TXL3-193 | BL2: TXL3-194 | BM2: TXL3-195 | BN2: TXL3-196 | BO2: TXL3-197 | BP2: TXL3-198 | BQ2: TXL3-199 | BR2: TXL3-200 | BS2: TXL3-201 | BT2: TXL3-218 | BU2: TXL4-001 | BV2: TXL4-002 | BW2: TXL4-003 | BX2: TXL4-004 | BY2: TXL4-005 | BZ2: TXL4-005-1 | CA2: TXL4-005-2 | CB2: TXL4-006 | CC2: TXL4-007 | CD2: TXL4-008 | CE2: TXL4-009 | CF2: TXL4-010 | CG2: TXL4-011 | CH2: TXL4-012 | CI2: TXL4-013 | CJ2: TXL4-014 | CK2: TXL4-015 | CL2: TXL4-016 | CM2: TXL4-019 | CN2: TXL4-024 | CO2: TXL4-033 | CP2: TXL4-034 | CQ2: TXL4-035 | CR2: TXL4-036 | CS2: TXL4-037 | CT2: TXL4-038 | CU2: TXL4-039 | CV2: TXL4-040 | CW2: TXL4-041 | CX2: TXL4-042 | CY2: TXL4-043 | CZ2: TXL4-044 | DA2: TXL4-045 | DB2: TXL4-046 | DC2: TXL4-047 | DD2: TXL4-048 | DE2: TXL4-049 | DF2: TXL4-050 | DG2: TXL4-051 | DH2: TXL4-052 | DI2: TXL4-053 | DJ2: TXL4-053-1 | DK2: TXL4-053-2 | DL2: TXL4-054 | DM2: TXL4-056 | DN2: TXL4-057 | DO2: TXL4-058 | DP2: TXL4-057-1 | DQ2: TXL4-059 | DR2: TXL4-060 | DS2: TXL4-061 | DT2: TXL4-062 | DU2: TXL5-042 | DV2: TXL5-043 | DW2: TXL5-044 | DX2: TXL5-045 | DY2: TXL5-046 | DZ2: TXL5-049 | EA2: TXL5-050 | EB2: TXL5-051 | EC2: TXL5-052 | ED2: TXL5-054 | EE2: TXL5-055 | EF2: TXL5-056 | EG2: TXL5-057 | EH2: TXL5-058 | EI2: TXL5-068 | EJ2: TXL5-069 | EK2: TXL5-070 | EL2: TXL5-071 | EM2: TXL5-074 | EN2: TXL5-076 | EO2: TXL5-077 | EP2: TXL6-001 | EQ2: TXL6-002 | ER2: TXL6-003 | ES2: TXL6-004 | ET2: TXL6-005 | EU2: TXL6-006 | EV2: TXL6-007 | EW2: TXL6-008 | EX2: TXL6-009 | EY2: TXL6-011 | EZ2: TXL6-013 | FA2: TXL6-015 | FB2: TXL6-018 | FC2: TXL6-027 | FD2: TXL6-029 | FE2: TXL6-073 | FF2: TXL6-073-1 | FG2: TXL6-075 | FH2: TXL6-075-1 | FI2: TXL6-079 | FJ2: TXL6-079-1 | FK2: TXL6-082 | FL2: TXL6-082-1 | FM2: TXL6-072 | FN2: TXL6-072-1 | FO2: TXL6-102 | FP2: TXL6-103 | FQ2: TXL6-104 | FR2: TXL6-106 | FS2: TXL6-108 | FT2: TXL6-110 | FU2: TXL6-112 | FV2: TXL6-113 | FW2: TXL6-114 | FX2: TXL6-115 | FY2: TXL6-116 | FZ2: TXL6-117 | GA2: TXL6-118 | GB2: TXL6-119 | GC2: TXL6-133 | GD2: TXL6-134 | GE2: TXL6-135 | GF2: TXL6-136 | GG2: TXL6-137 | GH2: TXL6-139 | GI2: TXL6-152 | GJ2: TXL6-153 | GK2: TXL6-165 | GL2: TXL6-166 | GM2: TXL6-167 | GN2: TXL6-168 | GO2: TXL6-169 | GP2: TXL6-170 | GQ2: TXL6-199 | GR2: TXL7-004 | GS2: TXL7-005 | GT2: TXL7-006 | GU2: TXL7-007 | GV2: TXL7-008 | GW2: TXL7-009 | GX2: TXL7-010 | GY2: TXL7-014 | GZ2: TXL7-016 | HA2: TXL7-023 | HB2: TXL7-024 | HC2: TXL7-025 | HD2: TXL7-026 | HE2: TXL7-027 | HF2: TXL7-028 | HG2: TXL7-029 | HH2: TXL7-030 | HI2: TXL7-031 | HJ2: TXL7-032 | HK2: TXL7-033 | HL2: TXL7-034 | HM2: TXL7-035 | HN2: TXL7-036 | HO2: TXL7-042 | HP2: TXL7-043 | HQ2: TXL7-044 | HR2: TXL7-045 | HS2: TXL7-046 | HT2: TXL7-056 | HU2: TXL7-064 | HV2: TXL7-065 | HW2: TXL7-066 | HX2: TXL7-067 | HY2: TXL7-077 | HZ2: TXL7-082 | IA2: TSY1-005 | IB2: TSY1-006 | IC2: TSY1-007 | ID2: TSY1-008 | IE2: TSY1-009 | IF2: TSY1-010 | IG2: TSY1-011 | IH2: TSY1-029 | II2: TSY1-030 | IJ2: TSY1-051 | IK2: TSY1-054 | IL2: TSY1-055 | IM2: TSY1-056 | IN2: TSY1-067 | IO2: TSY1-068 | IP2: TSY1-069 | IQ2: TSY1-079 | IR2: TSY1-080 | IS2: TSY1-081 | IT2: TSY1-082 | IU2: TSY1-089 | IV2: TSY1-089 | IW2: TSY1-090 | IX2: TSY1-100 | IY2: TSY2-002 | IZ2: TSY2-003 | JA2: TSY2-005 | JB2: TSY2-006 | JC2: TSY2-007 | JD2: TSY2-008 | JE2: TSY2-009 | JF2: TSY2-010 | JG2: TSY2-011 | JH2: TSY2-012 | JI2: TSY2-013 | JJ2: TSY2-014 | JK2: TSY2-015 | JL2: TSY2-016 | JM2: TSY2-019 | JN2: TSY2-059 | JO2: TSY2-064 | JP2: TSY2-067 | JQ2: TSY2-068 | JR2: TSY2-092 | JS2: TSY2-095 | JT2: TSY2-099 | JU2: TSY2-101 | JV2: TSY3-018 | JW2: TSY3-019 | JX2: TSY3-027 | JY2: TSY3-031 | JZ2: TSY3-032 | KA2: TSY3-033 | KB2: TSY3-034 | KC2: TSY3-035 | KD2: TSY3-036 | KE2: TSY3-047 | KF2: TSY3-063 | KG2: TSY3-064 | KH2: TSY3-066 | KI2: TSY3-067 | KJ2: TSY4-002 | KK2: TSY4-003 | KL2: TSY4-007 | KM2: TSY4-011 | KN2: TSY4-013 | KO2: TSY4-014 | KP2: TSY4-017 | KQ2: TSW2-105 | KR2: TSW2-106 | KS2: TSW2-107 | KT2: TSW2-108 | KU2: TSW2-109 | KV2: TSW2-110 | KW2: TSW2-111 | KX2: TSW2-112 | KY2: TSD3-006 | KZ2: TSD3-050 | LA2: 客响补充 | LB2: 客响补充 | LC2: 客响补充 | LD2: 客响补充 | LE2: 客响补充 | LF2: 客响补充 | LG2: 客响补充 | LH2: 客响补充 | LI2: 客响补充 | LJ2: 客响补充 | LK2: 客响补充 | LL2: 客响补充 | LO2: TXL4-011 | LP2: TSY1-007 | LQ2: TXL4-054
A3: 项目名称 | B3: 直埋光（电）缆工程施工测量 | C3: 架空光(电)缆工程施工测量 | D3: 管道光(电)缆工程施工测量 | E3: GPS定位 | F3: 单盘检验（单窗口） | G3: 单盘检验（双窗口） | H3: 人工开挖路面混凝土（100mm以内） | I3: 人工开挖路面混凝土（每增加10mm） | J3: 人工开挖路面沥青柏油（100mm以内） | K3: 人工开挖路面沥青柏油（每增加10mm） | L3: 人工开挖路面砂石（100mm以内） | M3: 人工开挖路面砂石（每增加10mm） | N3: 人工开挖路面混凝土砌块 | O3: 人工开挖路面水泥花砖 | P3: 人工开挖路面条石 | Q3: 挖、松填光（电）缆沟及接头坑普通土 | R3: 挖、松填光（电）缆沟及接头坑硬土 | S3: 挖、松填光（电）缆沟及接头坑砂砾土 | T3: 挖、夯填光（电）缆沟及接头坑普通土 | U3: 挖、夯填光（电）缆沟及接头坑硬土 | V3: 挖、夯填光（电）缆沟及接头坑砂砾土 | W3: 手推车倒运土方 | X3: 丘陵、水田、城区敷设埋式光缆36芯以下 | Y3: 丘陵、水田、城区敷设埋式光缆72芯以下 | Z3: 丘陵、水田、城区敷设埋式光缆96芯以下 | AA3: 丘陵、水田、城区敷设埋式光缆144芯以下 | AB3: 丘陵、水田、城区敷设埋式光缆288芯以下 | AC3: 丘陵、水田、城区敷设埋式光缆288芯以上 | AD3: 山区敷设埋式光缆36芯以下 | AE3: 山区敷设埋式光缆72芯以下 | AF3: 山区敷设埋式光缆96芯以下 | AG3: 山区敷设埋式光缆144芯以下 | AH3: 山区敷设埋式光缆288芯以下 | AI3: 山区敷设埋式光缆288芯以上 | AJ3: 敷设埋式电缆200对以下 | AK3: 铺管保护（钢管） | AL3: 埋设标石丘陵、水田、城区 | AM3: 埋设标石山区 | AN3: 安装宣传警示牌 | AO3: 安装防雷设施敷设排流线（单条） | AP3: 立9m以下水泥杆综合土 | AQ3: 立11m以下水泥杆综合土 | AR3: 立13m以下水泥杆综合土 | AS3: 立13m以下水泥H杆综合土 | AT3: 装水泥撑杆综合土 | AU3: 水泥杆夹板法装7/2.2单股拉线综合土 | AV3: 水泥杆夹板法装7/2.6单股拉线综合土 | AW3: 水泥杆夹板法装7/3.0单股拉线综合土 | AX3: 安装拉线隔电子 | AY3: 安装拉线警示保护管 | AZ3: 电杆接高装置(单槽钢) | BA3: 电杆接高装置(双槽钢) | BB3: 单杆地线拉线式 | BC3: 单杆地线直埋式 | BD3: 安装预留缆架 | BE3: 安装吊线保护装置 | BF3: 水泥杆架设7/2.2吊线（丘陵） | BG3: 水泥杆架设7/2.2吊线（山区） | BH3: 水泥杆架设7/2.2吊线（城区） | BI3: 架设100米以内辅助吊线 | BJ3: 挂钩法架设架空光缆丘陵、城区、水田（36芯以下） | BK3: 挂钩法架设架空光缆丘陵、城区、水田（72芯以下） | BL3: 挂钩法架设架空光缆丘陵、城区、水田（144芯以下） | BM3: 挂钩法架设架空光缆丘陵、城区、水田（288芯以下） | BN3: 挂钩法架设架空光缆丘陵、城区、水田（288芯以上） | BO3: 挂钩法架设架空光缆山区（36芯以下） | BP3: 挂钩法架设架空光缆山区（72芯以下） | BQ3: 挂钩法架设架空光缆山区（144芯以下） | BR3: 挂钩法架设架空光缆山区（288芯以下） | BS3: 挂钩法架设架空光缆山区（288芯以上） | BT3: 吊线式架空电缆（100对以下） | BU3: 布放光(电)缆人孔抽水(积水) | BV3: 布放光(电)缆人孔抽水(流水) | BW3: 布放光(电)缆手孔抽水 | BX3: 人工敷设塑料子管1孔子管 | BY3: 人工敷设塑料子管2孔子管 | BZ3: 人工敷设塑料子管(6孔子管) | CA3: 人工敷设塑料子管(15孔子管) | CB3: 人工敷设塑料子管3孔子管 | CC3: 人工敷设塑料子管4孔子管 | CD3: 人工敷设塑料子管5孔子管 | CE3: 空闲管孔中人工敷设一带纺织子管 | CF3: 非空闲管孔中人工敷设一带纺织子管 | CG3: 敷设管道光缆12芯以下 | CH3: 敷设管道光缆24芯以下 | CI3: 敷设管道光缆48芯以下 | CJ3: 敷设管道光缆96芯以下 | CK3: 敷设管道光缆144芯以下 | CL3: 敷设管道光缆288芯以下 | CM3: 人工敷设管道电缆200对以下 | CN3: 机械敷设管道电缆200对以下 | CO3: 打人（手）孔墙洞砖砌人孔3孔管以下 | CP3: 打人（手）孔墙洞砖砌人孔3孔管以上 | CQ3: 打人（手）孔墙洞混凝土人孔3孔管以下 | CR3: 打人（手）孔墙洞混凝土人孔3孔管以上 | CS3: 打穿楼墙洞砖墙 | CT3: 打穿楼墙洞混凝土墙 | CU3: 打穿楼层洞预制板楼层 | CV3: 打穿楼层洞混凝土楼层 | CW3: 增装支撑物终端支撑物 | CX3: 增装支撑物中间支撑物 | CY3: 安装引上钢管（Φ50以下）(杆上) | CZ3: 安装引上钢管（Φ50以下）(墙上) | DA3: 安装引上钢管（Φ50以上）(杆上) | DB3: 安装引上钢管（Φ50以上）(墙上) | DC3: 钉固塑料槽板 | DD3: 进局光(电)缆防水封堵 | DE3: 光(电)缆上线洞楼层间防火封堵 | DF3: 穿放引上光缆 | DG3: 穿放引上电缆200对以下 | DH3: 穿放引上电缆200对以上 | DI3: 架设吊线式墙壁光缆 | DJ3: 架设吊线式墙壁光缆（加吊） | DK3: 架设吊线式墙壁 | DL3: 布放钉固式墙壁光缆 | DM3: 墙壁方式敷设蝶形光缆 | DN3: 架设吊线式墙壁电缆200对以下 | DO3: 架设吊线式墙壁电缆200对以上 | DP3: 架设吊线式墙壁电缆200对以下加挂 | DQ3: 布放钉固式墙壁电缆200对以下 | DR3: 布放钉固式墙壁电缆200对以上 | DS3: 架挂自承式墙壁电缆100对以下 | DT3: 架挂自承式墙壁电缆100对以上 | DU3: 钉固式敷设室内通道光缆 | DV3: 竖井引上光缆 | DW3: 槽道光缆 | DX3: 布放槽道电缆 | DY3: 布放顶棚内电缆 | DZ3: 敷设钢管（φ25以内） | EA3: 敷设钢管（φ50以内） | EB3: 敷设硬质PVC管（φ25以内） | EC3: 敷设硬质PVC管（φ50以内） | ED3: 敷设金属线槽（150宽以下） | EE3: 敷设金属线槽（300宽以下） | EF3: 敷设金属线槽（300宽以上） | EG3: 敷设塑料线槽（100宽以下） | EH3: 敷设塑料线槽（100宽以上） | EI3: 管内、暗槽内穿放光缆 | EJ3: 穿放4对对绞电缆 | EK3: 穿放大对数对绞电缆非屏蔽50对以下 | EL3: 穿放大对数对绞电缆非屏蔽100对以下 | EM3: 桥架、线槽、地板内明布光缆 | EN3: 桥架、线槽、网络地板内明布电缆50对以下 | EO3: 桥架、线槽、网络地板内明布电缆100对以下 | EP3: 光缆掏纤（4芯以下） | EQ3: 光缆掏纤（每增加2芯） | ER3: 光缆接续(机械法) | ES3: 现场组装光纤活动连接器 | ET3: 光缆成端接头（束状） | EU3: 光缆成端接头（带状） | EV3: 光缆接续(4芯以下) | EW3: 光缆接续(12芯以下) | EX3: 光缆接续(24芯以下) | EY3: 光缆接续(48芯以下) | EZ3: 光缆接续(72芯以下) | FA3: 光缆接续(96芯以下) | FB3: 光缆接续(144芯以下) | FC3: 8芯带以上带状光缆接续（144芯以下） | FD3: 8芯带以上带状光缆接续（288芯以下） | FE3: 40km以下中继段光缆测试(24芯以下)（单窗口） | FF3: 40km以下中继段光缆测试(24芯以下)（双窗口*1.8） | FG3: 40km以下中继段光缆测试(48芯以下)（单窗口） | FH3: 40km以下中继段光缆测试(48芯以下)（双窗口*1.8） | FI3: 40km以下中继段光缆测试(96芯以下)（单窗口） | FJ3: 40km以下中继段光缆测试(96芯以下)（双窗口*1.8） | FK3: 40km以下中继段光缆测试(144芯以下)（单窗口） | FL3: 40km以下中继段光缆测试(144芯以下)（双窗口*1.8） | FM3: 40km以下中继段光缆测试(12芯以下)（单窗口） | FN3: 40km以下中继段光缆测试(12芯以下)（双窗口*1.8） | FO3: 用户光缆测试(6芯以下) | FP3: 用户光缆测试(12芯以下) | FQ3: 用户光缆测试(24芯以下) | FR3: 用户光缆测试(48芯以下) | FS3: 用户光缆测试(72芯以下) | FT3: 用户光缆测试(96芯以下) | FU3: 用户光缆测试(132芯以下) | FV3: 用户光缆测试(144芯以下) | FW3: 用户光缆测试(168芯以下) | FX3: 用户光缆测试(192芯以下) | FY3: 用户光缆测试(216芯以下) | FZ3: 用户光缆测试(240芯以下) | GA3: 用户光缆测试(264芯以下) | GB3: 用户光缆测试(288芯以下) | GC3: 光纤链路衰减测试（1:4） | GD3: 光纤链路衰减测试（1:8） | GE3: 光纤链路衰减测试（1:16） | GF3: 光纤链路衰减测试（1:32） | GG3: 光纤链路衰减测试（1:64） | GH3: 光分配网（ODN）光纤链路全程测试光纤链路回波损耗测试 | GI3: 布放总配线架成端电缆200对以下 | GJ3: 布放总配线架成端电缆400对以下 | GK3: 布放组线箱成端电缆10对以下 | GL3: 布放组线箱成端电缆20对以下 | GM3: 布放组线箱成端电缆30对以下 | GN3: 布放组线箱成端电缆50对以下 | GO3: 布放组线箱成端电缆100对以下 | GP3: 布放组线箱成端电缆100对以上 | GQ3: 安装多用接头盒 | GR3: 安装机柜、机架(落地式) | GS3: 安装机柜、机架(墙挂式) | GT3: 制作安装抗震底座 | GU3: 安装过线（路）盒（半周长）200以下 | GV3: 安装过线（路）盒（半周长）200以上 | GW3: 安装信息插盒底座明装 | GX3: 安装信息插盒底座砖墙内 | GY3: 安装8位模块式信息插座单口非屏蔽 | GZ3: 安装8位模块式信息插座双口非屏蔽 | HA3: 安装光分纤箱、光分路箱（架空式） | HB3: 安装光分纤箱、光分路箱（墙壁式） | HC3: 安装光缆终端盒 | HD3: 安装光缆接线箱 | HE3: 增（扩）装光纤一体化熔接托盘 | HF3: 机架（箱）内安装光分路器（安装高度1.5m以下） | HG3: 机架（箱）内安装光分路器（安装高度1.5m以上） | HH3: 光分路器与光纤线路插接 | HI3: 光分路器本机测试（1：2） | HJ3: 光分路器本机测试（1：4） | HK3: 光分路器本机测试（1：8） | HL3: 光分路器本机测试（1：16） | HM3: 光分路器本机测试（1：32） | HN3: 光分路器本机测试（1：64） | HO3: 安装光缆落地式交接箱(144芯以下) | HP3: 安装光缆落地式交接箱(288芯以下) | HQ3: 安装光缆落地式交接箱(288芯以上) | HR3: 安装壁挂式光缆交接箱（144芯以下） | HS3: 安装壁挂式光缆交接箱（288芯以下） | HT3: 安装挂墙式交接箱600对以下 | HU3: 制装塑缆分线盒10对以下 | HV3: 制装塑缆分线盒20对以下 | HW3: 制装塑缆分线盒30对以下 | HX3: 制装塑缆分线盒50对以下 | HY3: 安装测试100回线保安排试验排 | HZ3: 安装测试100回线接线排 | IA3: 安装室内有源机柜（落地式） | IB3: 安装室内有源机柜（嵌墙式） | IC3: 安装室内无源机柜（落地式） | ID3: 安装室内无源机柜（嵌墙式） | IE3: 安装室内挂墙机箱（有源） | IF3: 安装室内挂墙机箱（无源） | IG3: 安装电源分配柜、箱架顶式 | IH3: 安装光分配架（整架） | II3: 安装光分配架（子架） | IJ3: 布放音频隔离线（单、双芯） | IK3: 布放SYV类射频同轴电缆（单芯） | IL3: 放绑设备电缆(SYV类射频同轴电缆(多芯)) | IM3: 布放数据电缆（10芯以下） | IN3: 编扎、焊接音频隔离线（单、双芯） | IO3: 编扎、焊(绕、卡)接设备电缆(SYV类射频同轴电缆) | IP3: 编扎、焊接数据电缆（10芯以下） | IQ3: 放、绑软光纤（设备机架之间放、绑）（15m以下） | IR3: 放、绑软光纤（设备机架之间放、绑）（15m以上） | IS3: 光纤分配架内跳线 | IT3: 中间站跳纤 | IU3: 布放单芯电力电缆（16mm2以下) | IV3: 布放单芯电力电缆（16mm2以下)（3*2.5mm2） | IW3: 布放单芯电力电缆（35mm2以下) | IX3: 敷设硬质PVC管/槽 | IY3: 安装集成式小型设备 | IZ3: 增（扩）装、更换光模块 | JA3: 安装测试传输设备接口盘40Gb/s | JB3: 安装测试传输设备接口盘10Gb/s | JC3: 安装测试传输设备接口盘2.5Gb/s | JD3: 安装测试传输设备接口盘622Mb/s | JE3: 安装测试传输设备接口盘155Mb/s光口 | JF3: 安装测试传输设备接口盘155Mb/s电口 | JG3: 安装测试传输设备接口盘45/34Mb/s | JH3: 安装测试传输设备接口盘2Mb/s | JI3: 安装测试传输设备接口盘FE | JJ3: 安装测试传输设备接口盘GE | JK3: 安装测试传输设备接口盘10GE | JL3: 安装测试传输设备接口盘40GE | JM3: 安装测试光电转换模块 | JN3: 线路段光端对测 | JO3: 保护倒换测试 | JP3: 复用设备系统调测以太网光口 | JQ3: 复用设备系统调测以太网电口 | JR3: 安装光网络单元（ONU）(集成式) | JS3: ONU/ONT设备上联光接口本机测试 | JT3: 系统功能验证及性能测试ONU窄带端口64线以下 | JU3: 系统功能验证及性能测试ONU宽带端口64线以下） | JV3: 安装、调测无线局域网接入点（AP）设备 | JW3: 安装调测低端路由器安装路由器（整机型） | JX3: 安装调测低端路由器综合调测低端路由器 | JY3: 安装低端局域网交换机 | JZ3: 安装高、中端局域网交换机安装机箱及电源模块 | KA3: 安装高、中端局域网交换机安装接口板 | KB3: 调测局域网交换机低端 | KC3: 调测局域网交换机高中端 | KD3: 安装调测集线器 | KE3: 安装、测试光电转换器台式 | KF3: 安装网络安全设备低端 | KG3: 安装网络安全设备中端 | KH3: 调测网络安全设备低端 | KI3: 调测网络安全设备中端 | KJ3: 安装架空式集线器设备 | KK3: 安装用户集线器设备 | KL3: 交换机设备硬件调测用户线 | KM3: 交换机设备硬件调测以太网接口电口 | KN3: 交换机设备软件调测用户线 | KO3: 交换机设备软件调测以太网接口 | KP3: 调测用户集线器 | KQ3: 无线局域网交换机安装 | KR3: 无线局域网交换机调测 | KS3: 安装POE供电模块 | KT3: 安装、调测光电转换模块 | KU3: 路由器安装 | KV3: 路由器调测 | KW3: 集线器安装调测 | KX3: 无线局域网接入系统联调 | KY3: 安装24V蓄电池组200Ah以下 | KZ3: 安装、调试交流不间断电源3kVA以下 | LA3: 配合联网调测 | LB3: 语音业务割接 | LC3: 语音业务割接 | LD3: 语音业务割接 | LE3: 语音业务割接 | LF3: 数据业务割接 | LG3: 数据业务割接 | LH3: 数据业务割接 | LI3: 数据业务割接 | LJ3: 二次开通（8门以下） | LK3: 固定天花开口和修复 | LL3: 电表开户报装 | LM3: 拆除集成式小型设备 | LN3: 拆除光电转换器台式 | LO3: 敷设管道光缆12芯以下（回抽） | LP3: 安装室内无源机柜（落地式） | LQ3: 拆除钉固式墙壁光缆
A4: 单位 | B4: 百米 | C4: 百米 | D4: 百米 | E4: 点 | F4: 芯盘 | G4: 芯盘 | H4: 百平方米 | I4: 百平方米 | J4: 百平方米 | K4: 百平方米 | L4: 百平方米 | M4: 百平方米 | N4: 百平方米 | O4: 百平方米 | P4: 百平方米 | Q4: 百立方米 | R4: 百立方米 | S4: 百立方米 | T4: 百立方米 | U4: 百立方米 | V4: 百立方米 | W4: 百立方米 | X4: 千米条 | Y4: 千米条 | Z4: 千米条 | AA4: 千米条 | AB4: 千米条 | AC4: 千米条 | AD4: 千米条 | AE4: 千米条 | AF4: 千米条 | AG4: 千米条 | AH4: 千米条 | AI4: 千米条 | AJ4: 千米条 | AK4: m | AL4: 个 | AM4: 个 | AN4: 块 | AO4: 千米 | AP4: 根 | AQ4: 根 | AR4: 根 | AS4: 座 | AT4: 根 | AU4: 条 | AV4: 条 | AW4: 条 | AX4: 处 | AY4: 处 | AZ4: 处 | BA4: 处 | BB4: 条 | BC4: 条 | BD4: 架 | BE4: m | BF4: 千米条 | BG4: 千米条 | BH4: 千米条 | BI4: 条档 | BJ4: 千米条 | BK4: 千米条 | BL4: 千米条 | BM4: 千米条 | BN4: 千米条 | BO4: 千米条 | BP4: 千米条 | BQ4: 千米条 | BR4: 千米条 | BS4: 千米条 | BT4: 千米条 | BU4: 个 | BV4: 个 | BW4: 个 | BX4: 千米 | BY4: 千米 | BZ4: 千米 | CA4: 千米 | CB4: 千米 | CC4: 千米 | CD4: 千米 | CE4: 公里 | CF4: 公里 | CG4: 千米条 | CH4: 千米条 | CI4: 千米条 | CJ4: 千米条 | CK4: 千米条 | CL4: 千米条 | CM4: 千米条 | CN4: 千米条 | CO4: 处 | CP4: 处 | CQ4: 处 | CR4: 处 | CS4: 个 | CT4: 个 | CU4: 个 | CV4: 个 | CW4: 套 | CX4: 套 | CY4: 根 | CZ4: 根 | DA4: 根 | DB4: 根 | DC4: 百米条 | DD4: 处 | DE4: 处 | DF4: 条 | DG4: 条 | DH4: 条 | DI4: 百米条 | DJ4: 百米条 | DK4: 百米条 | DL4: 百米条 | DM4: 百米条 | DN4: 百米条 | DO4: 百米条 | DP4: 百米条 | DQ4: 百米条 | DR4: 百米条 | DS4: 百米条 | DT4: 百米条 | DU4: 百米条 | DV4: 百米条 | DW4: 百米条 | DX4: 百米条 | DY4: 百米条 | DZ4: 百米 | EA4: 百米 | EB4: 百米 | EC4: 百米 | ED4: 百米 | EE4: 百米 | EF4: 百米 | EG4: 百米 | EH4: 百米 | EI4: 百米条 | EJ4: 百米条 | EK4: 百米条 | EL4: 百米条 | EM4: 百米条 | EN4: 百米条 | EO4: 百米条 | EP4: 处 | EQ4: 处 | ER4: 芯 | ES4: 芯 | ET4: 芯 | EU4: 芯 | EV4: 头 | EW4: 头 | EX4: 头 | EY4: 头 | EZ4: 头 | FA4: 头 | FB4: 头 | FC4: 头 | FD4: 头 | FE4: 中继段 | FF4: 中继段 | FG4: 中继段 | FH4: 中继段 | FI4: 中继段 | FJ4: 中继段 | FK4: 中继段 | FL4: 中继段 | FM4: 中继段 | FN4: 中继段 | FO4: 段 | FP4: 段 | FQ4: 段 | FR4: 段 | FS4: 段 | FT4: 段 | FU4: 段 | FV4: 段 | FW4: 段 | FX4: 段 | FY4: 段 | FZ4: 段 | GA4: 段 | GB4: 段 | GC4: 链路组 | GD4: 链路组 | GE4: 链路组 | GF4: 链路组 | GG4: 链路组 | GH4: 链路组 | GI4: 条 | GJ4: 条 | GK4: 条 | GL4: 条 | GM4: 条 | GN4: 条 | GO4: 条 | GP4: 条 | GQ4: 个 | GR4: 架 | GS4: 架 | GT4: 个 | GU4: 十个 | GV4: 十个 | GW4: 10个 | GX4: 10个 | GY4: 10个 | GZ4: 10个 | HA4: 套 | HB4: 套 | HC4: 套 | HD4: 套 | HE4: 块 | HF4: 台 | HG4: 台 | HH4: 端口 | HI4: 套 | HJ4: 套 | HK4: 套 | HL4: 套 | HM4: 套 | HN4: 套 | HO4: 个 | HP4: 个 | HQ4: 个 | HR4: 个 | HS4: 个 | HT4: 个 | HU4: 个 | HV4: 个 | HW4: 个 | HX4: 个 | HY4: 块 | HZ4: 块 | IA4: 架 | IB4: 架 | IC4: 架 | ID4: 架 | IE4: 架 | IF4: 架 | IG4: 架 | IH4: 架 | II4: 个 | IJ4: 100米条 | IK4: 100米条 | IL4: 100米条 | IM4: 100米条 | IN4: 条 | IO4: 芯条 | IP4: 条 | IQ4: 条 | IR4: 条 | IS4: 条 | IT4: 条 | IU4: 10米条 | IV4: 10米条 | IW4: 10米条 | IX4: 十米 | IY4: 套 | IZ4: 个 | JA4: 端口 | JB4: 端口 | JC4: 端口 | JD4: 端口 | JE4: 端口 | JF4: 端口 | JG4: 端口 | JH4: 端口 | JI4: 端口 | JJ4: 端口 | JK4: 端口 | JL4: 端口 | JM4: 端口 | JN4: 方向·系统 | JO4: 环·系统 | JP4: 端口 | JQ4: 端口 | JR4: 台 | JS4: 端口 | JT4: 10线 | JU4: 10线 | JV4: 套 | JW4: 台 | JX4: 套 | JY4: 台 | JZ4: 台 | KA4: 块 | KB4: 台 | KC4: 台 | KD4: 台 | KE4: 台 | KF4: 台 | KG4: 台 | KH4: 台 | KI4: 台 | KJ4: 台 | KK4: 架 | KL4: 千门 | KM4: 端口 | KN4: 千门 | KO4: 端口 | KP4: 千门 | KQ4: 台 | KR4: 台 | KS4: 个 | KT4: 个 | KU4: 台 | KV4: 台 | KW4: 台 | KX4: 系统 | KY4: 组 | KZ4: 台 | LA4: 条 | LB4: 100线以下 | LC4: 100-300线 | LD4: 300-1000线 | LE4: 1000线以上 | LF4: 10端口以下 | LG4: 10-30端口 | LH4: 30-60端口 | LI4: 60端口以上 | LJ4: 每站点 | LK4: 口 | LL4: 站 | LM4: 套 | LN4: 台 | LO4: 千米条 | LP4: 架 | LQ4: 百米条
A5: 技工 | B5: 0.56 | C5: 0.46 | D5: 0.35 | E5: 0.05 | F5: 0.02 | G5: 0.024 | H5: 3.33 | I5: 0.33 | J5: 1.88 | K5: 0.19 | L5: 1.04 | M5: 0.09 | N5: 0.31 | O5: 0.31 | P5: 5 | Q5: 0 | R5: 0 | S5: 0 | T5: 0 | U5: 0 | V5: 0 | W5: 0 | X5: 7.44 | Y5: 10.05 | Z5: 12.76 | AA5: 15.5 | AB5: 17.88 | AC5: 22.1 | AD5: 9.05 | AE5: 12.55 | AF5: 15.86 | AG5: 19.2 | AH5: 22.53 | AI5: 27.5 | AJ5: 8.35 | AK5: 0.03 | AL5: 0.07 | AM5: 0.09 | AN5: 0.1 | AO5: 2.2 | AP5: 0.52 | AQ5: 0.77 | AR5: 1.02 | AS5: 1.92 | AT5: 0.62 | AU5: 0.78 | AV5: 0.84 | AW5: 0.98 | AX5: 0.24 | AY5: 0.2 | AZ5: 0.24 | BA5: 0.4 | BB5: 0.07 | BC5: 0.18 | BD5: 0.1 | BE5: 0.05 | BF5: 4.25 | BG5: 4.67 | BH5: 4.5 | BI5: 1 | BJ5: 8.68 | BK5: 9.93 | BL5: 11.05 | BM5: 11.68 | BN5: 12.23 | BO5: 10.24 | BP5: 11.72 | BQ5: 12.94 | BR5: 14.32 | BS5: 15.25 | BT5: 9.05 | BU5: 0.25 | BV5: 0.38 | BW5: 0.13 | BX5: 4 | BY5: 5.2 | BZ5: 9.32 | CA5: 27.5 | CB5: 6.17 | CC5: 7.13 | CD5: 8.1 | CE5: 3.63 | CF5: 6.53 | CG5: 5.5 | CH5: 6.83 | CI5: 8.02 | CJ5: 9.02 | CK5: 10.4 | CL5: 11.44 | CM5: 11.76 | CN5: 9.2 | CO5: 0.36 | CP5: 0.54 | CQ5: 0.6 | CR5: 0.9 | CS5: 0.07 | CT5: 0.14 | CU5: 0.07 | CV5: 0.14 | CW5: 0.3 | CX5: 0.15 | CY5: 0.2 | CZ5: 0.25 | DA5: 0.25 | DB5: 0.35 | DC5: 2.6 | DD5: 0.13 | DE5: 0.06 | DF5: 0.52 | DG5: 0.42 | DH5: 0.46 | DI5: 2.75 | DJ5: 1.375 | DK5: 1.925 | DL5: 1.76 | DM5: 2 | DN5: 5.23 | DO5: 5.48 | DP5: 2.615 | DQ5: 3.34 | DR5: 3.59 | DS5: 4.81 | DT5: 5.06 | DU5: 1.2 | DV5: 1.5 | DW5: 0.5 | DX5: 0.65 | DY5: 1 | DZ5: 1.5 | EA5: 2 | EB5: 0.94 | EC5: 1.5 | ED5: 3.27 | EE5: 4.17 | EF5: 7.13 | EG5: 2.45 | EH5: 2.65 | EI5: 0.49 | EJ5: 0.45 | EK5: 0.55 | EL5: 0.7 | EM5: 0.4 | EN5: 0.5 | EO5: 0.6 | EP5: 0.75 | EQ5: 0.09 | ER5: 0.1 | ES5: 0.08 | ET5: 0.15 | EU5: 0.05 | EV5: 0.5 | EW5: 1.5 | EX5: 2.49 | EY5: 4.29 | EZ5: 5.9 | FA5: 7.17 | FB5: 8.1 | FC5: 3.48 | FD5: 4.44 | FE5: 2.58 | FF5: 4.644 | FG5: 4.56 | FH5: 8.208 | FI5: 6.9 | FJ5: 12.42 | FK5: 7.84 | FL5: 14.112 | FM5: 1.84 | FN5: 1.84 | FO5: 0.5 | FP5: 0.92 | FQ5: 1.29 | FR5: 2.28 | FS5: 3.03 | FT5: 3.45 | FU5: 3.82 | FV5: 3.92 | FW5: 4.18 | FX5: 4.52 | FY5: 4.81 | FZ5: 5.04 | GA5: 5.37 | GB5: 5.66 | GC5: 0.45 | GD5: 0.6 | GE5: 0.75 | GF5: 0.85 | GG5: 0.93 | GH5: 0.1 | GI5: 3.12 | GJ5: 6.08 | GK5: 0.3 | GL5: 0.46 | GM5: 0.61 | GN5: 1.08 | GO5: 1.55 | GP5: 2.6 | GQ5: 1.1 | GR5: 1.25 | GS5: 2.25 | GT5: 1.67 | GU5: 0 | GV5: 0.9 | GW5: 0.4 | GX5: 0.98 | GY5: 0.45 | GZ5: 0.75 | HA5: 0.56 | HB5: 0.5 | HC5: 0.3 | HD5: 0.55 | HE5: 0.1 | HF5: 0.2 | HG5: 0.4 | HH5: 0.03 | HI5: 0.16 | HJ5: 0.29 | HK5: 0.4 | HL5: 0.5 | HM5: 0.61 | HN5: 0.7 | HO5: 0.67 | HP5: 0.78 | HQ5: 0.94 | HR5: 1.07 | HS5: 1.34 | HT5: 2.9 | HU5: 0.48 | HV5: 0.66 | HW5: 1.03 | HX5: 1.27 | HY5: 0.75 | HZ5: 0.4 | IA5: 1.86 | IB5: 4.05 | IC5: 1.61 | ID5: 2.79 | IE5: 1.2 | IF5: 0.96 | IG5: 1 | IH5: 2.42 | II5: 0.19 | IJ5: 0.8 | IK5: 1 | IL5: 1.35 | IM5: 0.71 | IN5: 0.06 | IO5: 0.08 | IP5: 0.08 | IQ5: 0.29 | IR5: 0.46 | IS5: 0.13 | IT5: 0.7 | IU5: 0.18 | IV5: 0.36 | IW5: 0.25 | IX5: 0.65 | IY5: 0.85 | IZ5: 0.05 | JA5: 5.55 | JB5: 4.8 | JC5: 1.35 | JD5: 3.15 | JE5: 2.4 | JF5: 1.95 | JG5: 0.9 | JH5: 0.75 | JI5: 0.75 | JJ5: 3.3 | JK5: 5.25 | JL5: 7.8 | JM5: 0.5 | JN5: 0.95 | JO5: 1.5 | JP5: 0.35 | JQ5: 0.25 | JR5: 0.5 | JS5: 0.1 | JT5: 0.2 | JU5: 0.5 | JV5: 0.5 | JW5: 1.25 | JX5: 0.5 | JY5: 1.25 | JZ5: 1.2 | KA5: 0.5 | KB5: 0.5 | KC5: 1.25 | KD5: 0.5 | KE5: 0.5 | KF5: 1.05 | KG5: 1.55 | KH5: 1.1 | KI5: 1.6 | KJ5: 4.2 | KK5: 6.06 | KL5: 5.05 | KM5: 0.5 | KN5: 6.25 | KO5: 0.5 | KP5: 14.75 | KQ5: 1.25 | KR5: 2.4 | KS5: 0.3 | KT5: 0.3 | KU5: 2 | KV5: 5 | KW5: 0.8 | KX5: 1.2 | KY5: 1.51 | KZ5: 1.95 | LA5: 1.85 | LB5: 5 | LC5: 12.5 | LD5: 16.67 | LE5: 23.33 | LF5: 2.5 | LG5: 4.17 | LH5: 8.33 | LI5: 10.83 | LJ5: 4.2 | LK5: 0.83 | LL5: 8.33 | LM5: 0.765 | LN5: 0.2 | LO5: 2.2 | LP5: 1.61 | LQ5: 0.704
A6: 普工 | B6: 0.14 | C6: 0.12 | D6: 0.09 | E6: 0 | F6: 0 | G6: 0 | H6: 24.25 | I6: 1.75 | J6: 13 | K6: 1.25 | L6: 6.29 | M6: 0.59 | N6: 2.88 | O6: 2.88 | P6: 25.88 | Q6: 39.38 | R6: 51.5 | S6: 62.13 | T6: 40.88 | U6: 55 | V6: 71.13 | W6: 12 | X6: 30.58 | Y6: 33.69 | Z6: 36.52 | AA6: 38.44 | AB6: 41.25 | AC6: 45 | AD6: 40.22 | AE6: 43.54 | AF6: 47.1 | AG6: 50.14 | AH6: 53.13 | AI6: 57.46 | AJ6: 22.84 | AK6: 0.1 | AL6: 0.14 | AM6: 0.18 | AN6: 0.5 | AO6: 8.25 | AP6: 0.56 | AQ6: 0.85 | AR6: 1.23 | AS6: 3.38 | AT6: 0.62 | AU6: 0.6 | AV6: 0.6 | AW6: 0.6 | AX6: 0.1 | AY6: 0.2 | AZ6: 0.24 | BA6: 0.4 | BB6: 0 | BC6: 0.18 | BD6: 0.1 | BE6: 0.05 | BF6: 4.54 | BG6: 4.86 | BH6: 4.9 | BI6: 1 | BJ6: 6.86 | BK6: 7.79 | BL6: 8.75 | BM6: 10.86 | BN6: 11.39 | BO6: 7.98 | BP6: 9.13 | BQ6: 11.12 | BR6: 13.2 | BS6: 14.1 | BT6: 10.63 | BU6: 0.5 | BV6: 1 | BW6: 0.25 | BX6: 5.57 | BY6: 8.13 | BZ6: 18.14 | CA6: 69.33 | CB6: 10.54 | CC6: 12.96 | CD6: 15.37 | CE6: 5.15 | CF6: 9.27 | CG6: 10.94 | CH6: 13.08 | CI6: 15.35 | CJ6: 17.62 | CK6: 19.87 | CL6: 21.86 | CM6: 20.03 | CN6: 15.67 | CO6: 0.36 | CP6: 0.54 | CQ6: 0.6 | CR6: 0.9 | CS6: 0.06 | CT6: 0.13 | CU6: 0.06 | CV6: 0.13 | CW6: 0.3 | CX6: 0.15 | CY6: 0.2 | CZ6: 0.25 | DA6: 0.25 | DB6: 0.35 | DC6: 2.6 | DD6: 0.13 | DE6: 0.06 | DF6: 0.52 | DG6: 0.42 | DH6: 0.46 | DI6: 2.75 | DJ6: 1.375 | DK6: 1.925 | DL6: 1.76 | DM6: 2.5 | DN6: 5.23 | DO6: 5.48 | DP6: 2.615 | DQ6: 3.33 | DR6: 3.58 | DS6: 4.81 | DT6: 5.06 | DU6: 1.8 | DV6: 2 | DW6: 0.5 | DX6: 0.65 | DY6: 1 | DZ6: 4.13 | EA6: 5.13 | EB6: 3 | EC6: 4.13 | ED6: 6.63 | EE6: 8.43 | EF6: 11.38 | EG6: 4.99 | EH6: 5.38 | EI6: 0.49 | EJ6: 0.45 | EK6: 0.55 | EL6: 0.7 | EM6: 0.4 | EN6: 0.5 | EO6: 0.6 | EP6: 0 | EQ6: 0 | ER6: 0 | ES6: 0 | ET6: 0 | EU6: 0 | EV6: 0 | EW6: 0 | EX6: 0 | EY6: 0 | EZ6: 0 | FA6: 0 | FB6: 0 | FC6: 0 | FD6: 0 | FE6: 0 | FF6: 0 | FG6: 0 | FH6: 0 | FI6: 0 | FJ6: 0 | FK6: 0 | FL6: 0 | FM6: 0 | FN6: 0 | FO6: 0 | FP6: 0 | FQ6: 0 | FR6: 0 | FS6: 0 | FT6: 0 | FU6: 0 | FV6: 0 | FW6: 0 | FX6: 0 | FY6: 0 | FZ6: 0 | GA6: 0 | GB6: 0 | GC6: 0 | GD6: 0 | GE6: 0 | GF6: 0 | GG6: 0 | GH6: 0 | GI6: 0 | GJ6: 0 | GK6: 0 | GL6: 0 | GM6: 0 | GN6: 0 | GO6: 0 | GP6: 0 | GQ6: 0.28 | GR6: 0.67 | GS6: 1 | GT6: 0.83 | GU6: 0.4 | GV6: 0.4 | GW6: 0 | GX6: 0 | GY6: 0.07 | GZ6: 0.07 | HA6: 0.56 | HB6: 0.5 | HC6: 0.3 | HD6: 0.55 | HE6: 0 | HF6: 0 | HG6: 0 | HH6: 0 | HI6: 0 | HJ6: 0 | HK6: 0 | HL6: 0 | HM6: 0 | HN6: 0 | HO6: 0.67 | HP6: 0.78 | HQ6: 0.94 | HR6: 1.07 | HS6: 1.34 | HT6: 2.9 | HU6: 0.19 | HV6: 0.28 | HW6: 0.36 | HX6: 0.54 | HY6: 0 | HZ6: 0 | IA6: 0 | IB6: 0 | IC6: 0 | ID6: 0 | IE6: 0 | IF6: 0 | IG6: 0 | IH6: 0 | II6: 0 | IJ6: 0 | IK6: 0 | IL6: 0 | IM6: 0 | IN6: 0 | IO6: 0 | IP6: 0 | IQ6: 0 | IR6: 0 | IS6: 0 | IT6: 0 | IU6: 0 | IV6: 0 | IW6: 0 | IX6: 0 | IY6: 0 | IZ6: 0 | JA6: 0 | JB6: 0 | JC6: 0 | JD6: 0 | JE6: 0 | JF6: 0 | JG6: 0 | JH6: 0 | JI6: 0 | JJ6: 0 | JK6: 0 | JL6: 0 | JM6: 0 | JN6: 0 | JO6: 0 | JP6: 0 | JQ6: 0 | JR6: 0 | JS6: 0 | JT6: 0 | JU6: 0 | JV6: 0 | JW6: 0 | JX6: 0 | JY6: 0 | JZ6: 0 | KA6: 0 | KB6: 0 | KC6: 0 | KD6: 0 | KE6: 0 | KF6: 0 | KG6: 0 | KH6: 0 | KI6: 0 | KJ6: 0 | KK6: 0 | KL6: 0 | KM6: 0 | KN6: 0 | KO6: 0 | KP6: 0 | KQ6: 0 | KR6: 0 | KS6: 0 | KT6: 0 | KU6: 0 | KV6: 0 | KW6: 0 | KX6: 0 | KY6: 0 | KZ6: 0 | LA6: 0 | LB6: 0 | LC6: 0 | LD6: 0 | LE6: 0 | LF6: 0 | LG6: 0 | LH6: 0 | LI6: 0 | LJ6: 0 | LK6: 0 | LL6: 0 | LM6: 0 | LN6: 0 | LO6: 4.376 | LP6: 0.4 | LQ6: 0.704
A7: 工程量合计 | B7: 2.57 | C7: 66.21 | D7: 21.31 | E7: 86 | F7: 0 | G7: 708 | H7: 0.735 | I7: 0 | J7: 0 | K7: 0 | L7: 0 | M7: 0 | N7: 0 | O7: 0.036 | P7: 0 | Q7: 1.323 | R7: 0.0648 | S7: 0 | T7: 0 | U7: 0 | V7: 0 | W7: 0 | X7: 0.241 | Y7: 0 | Z7: 0 | AA7: 0 | AB7: 0 | AC7: 0 | AD7: 0 | AE7: 0 | AF7: 0 | AG7: 0 | AH7: 0 | AI7: 0 | AJ7: 0 | AK7: 0 | AL7: 0 | AM7: 0 | AN7: 2 | AO7: 0 | AP7: 12 | AQ7: 0 | AR7: 0 | AS7: 0 | AT7: 0 | AU7: 0 | AV7: 8 | AW7: 0 | AX7: 0 | AY7: 0 | AZ7: 0 | BA7: 0 | BB7: 0 | BC7: 16 | BD7: 3 | BE7: 0 | BF7: 0 | BG7: 0 | BH7: 0 | BI7: 0 | BJ7: 1.658 | BK7: 0 | BL7: 0 | BM7: 0 | BN7: 0 | BO7: 0 | BP7: 0 | BQ7: 0 | BR7: 0 | BS7: 0 | BT7: 0 | BU7: 0 | BV7: 0 | BW7: 17 | BX7: 0.264 | BY7: 0 | BZ7: 0.025 | CA7: 0 | CB7: 0 | CC7: 0.089 | CD7: 0 | CE7: 0 | CF7: 0 | CG7: 0.848 | CH7: 0.767 | CI7: 0.877 | CJ7: 0 | CK7: 0 | CL7: 0 | CM7: 0 | CN7: 0 | CO7: 0 | CP7: 0 | CQ7: 0 | CR7: 0 | CS7: 21 | CT7: 0 | CU7: 1 | CV7: 0 | CW7: 0 | CX7: 0 | CY7: 0 | CZ7: 0 | DA7: 0 | DB7: 2 | DC7: 0 | DD7: 23 | DE7: 0 | DF7: 16 | DG7: 0 | DH7: 0 | DI7: 9.02 | DJ7: 23.19 | DK7: 0 | DL7: 25.18 | DM7: 0 | DN7: 0 | DO7: 0 | DP7: 0 | DQ7: 0 | DR7: 0 | DS7: 0 | DT7: 0 | DU7: 0 | DV7: 0 | DW7: 0.8 | DX7: 0 | DY7: 0 | DZ7: 0 | EA7: 0 | EB7: 9.49 | EC7: 0 | ED7: 0 | EE7: 0 | EF7: 0 | EG7: 0 | EH7: 0 | EI7: 0 | EJ7: 0 | EK7: 0 | EL7: 0 | EM7: 0 | EN7: 0 | EO7: 0 | EP7: 0 | EQ7: 0 | ER7: 0 | ES7: 0 | ET7: 714 | EU7: 0 | EV7: 0 | EW7: 4 | EX7: 9 | EY7: 0 | EZ7: 0 | FA7: 0 | FB7: 0 | FC7: 0 | FD7: 0 | FE7: 0 | FF7: 1 | FG7: 0 | FH7: 2 | FI7: 0 | FJ7: 0 | FK7: 0 | FL7: 0 | FM7: 0 | FN7: 0 | FO7: 0 | FP7: 30 | FQ7: 9 | FR7: 0 | FS7: 0 | FT7: 0 | FU7: 0 | FV7: 0 | FW7: 0 | FX7: 0 | FY7: 0 | FZ7: 0 | GA7: 0 | GB7: 0 | GC7: 0 | GD7: 0 | GE7: 0 | GF7: 0 | GG7: 0 | GH7: 0 | GI7: 0 | GJ7: 0 | GK7: 0 | GL7: 0 | GM7: 0 | GN7: 0 | GO7: 0 | GP7: 0 | GQ7: 5 | GR7: 0 | GS7: 0 | GT7: 0 | GU7: 0 | GV7: 0 | GW7: 0 | GX7: 0 | GY7: 0 | GZ7: 0 | HA7: 0 | HB7: 18 | HC7: 0 | HD7: 7 | HE7: 25 | HF7: 0 | HG7: 0 | HH7: 0 | HI7: 0 | HJ7: 0 | HK7: 0 | HL7: 0 | HM7: 0 | HN7: 0 | HO7: 0 | HP7: 0 | HQ7: 1 | HR7: 2 | HS7: 0 | HT7: 0 | HU7: 0 | HV7: 0 | HW7: 0 | HX7: 0 | HY7: 0 | HZ7: 0 | IA7: 0 | IB7: 0 | IC7: 0 | ID7: 0 | IE7: 0 | IF7: 0 | IG7: 0 | IH7: 0 | II7: 4 | IJ7: 0 | IK7: 0 | IL7: 0 | IM7: 0 | IN7: 0 | IO7: 0 | IP7: 0 | IQ7: 0 | IR7: 0 | IS7: 0 | IT7: 0 | IU7: 0 | IV7: 0 | IW7: 0 | IX7: 0 | IY7: 0 | IZ7: 0 | JA7: 0 | JB7: 0 | JC7: 0 | JD7: 0 | JE7: 0 | JF7: 0 | JG7: 0 | JH7: 0 | JI7: 0 | JJ7: 0 | JK7: 0 | JL7: 0 | JM7: 0 | JN7: 0 | JO7: 0 | JP7: 0 | JQ7: 0 | JR7: 0 | JS7: 0 | JT7: 0 | JU7: 0 | JV7: 0 | JW7: 0 | JX7: 0 | JY7: 0 | JZ7: 0 | KA7: 0 | KB7: 0 | KC7: 0 | KD7: 0 | KE7: 0 | KF7: 0 | KG7: 0 | KH7: 0 | KI7: 0 | KJ7: 0 | KK7: 0 | KL7: 0 | KM7: 0 | KN7: 0 | KO7: 0 | KP7: 0 | KQ7: 0 | KR7: 0 | KS7: 0 | KT7: 0 | KU7: 0 | KV7: 0 | KW7: 0 | KX7: 0 | KY7: 0 | KZ7: 0 | LA7: 0 | LB7: 0 | LC7: 0 | LD7: 0 | LE7: 0 | LF7: 0 | LG7: 0 | LH7: 0 | LI7: 0 | LJ7: 0 | LK7: 0 | LL7: 0 | LM7: 0 | LN7: 0 | LO7: 0 | LP7: 0 | LQ7: 0
A8: 恩平市中山医院+互联网专线+语音专线+新增
A9: 开平市公安局新昌派出所+互联网专线+搬迁 | C9: 0.81 | E9: 2 | G9: 12 | CS9: 1 | DD9: 1 | DL9: 0.81 | ET9: 12 | FP9: 1
A10: 开平市公安局新昌派出思始点+互联网专线+搬迁 | C10: 1.69 | E10: 2 | G10: 12 | CS10: 2 | DD10: 1 | DF10: 2 | DJ10: 1.74 | DL10: 0.3 | ET10: 12 | FP10: 1 | HE10: 1 | II10: 1
A11: 开平市公安局月山派出所+互联网专线+搬迁 | C11: 1.44 | E11: 2 | G11: 12 | BC11: 1 | DJ11: 0.92 | DL11: 0.67 | ET11: 12 | FP11: 1 | HB11: 2
A12: 开平市中心医院（水口医院） | C12: 0.8 | E12: 2 | G12: 12 | CS12: 1 | DD12: 1 | DJ12: 0.5 | DL12: 0.75 | ET12: 12 | FP12: 1 | HB12: 1
A13: 广东东方思维科技有限公司 | B13: 0.6 | C13: 0.06 | D13: 0.56 | E13: 2 | G13: 12 | H13: 0.18 | Q13: 0.324 | X13: 0.06 | BW13: 1 | BX13: 0.055 | CG13: 0.071 | DD13: 1 | DL13: 0.21 | ET13: 12 | FP13: 1 | HB13: 1 | HE13: 1
A14: 开平市美力服装有限公司 | C14: 2.7 | E14: 3 | G14: 24 | CS14: 1 | DD14: 1 | DI14: 0.2 | DJ14: 2.74 | DL14: 0.36 | ET14: 24 | FP14: 2 | HB14: 1 | HE14: 1
A15: 恩平市供水有限公司+集团专线+搬迁 | C15: 5.87 | E15: 2 | G15: 12 | BJ15: 0.066 | DD15: 2 | DJ15: 5.36 | DW15: 0.15 | EB15: 0.15 | ET15: 12 | FP15: 1 | HE15: 1
A16: 恩平富辉纺织企业有限公司 | C16: 4.9 | E16: 2 | G16: 12 | BC16: 1 | CS16: 1 | DF16: 2 | DI16: 0.35 | DL16: 5.1 | EB16: 4.8 | ET16: 12 | FP16: 1
A17: 恩平市溢丰纺织有限公司 | C17: 0.89 | E17: 2 | G17: 12 | CS17: 2 | CU17: 1 | DD17: 2 | DL17: 0.89 | DW17: 0.3 | ET17: 12 | FP17: 1 | HB17: 1 | HE17: 1
A18: 开平水口镇联竹村委会+IPVPN专线+新增 | C18: 0.12 | E18: 2 | G18: 24 | CS18: 1 | DD18: 1 | DL18: 0.32 | ET18: 12 | FQ18: 1 | HD18: 1
A19: 开平市丰优农业开发有限公司 | B19: 0.08 | C19: 9.84 | E19: 12 | G19: 24 | H19: 0.024 | Q19: 0.0432 | X19: 0.008 | AN19: 1 | AP19: 9 | AV19: 5 | BC19: 7 | BD19: 2 | BJ19: 1.01 | BX19: 0.008 | DD19: 1 | DL19: 0.3 | ET19: 36 | FQ19: 1 | HB19: 1 | II19: 1
A20: 恩平三力胶粘制品有限公司+互联网专线+新增 | B20: 0.33 | C20: 3.48 | D20: 4.06 | E20: 6 | G20: 60 | H20: 0.099 | Q20: 0.1782 | X20: 0.033 | AP20: 3 | AV20: 3 | BC20: 1 | BJ20: 0.068 | BW20: 2 | BX20: 0.033 | CC20: 0.089 | CI20: 0.44 | CS20: 1 | DB20: 1 | DF20: 1 | DI20: 2.8 | DL20: 0.3 | ET20: 108 | FH20: 1 | FP20: 1 | HB20: 1 | HD20: 1 | HE20: 4 | HR20: 1
A21: 恩平市公安消防大队集团专线搬迁 | C21: 1.05 | E21: 2 | G21: 48 | DL21: 1.55 | EB21: 0.75 | ET21: 12 | EX21: 2 | FQ21: 2 | GQ21: 1 | HD21: 2
A22: 开平市翡翠网吧 | C22: 0.23 | E22: 2 | G22: 12 | DL22: 0.38 | ET22: 12 | FP22: 1 | HB22: 1
A23: 开平市莱尚网咖网吧 | C23: 1.98 | E23: 2 | G23: 24 | DF23: 1 | DJ23: 1.7 | DL23: 0.61 | ET23: 24 | FF23: 1 | HE23: 2 | HR23: 1
A24: 广发证券股份有限公司江门恩平证券营业部 | C24: 0.7 | E24: 2 | G24: 12 | CS24: 1 | DL24: 1 | EB24: 0.13 | ET24: 12 | FP24: 1 | HE24: 2
A25: 开平市公安局潭江派出所（巡警大对） | C25: 0.59 | E25: 2 | G25: 12 | DJ25: 0.71 | DL25: 0.18 | ET25: 12 | FP25: 1 | HB25: 1
A26: 开平市水口镇东桥电镀有限公司
A27: 开平市公安局长沙派出所 | C27: 0.18 | D27: 0.9 | E27: 2 | G27: 12 | BW27: 1 | CG27: 0.105 | DF27: 1 | DL27: 0.03 | DW27: 0.18 | ET27: 12 | FP27: 1 | II27: 1
A28: 开平+开平市应急管理局+新增 | C28: 1.41 | E28: 2 | G28: 12 | CS28: 1 | DD28: 1 | DF28: 1 | DJ28: 0.55 | DL28: 1.04 | ET28: 12 | FP28: 1 | HB28: 1 | HE28: 1
A29: 恩平+恩平市君堂镇人民政府+变更 | C29: 1.75 | E29: 2 | G29: 12 | DD29: 2 | DL29: 2.05 | ET29: 12 | FP29: 1
A30: 开平市南大电力工程有限公司 | C30: 1.55 | E30: 2 | G30: 12 | CS30: 1 | DF30: 1 | DJ30: 1.4 | DL30: 0.33 | ET30: 12 | FP30: 1 | HB30: 1 | HE30: 1
A31: 恩平+广东通驿高速公路服务区有限公司大槐服务区+变更 | B31: 0.27 | C31: 1.03 | D31: 5.78 | E31: 3 | G31: 48 | H31: 0.081 | Q31: 0.1458 | X31: 0.042 | BW31: 1 | BZ31: 0.02 | CH31: 0.593 | DJ31: 0.18 | DL31: 1 | ET31: 24 | EX31: 6 | FQ31: 2 | GQ31: 2 | HD31: 1
A32: 开平+开平市环境卫生管理处+G325义祠路交叉公园内+新增 | B32: 0.8 | C32: 0.66 | D32: 0.53 | E32: 2 | G32: 12 | H32: 0.24 | Q32: 0.432 | X32: 0.08 | BW32: 1 | BX32: 0.095 | CG32: 0.068 | DF32: 1 | DJ32: 0.44 | DL32: 0.4 | ET32: 12 | FP32: 1 | HB32: 1
A33: 恩平+恩平市沙湖六乡市场+新增 | B33: 0.01 | C33: 0.92 | D33: 0.01 | E33: 2 | G33: 12 | H33: 0.003 | Q33: 0.0054 | X33: 0.001 | BJ33: 0.024 | BW33: 1 | BX33: 0.001 | CG33: 0.027 | DF33: 1 | DJ33: 0.88 | ET33: 12 | FP33: 1 | HB33: 1 | HE33: 1
A34: 恩平+恩平市科达声通电子器材厂（分厂）+新增 | B34: 0.05 | C34: 2.32 | D34: 0.01 | E34: 2 | G34: 12 | H34: 0.015 | Q34: 0.027 | X34: 0.005 | BC34: 1 | BW34: 1 | CG34: 0.016 | CS34: 2 | DD34: 2 | DF34: 1 | DI34: 0.05 | DL34: 2.52 | EB34: 1.94 | ET34: 12 | FP34: 1
A35: 恩平+恩平市万国商业城开发有限公司+新增 | B35: 0.12 | C35: 0.45 | D35: 2.24 | E35: 2 | G35: 36 | O35: 0.036 | R35: 0.0648 | X35: 0.012 | BW35: 2 | BX35: 0.012 | CG35: 0.104 | CH35: 0.165 | CS35: 2 | DD35: 1 | DL35: 0.6 | EB35: 0.45 | ET35: 30 | EX35: 1 | FP35: 1 | FQ35: 1 | GQ35: 1 | HE35: 2
A36: 恩平+江苏金江建设有限公司+新增 | C36: 1.79 | D36: 0.62 | E36: 2 | G36: 24 | BX36: 0.029 | CG36: 0.119 | CS36: 1 | DD36: 1 | DF36: 3 | DI36: 0.68 | DL36: 1.26 | EB36: 0.52 | ET36: 24 | EW36: 3 | FP36: 2 | HB36: 1
A37: 恩平+恩平市君堂镇中心小学（主校区）+新增 | B37: 0.31 | C37: 0.96 | E37: 3 | G37: 24 | H37: 0.093 | Q37: 0.1674 | BX37: 0.031 | CG37: 0.031 | CS37: 2 | DL37: 1.36 | EB37: 0.75 | ET37: 24 | FP37: 2 | HB37: 1 | HE37: 1
A38: 开平市国营镇海林场（2条互联网专线+电路租用） | C38: 6.78 | E38: 2 | G38: 24 | BC38: 2 | BD38: 1 | BJ38: 0.49 | DI38: 1.98 | DL38: 0.2 | ET38: 18 | FQ38: 1 | HB38: 1 | II38: 1
A39: 开平+开平市公安局+南环簕冲红绿灯+新增 | D39: 2.77 | E39: 2 | G39: 12 | BW39: 1 | CG39: 0.307 | ET39: 12 | FP39: 1 | HE39: 2
A40: 开平+广东开平文旅发展集团有限公司+Z端+新增 | C40: 0.23 | E40: 1 | G40: 12 | DL40: 0.36 | DW40: 0.17 | ET40: 12 | HB40: 1
A41: 开平+开平百事通计算机+新增 | C41: 8.48 | D41: 0.06 | E41: 4 | G41: 48 | AN41: 1 | BC41: 2 | BW41: 1 | BZ41: 0.003 | CH41: 0.009 | CS41: 1 | DB41: 1 | DF41: 1 | DI41: 2.41 | DJ41: 6.07 | DL41: 0.3 | ET41: 84 | FP41: 2 | FQ41: 1 | HD41: 1 | HE41: 2
A42: 开平+开平市百合镇消防专职队+新增 | C42: 0.55 | E42: 2 | G42: 12 | BC42: 1 | DI42: 0.55 | ET42: 6 | EW42: 1 | FP42: 1 | GQ42: 1 | HD42: 1
A43: 江门恩平市御茶餐饮店XWXJ | D43: 3.77 | E43: 2 | G43: 48 | BW43: 5 | BZ43: 0.002 | CI43: 0.437 | DD43: 5 | ET43: 48 | FH43: 1 | HE43: 2 | HQ43: 1
A44: =SUM(B44:LQ44) -> 1910.6978 | B44: =SUM(B8:B43) -> 2.57 | C44: =SUM(C8:C43) -> 66.21 | D44: =SUM(D8:D43) -> 21.31 | E44: =SUM(E8:E43) -> 86 | F44: =SUM(F8:F43) -> 0 | G44: =SUM(G8:G43) -> 708 | H44: =SUM(H8:H43) -> 0.735 | I44: =SUM(I8:I43) -> 0 | ... LQ44: =SUM(LQ8:LQ43) -> 0

Sheet Sheet3
H1: 1 | I1: 2 | J1: 3 | K1: 4 | L1: 5 | M1: 6 | N1: 7 | O1: 8 | P1: 9 | Q1: 10 | R1: 11 | S1: 12 | T1: 13 | U1: 14 | V1: 15 | W1: 16 | X1: 17 | Y1: 18 | Z1: 19 | AA1: 20 | AB1: 21 | AC1: 22 | AD1: 23 | AE1: 24 | AF1: 25 | AG1: 26 | AH1: 27 | AI1: 28 | AJ1: 29 | AK1: 30 | AL1: 31 | AM1: 32 | AN1: 33 | AO1: 34 | AP1: 35 | AQ1: 36 | AR1: 37 | AS1: 38 | AT1: 39 | AU1: 40 | AV1: 41 | AW1: 42 | AX1: 43 | AY1: 44 | AZ1: 45
H2: 恩平市金丰电子器材厂+语音专线+变更 | I2: 恩平市中山医院+互联网专线+语音专线+新增 | J2: 国家税务总局恩平市税务局前进街办事点+互联网专线+新增+融合 | K2: 国家税务总局恩平市税务局恩城税务分局+互联网专线+新增+融合 | L2: 国家税务总局恩平市税务局圣堂税务分局+互联网专线+新增+融合 | M2: 国家税务总局恩平市税务局大槐税务分局+互联网专线+新增+融合 | N2: 开平市公安局赤坎派出所+互联网专线+搬迁 | O2: 开平市公安局新昌派出所+互联网专线+搬迁 | P2: 开平市公安局新昌派出思始点+互联网专线+搬迁 | Q2: 开平市公安局月山派出所+互联网专线+搬迁 | R2: 江门开平市长沙福来旅店预覆盖工程（小微新建） | S2: 江门开平市味香皇食品厂预覆盖工程（小微新建） | T2: 开平市中心医院（水口医院） | U2: 广东东方思维科技有限公司 | V2: 开平市美力服装有限公司 | W2: 恩平市供水有限公司+集团专线+搬迁 | X2: 恩平富辉纺织企业有限公司 | Y2: 恩平市溢丰纺织有限公司 | Z2: 开平市翡翠网吧 | AA2: 开平市莱尚网咖网吧 | AB2: 广发证券股份有限公司江门恩平证券营业部 | AC2: 开平市公安局潭江派出所（巡警大对） | AD2: 江门市合山水利工程管理处（互联网专线+电路租用） | AE2: 开平市广侨汽车销售服务有限公司（恩平店）（统一Centrex+互联网专线） | AF2: 开平市公安局长沙派出所 | AG2: 开平+粤顺牧业有限公司+新增 | AH2: 开平+开平市应急管理局+新增 | AI2: 恩平+恩平市君堂镇人民政府+变更 | AJ2: 开平+开平市环境卫生管理处+G325义祠路交叉公园内+新增 | AK2: 恩平+恩平市沙湖六乡市场+新增 | AL2: 恩平+恩平锦兴纺织印染企业有限公司+变更 | AM2: 恩平+恩平市科达声通电子器材厂（分厂）+新增 | AN2: 恩平+恩平市万国商业城开发有限公司+新增 | AO2: 恩平+江苏金江建设有限公司+新增 | AP2: 恩平+恩平市君堂镇中心小学（主校区）+新增 | AQ2: 开平+开平市公安局+南环簕冲红绿灯+新增 | AR2: 恩平+恩平市水利局+青南角+二期+新增 | AS2: 恩平+恩平市水利局+江北灌区+二期+新增 | AT2: 恩平+恩平市水利局+凤子山+二期+新增 | AU2: 跨市+中华人民共和国珠海出入境边防检查总站+开平边检站+新增 | AV2: 开平+广东开平文旅发展集团有限公司+Z端+新增 | AW2: 开平+开平市世界遗产管理中心+新增 | AX2: 开平+开平百事通计算机+新增 | AY2: 开平+开平市百合镇消防专职队+新增 | AZ2: 江门恩平市御茶餐饮店XWXJ
H3: 城区 | I3: 设备 | J3: 城区 | K3: 城区 | L3: 乡镇 | M3: 乡镇 | N3: 乡镇 | O3: 城区 | P3: 城区 | Q3: 乡镇 | R3: 城区 | S3: 乡镇 | T3: 乡镇 | U3: 乡镇 | V3: 乡镇 | W3: 乡镇 | X3: 乡镇 | Y3: 乡镇 | Z3: 城区 | AA3: 城区 | AB3: 城区 | AC3: 城区 | AD3: 乡镇 | AE3: 城区 | AF3: 乡镇 | AG3: 乡镇 | AH3: 城区 | AI3: 乡镇 | AJ3: 城区 | AK3: 乡镇 | AL3: 乡镇 | AM3: 城区 | AN3: 城区 | AO3: 城区 | AP3: 乡镇 | AQ3: 城区 | AR3: 乡镇 | AS3: 乡镇 | AT3: 乡镇 | AU3: 城区 | AV3: 城区 | AW3: 城区 | AX3: 城区 | AY3: 乡镇 | AZ3: 城区
A4: 序号 | B4: 定额编号 | C4: 项目名称 | D4: 单位 | E4: 技工 | F4: 普工 | G4: 工程量合计 | H4: 数量 | I4: 数量 | J4: 数量 | K4: 数量 | L4: 数量 | M4: 数量 | N4: 数量 | O4: 数量 | P4: 数量 | Q4: 数量 | R4: 数量 | S4: 数量 | T4: 数量 | U4: 数量 | V4: 数量 | W4: 数量 | X4: 数量 | Y4: 数量 | Z4: 数量 | AA4: 数量 | AB4: 数量 | AC4: 数量 | AD4: 数量 | AE4: 数量 | AF4: 数量 | AG4: 数量 | AH4: 数量 | AI4: 数量 | AJ4: 数量 | AK4: 数量 | AL4: 数量 | AM4: 数量 | AN4: 数量 | AO4: 数量 | AP4: 数量 | AQ4: 数量 | AR4: 数量 | AS4: 数量 | AT4: 数量 | AU4: 数量 | AV4: 数量 | AW4: 数量 | AX4: 数量 | AY4: 数量 | AZ4: 数量
A5: 1 | B5: TXL1-001 | C5: 直埋光（电）缆工程施工测量 | D5: 百米 | E5: 0.56 | F5: 0.14 | G5: 0
A6: 2 | B6: TXL1-002 | C6: 架空光(电)缆工程施工测量 | D6: 百米 | E6: 0.46 | F6: 0.12 | G6: 13.88 | R6: 0.24 | S6: 8.42 | AZ6: 5.22
A7: 3 | B7: TXL1-003 | C7: 管道光(电)缆工程施工测量 | D7: 百米 | E7: 0.35 | F7: 0.09 | G7: 0.48 | AZ7: 0.48
A8: 4 | B8: TXL1-005 | C8: GPS定位 | D8: 点 | E8: 0.05 | F8: 0 | G8: 4 | R8: 1 | S8: 1 | AZ8: 2
A9: 5 | B9: TXL1-006 | C9: 单盘检验（单窗口） | D9: 芯盘 | E9: 0.02 | F9: 0 | G9: 0
A10: 6 | B10: TXL1-006-1 | C10: 单盘检验（双窗口） | D10: 芯盘 | E10: 0.024 | F10: 0 | G10: 84 | R10: 12 | S10: 60 | AZ10: 12
A11: 7 | B11: TXL1-008 | C11: 人工开挖路面 混凝土（100mm以内） | D11: 百平方米 | E11: 3.33 | F11: 24.25 | G11: 0
A12: 8 | B12: TXL1-009 | C12: 人工开挖路面 混凝土（每增加10mm） | D12: 百平方米 | E12: 0.33 | F12: 1.75 | G12: 0
A13: 9 | B13: TXL1-010 | C13: 人工开挖路面 沥青柏油（100mm以内） | D13: 百平方米 | E13: 1.88 | F13: 13 | G13: 0
A14: 10 | B14: TXL1-011 | C14: 人工开挖路面 沥青柏油（每增加10mm） | D14: 百平方米 | E14: 0.19 | F14: 1.25 | G14: 0
A15: 11 | B15: TXL1-012 | C15: 人工开挖路面 砂石（100mm以内） | D15: 百平方米 | E15: 1.04 | F15: 6.29 | G15: 0
A16: 12 | B16: TXL1-013 | C16: 人工开挖路面 砂石（每增加10mm） | D16: 百平方米 | E16: 0.09 | F16: 0.59 | G16: 0
A17: 13 | B17: TXL1-014 | C17: 人工开挖路面 混凝土砌块 | D17: 百平方米 | E17: 0.31 | F17: 2.88 | G17: 0
A18: 14 | B18: TXL1-015 | C18: 人工开挖路面 水泥花砖 | D18: 百平方米 | E18: 0.31 | F18: 2.88 | G18: 0
A19: 15 | B19: TXL1-016 | C19: 人工开挖路面 条石 | D19: 百平方米 | E19: 5 | F19: 25.88 | G19: 0
A20: 16 | B20: TXL2-001 | C20: 挖、松填光（电）缆沟及接头坑 普通土 | D20: 百立方米 | E20: 0 | F20: 39.38 | G20: 0
A21: 17 | B21: TXL2-002 | C21: 挖、松填光（电）缆沟及接头坑 硬土 | D21: 百立方米 | E21: 0 | F21: 51.5 | G21: 0
A22: 18 | B22: TXL2-003 | C22: 挖、松填光（电）缆沟及接头坑 砂砾土 | D22: 百立方米 | E22: 0 | F22: 62.13 | G22: 0
... A44: 40 | B44: TXL2-127 | C44: 安装防雷设施 敷设排流线（单条） | D44: 千米 | E44: 2.2 | F44: 8.25 | G44: 0
A45: 41 | B45: TXL3-001 | C45: 立9m 以下水泥杆 综合土 | D45: 根 | E45: 0.52 | F45: 0.56 | G45: 3 | S45: 3
A46: 42 | B46: TXL3-004 | C46: 立11m 以下水泥杆 综合土 | D46: 根 | E46: 0.77 | F46: 0.85 | G46: 0
A47: 43 | B47: TXL3-007 | C47: 立13m 以下水泥杆 综合土 | D47: 根 | E47: 1.02 | F47: 1.23 | G47: 0
A48: 44 | B48: TXL3-010 | C48: 立13m 以下水泥H杆 综合土 | D48: 座 | E48: 1.92 | F48: 3.38 | G48: 0
A49: 45 | B49: TXL3-048 | C49: 装水泥撑杆 综合土 | D49: 根 | E49: 0.62 | F49: 0.62 | G49: 0
A50: 46 | B50: TXL3-051 | C50: 水泥杆夹板法装7/2.2单股拉线 综合土 | D50: 条 | E50: 0.78 | F50: 0.6 | G50: 0
A51: 47 | B51: TXL3-054 | C51: 水泥杆夹板法装7/2.6单股拉线 综合土 | D51: 条 | E51: 0.84 | F51: 0.6 | G51: 2 | S51: 2
A52: 48 | B52: TXL3-057 | C52: 水泥杆夹板法装7/3.0单股拉线 综合土 | D52: 条 | E52: 0.98 | F52: 0.6 | G52: 0
A53: 49 | B53: TXL3-142 | C53: 安装拉线隔电子 | D53: 处 | E53: 0.24 | F53: 0.1 | G53: 0
A54: 50 | B54: TXL3-143 | C54: 安装拉线警示保护管 | D54: 处 | E54: 0.2 | F54: 0.2 | G54: 0
A55: 51 | B55: TXL3-144 | C55: 电杆接高装置(单槽钢) | D55: 处 | E55: 0.24 | F55: 0.24 | G55: 0
A56: 52 | B56: TXL3-145 | C56: 电杆接高装置(双槽钢) | D56: 处 | E56: 0.4 | F56: 0.4 | G56: 0
A57: 53 | B57: TXL3-146 | C57: 单杆地线 拉线式 | D57: 条 | E57: 0.07 | F57: 0 | G57: 0
A58: 54 | B58: TXL3-147 | C58: 单杆地线 直埋式 | D58: 条 | E58: 0.18 | F58: 0.18 | G58: 2 | AZ58: 2
A59: 55 | B59: TXL3-149 | C59: 安装预留缆架 | D59: 架 | E59: 0.1 | F59: 0.1 | G59: 0
A60: 56 | B60: TXL3-150 | C60: 安装吊线保护装置 | D60: m | E60: 0.05 | F60: 0.05 | G60: 20 | AZ60: 20
A61: 57 | B61: TXL3-169 | C61: 水泥杆架设7/2.2吊线（丘陵） | D61: 千米条 | E61: 4.25 | F61: 4.54 | G61: 0
A62: 58 | B62: TXL3-170 | C62: 水泥杆架设7/2.2吊线（山区） | D62: 千米条 | E62: 4.67 | F62: 4.86 | G62: 0
A63: 59 | B63: TXL3-171 | C63: 水泥杆架设7/2.2吊线（城区） | D63: 千米条 | E63: 4.5 | F63: 4.9 | G63: 0.16 | S63: 0.16
A64: 60 | B64: TXL3-180 | C64: 架设100米以内辅助吊线 | D64: 条档 | E64: 1 | F64: 1 | G64: 0
A65: 61 | B65: TXL3-192 | C65: 挂钩法架设架空光缆丘陵、城区、水田（36芯以下） | D65: 千米条 | E65: 8.68 | F65: 6.86 | G65: 0
A66: 62 | B66: TXL3-193 | C66: 挂钩法架设架空光缆丘陵、城区、水田（72芯以下） | D66: 千米条 | E66: 9.93 | F66: 7.79 | G66: 0.422 | S66: 0.422
A67: 63 | B67: TXL3-194 | C67: 挂钩法架设架空光缆丘陵、城区、水田（144芯以下） | D67: 千米条 | E67: 11.05 | F67: 8.75 | G67: 0
A68: 64 | B68: TXL3-195 | C68: 挂钩法架设架空光缆丘陵、城区、水田（288芯以下） | D68: 千米条 | E68: 11.68 | F68: 10.86 | G68: 0
A69: 65 | B69: TXL3-196 | C69: 挂钩法架设架空光缆丘陵、城区、水田（288芯以上） | D69: 千米条 | E69: 12.23 | F69: 11.39 | G69: 0
A70: 66 | B70: TXL3-197 | C70: 挂钩法架设架空光缆山区（36芯以下） | D70: 千米条 | E70: 10.24 | F70: 7.98 | G70: 0
A71: 67 | B71: TXL3-198 | C71: 挂钩法架设架空光缆山区（72芯以下） | D71: 千米条 | E71: 11.72 | F71: 9.13 | G71: 0
A72: 68 | B72: TXL3-199 | C72: 挂钩法架设架空光缆山区（144芯以下） | D72: 千米条 | E72: 12.94 | F72: 11.12 | G72: 0
A73: 69 | B73: TXL3-200 | C73: 挂钩法架设架空光缆山区（288芯以下） | D73: 千米条 | E73: 14.32 | F73: 13.2 | G73: 0
A74: 70 | B74: TXL3-201 | C74: 挂钩法架设架空光缆山区（288芯以上） | D74: 千米条 | E74: 15.25 | F74: 14.1 | G74: 0
A75: 71 | B75: TXL3-218 | C75: 吊线式架空电缆（100对以下） | D75: 千米条 | E75: 9.05 | F75: 10.63 | G75: 0
A76: 72 | B76: TXL4-001 | C76: 布放光(电)缆人孔抽水(积水) | D76: 个 | E76: 0.25 | F76: 0.5 | G76: 0
A77: 73 | B77: TXL4-002 | C77: 布放光(电)缆人孔抽水(流水) | D77: 个 | E77: 0.38 | F77: 1 | G77: 0
A78: 74 | B78: TXL4-003 | C78: 布放光(电)缆手孔抽水 | D78: 个 | E78: 0.13 | F78: 0.25 | G78: 2 | AZ78: 2
A79: 75 | B79: TXL4-004 | C79: 人工敷设塑料子管 1孔子管 | D79: 千米 | E79: 4 | F79: 5.57 | G79: 0
A80: 76 | B80: TXL4-005 | C80: 人工敷设塑料子管 2孔子管 | D80: 千米 | E80: 5.2 | F80: 8.13 | G80: 0
A81: 77 | B81: TXL4-005-1 | C81: 人工敷设塑料子管(6孔子管) | D81: 千米 | E81: 9.07 | F81: 17.78 | G81: 0.014 | AZ81: 0.014
A82: 78 | B82: TXL4-005-2 | C82: 人工敷设塑料子管(15孔子管) | D82: 千米 | E82: 27.5 | F82: 69.33 | G82: 0
A83: 79 | B83: TXL4-006 | C83: 人工敷设塑料子管 3孔子管 | D83: 千米 | E83: 6.17 | F83: 10.54 | G83: 0
A84: 80 | B84: TXL4-007 | C84: 人工敷设塑料子管 4孔子管 | D84: 千米 | E84: 7.13 | F84: 12.96 | G84: 0
A85: 81 | B85: TXL4-008 | C85: 人工敷设塑料子管 5孔子管 | D85: 千米 | E85: 8.1 | F85: 15.37 | G85: 0
A86: 82 | B86: TXL4-009 | C86: 空闲管孔中人工敷设一带纺织子管 | D86: 公里 | E86: 3.63 | F86: 5.15 | G86: 0
A87: 83 | B87: TXL4-010 | C87: 非空闲管孔中人工敷设一带纺织子管 | D87: 公里 | E87: 6.53 | F87: 9.27 | G87: 0
A88: 84 | B88: TXL4-011 | C88: 敷设管道光缆 12芯以下 | D88: 千米条 | E88: 5.5 | F88: 10.94 | G88: 0.063 | AZ88: 0.063
A89: 85 | B89: TXL4-012 | C89: 敷设管道光缆 24芯以下 | D89: 千米条 | E89: 6.83 | F89: 13.08 | G89: 0
A90: 86 | B90: TXL4-013 | C90: 敷设管道光缆 48芯以下 | D90: 千米条 | E90: 8.02 | F90: 15.35 | G90: 0
A91: 87 | B91: TXL4-014 | C91: 敷设管道光缆 96芯以下 | D91: 千米条 | E91: 9.02 | F91: 17.62 | G91: 0
A92: 88 | B92: TXL4-015 | C92: 敷设管道光缆 144芯以下 | D92: 千米条 | E92: 10.4 | F92: 19.87 | G92: 0
A93: 89 | B93: TXL4-016 | C93: 敷设管道光缆 288芯以下 | D93: 千米条 | E93: 11.44 | F93: 21.86 | G93: 0
A94: 90 | B94: TXL4-019 | C94: 人工敷设管道电缆 200对 以下 | D94: 千米条 | E94: 11.76 | F94: 20.03 | G94: 0
A95: 91 | B95: TXL4-024 | C95: 机械敷设管道电缆 200对 以下 | D95: 千米条 | E95: 9.2 | F95: 15.67 | G95: 0
A96: 92 | B96: TXL4-033 | C96: 打人（手）孔墙洞 砖砌人孔 3孔管 以下 | D96: 处 | E96: 0.36 | F96: 0.36 | G96: 0
A97: 93 | B97: TXL4-034 | C97: 打人（手）孔墙洞 砖砌人孔 3孔管 以上 | D97: 处 | E97: 0.54 | F97: 0.54 | G97: 0
A98: 94 | B98: TXL4-035 | C98: 打人（手）孔墙洞 混凝土人孔 3孔管 以下 | D98: 处 | E98: 0.6 | F98: 0.6 | G98: 0
A99: 95 | B99: TXL4-036 | C99: 打人（手）孔墙洞 混凝土人孔 3孔管 以上 | D99: 处 | E99: 0.9 | F99: 0.9 | G99: 0
A100: 96 | B100: TXL4-037 | C100: 打穿楼墙洞 砖墙 | D100: 个 | E100: 0.07 | F100: 0.06 | G100: 10 | R100: 7 | S100: 2 | AZ100: 1
A101: 97 | B101: TXL4-038 | C101: 打穿楼墙洞 混凝土墙 | D101: 个 | E101: 0.14 | F101: 0.13 | G101: 0
A102: 98 | B102: TXL4-039 | C102: 打穿楼层洞 预制板楼层 | D102: 个 | E102: 0.07 | F102: 0.06 | G102: 0
A103: 99 | B103: TXL4-040 | C103: 打穿楼层洞 混凝土楼层 | D103: 个 | E103: 0.14 | F103: 0.13 | G103: 4 | S103: 4
A104: 100 | B104: TXL4-041 | C104: 增装支撑物 终端支撑物 | D104: 套 | E104: 0.3 | F104: 0.3 | G104: 0
A105: 101 | B105: TXL4-042 | C105: 增装支撑物 中间支撑物 | D105: 套 | E105: 0.15 | F105: 0.15 | G105: 0
A106: 102 | B106: TXL4-043 | C106: 安装引上钢管（Φ50以下）(杆上) | D106: 根 | E106: 0.2 | F106: 0.2 | G106: 0
A107: 103 | B107: TXL4-044 | C107: 安装引上钢管（Φ50以下）(墙上) | D107: 根 | E107: 0.25 | F107: 0.25 | G107: 0
A108: 104 | B108: TXL4-045 | C108: 安装引上钢管（Φ50以上）(杆上) | D108: 根 | E108: 0.25 | F108: 0.25 | G108: 0
A109: 105 | B109: TXL4-046 | C109: 安装引上钢管（Φ50以上）(墙上) | D109: 根 | E109: 0.35 | F109: 0.35 | G109: 0
A110: 106 | B110: TXL4-047 | C110: 钉固塑料槽板 | D110: 百米条 | E110: 2.6 | F110: 2.6 | G110: 0
A111: 107 | B111: TXL4-048 | C111: 进局光(电)缆防水封堵 | D111: 处 | E111: 0.13 | F111: 0.13 | G111: 3 | R111: 1 | S111: 1 | AZ111: 1
A112: 108 | B112: TXL4-049 | C112: 光(电)缆上线洞楼层间防火封堵 | D112: 处 | E112: 0.06 | F112: 0.06 | G112: 0
A113: 109 | B113: TXL4-050 | C113: 穿放引上光缆 | D113: 条 | E113: 0.52 | F113: 0.52 | G113: 1 | AZ113: 1
A114: 110 | B114: TXL4-051 | C114: 穿放引上电缆 200对 以下 | D114: 条 | E114: 0.42 | F114: 0.42 | G114: 0
A115: 111 | B115: TXL4-052 | C115: 穿放引上电缆 200对 以上 | D115: 条 | E115: 0.46 | F115: 0.46 | G115: 0
A116: 112 | B116: TXL4-053 | C116: 架设吊线式墙壁光缆 | D116: 百米条 | E116: 2.75 | F116: 2.75 | G116: 4.2 | S116: 4.2
A117: 113 | B117: TXL4-053-1 | C117: 架设吊线式墙壁光缆（加吊） | D117: 百米条 | E117: 1.375 | F117: 1.375 | G117: 5.32 | AZ117: 5.32
A118: 114 | B118: TXL4-053-2 | C118: 架设吊线式墙壁 | D118: 百米条 | E118: 1.925 | F118: 1.925 | G118: 0
A119: 115 | B119: TXL4-054 | C119: 布放钉固式墙壁光缆 | D119: 百米条 | E119: 1.76 | F119: 1.76 | G119: 0.35 | AZ119: 0.35
A120: 116 | B120: TXL4-056 | C120: 墙壁方式敷设蝶形光缆 | D120: 百米条 | E120: 2 | F120: 2.5 | G120: 0
A121: 117 | B121: TXL4-057 | C121: 架设吊线式墙壁电缆 200对 以下 | D121: 百米条 | E121: 5.23 | F121: 5.23 | G121: 5.6 | AI121: 5.6
...

Sheet Sheet4
A1: 序号 | B1: 1 | C1: 2 | D1: 3 | E1: 4 | F1: 5 | G1: 6 | H1: 7 | I1: 8 | J1: 9 | K1: 10 | L1: 11 | M1: 12 | N1: 13 | O1: 14 | P1: 15 | Q1: 16 | R1: 17 | S1: 18 | T1: 19 | U1: 20 | V1: 21 | W1: 22 | X1: 23 | Y1: 24 | Z1: 25 | AA1: 26 | AB1: 27 | AC1: 28 | AD1: 29 | AE1: 30 | AF1: 31 | AG1: 32 | AH1: 33 | AI1: 34 | AJ1: 35 | AK1: 36 | AL1: 37 | AM1: 38 | AN1: 39 | AO1: 40 | AP1: 41 | AQ1: 42 | AR1: 43 | AS1: 44 | AT1: 45 | AU1: 46 | AV1: 47 | AW1: 48 | AX1: 49 | AY1: 50 | AZ1: 51 | BA1: 52 | BB1: 53 | BC1: 54 | BD1: 55 | BE1: 56 | BF1: 57 | BG1: 58 | BH1: 59 | BI1: 60 | BJ1: 61 | BK1: 62 | BL1: 63 | BM1: 64 | BN1: 65 | BO1: 66 | BP1: 67 | BQ1: 68 | BR1: 69 | BS1: 70 | BT1: 71 | BU1: 72 | BV1: 73 | BW1: 74 | BX1: 75 | BY1: 76 | BZ1: 77 | CA1: 78 | CB1: 79 | CC1: 80 | CD1: 81 | CE1: 82 | CF1: 83 | CG1: 84 | CH1: 85 | CI1: 86 | CJ1: 87 | CK1: 88 | CL1: 89 | CM1: 90 | CN1: 91 | CO1: 92 | CP1: 93 | CQ1: 94 | CR1: 95 | CS1: 96 | CT1: 97 | CU1: 98 | CV1: 99 | CW1: 100 | CX1: 101 | CY1: 102 | CZ1: 103 | DA1: 104 | DB1: 105 | DC1: 106 | DD1: 107 | DE1: 108 | DF1: 109 | DG1: 110 | DH1: 111 | DI1: 112 | DJ1: 113 | DK1: 114 | DL1: 115 | DM1: 116 | DN1: 117 | DO1: 118 | DP1: 119 | DQ1: 120 | DR1: 121 | DS1: 122 | DT1: 123 | DU1: 124 | DV1: 125 | DW1: 126 | DX1: 127 | DY1: 128 | DZ1: 129 | EA1: 130 | EB1: 131 | EC1: 132 | ED1: 133 | EE1: 134 | EF1: 135 | EG1: 136 | EH1: 137 | EI1: 138 | EJ1: 139 | EK1: 140 | EL1: 141 | EM1: 142 | EN1: 143 | EO1: 144 | EP1: 145 | EQ1: 146 | ER1: 147 | ES1: 148 | ET1: 149 | EU1: 150 | EV1: 151 | EW1: 152 | EX1: 153 | EY1: 154 | EZ1: 155 | FA1: 156 | FB1: 157 | FC1: 158 | FD1: 159 | FE1: 160 | FF1: 161 | FG1: 162 | FH1: 163 | FI1: 164 | FJ1: 165 | FK1: 166 | FL1: 167 | FM1: 168 | FN1: 169 | FO1: 170 | FP1: 171 | FQ1: 172 | FR1: 173 | FS1: 174 | FT1: 175 | FU1: 176 | FV1: 177 | FW1: 178 | FX1: 179 | FY1: 180 | FZ1: 181 | GA1: 182 | GB1: 183 | GC1: 184 | GD1: 185 | GE1: 186 | GF1: 187 | GG1: 188 | GH1: 189 | GI1: 190 | GJ1: 191 | GK1: 192 | GL1: 193 | GM1: 194 | GN1: 195 | GO1: 196 | GP1: 197 | GQ1: 198 | GR1: 199 | GS1: 200 | GT1: 201 | GU1: 202 | GV1: 203 | GW1: 204 | GX1: 205 | GY1: 206 | GZ1: 207 | HA1: 208 | HB1: 209 | HC1: 210 | HD1: 211 | HE1: 212 | HF1: 213 | HG1: 214 | HH1: 215 | HI1: 216 | HJ1: 217 | HK1: 218 | HL1: 219 | HM1: 220 | HN1: 221 | HO1: 222 | HP1: 223 | HQ1: 224 | HR1: 225 | HS1: 226 | HT1: 227 | HU1: 228 | HV1: 229 | HW1: 230 | HX1: 231 | HY1: 232 | HZ1: 233 | IA1: 234 | IB1: 235 | IC1: 236 | ID1: 237 | IE1: 238 | IF1: 239 | IG1: 240 | IH1: 241 | II1: 242 | IJ1: 243 | IK1: 244 | IL1: 245 | IM1: 246 | IN1: 247 | IO1: 248 | IP1: 249 | IQ1: 250 | IR1: 251 | IS1: 252 | IT1: 253 | IU1: 254 | IV1: 255 | IW1: 256 | IX1: 257 | IY1: 258 | IZ1: 259 | JA1: 260 | JB1: 261 | JC1: 262 | JD1: 263 | JE1: 264 | JF1: 265 | JG1: 266 | JH1: 267 | JI1: 268 | JJ1: 269 | JK1: 270 | JL1: 271 | JM1: 272 | JN1: 273 | JO1: 274 | JP1: 275 | JQ1: 276 | JR1: 277 | JS1: 278 | JT1: 279 | JU1: 280 | JV1: 281 | JW1: 282 | JX1: 283 | JY1: 284 | JZ1: 285 | KA1: 286 | KB1: 287 | KC1: 288 | KD1: 289 | KE1: 290 | KF1: 291 | KG1: 292 | KH1: 293 | KI1: 294 | KJ1: 295 | KK1: 296 | KL1: 297 | KM1: 298 | KN1: 299 | KO1: 300 | KP1: 301 | KQ1: 302 | KR1: 303 | KS1: 304 | KT1: 305 | KU1: 306 | KV1: 307 | KW1: 308 | KX1: 309 | KY1: 310 | KZ1: 311
A2: 定额编号 | B2: TXL1-001 | C2: TXL1-002 | D2: TXL1-003 | E2: TXL1-005 | F2: TXL1-006 | G2: TXL1-006-1 | H2: TXL1-008 | I2: TXL1-009 | J2: TXL1-010 | K2: TXL1-011 | L2: TXL1-012 | M2: TXL1-013 | N2: TXL1-014 | O2: TXL1-015 | P2: TXL1-016 | Q2: TXL2-001 | R2: TXL2-002 | S2: TXL2-003 | T2: TXL2-007 | U2: TXL2-008 | V2: TXL2-009 | W2: TXL2-014 | X2: TXL2-021 | Y2: TXL2-022 | Z2: TXL2-023 | AA2: TXL2-024 | AB2: TXL2-025 | AC2: TXL2-026 | AD2: TXL2-027 | AE2: TXL2-028 | AF2: TXL2-029 | AG2: TXL2-030 | AH2: TXL2-031 | AI2: TXL2-032 | AJ2: TXL2-033 | AK2: TXL2-109 | AL2: TXL2-121 | AM2: TXL2-122 | AN2: TXL2-123 | AO2: TXL2-127 | AP2: TXL3-001 | AQ2: TXL3-004 | AR2: TXL3-007 | AS2: TXL3-010 | AT2: TXL3-048 | AU2: TXL3-051 | AV2: TXL3-054 | AW2: TXL3-057 | AX2: TXL3-142 | AY2: TXL3-143 | AZ2: TXL3-144 | BA2: TXL3-145 | BB2: TXL3-146 | BC2: TXL3-147 | BD2: TXL3-149 | BE2: TXL3-150 | BF2: TXL3-169 | BG2: TXL3-170 | BH2: TXL3-171 | BI2: TXL3-180 | BJ2: TXL3-192 | BK2: TXL3-193 | BL2: TXL3-194 | BM2: TXL3-195 | BN2: TXL3-196 | BO2: TXL3-197 | BP2: TXL3-198 | BQ2: TXL3-199 | BR2: TXL3-200 | BS2: TXL3-201 | BT2: TXL3-218 | BU2: TXL4-001 | BV2: TXL4-002 | BW2: TXL4-003 | BX2: TXL4-004 | BY2: TXL4-005 | BZ2: TXL4-005-1 | CA2: TXL4-005-2 | CB2: TXL4-006 | CC2: TXL4-007 | CD2: TXL4-008 | CE2: TXL4-009 | CF2: TXL4-010 | CG2: TXL4-011 | CH2: TXL4-012 | CI2: TXL4-013 | CJ2: TXL4-014 | CK2: TXL4-015 | CL2: TXL4-016 | CM2: TXL4-019 | CN2: TXL4-024 | CO2: TXL4-033 | CP2: TXL4-034 | CQ2: TXL4-035 | CR2: TXL4-036 | CS2: TXL4-037 | CT2: TXL4-038 | CU2: TXL4-039 | CV2: TXL4-040 | CW2: TXL4-041 | CX2: TXL4-042 | CY2: TXL4-043 | CZ2: TXL4-044 | DA2: TXL4-045 | DB2: TXL4-046 | DC2: TXL4-047 | DD2: TXL4-048 | DE2: TXL4-049 | DF2: TXL4-050 | DG2: TXL4-051 | DH2: TXL4-052 | DI2: TXL4-053 | DJ2: TXL4-053-1 | DK2: TXL4-053-2 | DL2: TXL4-054 | DM2: TXL4-056 | DN2: TXL4-057 | DO2: TXL4-058 | DP2: TXL4-057-1 | DQ2: TXL4-059 | DR2: TXL4-060 | DS2: TXL4-061 | DT2: TXL4-062 | DU2: TXL5-042 | DV2: TXL5-043 | DW2: TXL5-044 | DX2: TXL5-045 | DY2: TXL5-046 | DZ2: TXL5-049 | EA2: TXL5-050 | EB2: TXL5-051 | EC2: TXL5-052 | ED2: TXL5-054 | EE2: TXL5-055 | EF2: TXL5-056 | EG2: TXL5-057 | EH2: TXL5-058 | EI2: TXL5-068 | EJ2: TXL5-069 | EK2: TXL5-070 | EL2: TXL5-071 | EM2: TXL5-074 | EN2: TXL5-076 | EO2: TXL5-077 | EP2: TXL6-001 | EQ2: TXL6-002 | ER2: TXL6-003 | ES2: TXL6-004 | ET2: TXL6-005 | EU2: TXL6-006 | EV2: TXL6-007 | EW2: TXL6-008 | EX2: TXL6-009 | EY2: TXL6-011 | EZ2: TXL6-013 | FA2: TXL6-015 | FB2: TXL6-018 | FC2: TXL6-027 | FD2: TXL6-029 | FE2: TXL6-073 | FF2: TXL6-073-1 | FG2: TXL6-075 | FH2: TXL6-075-1 | FI2: TXL6-079 | FJ2: TXL6-079-1 | FK2: TXL6-082 | FL2: TXL6-082-1 | FM2: TXL6-088 | FN2: TXL6-088-1 | FO2: TXL6-101 | FP2: TXL6-103 | FQ2: TXL6-104 | FR2: TXL6-106 | FS2: TXL6-108 | FT2: TXL6-110 | FU2: TXL6-112 | FV2: TXL6-113 | FW2: TXL6-114 | FX2: TXL6-115 | FY2: TXL6-116 | FZ2: TXL6-117 | GA2: TXL6-118 | GB2: TXL6-119 | GC2: TXL6-133 | GD2: TXL6-134 | GE2: TXL6-135 | GF2: TXL6-136 | GG2: TXL6-137 | GH2: TXL6-139 | GI2: TXL6-152 | GJ2: TXL6-153 | GK2: TXL6-165 | GL2: TXL6-166 | GM2: TXL6-167 | GN2: TXL6-168 | GO2: TXL6-169 | GP2: TXL6-170 | GQ2: TXL6-199 | GR2: TXL7-004 | GS2: TXL7-005 | GT2: TXL7-006 | GU2: TXL7-007 | GV2: TXL7-008 | GW2: TXL7-009 | GX2: TXL7-010 | GY2: TXL7-014 | GZ2: TXL7-016 | HA2: TXL7-023 | HB2: TXL7-024 | HC2: TXL7-025 | HD2: TXL7-026 | HE2: TXL7-027 | HF2: TXL7-028 | HG2: TXL7-029 | HH2: TXL7-030 | HI2: TXL7-031 | HJ2: TXL7-032 | HK2: TXL7-033 | HL2: TXL7-034 | HM2: TXL7-035 | HN2: TXL7-036 | HO2: TXL7-042 | HP2: TXL7-043 | HQ2: TXL7-044 | HR2: TXL7-045 | HS2: TXL7-046 | HT2: TXL7-056 | HU2: TXL7-064 | HV2: TXL7-065 | HW2: TXL7-066 | HX2: TXL7-067 | HY2: TXL7-077 | HZ2: TXL7-082 | IA2: TSY1-005 | IB2: TSY1-006 | IC2: TSY1-007 | ID2: TSY1-008 | IE2: TSY1-009 | IF2: TSY1-010 | IG2: TSY1-011 | IH2: TSY1-029 | II2: TSY1-030 | IJ2: TSY1-051 | IK2: TSY1-054 | IL2: TSY1-055 | IM2: TSY1-056 | IN2: TSY1-067 | IO2: TSY1-068 | IP2: TSY1-069 | IQ2: TSY1-079 | IR2: TSY1-080 | IS2: TSY1-081 | IT2: TSY1-082 | IU2: TSY1-089 | IV2: TSY1-089 | IW2: TSY1-090 | IX2: TSY1-100 | IY2: TSY2-002 | IZ2: TSY2-003 | JA2: TSY2-005 | JB2: TSY2-006 | JC2: TSY2-007 | JD2: TSY2-008 | JE2: TSY2-009 | JF2: TSY2-010 | JG2: TSY2-011 | JH2: TSY2-012 | JI2: TSY2-013 | JJ2: TSY2-014 | JK2: TSY2-015 | JL2: TSY2-016 | JM2: TSY2-019 | JN2: TSY2-059 | JO2: TSY2-064 | JP2: TSY2-067 | JQ2: TSY2-068 | JR2: TSY2-092 | JS2: TSY2-095 | JT2: TSY2-099 | JU2: TSY2-101 | JV2: TSY3-018 | JW2: TSY3-019 | JX2: TSY3-027 | JY2: TSY3-031 | JZ2: TSY3-032 | KA2: TSY3-033 | KB2: TSY3-034 | KC2: TSY3-035 | KD2: TSY3-036 | KE2: TSY3-047 | KF2: TSY3-063 | KG2: TSY3-064 | KH2: TSY3-066 | KI2: TSY3-067 | KJ2: TSY4-002 | KK2: TSY4-003 | KL2: TSY4-007 | KM2: TSY4-011 | KN2: TSY4-013 | KO2: TSY4-014 | KP2: TSY4-017 | KQ2: TSW2-105 | KR2: TSW2-106 | KS2: TSW2-107 | KT2: TSW2-108 | KU2: TSW2-109 | KV2: TSW2-110 | KW2: TSW2-111 | KX2: TSW2-112 | KY2: TSD3-006 | KZ2: TSD3-050
A3: 项目名称 | B3: 直埋光（电）缆工程施工测量 | C3: 架空光(电)缆工程施工测量 | D3: 管道光(电)缆工程施工测量 | E3: GPS定位 | F3: 单盘检验（单窗口） | G3: 单盘检验（双窗口） | H3: 人工开挖路面 混凝土（100mm以内） | I3: 人工开挖路面 混凝土（每增加10mm） | J3: 人工开挖路面 沥青柏油（100mm以内） | K3: 人工开挖路面 沥青柏油（每增加10mm） | L3: 人工开挖路面 砂石（100mm以内） | M3: 人工开挖路面 砂石（每增加10mm） | N3: 人工开挖路面 混凝土砌块 | O3: 人工开挖路面 水泥花砖 | P3: 人工开挖路面 条石 | Q3: 挖、松填光（电）缆沟及接头坑 普通土 | R3: 挖、松填光（电）缆沟及接头坑 硬土 | S3: 挖、松填光（电）缆沟及接头坑 砂砾土 | T3: 挖、夯填光（电）缆沟及接头坑 普通土 | U3: 挖、夯填光（电）缆沟及接头坑 硬土 | V3: 挖、夯填光（电）缆沟及接头坑 砂砾土 | W3: 手推车倒运土方 | X3: 丘陵、水田、城区敷设埋式光缆 36芯以下 | Y3: 丘陵、水田、城区敷设埋式光缆 72芯以下 | Z3: 丘陵、水田、城区敷设埋式光缆 96芯以下 | AA3: 丘陵、水田、城区敷设埋式光缆 144芯以下 | AB3: 丘陵、水田、城区敷设埋式光缆 288芯以下 | AC3: 丘陵、水田、城区敷设埋式光缆 288芯以上 | AD3: 山区敷设埋式光缆 36芯以下 | AE3: 山区敷设埋式光缆 72芯以下 | AF3: 山区敷设埋式光缆 96芯以下 | AG3: 山区敷设埋式光缆 144芯以下 | AH3: 山区敷设埋式光缆 288芯以下 | AI3: 山区敷设埋式光缆 288芯以上 | AJ3: 敷设埋式电缆 200对以下 | AK3: 铺管保护（钢管） | AL3: 埋设标石 丘陵、水田、城区 | AM3: 埋设标石 山区 | AN3: 安装宣传警示牌 | AO3: 安装防雷设施 敷设排流线（单条） | AP3: 立9m 以下水泥杆 综合土 | AQ3: 立11m 以下水泥杆 综合土 | AR3: 立13m 以下水泥杆 综合土 | AS3: 立13m 以下水泥H杆 综合土 | AT3: 装水泥撑杆 综合土 | AU3: 水泥杆夹板法装7/2.2单股拉线 综合土 | AV3: 水泥杆夹板法装7/2.6单股拉线 综合土 | AW3: 水泥杆夹板法装7/3.0单股拉线 综合土 | AX3: 安装拉线隔电子 | AY3: 安装拉线警示保护管 | AZ3: 电杆接高装置(单槽钢) | BA3: 电杆接高装置(双槽钢) | BB3: 单杆地线 拉线式 | BC3: 单杆地线 直埋式 | BD3: 安装预留缆架 | BE3: 安装吊线保护装置 | BF3: 水泥杆架设7/2.2吊线（丘陵） | BG3: 水泥杆架设7/2.2吊线（山区） | BH3: 水泥杆架设7/2.2吊线（城区） | BI3: 架设100米以内辅助吊线 | BJ3: 挂钩法架设架空光缆丘陵、城区、水田（36芯以下） | BK3: 挂钩法架设架空光缆丘陵、城区、水田（72芯以下） | BL3: 挂钩法架设架空光缆丘陵、城区、水田（144芯以下） | BM3: 挂钩法架设架空光缆丘陵、城区、水田（288芯以下） | BN3: 挂钩法架设架空光缆丘陵、城区、水田（288芯以上） | BO3: 挂钩法架设架空光缆山区（36芯以下） | BP3: 挂钩法架设架空光缆山区（72芯以下） | BQ3: 挂钩法架设架空光缆山区（144芯以下） | BR3: 挂钩法架设架空光缆山区（288芯以下） | BS3: 挂钩法架设架空光缆山区（288芯以上） | BT3: 吊线式架空电缆（100对以下） | BU3: 布放光(电)缆人孔抽水(积水) | BV3: 布放光(电)缆人孔抽水(流水) | BW3: 布放光(电)缆手孔抽水 | BX3: 人工敷设塑料子管 1孔子管 | BY3: 人工敷设塑料子管 2孔子管 | BZ3: 人工敷设塑料子管(6孔子管) | CA3: 人工敷设塑料子管(15孔子管) | CB3: 人工敷设塑料子管 3孔子管 | CC3: 人工敷设塑料子管 4孔子管 | CD3: 人工敷设塑料子管 5孔子管 | CE3: 空闲管孔中人工敷设一带纺织子管 | CF3: 非空闲管孔中人工敷设一带纺织子管 | CG3: 敷设管道光缆 12芯以下 | CH3: 敷设管道光缆 24芯以下 | CI3: 敷设管道光缆 48芯以下 | CJ3: 敷设管道光缆 96芯以下 | CK3: 敷设管道光缆 144芯以下 | CL3: 敷设管道光缆 288芯以下 | CM3: 人工敷设管道电缆 200对 以下 | CN3: 机械敷设管道电缆 200对 以下 | CO3: 打人（手）孔墙洞 砖砌人孔 3孔管 以下 | CP3: 打人（手）孔墙洞 砖砌人孔 3孔管 以上 | CQ3: 打人（手）孔墙洞 混凝土人孔 3孔管 以下 | CR3: 打人（手）孔墙洞 混凝土人孔 3孔管 以上 | CS3: 打穿楼墙洞 砖墙 | CT3: 打穿楼墙洞 混凝土墙 | CU3: 打穿楼层洞 预制板楼层 | CV3: 打穿楼层洞 混凝土楼层 | CW3: 增装支撑物 终端支撑物 | CX3: 增装支撑物 中间支撑物 | CY3: 安装引上钢管（Φ50以下）(杆上) | CZ3: 安装引上钢管（Φ50以下）(墙上) | DA3: 安装引上钢管（Φ50以上）(杆上) | DB3: 安装引上钢管（Φ50以上）(墙上) | DC3: 钉固塑料槽板 | DD3: 进局光(电)缆防水封堵 | DE3: 光(电)缆上线洞楼层间防火封堵 | DF3: 穿放引上光缆 | DG3: 穿放引上电缆 200对 以下 | DH3: 穿放引上电缆 200对 以上 | DI3: 架设吊线式墙壁光缆 | DJ3: 架设吊线式墙壁光缆（加吊） | DK3: 架设吊线式墙壁 | DL3: 布放钉固式墙壁光缆 | DM3: 墙壁方式敷设蝶形光缆 | DN3: 架设吊线式墙壁电缆 200对 以下 | DO3: 架设吊线式墙壁电缆 200对 以上 | DP3: 架设吊线式墙壁电缆 200对 以下 加挂 | DQ3: 布放钉固式墙壁电缆 200对 以下 | DR3: 布放钉固式墙壁电缆 200对 以上 | DS3: 架挂自承式墙壁电缆 100对 以下 | DT3: 架挂自承式墙壁电缆 100对 以上 | DU3: 钉固式敷设室内通道光缆 | DV3: 竖井引上光缆 | DW3: 槽道光缆 | DX3: 布放槽道电缆 | DY3: 布放顶棚内电缆 | DZ3: 敷设钢管（φ25以内） | EA3: 敷设钢管（φ50以内） | EB3: 敷设硬质PVC管（φ25以内） | EC3: 敷设硬质PVC管（φ50以内） | ED3: 敷设金属线槽（150宽以下） | EE3: 敷设金属线槽（300宽以下） | EF3: 敷设金属线槽（300宽以上） | EG3: 敷设塑料线槽（100宽以下） | EH3: 敷设塑料线槽（100宽以上） | EI3: 管内、暗槽内穿放光缆 | EJ3: 穿放4对对绞电缆 | EK3: 穿放大对数对绞电缆 非屏蔽50对 以下 | EL3: 穿放大对数对绞电缆 非屏蔽100对 以下 | EM3: 桥架、线槽、地板内明布光缆 | EN3: 桥架、线槽、网络地板内明布电缆 50对 以下 | EO3: 桥架、线槽、网络地板内明布电缆 100对 以下 | EP3: 光缆掏纤（4芯以下） | EQ3: 光缆掏纤（每增加2芯） | ER3: 光缆接续(机械法) | ES3: 现场组装光纤活动连接器 | ET3: 光缆成端接头（束状） | EU3: 光缆成端接头（带状） | EV3: 光缆接续(4芯以下) | EW3: 光缆接续(12芯以下) | EX3: 光缆接续(24芯以下) | EY3: 光缆接续(48芯以下) | EZ3: 光缆接续(72芯以下) | FA3: 光缆接续(96芯以下) | FB3: 光缆接续(144芯以下) | FC3: 8芯带以上带状光缆接续（144芯以下） | FD3: 8芯带以上带状光缆接续（288芯以下） | FE3: 40km以下中继段光缆测试(24芯以下)（单窗口） | FF3: 40km以下中继段光缆测试(24芯以下)（双窗口*1.8） | FG3: 40km以下中继段光缆测试(48芯以下)（单窗口） | FH3: 40km以下中继段光缆测试(48芯以下)（双窗口*1.8） | FI3: 40km以下中继段光缆测试(96芯以下)（单窗口） | FJ3: 40km以下中继段光缆测试(96芯以下)（双窗口*1.8） | FK3: 40km以下中继段光缆测试(144芯以下)（单窗口） | FL3: 40km以下中继段光缆测试(144芯以下)（双窗口*1.8） | FM3: 40km以下中继段光缆测试(288芯以下)（单窗口） | FN3: 40km以下中继段光缆测试(288芯以下)（双窗口*1.8） | FO3: 用户光缆测试(2芯以下) | FP3: 用户光缆测试(12芯以下) | FQ3: 用户光缆测试(24芯以下) | FR3: 用户光缆测试(48芯以下) | FS3: 用户光缆测试(72芯以下) | FT3: 用户光缆测试(96芯以下) | FU3: 用户光缆测试(132芯以下) | FV3: 用户光缆测试(144芯以下) | FW3: 用户光缆测试(168芯以下) | FX3: 用户光缆测试(192芯以下) | FY3: 用户光缆测试(216芯以下) | FZ3: 用户光缆测试(240芯以下) | GA3: 用户光缆测试(264芯以下) | GB3: 用户光缆测试(288芯以下) | GC3: 光纤链路衰减测试（1:4） | GD3: 光纤链路衰减测试（1:8） | GE3: 光纤链路衰减测试（1:16） | GF3: 光纤链路衰减测试（1:32） | GG3: 光纤链路衰减测试（1:64） | GH3: 光分配网（ODN）光纤链路全程测试 光纤链路回波损耗测试 | GI3: 布放总配线架成端电缆 200对 以下 | GJ3: 布放总配线架成端电缆 400对 以下 | GK3: 布放组线箱成端电缆 10对 以下 | GL3: 布放组线箱成端电缆 20对 以下 | GM3: 布放组线箱成端电缆 30对 以下 | GN3: 布放组线箱成端电缆 50对 以下 | GO3: 布放组线箱成端电缆 100对 以下 | GP3: 布放组线箱成端电缆 100对 以上 | GQ3: 安装多用接头盒 | GR3: 安装机柜、机架(落地式) | GS3: 安装机柜、机架(墙挂式) | GT3: 制作安装抗震底座 | GU3: 安装过线（路）盒（半周长） 200 以下 | GV3: 安装过线（路）盒（半周长） 200 以上 | GW3: 安装信息插盒底座 明装 | GX3: 安装信息插盒底座 砖墙内 | GY3: 安装8位模块式信息插座 单口 非屏蔽 | GZ3: 安装8位模块式信息插座 双口 非屏蔽 | HA3: 安装光分纤箱、光分路箱（架空式） | HB3: 安装光分纤箱、光分路箱（墙壁式） | HC3: 安装光缆终端盒 | HD3: 安装光缆接线箱 | HE3: 增（扩）装光纤一体化熔接托盘 | HF3: 机架（箱）内安装光分路器（安装高度1.5m以下） | HG3: 机架（箱）内安装光分路器（安装高度1.5m以上） | HH3: 光分路器与光纤线路插接 | HI3: 光分路器本机测试（1：2） | HJ3: 光分路器本机测试（1：4） | HK3: 光分路器本机测试（1：8） | HL3: 光分路器本机测试（1：16） | HM3: 光分路器本机测试（1：32） | HN3: 光分路器本机测试（1：64） | HO3: 安装光缆落地式交接箱(144芯以下) | HP3: 安装光缆落地式交接箱(288芯以下) | HQ3: 安装光缆落地式交接箱(288芯以上) | HR3: 安装壁挂式光缆交接箱（144芯以下） | HS3: 安装壁挂式光缆交接箱（288芯以下） | HT3: 安装挂墙式交接箱 600对以下 | HU3: 制装塑缆分线盒 10对以下 | HV3: 制装塑缆分线盒 20对以下 | HW3: 制装塑缆分线盒 30对以下 | HX3: 制装塑缆分线盒 50对以下 | HY3: 安装测试100回线保安排 试验排 | HZ3: 安装测试100回线接线排 | IA3: 安装室内有源机柜（落地式） | IB3: 安装室内有源机柜（嵌墙式） | IC3: 安装室内无源机柜（落地式） | ID3: 安装室内无源机柜（嵌墙式） | IE3: 安装室内挂墙机箱（有源） | IF3: 安装室内挂墙机箱（无源） | IG3: 安装电源分配柜、箱 架顶式 | IH3: 安装光分配架（整架） | II3: 安装光分配架（子架） | IJ3: 布放音频隔离线（单、双芯） | IK3: 布放SYV类射频同轴电缆（单芯） | IL3: 放绑设备电缆(SYV类射频同轴电缆(多芯)) | IM3: 布放数据电缆（10芯以下） | IN3: 编扎、焊接音频隔离线（单、双芯） | IO3: 编扎、焊(绕、卡)接设备电缆(SYV类射频同轴电缆) | IP3: 编扎、焊接数据电缆（10芯以下） | IQ3: 放、绑软光纤（设备机架之间放、绑）（15m以下） | IR3: 放、绑软光纤（设备机架之间放、绑）（15m以上） | IS3: 光纤分配架内跳线 | IT3: 中间站跳纤 | IU3: 布放单芯电力电缆（16mm2以下) | IV3: 布放单芯电力电缆（16mm2以下)（3*2.5mm2） | IW3: 布放单芯电力电缆（35mm2以下) | IX3: 敷设硬质PVC管/槽 | IY3: 安装集成式小型设备 | IZ3: 增（扩）装、更换光模块 | JA3: 安装测试传输设备接口盘 40Gb/s | JB3: 安装测试传输设备接口盘 10Gb/s | JC3: 安装测试传输设备接口盘 2.5Gb/s | JD3: 安装测试传输设备接口盘 622Mb/s | JE3: 安装测试传输设备接口盘 155Mb/s 光口 | JF3: 安装测试传输设备接口盘 155Mb/s 电口 | JG3: 安装测试传输设备接口盘 45/34Mb/s | JH3: 安装测试传输设备接口盘 2Mb/s | JI3: 安装测试传输设备接口盘 FE | JJ3: 安装测试传输设备接口盘 GE | JK3: 安装测试传输设备接口盘 10GE | JL3: 安装测试传输设备接口盘 40GE | JM3: 安装测试光电转换模块 | JN3: 线路段光端对测 | JO3: 保护倒换测试 | JP3: 复用设备系统调测 以太网光口 | JQ3: 复用设备系统调测 以太网电口 | JR3: 安装光网络单元（ONU）(集成式) | JS3: ONU/ONT设备上联光接口本机测试 | JT3: 系统功能验证及性能测试 ONU窄带端口 64线以下 | JU3: 系统功能验证及性能测试 ONU宽带端口 64线以下） | JV3: 安装、调测无线局域网接入点（AP）设备 | JW3: 安装调测低端路由器 安装路由器（整机型） | JX3: 安装调测低端路由器 综合调测低端路由器 | JY3: 安装低端局域网交换机 | JZ3: 安装高、中端局域网交换机 安装机箱及电源模块 | KA3: 安装高、中端局域网交换机 安装接口板 | KB3: 调测局域网交换机 低端 | KC3: 调测局域网交换机 高中端 | KD3: 安装调测集线器 | KE3: 安装、测试光电转换器 台式 | KF3: 安装网络安全设备 低端 | KG3: 安装网络安全设备 中端 | KH3: 调测网络安全设备 低端 | KI3: 调测网络安全设备 中端 | KJ3: 安装架空式集线器设备 | KK3: 安装用户集线器设备 | KL3: 交换机设备硬件调测 用户线 | KM3: 交换机设备硬件调测 以太网接口 电口 | KN3: 交换机设备软件调测 用户线 | KO3: 交换机设备软件调测 以太网接口 | KP3: 调测用户集线器 | KQ3: 无线局域网交换机 安装 | KR3: 无线局域网交换机 调测 | KS3: 安装POE供电模块 | KT3: 安装、调测光电转换模块 | KU3: 路由器 安装 | KV3: 路由器 调测 | KW3: 集线器 安装调测 | KX3: 无线局域网接入系统联调 | KY3: 安装24V蓄电池组 200Ah以下 | KZ3: 安装、调试交流不间断电源 3kVA以下
A4: 单位 | B4: 百米 | C4: 百米 | D4: 百米 | E4: 点 | F4: 芯盘 | G4: 芯盘 | H4: 百平方米 | I4: 百平方米 | J4: 百平方米 | K4: 百平方米 | L4: 百平方米 | M4: 百平方米 | N4: 百平方米 | O4: 百平方米 | P4: 百平方米 | Q4: 百立方米 | R4: 百立方米 | S4: 百立方米 | T4: 百立方米 | U4: 百立方米 | V4: 百立方米 | W4: 百立方米 | X4: 千米条 | Y4: 千米条 | Z4: 千米条 | AA4: 千米条 | AB4: 千米条 | AC4: 千米条 | AD4: 千米条 | AE4: 千米条 | AF4: 千米条 | AG4: 千米条 | AH4: 千米条 | AI4: 千米条 | AJ4: 千米条 | AK4: m | AL4: 个 | AM4: 个 | AN4: 块 | AO4: 千米 | AP4: 根 | AQ4: 根 | AR4: 根 | AS4: 座 | AT4: 根 | AU4: 条 | AV4: 条 | AW4: 条 | AX4: 处 | AY4: 处 | AZ4: 处 | BA4: 处 | BB4: 条 | BC4: 条 | BD4: 架 | BE4: m | BF4: 千米条 | BG4: 千米条 | BH4: 千米条 | BI4: 条档 | BJ4: 千米条 | BK4: 千米条 | BL4: 千米条 | BM4: 千米条 | BN4: 千米条 | BO4: 千米条 | BP4: 千米条 | BQ4: 千米条 | BR4: 千米条 | BS4: 千米条 | BT4: 千米条 | BU4: 个 | BV4: 个 | BW4: 个 | BX4: 千米 | BY4: 千米 | BZ4: 千米 | CA4: 千米 | CB4: 千米 | CC4: 千米 | CD4: 千米 | CE4: 公里 | CF4: 公里 | CG4: 千米条 | CH4: 千米条 | CI4: 千米条 | CJ4: 千米条 | CK4: 千米条 | CL4: 千米条 | CM4: 千米条 | CN4: 千米条 | CO4: 处 | CP4: 处 | CQ4: 处 | CR4: 处 | CS4: 个 | CT4: 个 | CU4: 个 | CV4: 个 | CW4: 套 | CX4: 套 | CY4: 根 | CZ4: 根 | DA4: 根 | DB4: 根 | DC4: 百米条 | DD4: 处 | DE4: 处 | DF4: 条 | DG4: 条 | DH4: 条 | DI4: 百米条 | DJ4: 百米条 | DK4: 百米条 | DL4: 百米条 | DM4: 百米条 | DN4: 百米条 | DO4: 百米条 | DP4: 百米条 | DQ4: 百米条 | DR4: 百米条 | DS4: 百米条 | DT4: 百米条 | DU4: 百米条 | DV4: 百米条 | DW4: 百米条 | DX4: 百米条 | DY4: 百米条 | DZ4: 百米 | EA4: 百米 | EB4: 百米 | EC4: 百米 | ED4: 百米 | EE4: 百米 | EF4: 百米 | EG4: 百米 | EH4: 百米 | EI4: 百米条 | EJ4: 百米条 | EK4: 百米条 | EL4: 百米条 | EM4: 百米条 | EN4: 百米条 | EO4: 百米条 | EP4: 处 | EQ4: 处 | ER4: 芯 | ES4: 芯 | ET4: 芯 | EU4: 芯 | EV4: 头 | EW4: 头 | EX4: 头 | EY4: 头 | EZ4: 头 | FA4: 头 | FB4: 头 | FC4: 头 | FD4: 头 | FE4: 中继段 | FF4: 中继段 | FG4: 中继段 | FH4: 中继段 | FI4: 中继段 | FJ4: 中继段 | FK4: 中继段 | FL4: 中继段 | FM4: 中继段 | FN4: 中继段 | FO4: 段 | FP4: 段 | FQ4: 段 | FR4: 段 | FS4: 段 | FT4: 段 | FU4: 段 | FV4: 段 | FW4: 段 | FX4: 段 | FY4: 段 | FZ4: 段 | GA4: 段 | GB4: 段 | GC4: 链路组 | GD4: 链路组 | GE4: 链路组 | GF4: 链路组 | GG4: 链路组 | GH4: 链路组 | GI4: 条 | GJ4: 条 | GK4: 条 | GL4: 条 | GM4: 条 | GN4: 条 | GO4: 条 | GP4: 条 | GQ4: 个 | GR4: 架 | GS4: 架 | GT4: 个 | GU4: 十个 | GV4: 十个 | GW4: 10个 | GX4: 10个 | GY4: 10个 | GZ4: 10个 | HA4: 套 | HB4: 套 | HC4: 套 | HD4: 套 | HE4: 块 | HF4: 台 | HG4: 台 | HH4: 端口 | HI4: 套 | HJ4: 套 | HK4: 套 | HL4: 套 | HM4: 套 | HN4: 套 | HO4: 个 | HP4: 个 | HQ4: 个 | HR4: 个 | HS4: 个 | HT4: 个 | HU4: 个 | HV4: 个 | HW4: 个 | HX4: 个 | HY4: 块 | HZ4: 块 | IA4: 架 | IB4: 架 | IC4: 架 | ID4: 架 | IE4: 架 | IF4: 架 | IG4: 架 | IH4: 架 | II4: 个 | IJ4: 100米条 | IK4: 100米条 | IL4: 100米条 | IM4: 100米条 | IN4: 条 | IO4: 芯条 | IP4: 条 | IQ4: 条 | IR4: 条 | IS4: 条 | IT4: 条 | IU4: 10米条 | IV4: 10米条 | IW4: 10米条 | IX4: 百米 | IY4: 套 | IZ4: 个 | JA4: 端口 | JB4: 端口 | JC4: 端口 | JD4: 端口 | JE4: 端口 | JF4: 端口 | JG4: 端口 | JH4: 端口 | JI4: 端口 | JJ4: 端口 | JK4: 端口 | JL4: 端口 | JM4: 端口 | JN4: 方向·系统 | JO4: 环·系统 | JP4: 端口 | JQ4: 端口 | JR4: 台 | JS4: 端口 | JT4: 10线 | JU4: 10线 | JV4: 套 | JW4: 台 | JX4: 套 | JY4: 台 | JZ4: 台 | KA4: 块 | KB4: 台 | KC4: 台 | KD4: 台 | KE4: 台 | KF4: 台 | KG4: 台 | KH4: 台 | KI4: 台 | KJ4: 台 | KK4: 架 | KL4: 千门 | KM4: 端口 | KN4: 千门 | KO4: 端口 | KP4: 千门 | KQ4: 台 | KR4: 台 | KS4: 个 | KT4: 个 | KU4: 台 | KV4: 台 | KW4: 台 | KX4: 系统 | KY4: 组 | KZ4: 台
A5: 技工 | B5: 0.56 | C5: 0.46 | D5: 0.35 | E5: 0.05 | F5: 0.02 | G5: 0.024 | H5: 3.33 | I5: 0.33 | J5: 1.88 | K5: 0.19 | L5: 1.04 | M5: 0.09 | N5: 0.31 | O5: 0.31 | P5: 5 | Q5: 0 | R5: 0 | S5: 0 | T5: 0 | U5: 0 | V5: 0 | W5: 0 | X5: 7.44 | Y5: 10.05 | Z5: 12.76 | AA5: 15.5 | AB5: 17.88 | AC5: 22.1 | AD5: 9.05 | AE5: 12.55 | AF5: 15.86 | AG5: 19.2 | AH5: 22.53 | AI5: 27.5 | AJ5: 8.35 | AK5: 0.03 | AL5: 0.07 | AM5: 0.09 | AN5: 0.1 | AO5: 2.2 | AP5: 0.52 | AQ5: 0.77 | AR5: 1.02 | AS5: 1.92 | AT5: 0.62 | AU5: 0.78 | AV5: 0.84 | AW5: 0.98 | AX5: 0.24 | AY5: 0.2 | AZ5: 0.24 | BA5: 0.4 | BB5: 0.07 | BC5: 0.18 | BD5: 0.1 | BE5: 0.05 | BF5: 4.25 | BG5: 4.67 | BH5: 4.5 | BI5: 1 | BJ5: 8.68 | BK5: 9.93 | BL5: 11.05 | BM5: 11.68 | BN5: 12.23 | BO5: 10.24 | BP5: 11.72 | BQ5: 12.94 | BR5: 14.32 | BS5: 15.25 | BT5: 9.05 | BU5: 0.25 | BV5: 0.38 | BW5: 0.13 | BX5: 4 | BY5: 5.2 | BZ5: 9.07 | CA5: 27.5 | CB5: 6.17 | CC5: 7.13 | CD5: 8.1 | CE5: 3.63 | CF5: 6.53 | CG5: 5.5 | CH5: 6.83 | CI5: 8.02 | CJ5: 9.02 | CK5: 10.4 | CL5: 11.44 | CM5: 11.76 | CN5: 9.2 | CO5: 0.36 | CP5: 0.54 | CQ5: 0.6 | CR5: 0.9 | CS5: 0.07 | CT5: 0.14 | CU5: 0.07 | CV5: 0.14 | CW5: 0.3 | CX5: 0.15 | CY5: 0.2 | CZ5: 0.25 | DA5: 0.25 | DB5: 0.35 | DC5: 2.6 | DD5: 0.13 | DE5: 0.06 | DF5: 0.52 | DG5: 0.42 | DH5: 0.46 | DI5: 2.75 | DJ5: 1.375 | DK5: 1.925 | DL5: 1.76 | DM5: 2 | DN5: 5.23 | DO5: 5.48 | DP5: 2.615 | DQ5: 3.34 | DR5: 3.59 | DS5: 4.81 | DT5: 5.06 | DU5: 1.2 | DV5: 1.5 | DW5: 0.5 | DX5: 0.65 | DY5: 1 | DZ5: 1.5 | EA5: 2 | EB5: 0.94 | EC5: 1.5 | ED5: 3.27 | EE5: 4.17 | EF5: 7.13 | EG5: 2.45 | EH5: 2.65 | EI5: 0.49 | EJ5: 0.45 | EK5: 0.55 | EL5: 0.7 | EM5: 0.4 | EN5: 0.5 | EO5: 0.6 | EP5: 0.75 | EQ5: 0.09 | ER5: 0.1 | ES5: 0.08 | ET5: 0.15 | EU5: 0.05 | EV5: 0.5 | EW5: 1.5 | EX5: 2.49 | EY5: 4.29 | EZ5: 5.9 | FA5: 7.17 | FB5: 8.1 | FC5: 3.48 | FD5: 4.44 | FE5: 2.58 | FF5: 4.644 | FG5: 4.56 | FH5: 8.208 | FI5: 6.9 | FJ5: 12.42 | FK5: 7.84 | FL5: 14.112 | FM5: 11.32 | FN5: 20.376 | FO5: 0.26 | FP5: 0.92 | FQ5: 1.29 | FR5: 2.28 | FS5: 3.03 | FT5: 3.45 | FU5: 3.82 | FV5: 3.92 | FW5: 4.18 | FX5: 4.52 | FY5: 4.81 | FZ5: 5.04 | GA5: 5.37 | GB5: 5.66 | GC5: 0.45 | GD5: 0.6 | GE5: 0.75 | GF5: 0.85 | GG5: 0.93 | GH5: 0.1 | GI5: 3.12 | GJ5: 6.08 | GK5: 0.3 | GL5: 0.46 | GM5: 0.61 | GN5: 1.08 | GO5: 1.55 | GP5: 2.6 | GQ5: 1.1 | GR5: 1.25 | GS5: 2.25 | GT5: 1.67 | GU5: 0 | GV5: 0.9 | GW5: 0.4 | GX5: 0.98 | GY5: 0.45 | GZ5: 0.75 | HA5: 0.56 | HB5: 0.5 | HC5: 0.3 | HD5: 0.55 | HE5: 0.1 | HF5: 0.2 | HG5: 0.4 | HH5: 0.03 | HI5: 0.16 | HJ5: 0.29 | HK5: 0.4 | HL5: 0.5 | HM5: 0.61 | HN5: 0.7 | HO5: 0.67 | HP5: 0.78 | HQ5: 0.94 | HR5: 1.07 | HS5: 1.34 | HT5: 2.9 | HU5: 0.48 | HV5: 0.66 | HW5: 1.03 | HX5: 1.27 | HY5: 0.75 | HZ5: 0.4 | IA5: 1.86 | IB5: 4.05 | IC5: 1.61 | ID5: 2.79 | IE5: 1.2 | IF5: 0.96 | IG5: 1 | IH5: 2.42 | II5: 0.19 | IJ5: 0.8 | IK5: 1 | IL5: 1.35 | IM5: 0.71 | IN5: 0.06 | IO5: 0.08 | IP5: 0.08 | IQ5: 0.29 | IR5: 0.46 | IS5: 0.13 | IT5: 0.7 | IU5: 0.18 | IV5: 0.36 | IW5: 0.25 | IX5: 0.65 | IY5: 0.85 | IZ5: 0.05 | JA5: 5.55 | JB5: 4.8 | JC5: 1.35 | JD5: 3.15 | JE5: 2.4 | JF5: 1.95 | JG5: 0.9 | JH5: 0.75 | JI5: 0.75 | JJ5: 3.3 | JK5: 5.25 | JL5: 7.8 | JM5: 0.5 | JN5: 0.95 | JO5: 1.5 | JP5: 0.35 | JQ5: 0.25 | JR5: 0.5 | JS5: 0.1 | JT5: 0.2 | JU5: 0.5 | JV5: 0.5 | JW5: 1.25 | JX5: 0.5 | JY5: 1.25 | JZ5: 1.2 | KA5: 0.5 | KB5: 0.5 | KC5: 1.25 | KD5: 0.5 | KE5: 0.5 | KF5: 1.05 | KG5: 1.55 | KH5: 1.1 | KI5: 1.6 | KJ5: 4.2 | KK5: 6.06 | KL5: 5.05 | KM5: 0.5 | KN5: 6.25 | KO5: 0.5 | KP5: 14.75 | KQ5: 1.25 | KR5: 2.4 | KS5: 0.3 | KT5: 0.3 | KU5: 2 | KV5: 5 | KW5: 0.8 | KX5: 1.2 | KY5: 1.51 | KZ5: 1.95
A6: 普工 | B6: 0.14 | C6: 0.12 | D6: 0.09 | E6: 0 | F6: 0 | G6: 0 | H6: 24.25 | I6: 1.75 | J6: 13 | K6: 1.25 | L6: 6.29 | M6: 0.59 | N6: 2.88 | O6: 2.88 | P6: 25.88 | Q6: 39.38 | R6: 51.5 | S6: 62.13 | T6: 40.88 | U6: 55 | V6: 71.13 | W6: 12 | X6: 30.58 | Y6: 33.69 | Z6: 36.52 | AA6: 38.44 | AB6: 41.25 | AC6: 45 | AD6: 40.22 | AE6: 43.54 | AF6: 47.1 | AG6: 50.14 | AH6: 53.13 | AI6: 57.46 | AJ6: 22.84 | AK6: 0.1 | AL6: 0.14 | AM6: 0.18 | AN6: 0.5 | AO6: 8.25 | AP6: 0.56 | AQ6: 0.85 | AR6: 1.23 | AS6: 3.38 | AT6: 0.62 | AU6: 0.6 | AV6: 0.6 | AW6: 0.6 | AX6: 0.1 | AY6: 0.2 | AZ6: 0.24 | BA6: 0.4 | BB6: 0 | BC6: 0.18 | BD6: 0.1 | BE6: 0.05 | BF6: 4.54 | BG6: 4.86 | BH6: 4.9 | BI6: 1 | BJ6: 6.86 | BK6: 7.79 | BL6: 8.75 | BM6: 10.86 | BN6: 11.39 | BO6: 7.98 | BP6: 9.13 | BQ6: 11.12 | BR6: 13.2 | BS6: 14.1 | BT6: 10.63 | BU6: 0.5 | BV6: 1 | BW6: 0.25 | BX6: 5.57 | BY6: 8.13 | BZ6: 17.78 | CA6: 69.33 | CB6: 10.54 | CC6: 12.96 | CD6: 15.37 | CE6: 5.15 | CF6: 9.27 | CG6: 10.94 | CH6: 13.08 | CI6: 15.35 | CJ6: 17.62 | CK6: 19.87 | CL6: 21.86 | CM6: 20.03 | CN6: 15.67 | CO6: 0.36 | CP6: 0.54 | CQ6: 0.6 | CR6: 0.9 | CS6: 0.06 | CT6: 0.13 | CU6: 0.06 | CV6: 0.13 | CW6: 0.3 | CX6: 0.15 | CY6: 0.2 | CZ6: 0.25 | DA6: 0.25 | DB6: 0.35 | DC6: 2.6 | DD6: 0.13 | DE6: 0.06 | DF6: 0.52 | DG6: 0.42 | DH6: 0.46 | DI6: 2.75 | DJ6: 1.375 | DK6: 1.925 | DL6: 1.76 | DM6: 2.5 | DN6: 5.23 | DO6: 5.48 | DP6: 2.615 | DQ6: 3.33 | DR6: 3.58 | DS6: 4.81 | DT6: 5.06 | DU6: 1.8 | DV6: 2 | DW6: 0.5 | DX6: 0.65 | DY6: 1 | DZ6: 4.13 | EA6: 5.13 | EB6: 3 | EC6: 4.13 | ED6: 6.63 | EE6: 8.43 | EF6: 11.38 | EG6: 4.99 | EH6: 5.38 | EI6: 0.49 | EJ6: 0.45 | EK6: 0.55 | EL6: 0.7 | EM6: 0.4 | EN6: 0.5 | EO6: 0.6 | EP6: 0 | EQ6: 0 | ER6: 0 | ES6: 0 | ET6: 0 | EU6: 0 | EV6: 0 | EW6: 0 | EX6: 0 | EY6: 0 | EZ6: 0 | FA6: 0 | FB6: 0 | FC6: 0 | FD6: 0 | FE6: 0 | FF6: 0 | FG6: 0 | FH6: 0 | FI6: 0 | FJ6: 0 | FK6: 0 | FL6: 0 | FM6: 0 | FN6: 0 | FO6: 0 | FP6: 0 | FQ6: 0 | FR6: 0 | FS6: 0 | FT6: 0 | FU6: 0 | FV6: 0 | FW6: 0 | FX6: 0 | FY6: 0 | FZ6: 0 | GA6: 0 | GB6: 0 | GC6: 0 | GD6: 0 | GE6: 0 | GF6: 0 | GG6: 0 | GH6: 0 | GI6: 0 | GJ6: 0 | GK6: 0 | GL6: 0 | GM6: 0 | GN6: 0 | GO6: 0 | GP6: 0 | GQ6: 0.28 | GR6: 0.67 | GS6: 1 | GT6: 0.83 | GU6: 0.4 | GV6: 0.4 | GW6: 0 | GX6: 0 | GY6: 0.07 | GZ6: 0.07 | HA6: 0.56 | HB6: 0.5 | HC6: 0.3 | HD6: 0.55 | HE6: 0 | HF6: 0 | HG6: 0 | HH6: 0 | HI6: 0 | HJ6: 0 | HK6: 0 | HL6: 0 | HM6: 0 | HN6: 0 | HO6: 0.67 | HP6: 0.78 | HQ6: 0.94 | HR6: 1.07 | HS6: 1.34 | HT6: 2.9 | HU6: 0.19 | HV6: 0.28 | HW6: 0.36 | HX6: 0.54 | HY6: 0 | HZ6: 0 | IA6: 0 | IB6: 0 | IC6: 0 | ID6: 0 | IE6: 0 | IF6: 0 | IG6: 0 | IH6: 0 | II6: 0 | IJ6: 0 | IK6: 0 | IL6: 0 | IM6: 0 | IN6: 0 | IO6: 0 | IP6: 0 | IQ6: 0 | IR6: 0 | IS6: 0 | IT6: 0 | IU6: 0 | IV6: 0 | IW6: 0 | IX6: 0 | IY6: 0 | IZ6: 0 | JA6: 0 | JB6: 0 | JC6: 0 | JD6: 0 | JE6: 0 | JF6: 0 | JG6: 0 | JH6: 0 | JI6: 0 | JJ6: 0 | JK6: 0 | JL6: 0 | JM6: 0 | JN6: 0 | JO6: 0 | JP6: 0 | JQ6: 0 | JR6: 0 | JS6: 0 | JT6: 0 | JU6: 0 | JV6: 0 | JW6: 0 | JX6: 0 | JY6: 0 | JZ6: 0 | KA6: 0 | KB6: 0 | KC6: 0 | KD6: 0 | KE6: 0 | KF6: 0 | KG6: 0 | KH6: 0 | KI6: 0 | KJ6: 0 | KK6: 0 | KL6: 0 | KM6: 0 | KN6: 0 | KO6: 0 | KP6: 0 | KQ6: 0 | KR6: 0 | KS6: 0 | KT6: 0 | KU6: 0 | KV6: 0 | KW6: 0 | KX6: 0 | KY6: 0 | KZ6: 0
A7: 工程量合计 | B7: 0 | C7: 13.88 | D7: 0.48 | E7: 4 | F7: 0 | G7: 84 | H7: 0 | I7: 0 | J7: 0 | K7: 0 | L7: 0 | M7: 0 | N7: 0 | O7: 0 | P7: 0 | Q7: 0 | R7: 0 | S7: 0 | T7: 0 | U7: 0 | V7: 0 | W7: 0 | X7: 0 | Y7: 0 | Z7: 0 | AA7: 0 | AB7: 0 | AC7: 0 | AD7: 0 | AE7: 0 | AF7: 0 | AG7: 0 | AH7: 0 | AI7: 0 | AJ7: 0 | AK7: 0 | AL7: 0 | AM7: 0 | AN7: 0 | AO7: 0 | AP7: 3 | AQ7: 0 | AR7: 0 | AS7: 0 | AT7: 0 | AU7: 0 | AV7: 2 | AW7: 0 | AX7: 0 | AY7: 0 | AZ7: 0 | BA7: 0 | BB7: 0 | BC7: 2 | BD7: 0 | BE7: 20 | BF7: 0 | BG7: 0 | BH7: 0.16 | BI7: 0 | BJ7: 0 | BK7: 0.422 | BL7: 0 | BM7: 0 | BN7: 0 | BO7: 0 | BP7: 0 | BQ7: 0 | BR7: 0 | BS7: 0 | BT7: 0 | BU7: 0 | BV7: 0 | BW7: 2 | BX7: 0 | BY7: 0 | BZ7: 0.014 | CA7: 0 | CB7: 0 | CC7: 0 | CD7: 0 | CE7: 0 | CF7: 0 | CG7: 0.063 | CH7: 0 | CI7: 0 | CJ7: 0 | CK7: 0 | CL7: 0 | CM7: 0 | CN7: 0 | CO7: 0 | CP7: 0 | CQ7: 0 | CR7: 0 | CS7: 10 | CT7: 0 | CU7: 0 | CV7: 4 | CW7: 0 | CX7: 0 | CY7: 0 | CZ7: 0 | DA7: 0 | DB7: 0 | DC7: 0 | DD7: 3 | DE7: 0 | DF7: 1 | DG7: 0 | DH7: 0 | DI7: 4.2 | DJ7: 5.32 | DK7: 0 | DL7: 0.35 | DM7: 0 | DN7: 5.6 | DO7: 0 | DP7: 0 | DQ7: 0 | DR7: 0 | DS7: 0 | DT7: 0 | DU7: 0 | DV7: 0 | DW7: 8.61 | DX7: 0 | DY7: 0 | DZ7: 0 | EA7: 0 | EB7: 0.2 | EC7: 0 | ED7: 0 | EE7: 0 | EF7: 0 | EG7: 9.37 | EH7: 0.05 | EI7: 0 | EJ7: 0 | EK7: 0 | EL7: 0 | EM7: 0 | EN7: 0 | EO7: 0 | EP7: 0 | EQ7: 0 | ER7: 0 | ES7: 0 | ET7: 102 | EU7: 0 | EV7: 0 | EW7: 5 | EX7: 0 | EY7: 1 | EZ7: 0 | FA7: 0 | FB7: 0 | FC7: 0 | FD7: 0 | FE7: 0 | FF7: 0 | FG7: 0 | FH7: 0 | FI7: 0 | FJ7: 0 | FK7: 0 | FL7: 0 | FM7: 0 | FN7: 0 | FO7: 0 | FP7: 2 | FQ7: 0 | FR7: 1 | FS7: 0 | FT7: 0 | FU7: 0 | FV7: 0 | FW7: 0 | FX7: 0 | FY7: 0 | FZ7: 0 | GA7: 0 | GB7: 0 | GC7: 0 | GD7: 4 | GE7: 0 | GF7: 0 | GG7: 0 | GH7: 0 | GI7: 2 | GJ7: 0 | GK7: 1 | GL7: 0 | GM7: 0 | GN7: 0 | GO7: 0 | GP7: 0 | GQ7: 0 | GR7: 0 | GS7: 0 | GT7: 0 | GU7: 0 | GV7: 0 | GW7: 9 | GX7: 0 | GY7: 0 | GZ7: 0 | HA7: 0 | HB7: 9 | HC7: 0 | HD7: 0 | HE7: 5 | HF7: 5 | HG7: 28 | HH7: 0 | HI7: 0 | HJ7: 0 | HK7: 33 | HL7: 0 | HM7: 0 | HN7: 0 | HO7: 0 | HP7: 0 | HQ7: 0 | HR7: 0 | HS7: 0 | HT7: 0 | HU7: 0 | HV7: 1 | HW7: 0 | HX7: 0 | HY7: 0 | HZ7: 0 | IA7: 6 | IB7: 1 | IC7: 0 | ID7: 1 | IE7: 1 | IF7: 0 | IG7: 0 | IH7: 0 | II7: 0 | IJ7: 7.3 | IK7: 0 | IL7: 0 | IM7: 16.87 | IN7: 17 | IO7: 4 | IP7: 98 | IQ7: 156 | IR7: 30 | IS7: 144 | IT7: 154 | IU7: 2 | IV7: 1 | IW7: 0 | IX7: 74 | IY7: 21 | IZ7: 44 | JA7: 0 | JB7: 0 | JC7: 0 | JD7: 0 | JE7: 0 | JF7: 0 | JG7: 0 | JH7: 0 | JI7: 19 | JJ7: 11 | JK7: 2 | JL7: 0 | JM7: 0 | JN7: 1 | JO7: 1 | JP7: 0 | JQ7: 14 | JR7: 15 | JS7: 16 | JT7: 0 | JU7: 10.7 | JV7: 0 | JW7: 2 | JX7: 0 | JY7: 2 | JZ7: 0 | KA7: 0 | KB7: 1 | KC7: 0 | KD7: 0 | KE7: 5 | KF7: 0 | KG7: 0 | KH7: 0 | KI7: 0 | KJ7: 4 | KK7: 2 | KL7: 0.141 | KM7: 5 | KN7: 0.14 | KO7: 5 | KP7: 0.1 | KQ7: 0 | KR7: 0 | KS7: 0 | KT7: 4 | KU7: 0 | KV7: 0 | KW7: 0 | KX7: 0 | KY7: 0 | KZ7: 0
A8: 恩平市金丰电子器材厂+语音专线+变更 | IM8: 0.2 | IP8: 1 | JI8: 1 | KK8: 1 | KL8: 0.1 | KM8: 1 | KN8: 0.1 | KO8: 1 | KP8: 0.1
A9: 恩平市中山医院+互联网专线+语音专线+新增
A10: 国家税务总局恩平市税务局前进街办事点+互联网专线+新增+融合 | IM10: 0.2 | IP10: 2 | IQ10: 2 | IS10: 2 | IT10: 4 | IX10: 1 | IY10: 1 | JJ10: 1 | JQ10: 1
A11: 国家税务总局恩平市税务局恩城税务分局+互联网专线+新增+融合 | IM11: 0.2 | IP11: 2 | IQ11: 2 | IS11: 4 | IT11: 2 | IX11: 1 | IY11: 1 | JJ11: 1 | JQ11: 1
A12: 国家税务总局恩平市税务局圣堂税务分局+互联网专线+新增+融合 | IM12: 0.3 | IP12: 2 | IQ12: 2 | IS12: 4 | IT12: 2 | IX12: 1 | IY12: 1 | JJ12: 1 | JQ12: 1
A13: 国家税务总局恩平市税务局大槐税务分局+互联网专线+新增+融合 | IM13: 0.2 | IP13: 2 | IQ13: 2 | IS13: 2 | IT13: 4 | IX13: 1 | IY13: 1 | JJ13: 1 | JQ13: 1
A14: 开平市公安局赤坎派出所+互联网专线+搬迁 | IM14: 0.1 | IP14: 1 | IQ14: 2 | JR14: 1 | JS14: 1 | JU14: 0.5
A15: 开平市公安局新昌派出所+互联网专线+搬迁 | IM15: 0.1 | IP15: 1 | IQ15: 4 | JR15: 1 | JS15: 1 | JU15: 0.5
A16: 开平市公安局新昌派出思始点+互联网专线+搬迁 | IB16: 1 | IM16: 0.1 | IP16: 1 | IQ16: 4 | IU16: 1 | JR16: 1 | JS16: 1 | JU16: 0.5
A17: 开平市公安局月山派出所+互联网专线+搬迁 | IM17: 0.1 | IP17: 1 | IQ17: 3 | JR17: 1 | JS17: 1 | JU17: 0.5
A18: 江门开平市长沙福来旅店预覆盖工程（小微新建） | C18: 0.24 | E18: 1 | G18: 12 | CS18: 7 | DD18: 1 | DW18: 7.97 | EG18: 2.09 | ET18: 6 | EW18: 2 | FP18: 1 | GD18: 1 | HB18: 1 | HF18: 1 | HG18: 3 | HK18: 4 | IQ18: 1 | IR18: 4 | IS18: 5 | IT18: 1
A19: 江门开平市味香皇食品厂预覆盖工程（小微新建） | C19: 8.42 | E19: 1 | G19: 60 | AP19: 3 | AV19: 2 | BH19: 0.16 | BK19: 0.422 | CS19: 2 | CV19: 4 | DD19: 1 | DI19: 4.2 | DW19: 0.64 | EG19: 7.28 | ET19: 84 | EW19: 3 | EY19: 1 | FR19: 1 | HB19: 7 | HE19: 4 | HF19: 3 | HG19: 22 | HK19: 25 | IQ19: 3 | IR19: 25 | IS19: 25 | IT19: 6
A20: 开平市中心医院（水口医院） | IM20: 0.05 | IP20: 1 | IQ20: 4 | IT20: 2 | IY20: 1 | IZ20: 1
A21: 广东东方思维科技有限公司 | IM21: 0.05 | IP21: 1 | IQ21: 4 | IT21: 2 | IY21: 1 | IZ21: 1
A22: 开平市美力服装有限公司 | ID22: 1 | IJ22: 0.2 | IM22: 0.25 | IN22: 1 | IP22: 2 | IQ22: 4 | IU22: 1 | IV22: 1 | JR22: 1 | JS22: 1 | JU22: 0.2 | KK22: 1 | KL22: 0.001
A23: 恩平市供水有限公司+集团专线+搬迁 | GW23: 1 | IE23: 1 | IM23: 0.2 | IP23: 1 | IQ23: 2 | IS23: 4 | IT23: 2 | JI23: 1 | KE23: 1
A24: 恩平富辉纺织企业有限公司 | GW24: 1 | IA24: 1 | IM24: 0.2 | IP24: 3 | JI24: 2 | KT24: 2
A25: 恩平市溢丰纺织有限公司 | GW25: 1 | IM25: 0.4 | IP25: 2 | IQ25: 4 | IS25: 6 | IT25: 6 | JI25: 2 | JQ25: 2 | KE25: 2
A26: 开平市翡翠网吧 | IM26: 0.1 | IO26: 1 | IQ26: 24 | IT26: 4 | IY26: 1 | IZ26: 2 | JJ26: 1
A27: 开平市莱尚网咖网吧 | IM27: 0.1 | IO27: 1 | IQ27: 24 | IT27: 4 | IY27: 1 | IZ27: 2
A28: 广发证券股份有限公司江门恩平证券营业部 | GW28: 1 | IM28: 0.3 | IP28: 3 | IQ28: 1 | IS28: 2 | JI28: 1 | JR28: 1 | JS28: 1 | JU28: 1 | KJ28: 1 | KL28: 0.01 | KM28: 1 | KN28: 0.01 | KO28: 1
A29: 开平市公安局潭江派出所（巡警大对） | IM29: 0.1 | IO29: 1 | IQ29: 3 | JR29: 1 | JS29: 1 | JU29: 0.1
A30: 江门市合山水利工程管理处（互联网专线+电路租用） | IM30: 0.1 | IP30: 2 | IQ30: 4 | IT30: 4 | IY30: 1 | IZ30: 1 | JU30: 0.1
A31: 开平市广侨汽车销售服务有限公司（恩平店）（统一Centrex+互联网专线） | GW31: 1 | IA31: 1 | IM31: 0.2 | IP31: 2 | IQ31: 1 | IS31: 1 | JI31: 2 | JR31: 1 | JS31: 1 | JU31: 1 | KJ31: 1 | KL31: 0.01 | KM31: 1 | KN31: 0.01 | KO31: 1
A32: 开平市公安局长沙派出所 | IM32: 0.1 | IO32: 1 | IQ32: 3 | IT32: 1 | JR32: 1 | JS32: 1 | JU32: 0.1
A33: 开平+粤顺牧业有限公司+新增 | IM33: 0.06 | IP33: 3 | IQ33: 6 | IT33: 2 | JR33: 1 | JS33: 1 | JU33: 0.1 | KE33: 2
A34: 开平+开平市应急管理局+新增 | IM34: 0.1 | IP34: 1 | IQ34: 6 | IT34: 4 | IY34: 1 | IZ34: 1 | JU34: 0.1
A35: 恩平+恩平市君堂镇人民政府+变更 | DN35: 5.6 | GI35: 2 | HV35: 1 | IM35: 0.2 | IX35: 19
A36: 开平+开平市环境卫生管理处+G325义祠路交叉公园内+新增 | IM36: 0.1 | IP36: 1 | IQ36: 4 | IT36: 4 | IY36: 1 | IZ36: 1
A37: 恩平+恩平市沙湖六乡市场+新增 | IM37: 0.2 | IP37: 1 | IQ37: 1 | IS37: 1 | JJ37: 1 | JR37: 1 | JS37: 1 | JU37: 1
A38: 恩平+恩平锦兴纺织印染企业有限公司+变更 | IJ38: 7 | IN38: 15 | IX38: 7
A39: 恩平+恩平市科达声通电子器材厂（分厂）+新增 | GK39: 1 | GW39: 1 | IA39: 1 | IM39: 0.2 | IP39: 6 | IQ39: 1 | IS39: 1 | JI39: 4 | JR39: 1 | JS39: 1 | JU39: 1 | KJ39: 1 | KL39: 0.01 | KM39: 1 | KN39: 0.01 | KO39: 1
A40: 恩平+恩平市万国商业城开发有限公司+新增 | GW40: 1 | IA40: 1 | IJ40: 0.1 | IM40: 0.2 | IN40: 1 | IP40: 3 | IQ40: 1 | IS40: 3 | JI40: 3 | JR40: 1 | JS40: 1 | JU40: 1 | KJ40: 1 | KL40: 0.01 | KM40: 1 | KN40: 0.01 | KO40: 1
A41: 恩平+江苏金江建设有限公司+新增 | GW41: 1 | IA41: 1 | IM41: 6 | IP41: 20 | IQ41: 1 | IS41: 3 | IX41: 24 | JJ41: 2 | JR41: 1 | JS41: 1 | JU41: 1
A42: 恩平+恩平市君堂镇中心小学（主校区）+新增 | GW42: 1 | IA42: 1 | IM42: 5 | IP42: 20 | IQ42: 1 | IS42: 2 | IX42: 20 | JJ42: 2 | JR42: 1 | JS42: 2 | JU42: 2 | JW42: 1 | JY42: 1 | KT42: 2
A43: 开平+开平市公安局+南环簕冲红绿灯+新增 | IQ43: 8 | IT43: 16 | IZ43: 2
A44: 恩平+恩平市水利局+青南角+二期+新增 | IM44: 0.2 | IP44: 2 | IQ44: 2 | IT44: 2 | IY44: 1 | JI44: 1 | JJ44: 1 | JQ44: 1
A45: 恩平+恩平市水利局+江北灌区+二期+新增 | IM45: 0.2 | IP45: 1 | IQ45: 2 | IS45: 4 | IT45: 4 | IY45: 1 | JI45: 1 | JQ45: 1
A46: 恩平+恩平市水利局+凤子山+二期+新增 | IM46: 0.2 | IP46: 1 | IQ46: 2 | IS46: 4 | IT46: 2 | IY46: 1 | JI46: 1 | JQ46: 1
A47: 跨市+中华人民共和国珠海出入境边防检查总站+开平边检站+新增 | IM47: 0.08 | IP47: 4 | IQ47: 12 | IT47: 4 | IY47: 1 | IZ47: 2 | JK47: 2 | JN47: 1 | JO47: 1 | JQ47: 4 | JW47: 1
A48: 开平+广东开平文旅发展集团有限公司+Z端+新增 | IM48: 0.4 | IP48: 2 | IQ48: 6 | IT48: 4 | IY48: 1 | IZ48: 1
A49: 开平+开平市世界遗产管理中心+新增 | IM49: 0.06 | IP49: 3 | IS49: 4 | IT49: 2 | IY49: 1 | IZ49: 2 | JY49: 1 | KB49: 1
A50: 开平+开平百事通计算机+新增 | IM50: 0 | IP50: 0 | IS50: 58 | IT50: 62 | IY50: 3 | IZ50: 26 | JY50: 0 | KB50: 0
A51: 开平+开平市百合镇消防专职队+新增 | IM51: 0.02 | IP51: 0 | IS51: 2 | IT51: 2 | IY51: 1 | IZ51: 2 | JQ51: 1 | JY51: 0 | KB51: 0
A52: 江门恩平市御茶餐饮店XWXJ | C52: 5.22 | D52: 0.48 | E52: 2 | G52: 12 | BC52: 2 | BE52: 20 | BW52: 2 | BZ52: 0.014 | CG52: 0.063 | CS52: 1 | DD52: 1 | DF52: 1 | DJ52: 5.32 | DL52: 0.35 | EB52: 0.2 | EH52: 0.05 | ET52: 12 | FP52: 1 | GD52: 3 | HB52: 1 | HE52: 1 | HF52: 1 | HG52: 3 | HK52: 4 | IR52: 1 | IS52: 7 | IT52: 2
A53: =SUM(B53:LQ53) -> 1289.97 | B53: =SUM(B8:B52) -> 0 | C53: =SUM(C8:C52) -> 13.88 | D53: =SUM(D8:D52) -> 0.48 | E53: =SUM(E8:E52) -> 4 | F53: =SUM(F8:F52) -> 0 | G53: =SUM(G8:G52) -> 84 | H53: =SUM(H8:H52) -> 0 | I53: =SUM(I8:I52) -> 0 | ... KZ53: =SUM(KZ8:KZ52) -> 0 | LA53: =SUM(LA17:LA52) -> 0 | LB53: =SUM(LB17:LB52) -> 0 | LC53: =SUM(LC17:LC52) -> 0 | LD53: =SUM(LD17:LD52) -> 0 | LE53: =SUM(LE17:LE52) -> 0 | LF53: =SUM(LF17:LF52) -> 0 | LG53: =SUM(LG17:LG52) -> 0 | LH53: =SUM(LH17:LH52) -> 0 | ... LQ53: =SUM(LQ17:LQ52) -> 0

Sheet Sheet5
A1: 序号 | B1: 1 | C1: 2 | D1: 3 | E1: 4 | F1: 5 | G1: 6 | H1: 7 | I1: 8 | J1: 9 | K1: 10 | L1: 11 | M1: 12 | N1: 13 | O1: 14 | P1: 15 | Q1: 16 | R1: 17 | S1: 18 | T1: 19 | U1: 20 | V1: 21 | W1: 22 | X1: 23 | Y1: 24 | Z1: 25 | AA1: 26 | AB1: 27 | AC1: 28 | AD1: 29 | AE1: 30 | AF1: 31 | AG1: 32 | AH1: 33 | AI1: 34 | AJ1: 35 | AK1: 36 | AL1: 37 | AM1: 38 | AN1: 39 | AO1: 40 | AP1: 41 | AQ1: 42 | AR1: 43 | AS1: 44 | AT1: 45 | AU1: 46 | AV1: 47 | AW1: 48 | AX1: 49 | AY1: 50 | AZ1: 51 | BA1: 52 | BB1: 53 | BC1: 54 | BD1: 55 | BE1: 56 | BF1: 57 | BG1: 58 | BH1: 59 | BI1: 60 | BJ1: 61 | BK1: 62 | BL1: 63 | BM1: 64 | BN1: 65 | BO1: 66 | BP1: 67 | BQ1: 68 | BR1: 69 | BS1: 70 | BT1: 71 | BU1: 72 | BV1: 73 | BW1: 74 | BX1: 75 | BY1: 76 | BZ1: 77 | CA1: 78 | CB1: 79 | CC1: 80 | CD1: 81 | CE1: 82 | CF1: 83 | CG1: 84 | CH1: 85 | CI1: 86 | CJ1: 87 | CK1: 88 | CL1: 89 | CM1: 90 | CN1: 91 | CO1: 92 | CP1: 93 | CQ1: 94 | CR1: 95 | CS1: 96 | CT1: 97 | CU1: 98 | CV1: 99 | CW1: 100 | CX1: 101 | CY1: 102 | CZ1: 103 | DA1: 104 | DB1: 105 | DC1: 106 | DD1: 107 | DE1: 108 | DF1: 109 | DG1: 110 | DH1: 111 | DI1: 112 | DJ1: 113 | DK1: 114 | DL1: 115 | DM1: 116 | DN1: 117 | DO1: 118 | DP1: 119 | DQ1: 120 | DR1: 121 | DS1: 122 | DT1: 123 | DU1: 124 | DV1: 125 | DW1: 126 | DX1: 127 | DY1: 128 | DZ1: 129 | EA1: 130 | EB1: 131 | EC1: 132 | ED1: 133 | EE1: 134 | EF1: 135 | EG1: 136 | EH1: 137 | EI1: 138 | EJ1: 139 | EK1: 140 | EL1: 141 | EM1: 142 | EN1: 143 | EO1: 144 | EP1: 145 | EQ1: 146 | ER1: 147 | ES1: 148 | ET1: 149 | EU1: 150 | EV1: 151 | EW1: 152 | EX1: 153 | EY1: 154 | EZ1: 155 | FA1: 156 | FB1: 157 | FC1: 158 | FD1: 159 | FE1: 160 | FF1: 161 | FG1: 162 | FH1: 163 | FI1: 164 | FJ1: 165 | FK1: 166 | FL1: 167 | FM1: 168 | FN1: 169 | FO1: 170 | FP1: 171 | FQ1: 172 | FR1: 173 | FS1: 174 | FT1: 175 | FU1: 176 | FV1: 177 | FW1: 178 | FX1: 179 | FY1: 180 | FZ1: 181 | GA1: 182 | GB1: 183 | GC1: 184 | GD1: 185 | GE1: 186 | GF1: 187 | GG1: 188 | GH1: 189 | GI1: 190 | GJ1: 191 | GK1: 192 | GL1: 193 | GM1: 194 | GN1: 195 | GO1: 196 | GP1: 197 | GQ1: 198 | GR1: 199 | GS1: 200 | GT1: 201 | GU1: 202 | GV1: 203 | GW1: 204 | GX1: 205 | GY1: 206 | GZ1: 207 | HA1: 208 | HB1: 209 | HC1: 210 | HD1: 211 | HE1: 212 | HF1: 213 | HG1: 214 | HH1: 215 | HI1: 216 | HJ1: 217 | HK1: 218 | HL1: 219 | HM1: 220 | HN1: 221 | HO1: 222 | HP1: 223 | HQ1: 224 | HR1: 225 | HS1: 226 | HT1: 227 | HU1: 228 | HV1: 229 | HW1: 230 | HX1: 231 | HY1: 232 | HZ1: 233 | IA1: 234 | IB1: 235 | IC1: 236 | ID1: 237 | IE1: 238 | IF1: 239 | IG1: 240 | IH1: 241 | II1: 242 | IJ1: 243 | IK1: 244 | IL1: 245 | IM1: 246 | IN1: 247 | IO1: 248 | IP1: 249 | IQ1: 250 | IR1: 251 | IS1: 252 | IT1: 253 | IU1: 254 | IV1: 255 | IW1: 256 | IX1: 257 | IY1: 258 | IZ1: 259 | JA1: 260 | JB1: 261 | JC1: 262 | JD1: 263 | JE1: 264 | JF1: 265 | JG1: 266 | JH1: 267 | JI1: 268 | JJ1: 269 | JK1: 270 | JL1: 271 | JM1: 272 | JN1: 273 | JO1: 274 | JP1: 275 | JQ1: 276 | JR1: 277 | JS1: 278 | JT1: 279 | JU1: 280 | JV1: 281 | JW1: 282 | JX1: 283 | JY1: 284 | JZ1: 285 | KA1: 286 | KB1: 287 | KC1: 288 | KD1: 289 | KE1: 290 | KF1: 291 | KG1: 292 | KH1: 293 | KI1: 294 | KJ1: 295 | KK1: 296 | KL1: 297 | KM1: 298 | KN1: 299 | KO1: 300 | KP1: 301 | KQ1: 302 | KR1: 303 | KS1: 304 | KT1: 305 | KU1: 306 | KV1: 307 | KW1: 308 | KX1: 309 | KY1: 310 | KZ1: 311
A2: 定额编号 | B2: TXL1-001 | C2: TXL1-002 | D2: TXL1-003 | E2: TXL1-005 | F2: TXL1-006 | G2: TXL1-006-1 | H2: TXL1-008 | I2: TXL1-009 | J2: TXL1-010 | K2: TXL1-011 | L2: TXL1-012 | M2: TXL1-013 | N2: TXL1-014 | O2: TXL1-015 | P2: TXL1-016 | Q2: TXL2-001 | R2: TXL2-002 | S2: TXL2-003 | T2: TXL2-007 | U2: TXL2-008 | V2: TXL2-009 | W2: TXL2-014 | X2: TXL2-021 | Y2: TXL2-022 | Z2: TXL2-023 | AA2: TXL2-024 | AB2: TXL2-025 | AC2: TXL2-026 | AD2: TXL2-027 | AE2: TXL2-028 | AF2: TXL2-029 | AG2: TXL2-030 | AH2: TXL2-031 | AI2: TXL2-032 | AJ2: TXL2-033 | AK2: TXL2-109 | AL2: TXL2-121 | AM2: TXL2-122 | AN2: TXL2-123 | AO2: TXL2-127 | AP2: TXL3-001 | AQ2: TXL3-004 | AR2: TXL3-007 | AS2: TXL3-010 | AT2: TXL3-048 | AU2: TXL3-051 | AV2: TXL3-054 | AW2: TXL3-057 | AX2: TXL3-142 | AY2: TXL3-143 | AZ2: TXL3-144 | BA2: TXL3-145 | BB2: TXL3-146 | BC2: TXL3-147 | BD2: TXL3-149 | BE2: TXL3-150 | BF2: TXL3-169 | BG2: TXL3-170 | BH2: TXL3-171 | BI2: TXL3-180 | BJ2: TXL3-192 | BK2: TXL3-193 | BL2: TXL3-194 | BM2: TXL3-195 | BN2: TXL3-196 | BO2: TXL3-197 | BP2: TXL3-198 | BQ2: TXL3-199 | BR2: TXL3-200 | BS2: TXL3-201 | BT2: TXL3-218 | BU2: TXL4-001 | BV2: TXL4-002 | BW2: TXL4-003 | BX2: TXL4-004 | BY2: TXL4-005 | BZ2: TXL4-005-1 | CA2: TXL4-005-2 | CB2: TXL4-006 | CC2: TXL4-007 | CD2: TXL4-008 | CE2: TXL4-009 | CF2: TXL4-010 | CG2: TXL4-011 | CH2: TXL4-012 | CI2: TXL4-013 | CJ2: TXL4-014 | CK2: TXL4-015 | CL2: TXL4-016 | CM2: TXL4-019 | CN2: TXL4-024 | CO2: TXL4-033 | CP2: TXL4-034 | CQ2: TXL4-035 | CR2: TXL4-036 | CS2: TXL4-037 | CT2: TXL4-038 | CU2: TXL4-039 | CV2: TXL4-040 | CW2: TXL4-041 | CX2: TXL4-042 | CY2: TXL4-043 | CZ2: TXL4-044 | DA2: TXL4-045 | DB2: TXL4-046 | DC2: TXL4-047 | DD2: TXL4-048 | DE2: TXL4-049 | DF2: TXL4-050 | DG2: TXL4-051 | DH2: TXL4-052 | DI2: TXL4-053 | DJ2: TXL4-053-1 | DK2: TXL4-053-2 | DL2: TXL4-054 | DM2: TXL4-056 | DN2: TXL4-057 | DO2: TXL4-058 | DP2: TXL4-057-1 | DQ2: TXL4-059 | DR2: TXL4-060 | DS2: TXL4-061 | DT2: TXL4-062 | DU2: TXL5-042 | DV2: TXL5-043 | DW2: TXL5-044 | DX2: TXL5-045 | DY2: TXL5-046 | DZ2: TXL5-049 | EA2: TXL5-050 | EB2: TXL5-051 | EC2: TXL5-052 | ED2: TXL5-054 | EE2: TXL5-055 | EF2: TXL5-056 | EG2: TXL5-057 | EH2: TXL5-058 | EI2: TXL5-068 | EJ2: TXL5-069 | EK2: TXL5-070 | EL2: TXL5-071 | EM2: TXL5-074 | EN2: TXL5-076 | EO2: TXL5-077 | EP2: TXL6-001 | EQ2: TXL6-002 | ER2: TXL6-003 | ES2: TXL6-004 | ET2: TXL6-005 | EU2: TXL6-006 | EV2: TXL6-007 | EW2: TXL6-008 | EX2: TXL6-009 | EY2: TXL6-011 | EZ2: TXL6-013 | FA2: TXL6-015 | FB2: TXL6-018 | FC2: TXL6-027 | FD2: TXL6-029 | FE2: TXL6-073 | FF2: TXL6-073-1 | FG2: TXL6-075 | FH2: TXL6-075-1 | FI2: TXL6-079 | FJ2: TXL6-079-1 | FK2: TXL6-082 | FL2: TXL6-082-1 | FM2: TXL6-088 | FN2: TXL6-088-1 | FO2: TXL6-101 | FP2: TXL6-103 | FQ2: TXL6-104 | FR2: TXL6-106 | FS2: TXL6-108 | FT2: TXL6-110 | FU2: TXL6-112 | FV2: TXL6-113 | FW2: TXL6-114 | FX2: TXL6-115 | FY2: TXL6-116 | FZ2: TXL6-117 | GA2: TXL6-118 | GB2: TXL6-119 | GC2: TXL6-133 | GD2: TXL6-134 | GE2: TXL6-135 | GF2: TXL6-136 | GG2: TXL6-137 | GH2: TXL6-139 | GI2: TXL6-152 | GJ2: TXL6-153 | GK2: TXL6-165 | GL2: TXL6-166 | GM2: TXL6-167 | GN2: TXL6-168 | GO2: TXL6-169 | GP2: TXL6-170 | GQ2: TXL6-199 | GR2: TXL7-004 | GS2: TXL7-005 | GT2: TXL7-006 | GU2: TXL7-007 | GV2: TXL7-008 | GW2: TXL7-009 | GX2: TXL7-010 | GY2: TXL7-014 | GZ2: TXL7-016 | HA2: TXL7-023 | HB2: TXL7-024 | HC2: TXL7-025 | HD2: TXL7-026 | HE2: TXL7-027 | HF2: TXL7-028 | HG2: TXL7-029 | HH2: TXL7-030 | HI2: TXL7-031 | HJ2: TXL7-032 | HK2: TXL7-033 | HL2: TXL7-034 | HM2: TXL7-035 | HN2: TXL7-036 | HO2: TXL7-042 | HP2: TXL7-043 | HQ2: TXL7-044 | HR2: TXL7-045 | HS2: TXL7-046 | HT2: TXL7-056 | HU2: TXL7-064 | HV2: TXL7-065 | HW2: TXL7-066 | HX2: TXL7-067 | HY2: TXL7-077 | HZ2: TXL7-082 | IA2: TSY1-005 | IB2: TSY1-006 | IC2: TSY1-007 | ID2: TSY1-008 | IE2: TSY1-009 | IF2: TSY1-010 | IG2: TSY1-011 | IH2: TSY1-029 | II2: TSY1-030 | IJ2: TSY1-051 | IK2: TSY1-054 | IL2: TSY1-055 | IM2: TSY1-056 | IN2: TSY1-067 | IO2: TSY1-068 | IP2: TSY1-069 | IQ2: TSY1-079 | IR2: TSY1-080 | IS2: TSY1-081 | IT2: TSY1-082 | IU2: TSY1-089 | IV2: TSY1-089 | IW2: TSY1-090 | IX2: TSY1-100 | IY2: TSY2-002 | IZ2: TSY2-003 | JA2: TSY2-005 | JB2: TSY2-006 | JC2: TSY2-007 | JD2: TSY2-008 | JE2: TSY2-009 | JF2: TSY2-010 | JG2: TSY2-011 | JH2: TSY2-012 | JI2: TSY2-013 | JJ2: TSY2-014 | JK2: TSY2-015 | JL2: TSY2-016 | JM2: TSY2-019 | JN2: TSY2-059 | JO2: TSY2-064 | JP2: TSY2-067 | JQ2: TSY2-068 | JR2: TSY2-092 | JS2: TSY2-095 | JT2: TSY2-099 | JU2: TSY2-101 | JV2: TSY3-018 | JW2: TSY3-019 | JX2: TSY3-027 | JY2: TSY3-031 | JZ2: TSY3-032 | KA2: TSY3-033 | KB2: TSY3-034 | KC2: TSY3-035 | KD2: TSY3-036 | KE2: TSY3-047 | KF2: TSY3-063 | KG2: TSY3-064 | KH2: TSY3-066 | KI2: TSY3-067 | KJ2: TSY4-002 | KK2: TSY4-003 | KL2: TSY4-007 | KM2: TSY4-011 | KN2: TSY4-013 | KO2: TSY4-014 | KP2: TSY4-017 | KQ2: TSW2-105 | KR2: TSW2-106 | KS2: TSW2-107 | KT2: TSW2-108 | KU2: TSW2-109 | KV2: TSW2-110 | KW2: TSW2-111 | KX2: TSW2-112 | KY2: TSD3-006 | KZ2: TSD3-050
A3: 项目名称 | B3: 直埋光（电）缆工程施工测量 | C3: 架空光(电)缆工程施工测量 | D3: 管道光(电)缆工程施工测量 | E3: GPS定位 | F3: 单盘检验（单窗口） | G3: 单盘检验（双窗口） | H3: 人工开挖路面 混凝土（100mm以内） | I3: 人工开挖路面 混凝土（每增加10mm） | J3: 人工开挖路面 沥青柏油（100mm以内） | K3: 人工开挖路面 沥青柏油（每增加10mm） | L3: 人工开挖路面 砂石（100mm以内） | M3: 人工开挖路面 砂石（每增加10mm） | N3: 人工开挖路面 混凝土砌块 | O3: 人工开挖路面 水泥花砖 | P3: 人工开挖路面 条石 | Q3: 挖、松填光（电）缆沟及接头坑 普通土 | R3: 挖、松填光（电）缆沟及接头坑 硬土 | S3: 挖、松填光（电）缆沟及接头坑 砂砾土 | T3: 挖、夯填光（电）缆沟及接头坑 普通土 | U3: 挖、夯填光（电）缆沟及接头坑 硬土 | V3: 挖、夯填光（电）缆沟及接头坑 砂砾土 | W3: 手推车倒运土方 | X3: 丘陵、水田、城区敷设埋式光缆 36芯以下 | Y3: 丘陵、水田、城区敷设埋式光缆 72芯以下 | Z3: 丘陵、水田、城区敷设埋式光缆 96芯以下 | AA3: 丘陵、水田、城区敷设埋式光缆 144芯以下 | AB3: 丘陵、水田、城区敷设埋式光缆 288芯以下 | AC3: 丘陵、水田、城区敷设埋式光缆 288芯以上 | AD3: 山区敷设埋式光缆 36芯以下 | AE3: 山区敷设埋式光缆 72芯以下 | AF3: 山区敷设埋式光缆 96芯以下 | AG3: 山区敷设埋式光缆 144芯以下 | AH3: 山区敷设埋式光缆 288芯以下 | AI3: 山区敷设埋式光缆 288芯以上 | AJ3: 敷设埋式电缆 200对以下 | AK3: 铺管保护（钢管） | AL3: 埋设标石 丘陵、水田、城区 | AM3: 埋设标石 山区 | AN3: 安装宣传警示牌 | AO3: 安装防雷设施 敷设排流线（单条） | AP3: 立9m 以下水泥杆 综合土 | AQ3: 立11m 以下水泥杆 综合土 | AR3: 立13m 以下水泥杆 综合土 | AS3: 立13m 以下水泥H杆 综合土 | AT3: 装水泥撑杆 综合土 | AU3: 水泥杆夹板法装7/2.2单股拉线 综合土 | AV3: 水泥杆夹板法装7/2.6单股拉线 综合土 | AW3: 水泥杆夹板法装7/3.0单股拉线 综合土 | AX3: 安装拉线隔电子 | AY3: 安装拉线警示保护管 | AZ3: 电杆接高装置(单槽钢) | BA3: 电杆接高装置(双槽钢) | BB3: 单杆地线 拉线式 | BC3: 单杆地线 直埋式 | BD3: 安装预留缆架 | BE3: 安装吊线保护装置 | BF3: 水泥杆架设7/2.2吊线（丘陵） | BG3: 水泥杆架设7/2.2吊线（山区） | BH3: 水泥杆架设7/2.2吊线（城区） | BI3: 架设100米以内辅助吊线 | BJ3: 挂钩法架设架空光缆丘陵、城区、水田（36芯以下） | BK3: 挂钩法架设架空光缆丘陵、城区、水田（72芯以下） | BL3: 挂钩法架设架空光缆丘陵、城区、水田（144芯以下） | BM3: 挂钩法架设架空光缆丘陵、城区、水田（288芯以下） | BN3: 挂钩法架设架空光缆丘陵、城区、水田（288芯以上） | BO3: 挂钩法架设架空光缆山区（36芯以下） | BP3: 挂钩法架设架空光缆山区（72芯以下） | BQ3: 挂钩法架设架空光缆山区（144芯以下） | BR3: 挂钩法架设架空光缆山区（288芯以下） | BS3: 挂钩法架设架空光缆山区（288芯以上） | BT3: 吊线式架空电缆（100对以下） | BU3: 布放光(电)缆人孔抽水(积水) | BV3: 布放光(电)缆人孔抽水(流水) | BW3: 布放光(电)缆手孔抽水 | BX3: 人工敷设塑料子管 1孔子管 | BY3: 人工敷设塑料子管 2孔子管 | BZ3: 人工敷设塑料子管(6孔子管) | CA3: 人工敷设塑料子管(15孔子管) | CB3: 人工敷设塑料子管 3孔子管 | CC3: 人工敷设塑料子管 4孔子管 | CD3: 人工敷设塑料子管 5孔子管 | CE3: 空闲管孔中人工敷设一带纺织子管 | CF3: 非空闲管孔中人工敷设一带纺织子管 | CG3: 敷设管道光缆 12芯以下 | CH3: 敷设管道光缆 24芯以下 | CI3: 敷设管道光缆 48芯以下 | CJ3: 敷设管道光缆 96芯以下 | CK3: 敷设管道光缆 144芯以下 | CL3: 敷设管道光缆 288芯以下 | CM3: 人工敷设管道电缆 200对 以下 | CN3: 机械敷设管道电缆 200对 以下 | CO3: 打人（手）孔墙洞 砖砌人孔 3孔管 以下 | CP3: 打人（手）孔墙洞 砖砌人孔 3孔管 以上 | CQ3: 打人（手）孔墙洞 混凝土人孔 3孔管 以下 | CR3: 打人（手）孔墙洞 混凝土人孔 3孔管 以上 | CS3: 打穿楼墙洞 砖墙 | CT3: 打穿楼墙洞 混凝土墙 | CU3: 打穿楼层洞 预制板楼层 | CV3: 打穿楼层洞 混凝土楼层 | CW3: 增装支撑物 终端支撑物 | CX3: 增装支撑物 中间支撑物 | CY3: 安装引上钢管（Φ50以下）(杆上) | CZ3: 安装引上钢管（Φ50以下）(墙上) | DA3: 安装引上钢管（Φ50以上）(杆上) | DB3: 安装引上钢管（Φ50以上）(墙上) | DC3: 钉固塑料槽板 | DD3: 进局光(电)缆防水封堵 | DE3: 光(电)缆上线洞楼层间防火封堵 | DF3: 穿放引上光缆 | DG3: 穿放引上电缆 200对 以下 | DH3: 穿放引上电缆 200对 以上 | DI3: 架设吊线式墙壁光缆 | DJ3: 架设吊线式墙壁光缆（加吊） | DK3: 架设吊线式墙壁 | DL3: 布放钉固式墙壁光缆 | DM3: 墙壁方式敷设蝶形光缆 | DN3: 架设吊线式墙壁电缆 200对 以下 | DO3: 架设吊线式墙壁电缆 200对 以上 | DP3: 架设吊线式墙壁电缆 200对 以下 加挂 | DQ3: 布放钉固式墙壁电缆 200对 以下 | DR3: 布放钉固式墙壁电缆 200对 以上 | DS3: 架挂自承式墙壁电缆 100对 以下 | DT3: 架挂自承式墙壁电缆 100对 以上 | DU3: 钉固式敷设室内通道光缆 | DV3: 竖井引上光缆 | DW3: 槽道光缆 | DX3: 布放槽道电缆 | DY3: 布放顶棚内电缆 | DZ3: 敷设钢管（φ25以内） | EA3: 敷设钢管（φ50以内） | EB3: 敷设硬质PVC管（φ25以内） | EC3: 敷设硬质PVC管（φ50以内） | ED3: 敷设金属线槽（150宽以下） | EE3: 敷设金属线槽（300宽以下） | EF3: 敷设金属线槽（300宽以上） | EG3: 敷设塑料线槽（100宽以下） | EH3: 敷设塑料线槽（100宽以上） | EI3: 管内、暗槽内穿放光缆 | EJ3: 穿放4对对绞电缆 | EK3: 穿放大对数对绞电缆 非屏蔽50对 以下 | EL3: 穿放大对数对绞电缆 非屏蔽100对 以下 | EM3: 桥架、线槽、地板内明布光缆 | EN3: 桥架、线槽、网络地板内明布电缆 50对 以下 | EO3: 桥架、线槽、网络地板内明布电缆 100对 以下 | EP3: 光缆掏纤（4芯以下） | EQ3: 光缆掏纤（每增加2芯） | ER3: 光缆接续(机械法) | ES3: 现场组装光纤活动连接器 | ET3: 光缆成端接头（束状） | EU3: 光缆成端接头（带状） | EV3: 光缆接续(4芯以下) | EW3: 光缆接续(12芯以下) | EX3: 光缆接续(24芯以下) | EY3: 光缆接续(48芯以下) | EZ3: 光缆接续(72芯以下) | FA3: 光缆接续(96芯以下) | FB3: 光缆接续(144芯以下) | FC3: 8芯带以上带状光缆接续（144芯以下） | FD3: 8芯带以上带状光缆接续（288芯以下） | FE3: 40km以下中继段光缆测试(24芯以下)（单窗口） | FF3: 40km以下中继段光缆测试(24芯以下)（双窗口*1.8） | FG3: 40km以下中继段光缆测试(48芯以下)（单窗口） | FH3: 40km以下中继段光缆测试(48芯以下)（双窗口*1.8） | FI3: 40km以下中继段光缆测试(96芯以下)（单窗口） | FJ3: 40km以下中继段光缆测试(96芯以下)（双窗口*1.8） | FK3: 40km以下中继段光缆测试(144芯以下)（单窗口） | FL3: 40km以下中继段光缆测试(144芯以下)（双窗口*1.8） | FM3: 40km以下中继段光缆测试(288芯以下)（单窗口） | FN3: 40km以下中继段光缆测试(288芯以下)（双窗口*1.8） | FO3: 用户光缆测试(2芯以下) | FP3: 用户光缆测试(12芯以下) | FQ3: 用户光缆测试(24芯以下) | FR3: 用户光缆测试(48芯以下) | FS3: 用户光缆测试(72芯以下) | FT3: 用户光缆测试(96芯以下) | FU3: 用户光缆测试(132芯以下) | FV3: 用户光缆测试(144芯以下) | FW3: 用户光缆测试(168芯以下) | FX3: 用户光缆测试(192芯以下) | FY3: 用户光缆测试(216芯以下) | FZ3: 用户光缆测试(240芯以下) | GA3: 用户光缆测试(264芯以下) | GB3: 用户光缆测试(288芯以下) | GC3: 光纤链路衰减测试（1:4） | GD3: 光纤链路衰减测试（1:8） | GE3: 光纤链路衰减测试（1:16） | GF3: 光纤链路衰减测试（1:32） | GG3: 光纤链路衰减测试（1:64） | GH3: 光分配网（ODN）光纤链路全程测试 光纤链路回波损耗测试 | GI3: 布放总配线架成端电缆 200对 以下 | GJ3: 布放总配线架成端电缆 400对 以下 | GK3: 布放组线箱成端电缆 10对 以下 | GL3: 布放组线箱成端电缆 20对 以下 | GM3: 布放组线箱成端电缆 30对 以下 | GN3: 布放组线箱成端电缆 50对 以下 | GO3: 布放组线箱成端电缆 100对 以下 | GP3: 布放组线箱成端电缆 100对 以上 | GQ3: 安装多用接头盒 | GR3: 安装机柜、机架(落地式) | GS3: 安装机柜、机架(墙挂式) | GT3: 制作安装抗震底座 | GU3: 安装过线（路）盒（半周长） 200 以下 | GV3: 安装过线（路）盒（半周长） 200 以上 | GW3: 安装信息插盒底座 明装 | GX3: 安装信息插盒底座 砖墙内 | GY3: 安装8位模块式信息插座 单口 非屏蔽 | GZ3: 安装8位模块式信息插座 双口 非屏蔽 | HA3: 安装光分纤箱、光分路箱（架空式） | HB3: 安装光分纤箱、光分路箱（墙壁式） | HC3: 安装光缆终端盒 | HD3: 安装光缆接线箱 | HE3: 增（扩）装光纤一体化熔接托盘 | HF3: 机架（箱）内安装光分路器（安装高度1.5m以下） | HG3: 机架（箱）内安装光分路器（安装高度1.5m以上） | HH3: 光分路器与光纤线路插接 | HI3: 光分路器本机测试（1：2） | HJ3: 光分路器本机测试（1：4） | HK3: 光分路器本机测试（1：8） | HL3: 光分路器本机测试（1：16） | HM3: 光分路器本机测试（1：32） | HN3: 光分路器本机测试（1：64） | HO3: 安装光缆落地式交接箱(144芯以下) | HP3: 安装光缆落地式交接箱(288芯以下) | HQ3: 安装光缆落地式交接箱(288芯以上) | HR3: 安装壁挂式光缆交接箱（144芯以下） | HS3: 安装壁挂式光缆交接箱（288芯以下） | HT3: 安装挂墙式交接箱 600对以下 | HU3: 制装塑缆分线盒 10对以下 | HV3: 制装塑缆分线盒 20对以下 | HW3: 制装塑缆分线盒 30对以下 | HX3: 制装塑缆分线盒 50对以下 | HY3: 安装测试100回线保安排 试验排 | HZ3: 安装测试100回线接线排 | IA3: 安装室内有源机柜（落地式） | IB3: 安装室内有源机柜（嵌墙式） | IC3: 安装室内无源机柜（落地式） | ID3: 安装室内无源机柜（嵌墙式） | IE3: 安装室内挂墙机箱（有源） | IF3: 安装室内挂墙机箱（无源） | IG3: 安装电源分配柜、箱 架顶式 | IH3: 安装光分配架（整架） | II3: 安装光分配架（子架） | IJ3: 布放音频隔离线（单、双芯） | IK3: 布放SYV类射频同轴电缆（单芯） | IL3: 放绑设备电缆(SYV类射频同轴电缆(多芯)) | IM3: 布放数据电缆（10芯以下） | IN3: 编扎、焊接音频隔离线（单、双芯） | IO3: 编扎、焊(绕、卡)接设备电缆(SYV类射频同轴电缆) | IP3: 编扎、焊接数据电缆（10芯以下） | IQ3: 放、绑软光纤（设备机架之间放、绑）（15m以下） | IR3: 放、绑软光纤（设备机架之间放、绑）（15m以上） | IS3: 光纤分配架内跳线 | IT3: 中间站跳纤 | IU3: 布放单芯电力电缆（16mm2以下) | IV3: 布放单芯电力电缆（16mm2以下)（3*2.5mm2） | IW3: 布放单芯电力电缆（35mm2以下) | IX3: 敷设硬质PVC管/槽 | IY3: 安装集成式小型设备 | IZ3: 增（扩）装、更换光模块 | JA3: 安装测试传输设备接口盘 40Gb/s | JB3: 安装测试传输设备接口盘 10Gb/s | JC3: 安装测试传输设备接口盘 2.5Gb/s | JD3: 安装测试传输设备接口盘 622Mb/s | JE3: 安装测试传输设备接口盘 155Mb/s 光口 | JF3: 安装测试传输设备接口盘 155Mb/s 电口 | JG3: 安装测试传输设备接口盘 45/34Mb/s | JH3: 安装测试传输设备接口盘 2Mb/s | JI3: 安装测试传输设备接口盘 FE | JJ3: 安装测试传输设备接口盘 GE | JK3: 安装测试传输设备接口盘 10GE | JL3: 安装测试传输设备接口盘 40GE | JM3: 安装测试光电转换模块 | JN3: 线路段光端对测 | JO3: 保护倒换测试 | JP3: 复用设备系统调测 以太网光口 | JQ3: 复用设备系统调测 以太网电口 | JR3: 安装光网络单元（ONU）(集成式) | JS3: ONU/ONT设备上联光接口本机测试 | JT3: 系统功能验证及性能测试 ONU窄带端口 64线以下 | JU3: 系统功能验证及性能测试 ONU宽带端口 64线以下） | JV3: 安装、调测无线局域网接入点（AP）设备 | JW3: 安装调测低端路由器 安装路由器（整机型） | JX3: 安装调测低端路由器 综合调测低端路由器 | JY3: 安装低端局域网交换机 | JZ3: 安装高、中端局域网交换机 安装机箱及电源模块 | KA3: 安装高、中端局域网交换机 安装接口板 | KB3: 调测局域网交换机 低端 | KC3: 调测局域网交换机 高中端 | KD3: 安装调测集线器 | KE3: 安装、测试光电转换器 台式 | KF3: 安装网络安全设备 低端 | KG3: 安装网络安全设备 中端 | KH3: 调测网络安全设备 低端 | KI3: 调测网络安全设备 中端 | KJ3: 安装架空式集线器设备 | KK3: 安装用户集线器设备 | KL3: 交换机设备硬件调测 用户线 | KM3: 交换机设备硬件调测 以太网接口 电口 | KN3: 交换机设备软件调测 用户线 | KO3: 交换机设备软件调测 以太网接口 | KP3: 调测用户集线器 | KQ3: 无线局域网交换机 安装 | KR3: 无线局域网交换机 调测 | KS3: 安装POE供电模块 | KT3: 安装、调测光电转换模块 | KU3: 路由器 安装 | KV3: 路由器 调测 | KW3: 集线器 安装调测 | KX3: 无线局域网接入系统联调 | KY3: 安装24V蓄电池组 200Ah以下 | KZ3: 安装、调试交流不间断电源 3kVA以下
A4: 恩平市金丰电子器材厂+语音专线+变更 | B4: 0 | C4: 0 | D4: 0 | E4: 0 | F4: 0 | G4: 0 | H4: 0 | I4: 0 | J4: 0 | K4: 0 | L4: 0 | M4: 0 | N4: 0 | O4: 0 | P4: 0 | Q4: 0 | R4: 0 | S4: 0 | T4: 0 | U4: 0 | V4: 0 | W4: 0 | X4: 0 | Y4: 0 | Z4: 0 | AA4: 0 | AB4: 0 | AC4: 0 | AD4: 0 | AE4: 0 | AF4: 0 | AG4: 0 | AH4: 0 | AI4: 0 | AJ4: 0 | AK4: 0 | AL4: 0 | AM4: 0 | AN4: 0 | AO4: 0 | AP4: 0 | AQ4: 0 | AR4: 0 | AS4: 0 | AT4: 0 | AU4: 0 | AV4: 0 | AW4: 0 | AX4: 0 | AY4: 0 | AZ4: 0 | BA4: 0 | BB4: 0 | BC4: 0 | BD4: 0 | BE4: 0 | BF4: 0 | BG4: 0 | BH4: 0 | BI4: 0 | BJ4: 0 | BK4: 0 | BL4: 0 | BM4: 0 | BN4: 0 | BO4: 0 | BP4: 0 | BQ4: 0 | BR4: 0 | BS4: 0 | BT4: 0 | BU4: 0 | BV4: 0 | BW4: 0 | BX4: 0 | BY4: 0 | BZ4: 0 | CA4: 0 | CB4: 0 | CC4: 0 | CD4: 0 | CE4: 0 | CF4: 0 | CG4: 0 | CH4: 0 | CI4: 0 | CJ4: 0 | CK4: 0 | CL4: 0 | CM4: 0 | CN4: 0 | CO4: 0 | CP4: 0 | CQ4: 0 | CR4: 0 | CS4: 0 | CT4: 0 | CU4: 0 | CV4: 0 | CW4: 0 | CX4: 0 | CY4: 0 | CZ4: 0 | DA4: 0 | DB4: 0 | DC4: 0 | DD4: 0 | DE4: 0 | DF4: 0 | DG4: 0 | DH4: 0 | DI4: 0 | DJ4: 0 | DK4: 0 | DL4: 0 | DM4: 0 | DN4: 0 | DO4: 0 | DP4: 0 | DQ4: 0 | DR4: 0 | DS4: 0 | DT4: 0 | DU4: 0 | DV4: 0 | DW4: 0 | DX4: 0 | DY4: 0 | DZ4: 0 | EA4: 0 | EB4: 0 | EC4: 0 | ED4: 0 | EE4: 0 | EF4: 0 | EG4: 0 | EH4: 0 | EI4: 0 | EJ4: 0 | EK4: 0 | EL4: 0 | EM4: 0 | EN4: 0 | EO4: 0 | EP4: 0 | EQ4: 0 | ER4: 0 | ES4: 0 | ET4: 0 | EU4: 0 | EV4: 0 | EW4: 0 | EX4: 0 | EY4: 0 | EZ4: 0 | FA4: 0 | FB4: 0 | FC4: 0 | FD4: 0 | FE4: 0 | FF4: 0 | FG4: 0 | FH4: 0 | FI4: 0 | FJ4: 0 | FK4: 0 | FL4: 0 | FM4: 0 | FN4: 0 | FO4: 0 | FP4: 0 | FQ4: 0 | FR4: 0 | FS4: 0 | FT4: 0 | FU4: 0 | FV4: 0 | FW4: 0 | FX4: 0 | FY4: 0 | FZ4: 0 | GA4: 0 | GB4: 0 | GC4: 0 | GD4: 0 | GE4: 0 | GF4: 0 | GG4: 0 | GH4: 0 | GI4: 0 | GJ4: 0 | GK4: 0 | GL4: 0 | GM4: 0 | GN4: 0 | GO4: 0 | GP4: 0 | GQ4: 0 | GR4: 0 | GS4: 0 | GT4: 0 | GU4: 0 | GV4: 0 | GW4: 0 | GX4: 0 | GY4: 0 | GZ4: 0 | HA4: 0 | HB4: 0 | HC4: 0 | HD4: 0 | HE4: 0 | HF4: 0 | HG4: 0 | HH4: 0 | HI4: 0 | HJ4: 0 | HK4: 0 | HL4: 0 | HM4: 0 | HN4: 0 | HO4: 0 | HP4: 0 | HQ4: 0 | HR4: 0 | HS4: 0 | HT4: 0 | HU4: 0 | HV4: 0 | HW4: 0 | HX4: 0 | HY4: 0 | HZ4: 0 | IA4: 0 | IB4: 0 | IC4: 0 | ID4: 0 | IE4: 0 | IF4: 0 | IG4: 0 | IH4: 0 | II4: 0 | IJ4: 0 | IK4: 0 | IL4: 0 | IM4: 0 | IN4: 0 | IO4: 0 | IP4: 0 | IQ4: 0 | IR4: 0 | IS4: 0 | IT4: 0 | IU4: 0 | IV4: 0 | IW4: 0 | IX4: 0 | IY4: 0 | IZ4: 0 | JA4: 0 | JB4: 0 | JC4: 0 | JD4: 0 | JE4: 0 | JF4: 0 | JG4: 0 | JH4: 0 | JI4: 0 | JJ4: 0 | JK4: 0 | JL4: 0 | JM4: 0 | JN4: 0 | JO4: 0 | JP4: 0 | JQ4: 0 | JR4: 0 | JS4: 0 | JT4: 0 | JU4: 0 | JV4: 0 | JW4: 0 | JX4: 0 | JY4: 0 | JZ4: 0 | KA4: 0 | KB4: 0 | KC4: 0 | KD4: 0 | KE4: 0 | KF4: 0 | KG4: 0 | KH4: 0 | KI4: 0 | KJ4: 0 | KK4: 0 | KL4: 0 | KM4: 0 | KN4: 0 | KO4: 0 | KP4: 0 | KQ4: 0 | KR4: 0 | KS4: 0 | KT4: 0 | KU4: 0 | KV4: 0 | KW4: 0 | KX4: 0 | KY4: 0 | KZ4: 0
A5: 恩平市中山医院+互联网专线+语音专线+新增 | B5: =VLOOKUP($A$4:$A$56,Sheet2!$A$8:$LQ$43,COLUMN(B5),FALSE) -> 0 | C5: =VLOOKUP($A$4:$A$56,Sheet2!$A$8:$LQ$43,COLUMN(C5),FALSE) -> 0 | D5: =VLOOKUP($A$4:$A$56,Sheet2!$A$8:$LQ$43,COLUMN(D5),FALSE) -> 0 | E5: =IFERROR(VLOOKUP($A$4:$A$56,Sheet2!$A$8:$LQ$43,COLUMN(E5),FALSE),"") -> 0 | F5: =IFERROR(VLOOKUP($A$4:$A$56,Sheet2!$A$8:$LQ$43,COLUMN(F5),FALSE),"") -> 0 | G5: =IFERROR(VLOOKUP($A$4:$A$56,Sheet2!$A$8:$LQ$43,COLUMN(G5),FALSE),"") -> 0 | H5: =IFERROR(VLOOKUP($A$4:$A$56,Sheet2!$A$8:$LQ$43,COLUMN(H5),FALSE),"") -> 0 | I5: =IFERROR(VLOOKUP($A$4:$A$56,Sheet2!$A$8:$LQ$43,COLUMN(I5),FALSE),"") -> 0 | J5: =IFERROR(VLOOKUP($A$4:$A$56,Sheet2!$A$8:$LQ$43,COLUMN(J5),FALSE),"") -> 0 | K5: =IFERROR(VLOOKUP($A$4:$A$56,Sheet2!$A$8:$LQ$43,COLUMN(K5),FALSE),"") -> 0 | L5: =IFERROR(VLOOKUP($A$4:$A$56,Sheet2!$A$8:$LQ$43,COLUMN(L5),FALSE),"") -> 0 | ... KZ5: =IFERROR(VLOOKUP($A$4:$A$56,Sheet2!$A$8:$LQ$43,COLUMN(KZ5),FALSE),"") -> 0
A6: 国家税务总局恩平市税务局前进街办事点+互联网专线+新增+融合 | B6: 0 | C6: 0 | D6: 0 | E6: 0 | F6: 0 | G6: 0 | H6: 0 | I6: 0 | J6: 0 | K6: 0 | L6: 0 | M6: 0 | N6: 0 | O6: 0 | P6: 0 | Q6: 0 | R6: 0 | S6: 0 | T6: 0 | U6: 0 | V6: 0 | W6: 0 | X6: 0 | Y6: 0 | Z6: 0 | AA6: 0 | AB6: 0 | AC6: 0 | AD6: 0 | AE6: 0 | AF6: 0 | AG6: 0 | AH6: 0 | AI6: 0 | AJ6: 0 | AK6: 0 | AL6: 0 | AM6: 0 | AN6: 0 | AO6: 0 | AP6: 0 | AQ6: 0 | AR6: 0 | AS6: 0 | AT6: 0 | AU6: 0 | AV6: 0 | AW6: 0 | AX6: 0 | AY6: 0 | AZ6: 0 | BA6: 0 | BB6: 0 | BC6: 0 | BD6: 0 | BE6: 0 | BF6: 0 | BG6: 0 | BH6: 0 | BI6: 0 | BJ6: 0 | BK6: 0 | BL6: 0 | BM6: 0 | BN6: 0 | BO6: 0 | BP6: 0 | BQ6: 0 | BR6: 0 | BS6: 0 | BT6: 0 | BU6: 0 | BV6: 0 | BW6: 0 | BX6: 0 | BY6: 0 | BZ6: 0 | CA6: 0 | CB6: 0 | CC6: 0 | CD6: 0 | CE6: 0 | CF6: 0 | CG6: 0 | CH6: 0 | CI6: 0 | CJ6: 0 | CK6: 0 | CL6: 0 | CM6: 0 | CN6: 0 | CO6: 0 | CP6: 0 | CQ6: 0 | CR6: 0 | CS6: 0 | CT6: 0 | CU6: 0 | CV6: 0 | CW6: 0 | CX6: 0 | CY6: 0 | CZ6: 0 | DA6: 0 | DB6: 0 | DC6: 0 | DD6: 0 | DE6: 0 | DF6: 0 | DG6: 0 | DH6: 0 | DI6: 0 | DJ6: 0 | DK6: 0 | DL6: 0 | DM6: 0 | DN6: 0 | DO6: 0 | DP6: 0 | DQ6: 0 | DR6: 0 | DS6: 0 | DT6: 0 | DU6: 0 | DV6: 0 | DW6: 0 | DX6: 0 | DY6: 0 | DZ6: 0 | EA6: 0 | EB6: 0 | EC6: 0 | ED6: 0 | EE6: 0 | EF6: 0 | EG6: 0 | EH6: 0 | EI6: 0 | EJ6: 0 | EK6: 0 | EL6: 0 | EM6: 0 | EN6: 0 | EO6: 0 | EP6: 0 | EQ6: 0 | ER6: 0 | ES6: 0 | ET6: 0 | EU6: 0 | EV6: 0 | EW6: 0 | EX6: 0 | EY6: 0 | EZ6: 0 | FA6: 0 | FB6: 0 | FC6: 0 | FD6: 0 | FE6: 0 | FF6: 0 | FG6: 0 | FH6: 0 | FI6: 0 | FJ6: 0 | FK6: 0 | FL6: 0 | FM6: 0 | FN6: 0 | FO6: 0 | FP6: 0 | FQ6: 0 | FR6: 0 | FS6: 0 | FT6: 0 | FU6: 0 | FV6: 0 | FW6: 0 | FX6: 0 | FY6: 0 | FZ6: 0 | GA6: 0 | GB6: 0 | GC6: 0 | GD6: 0 | GE6: 0 | GF6: 0 | GG6: 0 | GH6: 0 | GI6: 0 | GJ6: 0 | GK6: 0 | GL6: 0 | GM6: 0 | GN6: 0 | GO6: 0 | GP6: 0 | GQ6: 0 | GR6: 0 | GS6: 0 | GT6: 0 | GU6: 0 | GV6: 0 | GW6: 0 | GX6: 0 | GY6: 0 | GZ6: 0 | HA6: 0 | HB6: 0 | HC6: 0 | HD6: 0 | HE6: 0 | HF6: 0 | HG6: 0 | HH6: 0 | HI6: 0 | HJ6: 0 | HK6: 0 | HL6: 0 | HM6: 0 | HN6: 0 | HO6: 0 | HP6: 0 | HQ6: 0 | HR6: 0 | HS6: 0 | HT6: 0 | HU6: 0 | HV6: 0 | HW6: 0 | HX6: 0 | HY6: 0 | HZ6: 0 | IA6: 0 | IB6: 0 | IC6: 0 | ID6: 0 | IE6: 0 | IF6: 0 | IG6: 0 | IH6: 0 | II6: 0 | IJ6: 0 | IK6: 0 | IL6: 0 | IM6: 0 | IN6: 0 | IO6: 0 | IP6: 0 | IQ6: 0 | IR6: 0 | IS6: 0 | IT6: 0 | IU6: 0 | IV6: 0 | IW6: 0 | IX6: 0 | IY6: 0 | IZ6: 0 | JA6: 0 | JB6: 0 | JC6: 0 | JD6: 0 | JE6: 0 | JF6: 0 | JG6: 0 | JH6: 0 | JI6: 0 | JJ6: 0 | JK6: 0 | JL6: 0 | JM6: 0 | JN6: 0 | JO6: 0 | JP6: 0 | JQ6: 0 | JR6: 0 | JS6: 0 | JT6: 0 | JU6: 0 | JV6: 0 | JW6: 0 | JX6: 0 | JY6: 0 | JZ6: 0 | KA6: 0 | KB6: 0 | KC6: 0 | KD6: 0 | KE6: 0 | KF6: 0 | KG6: 0 | KH6: 0 | KI6: 0 | KJ6: 0 | KK6: 0 | KL6: 0 | KM6: 0 | KN6: 0 | KO6: 0 | KP6: 0 | KQ6: 0 | KR6: 0 | KS6: 0 | KT6: 0 | KU6: 0 | KV6: 0 | KW6: 0 | KX6: 0 | KY6: 0 | KZ6: 0
A7: 国家税务总局恩平市税务局恩城税务分局+互联网专线+新增+融合 | B7: 0 | C7: 0 | D7: 0 | E7: 0 | F7: 0 | G7: 0 | H7: 0 | I7: 0 | J7: 0 | K7: 0 | L7: 0 | M7: 0 | N7: 0 | O7: 0 | P7: 0 | Q7: 0 | R7: 0 | S7: 0 | T7: 0 | U7: 0 | V7: 0 | W7: 0 | X7: 0 | Y7: 0 | Z7: 0 | AA7: 0 | AB7: 0 | AC7: 0 | AD7: 0 | AE7: 0 | AF7: 0 | AG7: 0 | AH7: 0 | AI7: 0 | AJ7: 0 | AK7: 0 | AL7: 0 | AM7: 0 | AN7: 0 | AO7: 0 | AP7: 0 | AQ7: 0 | AR7: 0 | AS7: 0 | AT7: 0 | AU7: 0 | AV7: 0 | AW7: 0 | AX7: 0 | AY7: 0 | AZ7: 0 | BA7: 0 | BB7: 0 | BC7: 0 | BD7: 0 | BE7: 0 | BF7: 0 | BG7: 0 | BH7: 0 | BI7: 0 | BJ7: 0 | BK7: 0 | BL7: 0 | BM7: 0 | BN7: 0 | BO7: 0 | BP7: 0 | BQ7: 0 | BR7: 0 | BS7: 0 | BT7: 0 | BU7: 0 | BV7: 0 | BW7: 0 | BX7: 0 | BY7: 0 | BZ7: 0 | CA7: 0 | CB7: 0 | CC7: 0 | CD7: 0 | CE7: 0 | CF7: 0 | CG7: 0 | CH7: 0 | CI7: 0 | CJ7: 0 | CK7: 0 | CL7: 0 | CM7: 0 | CN7: 0 | CO7: 0 | CP7: 0 | CQ7: 0 | CR7: 0 | CS7: 0 | CT7: 0 | CU7: 0 | CV7: 0 | CW7: 0 | CX7: 0 | CY7: 0 | CZ7: 0 | DA7: 0 | DB7: 0 | DC7: 0 | DD7: 0 | DE7: 0 | DF7: 0 | DG7: 0 | DH7: 0 | DI7: 0 | DJ7: 0 | DK7: 0 | DL7: 0 | DM7: 0 | DN7: 0 | DO7: 0 | DP7: 0 | DQ7: 0 | DR7: 0 | DS7: 0 | DT7: 0 | DU7: 0 | DV7: 0 | DW7: 0 | DX7: 0 | DY7: 0 | DZ7: 0 | EA7: 0 | EB7: 0 | EC7: 0 | ED7: 0 | EE7: 0 | EF7: 0 | EG7: 0 | EH7: 0 | EI7: 0 | EJ7: 0 | EK7: 0 | EL7: 0 | EM7: 0 | EN7: 0 | EO7: 0 | EP7: 0 | EQ7: 0 | ER7: 0 | ES7: 0 | ET7: 0 | EU7: 0 | EV7: 0 | EW7: 0 | EX7: 0 | EY7: 0 | EZ7: 0 | FA7: 0 | FB7: 0 | FC7: 0 | FD7: 0 | FE7: 0 | FF7: 0 | FG7: 0 | FH7: 0 | FI7: 0 | FJ7: 0 | FK7: 0 | FL7: 0 | FM7: 0 | FN7: 0 | FO7: 0 | FP7: 0 | FQ7: 0 | FR7: 0 | FS7: 0 | FT7: 0 | FU7: 0 | FV7: 0 | FW7: 0 | FX7: 0 | FY7: 0 | FZ7: 0 | GA7: 0 | GB7: 0 | GC7: 0 | GD7: 0 | GE7: 0 | GF7: 0 | GG7: 0 | GH7: 0 | GI7: 0 | GJ7: 0 | GK7: 0 | GL7: 0 | GM7: 0 | GN7: 0 | GO7: 0 | GP7: 0 | GQ7: 0 | GR7: 0 | GS7: 0 | GT7: 0 | GU7: 0 | GV7: 0 | GW7: 0 | GX7: 0 | GY7: 0 | GZ7: 0 | HA7: 0 | HB7: 0 | HC7: 0 | HD7: 0 | HE7: 0 | HF7: 0 | HG7: 0 | HH7: 0 | HI7: 0 | HJ7: 0 | HK7: 0 | HL7: 0 | HM7: 0 | HN7: 0 | HO7: 0 | HP7: 0 | HQ7: 0 | HR7: 0 | HS7: 0 | HT7: 0 | HU7: 0 | HV7: 0 | HW7: 0 | HX7: 0 | HY7: 0 | HZ7: 0 | IA7: 0 | IB7: 0 | IC7: 0 | ID7: 0 | IE7: 0 | IF7: 0 | IG7: 0 | IH7: 0 | II7: 0 | IJ7: 0 | IK7: 0 | IL7: 0 | IM7: 0 | IN7: 0 | IO7: 0 | IP7: 0 | IQ7: 0 | IR7: 0 | IS7: 0 | IT7: 0 | IU7: 0 | IV7: 0 | IW7: 0 | IX7: 0 | IY7: 0 | IZ7: 0 | JA7: 0 | JB7: 0 | JC7: 0 | JD7: 0 | JE7: 0 | JF7: 0 | JG7: 0 | JH7: 0 | JI7: 0 | JJ7: 0 | JK7: 0 | JL7: 0 | JM7: 0 | JN7: 0 | JO7: 0 | JP7: 0 | JQ7: 0 | JR7: 0 | JS7: 0 | JT7: 0 | JU7: 0 | JV7: 0 | JW7: 0 | JX7: 0 | JY7: 0 | JZ7: 0 | KA7: 0 | KB7: 0 | KC7: 0 | KD7: 0 | KE7: 0 | KF7: 0 | KG7: 0 | KH7: 0 | KI7: 0 | KJ7: 0 | KK7: 0 | KL7: 0 | KM7: 0 | KN7: 0 | KO7: 0 | KP7: 0 | KQ7: 0 | KR7: 0 | KS7: 0 | KT7: 0 | KU7: 0 | KV7: 0 | KW7: 0 | KX7: 0 | KY7: 0 | KZ7: 0
A8: 国家税务总局恩平市税务局圣堂税务分局+互联网专线+新增+融合 | B8: 0 | C8: 0 | D8: 0 | E8: 0 | F8: 0 | G8: 0 | H8: 0 | I8: 0 | J8: 0 | K8: 0 | L8: 0 | M8: 0 | N8: 0 | O8: 0 | P8: 0 | Q8: 0 | R8: 0 | S8: 0 | T8: 0 | U8: 0 | V8: 0 | W8: 0 | X8: 0 | Y8: 0 | Z8: 0 | AA8: 0 | AB8: 0 | AC8: 0 | AD8: 0 | AE8: 0 | AF8: 0 | AG8: 0 | AH8: 0 | AI8: 0 | AJ8: 0 | AK8: 0 | AL8: 0 | AM8: 0 | AN8: 0 | AO8: 0 | AP8: 0 | AQ8: 0 | AR8: 0 | AS8: 0 | AT8: 0 | AU8: 0 | AV8: 0 | AW8: 0 | AX8: 0 | AY8: 0 | AZ8: 0 | BA8: 0 | BB8: 0 | BC8: 0 | BD8: 0 | BE8: 0 | BF8: 0 | BG8: 0 | BH8: 0 | BI8: 0 | BJ8: 0 | BK8: 0 | BL8: 0 | BM8: 0 | BN8: 0 | BO8: 0 | BP8: 0 | BQ8: 0 | BR8: 0 | BS8: 0 | BT8: 0 | BU8: 0 | BV8: 0 | BW8: 0 | BX8: 0 | BY8: 0 | BZ8: 0 | CA8: 0 | CB8: 0 | CC8: 0 | CD8: 0 | CE8: 0 | CF8: 0 | CG8: 0 | CH8: 0 | CI8: 0 | CJ8: 0 | CK8: 0 | CL8: 0 | CM8: 0 | CN8: 0 | CO8: 0 | CP8: 0 | CQ8: 0 | CR8: 0 | CS8: 0 | CT8: 0 | CU8: 0 | CV8: 0 | CW8: 0 | CX8: 0 | CY8: 0 | CZ8: 0 | DA8: 0 | DB8: 0 | DC8: 0 | DD8: 0 | DE8: 0 | DF8: 0 | DG8: 0 | DH8: 0 | DI8: 0 | DJ8: 0 | DK8: 0 | DL8: 0 | DM8: 0 | DN8: 0 | DO8: 0 | DP8: 0 | DQ8: 0 | DR8: 0 | DS8: 0 | DT8: 0 | DU8: 0 | DV8: 0 | DW8: 0 | DX8: 0 | DY8: 0 | DZ8: 0 | EA8: 0 | EB8: 0 | EC8: 0 | ED8: 0 | EE8: 0 | EF8: 0 | EG8: 0 | EH8: 0 | EI8: 0 | EJ8: 0 | EK8: 0 | EL8: 0 | EM8: 0 | EN8: 0 | EO8: 0 | EP8: 0 | EQ8: 0 | ER8: 0 | ES8: 0 | ET8: 0 | EU8: 0 | EV8: 0 | EW8: 0 | EX8: 0 | EY8: 0 | EZ8: 0 | FA8: 0 | FB8: 0 | FC8: 0 | FD8: 0 | FE8: 0 | FF8: 0 | FG8: 0 | FH8: 0 | FI8: 0 | FJ8: 0 | FK8: 0 | FL8: 0 | FM8: 0 | FN8: 0 | FO8: 0 | FP8: 0 | FQ8: 0 | FR8: 0 | FS8: 0 | FT8: 0 | FU8: 0 | FV8: 0 | FW8: 0 | FX8: 0 | FY8: 0 | FZ8: 0 | GA8: 0 | GB8: 0 | GC8: 0 | GD8: 0 | GE8: 0 | GF8: 0 | GG8: 0 | GH8: 0 | GI8: 0 | GJ8: 0 | GK8: 0 | GL8: 0 | GM8: 0 | GN8: 0 | GO8: 0 | GP8: 0 | GQ8: 0 | GR8: 0 | GS8: 0 | GT8: 0 | GU8: 0 | GV8: 0 | GW8: 0 | GX8: 0 | GY8: 0 | GZ8: 0 | HA8: 0 | HB8: 0 | HC8: 0 | HD8: 0 | HE8: 0 | HF8: 0 | HG8: 0 | HH8: 0 | HI8: 0 | HJ8: 0 | HK8: 0 | HL8: 0 | HM8: 0 | HN8: 0 | HO8: 0 | HP8: 0 | HQ8: 0 | HR8: 0 | HS8: 0 | HT8: 0 | HU8: 0 | HV8: 0 | HW8: 0 | HX8: 0 | HY8: 0 | HZ8: 0 | IA8: 0 | IB8: 0 | IC8: 0 | ID8: 0 | IE8: 0 | IF8: 0 | IG8: 0 | IH8: 0 | II8: 0 | IJ8: 0 | IK8: 0 | IL8: 0 | IM8: 0 | IN8: 0 | IO8: 0 | IP8: 0 | IQ8: 0 | IR8: 0 | IS8: 0 | IT8: 0 | IU8: 0 | IV8: 0 | IW8: 0 | IX8: 0 | IY8: 0 | IZ8: 0 | JA8: 0 | JB8: 0 | JC8: 0 | JD8: 0 | JE8: 0 | JF8: 0 | JG8: 0 | JH8: 0 | JI8: 0 | JJ8: 0 | JK8: 0 | JL8: 0 | JM8: 0 | JN8: 0 | JO8: 0 | JP8: 0 | JQ8: 0 | JR8: 0 | JS8: 0 | JT8: 0 | JU8: 0 | JV8: 0 | JW8: 0 | JX8: 0 | JY8: 0 | JZ8: 0 | KA8: 0 | KB8: 0 | KC8: 0 | KD8: 0 | KE8: 0 | KF8: 0 | KG8: 0 | KH8: 0 | KI8: 0 | KJ8: 0 | KK8: 0 | KL8: 0 | KM8: 0 | KN8: 0 | KO8: 0 | KP8: 0 | KQ8: 0 | KR8: 0 | KS8: 0 | KT8: 0 | KU8: 0 | KV8: 0 | KW8: 0 | KX8: 0 | KY8: 0 | KZ8: 0
A9: 国家税务总局恩平市税务局大槐税务分局+互联网专线+新增+融合 | B9: 0 | C9: 0 | D9: 0 | E9: 0 | F9: 0 | G9: 0 | H9: 0 | I9: 0 | J9: 0 | K9: 0 | L9: 0 | M9: 0 | N9: 0 | O9: 0 | P9: 0 | Q9: 0 | R9: 0 | S9: 0 | T9: 0 | U9: 0 | V9: 0 | W9: 0 | X9: 0 | Y9: 0 | Z9: 0 | AA9: 0 | AB9: 0 | AC9: 0 | AD9: 0 | AE9: 0 | AF9: 0 | AG9: 0 | AH9: 0 | AI9: 0 | AJ9: 0 | AK9: 0 | AL9: 0 | AM9: 0 | AN9: 0 | AO9: 0 | AP9: 0 | AQ9: 0 | AR9: 0 | AS9: 0 | AT9: 0 | AU9: 0 | AV9: 0 | AW9: 0 | AX9: 0 | AY9: 0 | AZ9: 0 | BA9: 0 | BB9: 0 | BC9: 0 | BD9: 0 | BE9: 0 | BF9: 0 | BG9: 0 | BH9: 0 | BI9: 0 | BJ9: 0 | BK9: 0 | BL9: 0 | BM9: 0 | BN9: 0 | BO9: 0 | BP9: 0 | BQ9: 0 | BR9: 0 | BS9: 0 | BT9: 0 | BU9: 0 | BV9: 0 | BW9: 0 | BX9: 0 | BY9: 0 | BZ9: 0 | CA9: 0 | CB9: 0 | CC9: 0 | CD9: 0 | CE9: 0 | CF9: 0 | CG9: 0 | CH9: 0 | CI9: 0 | CJ9: 0 | CK9: 0 | CL9: 0 | CM9: 0 | CN9: 0 | CO9: 0 | CP9: 0 | CQ9: 0 | CR9: 0 | CS9: 0 | CT9: 0 | CU9: 0 | CV9: 0 | CW9: 0 | CX9: 0 | CY9: 0 | CZ9: 0 | DA9: 0 | DB9: 0 | DC9: 0 | DD9: 0 | DE9: 0 | DF9: 0 | DG9: 0 | DH9: 0 | DI9: 0 | DJ9: 0 | DK9: 0 | DL9: 0 | DM9: 0 | DN9: 0 | DO9: 0 | DP9: 0 | DQ9: 0 | DR9: 0 | DS9: 0 | DT9: 0 | DU9: 0 | DV9: 0 | DW9: 0 | DX9: 0 | DY9: 0 | DZ9: 0 | EA9: 0 | EB9: 0 | EC9: 0 | ED9: 0 | EE9: 0 | EF9: 0 | EG9: 0 | EH9: 0 | EI9: 0 | EJ9: 0 | EK9: 0 | EL9: 0 | EM9: 0 | EN9: 0 | EO9: 0 | EP9: 0 | EQ9: 0 | ER9: 0 | ES9: 0 | ET9: 0 | EU9: 0 | EV9: 0 | EW9: 0 | EX9: 0 | EY9: 0 | EZ9: 0 | FA9: 0 | FB9: 0 | FC9: 0 | FD9: 0 | FE9: 0 | FF9: 0 | FG9: 0 | FH9: 0 | FI9: 0 | FJ9: 0 | FK9: 0 | FL9: 0 | FM9: 0 | FN9: 0 | FO9: 0 | FP9: 0 | FQ9: 0 | FR9: 0 | FS9: 0 | FT9: 0 | FU9: 0 | FV9: 0 | FW9: 0 | FX9: 0 | FY9: 0 | FZ9: 0 | GA9: 0 | GB9: 0 | GC9: 0 | GD9: 0 | GE9: 0 | GF9: 0 | GG9: 0 | GH9: 0 | GI9: 0 | GJ9: 0 | GK9: 0 | GL9: 0 | GM9: 0 | GN9: 0 | GO9: 0 | GP9: 0 | GQ9: 0 | GR9: 0 | GS9: 0 | GT9: 0 | GU9: 0 | GV9: 0 | GW9: 0 | GX9: 0 | GY9: 0 | GZ9: 0 | HA9: 0 | HB9: 0 | HC9: 0 | HD9: 0 | HE9: 0 | HF9: 0 | HG9: 0 | HH9: 0 | HI9: 0 | HJ9: 0 | HK9: 0 | HL9: 0 | HM9: 0 | HN9: 0 | HO9: 0 | HP9: 0 | HQ9: 0 | HR9: 0 | HS9: 0 | HT9: 0 | HU9: 0 | HV9: 0 | HW9: 0 | HX9: 0 | HY9: 0 | HZ9: 0 | IA9: 0 | IB9: 0 | IC9: 0 | ID9: 0 | IE9: 0 | IF9: 0 | IG9: 0 | IH9: 0 | II9: 0 | IJ9: 0 | IK9: 0 | IL9: 0 | IM9: 0 | IN9: 0 | IO9: 0 | IP9: 0 | IQ9: 0 | IR9: 0 | IS9: 0 | IT9: 0 | IU9: 0 | IV9: 0 | IW9: 0 | IX9: 0 | IY9: 0 | IZ9: 0 | JA9: 0 | JB9: 0 | JC9: 0 | JD9: 0 | JE9: 0 | JF9: 0 | JG9: 0 | JH9: 0 | JI9: 0 | JJ9: 0 | JK9: 0 | JL9: 0 | JM9: 0 | JN9: 0 | JO9: 0 | JP9: 0 | JQ9: 0 | JR9: 0 | JS9: 0 | JT9: 0 | JU9: 0 | JV9: 0 | JW9: 0 | JX9: 0 | JY9: 0 | JZ9: 0 | KA9: 0 | KB9: 0 | KC9: 0 | KD9: 0 | KE9: 0 | KF9: 0 | KG9: 0 | KH9: 0 | KI9: 0 | KJ9: 0 | KK9: 0 | KL9: 0 | KM9: 0 | KN9: 0 | KO9: 0 | KP9: 0 | KQ9: 0 | KR9: 0 | KS9: 0 | KT9: 0 | KU9: 0 | KV9: 0 | KW9: 0 | KX9: 0 | KY9: 0 | KZ9: 0
A10: 开平市公安局赤坎派出所+互联网专线+搬迁 | B10: 0 | C10: 0 | D10: 0 | E10: 0 | F10: 0 | G10: 0 | H10: 0 | I10: 0 | J10: 0 | K10: 0 | L10: 0 | M10: 0 | N10: 0 | O10: 0 | P10: 0 | Q10: 0 | R10: 0 | S10: 0 | T10: 0 | U10: 0 | V10: 0 | W10: 0 | X10: 0 | Y10: 0 | Z10: 0 | AA10: 0 | AB10: 0 | AC10: 0 | AD10: 0 | AE10: 0 | AF10: 0 | AG10: 0 | AH10: 0 | AI10: 0 | AJ10: 0 | AK10: 0 | AL10: 0 | AM10: 0 | AN10: 0 | AO10: 0 | AP10: 0 | AQ10: 0 | AR10: 0 | AS10: 0 | AT10: 0 | AU10: 0 | AV10: 0 | AW10: 0 | AX10: 0 | AY10: 0 | AZ10: 0 | BA10: 0 | BB10: 0 | BC10: 0 | BD10: 0 | BE10: 0 | BF10: 0 | BG10: 0 | BH10: 0 | BI10: 0 | BJ10: 0 | BK10: 0 | BL10: 0 | BM10: 0 | BN10: 0 | BO10: 0 | BP10: 0 | BQ10: 0 | BR10: 0 | BS10: 0 | BT10: 0 | BU10: 0 | BV10: 0 | BW10: 0 | BX10: 0 | BY10: 0 | BZ10: 0 | CA10: 0 | CB10: 0 | CC10: 0 | CD10: 0 | CE10: 0 | CF10: 0 | CG10: 0 | CH10: 0 | CI10: 0 | CJ10: 0 | CK10: 0 | CL10: 0 | CM10: 0 | CN10: 0 | CO10: 0 | CP10: 0 | CQ10: 0 | CR10: 0 | CS10: 0 | CT10: 0 | CU10: 0 | CV10: 0 | CW10: 0 | CX10: 0 | CY10: 0 | CZ10: 0 | DA10: 0 | DB10: 0 | DC10: 0 | DD10: 0 | DE10: 0 | DF10: 0 | DG10: 0 | DH10: 0 | DI10: 0 | DJ10: 0 | DK10: 0 | DL10: 0 | DM10: 0 | DN10: 0 | DO10: 0 | DP10: 0 | DQ10: 0 | DR10: 0 | DS10: 0 | DT10: 0 | DU10: 0 | DV10: 0 | DW10: 0 | DX10: 0 | DY10: 0 | DZ10: 0 | EA10: 0 | EB10: 0 | EC10: 0 | ED10: 0 | EE10: 0 | EF10: 0 | EG10: 0 | EH10: 0 | EI10: 0 | EJ10: 0 | EK10: 0 | EL10: 0 | EM10: 0 | EN10: 0 | EO10: 0 | EP10: 0 | EQ10: 0 | ER10: 0 | ES10: 0 | ET10: 0 | EU10: 0 | EV10: 0 | EW10: 0 | EX10: 0 | EY10: 0 | EZ10: 0 | FA10: 0 | FB10: 0 | FC10: 0 | FD10: 0 | FE10: 0 | FF10: 0 | FG10: 0 | FH10: 0 | FI10: 0 | FJ10: 0 | FK10: 0 | FL10: 0 | FM10: 0 | FN10: 0 | FO10: 0 | FP10: 0 | FQ10: 0 | FR10: 0 | FS10: 0 | FT10: 0 | FU10: 0 | FV10: 0 | FW10: 0 | FX10: 0 | FY10: 0 | FZ10: 0 | GA10: 0 | GB10: 0 | GC10: 0 | GD10: 0 | GE10: 0 | GF10: 0 | GG10: 0 | GH10: 0 | GI10: 0 | GJ10: 0 | GK10: 0 | GL10: 0 | GM10: 0 | GN10: 0 | GO10: 0 | GP10: 0 | GQ10: 0 | GR10: 0 | GS10: 0 | GT10: 0 | GU10: 0 | GV10: 0 | GW10: 0 | GX10: 0 | GY10: 0 | GZ10: 0 | HA10: 0 | HB10: 0 | HC10: 0 | HD10: 0 | HE10: 0 | HF10: 0 | HG10: 0 | HH10: 0 | HI10: 0 | HJ10: 0 | HK10: 0 | HL10: 0 | HM10: 0 | HN10: 0 | HO10: 0 | HP10: 0 | HQ10: 0 | HR10: 0 | HS10: 0 | HT10: 0 | HU10: 0 | HV10: 0 | HW10: 0 | HX10: 0 | HY10: 0 | HZ10: 0 | IA10: 0 | IB10: 0 | IC10: 0 | ID10: 0 | IE10: 0 | IF10: 0 | IG10: 0 | IH10: 0 | II10: 0 | IJ10: 0 | IK10: 0 | IL10: 0 | IM10: 0 | IN10: 0 | IO10: 0 | IP10: 0 | IQ10: 0 | IR10: 0 | IS10: 0 | IT10: 0 | IU10: 0 | IV10: 0 | IW10: 0 | IX10: 0 | IY10: 0 | IZ10: 0 | JA10: 0 | JB10: 0 | JC10: 0 | JD10: 0 | JE10: 0 | JF10: 0 | JG10: 0 | JH10: 0 | JI10: 0 | JJ10: 0 | JK10: 0 | JL10: 0 | JM10: 0 | JN10: 0 | JO10: 0 | JP10: 0 | JQ10: 0 | JR10: 0 | JS10: 0 | JT10: 0 | JU10: 0 | JV10: 0 | JW10: 0 | JX10: 0 | JY10: 0 | JZ10: 0 | KA10: 0 | KB10: 0 | KC10: 0 | KD10: 0 | KE10: 0 | KF10: 0 | KG10: 0 | KH10: 0 | KI10: 0 | KJ10: 0 | KK10: 0 | KL10: 0 | KM10: 0 | KN10: 0 | KO10: 0 | KP10: 0 | KQ10: 0 | KR10: 0 | KS10: 0 | KT10: 0 | KU10: 0 | KV10: 0 | KW10: 0 | KX10: 0 | KY10: 0 | KZ10: 0
A11: 开平市公安局新昌派出所+互联网专线+搬迁 | B11: =VLOOKUP($A$4:$A$56,Sheet2!$A$8:$LQ$43,2,FALSE) -> 0 | C11: =VLOOKUP($A$4:$A$56,Sheet2!$A$8:$LQ$43,3,FALSE) -> 0.81 | D11: =VLOOKUP($A$4:$A$56,Sheet2!$A$8:$LQ$43,COLUMN(D11),FALSE) -> 0 | E11: =IFERROR(VLOOKUP($A$4:$A$56,Sheet2!$A$8:$LQ$43,COLUMN(E11),FALSE),"") -> 2 | F11: =IFERROR(VLOOKUP($A$4:$A$56,Sheet2!$A$8:$LQ$43,COLUMN(F11),FALSE),"") -> 0 | G11: =IFERROR(VLOOKUP($A$4:$A$56,Sheet2!$A$8:$LQ$43,COLUMN(G11),FALSE),"") -> 12 | H11: =IFERROR(VLOOKUP($A$4:$A$56,Sheet2!$A$8:$LQ$43,COLUMN(H11),FALSE),"") -> 0 | I11: =IFERROR(VLOOKUP($A$4:$A$56,Sheet2!$A$8:$LQ$43,COLUMN(I11),FALSE),"") -> 0 | J11: =IFERROR(VLOOKUP($A$4:$A$56,Sheet2!$A$8:$LQ$43,COLUMN(J11),FALSE),"") -> 0 | K11: =IFERROR(VLOOKUP($A$4:$A$56,Sheet2!$A$8:$LQ$43,COLUMN(K11),FALSE),"") -> 0 | L11: =IFERROR(VLOOKUP($A$4:$A$56,Sheet2!$A$8:$LQ$43,COLUMN(L11),FALSE),"") -> 0 | ... KZ11: =IFERROR(VLOOKUP($A$4:$A$56,Sheet2!$A$8:$LQ$43,COLUMN(KZ11),FALSE),"") -> 0
A12: 开平市公安局新昌派出思始点+互联网专线+搬迁 | B12: =VLOOKUP($A$4:$A$56,Sheet2!$A$8:$LQ$43,2,FALSE) -> 0 | C12: =VLOOKUP($A$4:$A$56,Sheet2!$A$8:$LQ$43,3,FALSE) -> 1.69 | D12: =VLOOKUP($A$4:$A$56,Sheet2!$A$8:$LQ$43,COLUMN(D12),FALSE) -> 0 | E12: =IFERROR(VLOOKUP($A$4:$A$56,Sheet2!$A$8:$LQ$43,COLUMN(E12),FALSE),"") -> 2 | F12: =IFERROR(VLOOKUP($A$4:$A$56,Sheet2!$A$8:$LQ$43,COLUMN(F12),FALSE),"") -> 0 | G12: =IFERROR(VLOOKUP($A$4:$A$56,Sheet2!$A$8:$LQ$43,COLUMN(G12),FALSE),"") -> 12 | H12: =IFERROR(VLOOKUP($A$4:$A$56,Sheet2!$A$8:$LQ$43,COLUMN(H12),FALSE),"") -> 0 | I12: =IFERROR(VLOOKUP($A$4:$A$56,Sheet2!$A$8:$LQ$43,COLUMN(I12),FALSE),"") -> 0 | J12: =IFERROR(VLOOKUP($A$4:$A$56,Sheet2!$A$8:$LQ$43,COLUMN(J12),FALSE),"") -> 0 | K12: =IFERROR(VLOOKUP($A$4:$A$56,Sheet2!$A$8:$LQ$43,COLUMN(K12),FALSE),"") -> 0 | L12: =IFERROR(VLOOKUP($A$4:$A$56,Sheet2!$A$8:$LQ$43,COLUMN(L12),FALSE),"") -> 0 | ... KZ12: =IFERROR(VLOOKUP($A$4:$A$56,Sheet2!$A$8:$LQ$43,COLUMN(KZ12),FALSE),"") -> 0
A13: 开平市公安局月山派出所+互联网专线+搬迁 | B13: =VLOOKUP($A$4:$A$56,Sheet2!$A$8:$LQ$43,2,FALSE) -> 0 | C13: =VLOOKUP($A$4:$A$56,Sheet2!$A$8:$LQ$43,3,FALSE) -> 1.44 | D13: =VLOOKUP($A$4:$A$56,Sheet2!$A$8:$LQ$43,COLUMN(D13),FALSE) -> 0 | E13: =IFERROR(VLOOKUP($A$4:$A$56,Sheet2!$A$8:$LQ$43,COLUMN(E13),FALSE),"") -> 2 | F13: =IFERROR(VLOOKUP($A$4:$A$56,Sheet2!$A$8:$LQ$43,COLUMN(F13),FALSE),"") -> 0 | G13: =IFERROR(VLOOKUP($A$4:$A$56,Sheet2!$A$8:$LQ$43,COLUMN(G13),FALSE),"") -> 12 | H13: =IFERROR(VLOOKUP($A$4:$A$56,Sheet2!$A$8:$LQ$43,COLUMN(H13),FALSE),"") -> 0 | I13: =IFERROR(VLOOKUP($A$4:$A$56,Sheet2!$A$8:$LQ$43,COLUMN(I13),FALSE),"") -> 0 | J13: =IFERROR(VLOOKUP($A$4:$A$56,Sheet2!$A$8:$LQ$43,COLUMN(J13),FALSE),"") -> 0 | K13: =IFERROR(VLOOKUP($A$4:$A$56,Sheet2!$A$8:$LQ$43,COLUMN(K13),FALSE),"") -> 0 | L13: =IFERROR(VLOOKUP($A$4:$A$56,Sheet2!$A$8:$LQ$43,COLUMN(L13),FALSE),"") -> 0 | ... KZ13: =IFERROR(VLOOKUP($A$4:$A$56,Sheet2!$A$8:$LQ$43,COLUMN(KZ13),FALSE),"") -> 0
